Workbook

Sheet 2026_Мустафин
E1: Дата | G1: 46168
A2: 11.25 | B2: - курс юань/рубль | E2: 8.33 | G2: - курс евро/юань
F3: Подсветить артикул: | G3: - | I3: 2026-I | J3: 2026-II | K3: 2025 - II полугодие | L3: Валюта продажи | M3: Продажи 2024 | BO3: Продажи 2025
A4: Клиент | B4: Условия оплаты | C4: Поставщик | D4: Менеджер | E4: п\п | F4: 2 - продукт WABCO | G4: Номер изделия/ артикул | H4: Наименование | I4: Цена, юань, без НДС | J4: Цена, юань, без НДС | K4: Цена в валюте из контракта с клиентом, без НДС | L4: Валюта из контракта с клиентом | M4: Январь 2024 | Q4: Февраль 2024 | U4: Март 2024 | Y4: Апрель 2024 | AC4: Май 2024 | AG4: Июнь 2024 | AK4: Июль 2024 | AO4: Август 2024 | AS4: Сентябрь 2024 | AW4: Октябрь 2024 | BA4: 45597 | BE4: 45627 | BI4: ИТОГО, 2024 | BO4: 45658 | BT4: 45689 | BY4: 45717 | CD4: 45748 | CI4: 45778 | CN4: 45809 | CS4: 45839 | CX4: 45870 | DC4: 45901 | DH4: 45931 | DM4: 45962 | DR4: 45992 | DW4: ИТОГО, 2025 | EE4: 46023 | EI4: 46054 | EM4: 46082 | EQ4: 46113 | EU4: 46143 | EY4: 46174 | FC4: 46204 | FG4: 46235 | FK4: 46266 | FO4: 46296 | FS4: 46327 | FW4: 46357 | GA4: ИТОГО, 2026 | GG4: 46388 | GK4: 46419 | GO4: 46447 | GS4: 46478 | GW4: 46508 | HA4: 46539 | HE4: 46569 | HI4: 46600 | HM4: 46631 | HQ4: 46661 | HU4: 46692 | HY4: 46722 | IC4: ИТОГО, 2027 | II4: 46753 | IM4: 46784 | IQ4: 46813 | IU4: 46844 | IY4: 46874 | JC4: 46905 | JG4: 46935 | JK4: 46966 | JO4: 46997 | JS4: 47027 | JW4: 47058 | KA4: 47088 | KE4: ИТОГО, 2028
M5: AOP, шт | N5: Прогноз, шт | O5: Факт, шт | P5: Коментарий | Q5: AOP, шт | R5: Прогноз, шт | S5: Факт, шт | T5: Коментарий | U5: AOP, шт | V5: Прогноз, шт | W5: Факт, шт | X5: Коментарий | Y5: AOP, шт | Z5: Прогноз, шт | AA5: Факт, шт | AB5: Коментарий | AC5: AOP, шт | AD5: Прогноз, шт | AE5: Факт, шт | AF5: Коментарий | AG5: AOP, шт | AH5: Прогноз, шт | AI5: Факт, шт | AJ5: Коментарий | AK5: AOP, шт | AL5: Прогноз, шт | AM5: Факт, шт | AN5: Коментарий | AO5: AOP, шт | AP5: Прогноз, шт | AQ5: Факт, шт | AR5: Коментарий | AS5: AOP, шт | AT5: Прогноз, шт | AU5: Факт, шт | AV5: Коментарий | AW5: AOP, шт | AX5: Прогноз, шт | AY5: Факт, шт | AZ5: Коментарий | BA5: AOP, шт | BB5: Прогноз, шт | BC5: Факт, шт | BD5: Коментарий | BE5: AOP, шт | BF5: Прогноз, шт | BG5: Факт, шт | BH5: Коментарий | BI5: AOP, шт | BJ5: Продажи AOP, CNY | BK5: Прогноз, шт | BL5: Продажи Прогноз, CNY | BM5: Факт, шт | BN5: Продажи Факт, CNY | BO5: AOP, шт | BP5: AOP негатив, шт | BQ5: Прогноз, шт | BR5: Факт, шт | BS5: Коментарий | BT5: AOP, шт | BU5: AOP негатив, шт | BV5: Прогноз, шт | BW5: Факт, шт | BX5: Коментарий | BY5: AOP, шт | BZ5: AOP негатив, шт | CA5: Прогноз, шт | CB5: Факт, шт | CC5: Коментарий | CD5: AOP, шт | CE5: AOP негатив, шт | CF5: Прогноз, шт | CG5: Факт, шт | CH5: Коментарий | CI5: AOP, шт | CJ5: AOP негатив, шт | CK5: Прогноз, шт | CL5: Факт, шт | CM5: Коментарий | CN5: AOP, шт | CO5: AOP негатив, шт | CP5: Прогноз, шт | CQ5: Факт, шт | CR5: Коментарий | CS5: AOP, шт | CT5: AOP негатив, шт | CU5: Прогноз, шт | CV5: Факт, шт | CW5: Коментарий | CX5: AOP, шт | CY5: AOP негатив, шт | CZ5: Прогноз, шт | DA5: Факт, шт | DB5: Коментарий | DC5: AOP, шт | DD5: AOP негатив, шт | DE5: Прогноз, шт | DF5: Факт, шт | DG5: Коментарий | DH5: AOP, шт | DI5: AOP негатив, шт | DJ5: Прогноз, шт | DK5: Факт, шт | DL5: Коментарий | DM5: AOP, шт | DN5: AOP негатив, шт | DO5: Прогноз, шт | DP5: Факт, шт | DQ5: Коментарий | DR5: AOP, шт | DS5: AOP негатив, шт | DT5: Прогноз, шт | DU5: Факт, шт | DV5: Коментарий | DW5: AOP, шт | DX5: Продажи AOP, CNY | DY5: AOP негатив, шт | DZ5: Продажи AOP негатив, CNY | EA5: Прогноз, шт | EB5: Продажи Прогноз, CNY | EC5: Факт, шт | ED5: Продажи Факт, CNY | EE5: AOP, шт | EF5: Прогноз, шт | EG5: Факт, шт | EH5: Коментарий | EI5: AOP, шт | EJ5: Прогноз, шт | EK5: Факт, шт | EL5: Коментарий | EM5: AOP, шт | EN5: Прогноз, шт | EO5: Факт, шт | EP5: Коментарий | EQ5: AOP, шт | ER5: Прогноз, шт | ES5: Факт, шт | ET5: Коментарий | EU5: AOP, шт | EV5: Прогноз, шт | EW5: Факт, шт | EX5: Коментарий | EY5: AOP, шт | EZ5: Прогноз, шт | FA5: Факт, шт | FB5: Коментарий | FC5: AOP, шт | FD5: Прогноз, шт | FE5: Факт, шт | FF5: Коментарий | FG5: AOP, шт | FH5: Прогноз, шт | FI5: Факт, шт | FJ5: Коментарий | FK5: AOP, шт | FL5: Прогноз, шт | FM5: Факт, шт | FN5: Коментарий | FO5: AOP, шт | FP5: Прогноз, шт | FQ5: Факт, шт | FR5: Коментарий | FS5: AOP, шт | FT5: Прогноз, шт | FU5: Факт, шт | FV5: Коментарий | FW5: AOP, шт | FX5: Прогноз, шт | FY5: Факт, шт | FZ5: Коментарий | GA5: AOP, шт | GB5: Продажи AOP, CNY | GC5: Прогноз, шт | GD5: Продажи Прогноз, CNY | GE5: Факт, шт | GF5: Продажи Факт, CNY | GG5: AOP, шт | GH5: Прогноз, шт | GI5: Факт, шт | GJ5: Коментарий | GK5: AOP, шт | GL5: Прогноз, шт | GM5: Факт, шт | GN5: Коментарий | GO5: AOP, шт | GP5: Прогноз, шт | GQ5: Факт, шт | GR5: Коментарий | GS5: AOP, шт | GT5: Прогноз, шт | GU5: Факт, шт | GV5: Коментарий | GW5: AOP, шт | GX5: Прогноз, шт | GY5: Факт, шт | GZ5: Коментарий | HA5: AOP, шт | HB5: Прогноз, шт | HC5: Факт, шт | HD5: Коментарий | HE5: AOP, шт | HF5: Прогноз, шт | HG5: Факт, шт | HH5: Коментарий | HI5: AOP, шт | HJ5: Прогноз, шт | HK5: Факт, шт | HL5: Коментарий | HM5: AOP, шт | HN5: Прогноз, шт | HO5: Факт, шт | HP5: Коментарий | HQ5: AOP, шт | HR5: Прогноз, шт | HS5: Факт, шт | HT5: Коментарий | HU5: AOP, шт | HV5: Прогноз, шт | HW5: Факт, шт | HX5: Коментарий | HY5: AOP, шт | HZ5: Прогноз, шт | IA5: Факт, шт | IB5: Коментарий | IC5: AOP, шт | ID5: Продажи AOP, CNY | IE5: Прогноз, шт | IF5: Продажи Прогноз, CNY | IG5: Факт, шт | IH5: Продажи Факт, CNY | II5: AOP, шт | IJ5: Прогноз, шт | IK5: Факт, шт | IL5: Коментарий | IM5: AOP, шт | IN5: Прогноз, шт | IO5: Факт, шт | IP5: Коментарий | IQ5: AOP, шт | IR5: Прогноз, шт | IS5: Факт, шт | IT5: Коментарий | IU5: AOP, шт | IV5: Прогноз, шт | IW5: Факт, шт | IX5: Коментарий | IY5: AOP, шт | IZ5: Прогноз, шт | JA5: Факт, шт | JB5: Коментарий | JC5: AOP, шт | JD5: Прогноз, шт | JE5: Факт, шт | JF5: Коментарий | JG5: AOP, шт | JH5: Прогноз, шт | JI5: Факт, шт | JJ5: Коментарий | JK5: AOP, шт | JL5: Прогноз, шт | JM5: Факт, шт | JN5: Коментарий | JO5: AOP, шт | JP5: Прогноз, шт | JQ5: Факт, шт | JR5: Коментарий | JS5: AOP, шт | JT5: Прогноз, шт | JU5: Факт, шт | JV5: Коментарий | JW5: AOP, шт | JX5: Прогноз, шт | JY5: Факт, шт | JZ5: Коментарий | KA5: AOP, шт | KB5: Прогноз, шт | KC5: Факт, шт | KD5: Коментарий | KE5: AOP, шт | KF5: Продажи AOP, CNY | KG5: Прогноз, шт | KH5: Продажи Прогноз, CNY | KI5: Факт, шт | KJ5: Продажи Факт, CNY | KN5: Кол-во в сете | KO5: Сет
A6: НЕФАЗ ПАО | B6: Отсрочка 30 дней | C6: ВБК РУС | D6: Мустафин Ринат | E6: 1 | F6: 1 | G6: 9522010010 | H6: Головка соединительная (управляющая) | I6: =89.6/1.2 -> 74.666667 | J6: =89.6/1.2 -> 74.666667 | M6: 102 | N6: 102 | O6: 0 | Q6: 50 | R6: 32 | S6: 32 | T6: Клиент изменил план | U6: 0 | V6: 50 | W6: 50 | X6: Клиент изменил план | Y6: 40 | Z6: 50 | AA6: 50 | AB6: Клиент изменил план | AC6: 40 | AD6: 40 | AE6: 0 | AG6: 40 | AH6: 25 | AI6: 25 | AJ6: КамАЗ не дает в необходимом объеме шасси для выполнения ранее намеченного плана по производству-продаже | AK6: 40 | AL6: 25 | AM6: 25 | AN6: КамАЗ не дает в необходимом объеме шасси для выполнения ранее намеченного плана по производству-продаже | AO6: 40 | AP6: 0 | AQ6: 0 | AR6: КамАЗ не дает в необходимом объеме шасси для выполнения ранее намеченного плана по производству-продаже | AS6: 40 | AT6: 0 | AU6: 0 | AV6: КамАЗ не дает в необходимом объеме шасси для выполнения ранее намеченного плана по производству-продаже, также имеет место общее снижение спроса | AW6: 40 | AX6: 0 | AY6: 0 | AZ6: КамАЗ не дает в необходимом объеме шасси для выполнения ранее намеченного плана по производству-продаже, также имеет место общее снижение спроса | BA6: 40 | BB6: 0 | BC6: 0 | BD6: КамАЗ не дает в необходимом объеме шасси для выполнения ранее намеченного плана по производству-продаже, также имеет место общее снижение спроса | BE6: 40 | BF6: 0 | BG6: 0 | BH6: КамАЗ не дает в необходимом объеме шасси для выполнения ранее намеченного плана по производству-продаже, также имеет место общее снижение спроса | BI6: =SUMPRODUCT(--(MOD(COLUMN($M6:$BH6),4)=MOD(COLUMN($M6),4)),$M6:$BH6) -> 512 | BJ6: =BI6*$I6 -> 38229.333 | BK6: =SUMPRODUCT(--(MOD(COLUMN($M6:$BH6),4)=MOD(COLUMN($M6)+1,4)),$M6:$BH6) -> 324 | BL6: =BK6*$I6 -> 24192 | BM6: =SUMPRODUCT(--(MOD(COLUMN($M6:$BH6),4)=MOD(COLUMN($M6)+2,4)),$M6:$BH6) -> 182 | BN6: =BM6*$I6 -> 13589.333 | BO6: =$KN6*0 -> 0 | BP6: =$KN6*0 -> 0 | BQ6: =$KN6*0 -> 0 | BR6: 0 | BT6: =$KN6*5 -> 5 | BU6: =$KN6*0 -> 0 | BV6: =$KN6*0 -> 0 | BW6: 0 | BY6: =$KN6*15 -> 15 | BZ6: =$KN6*15 -> 15 | CA6: =$KN6*0 -> 0 | CB6: 0 | CD6: =$KN6*15 -> 15 | CE6: =$KN6*15 -> 15 | CF6: =$KN6*0 -> 0 | CG6: 0 | CI6: =$KN6*15 -> 15 | CJ6: =$KN6*15 -> 15 | CK6: =$KN6*0 -> 0 | CL6: 0 | CN6: =$KN6*15 -> 15 | CO6: =$KN6*15 -> 15 | CP6: =$KN6*0 -> 0 | CQ6: 0 | CS6: =$KN6*15 -> 15 | CT6: =$KN6*15 -> 15 | CU6: =$KN6*0 -> 0 | CV6: 0 | CX6: =$KN6*15 -> 15 | CY6: =$KN6*15 -> 15 | CZ6: =$KN6*0 -> 0 | DA6: 0 | DC6: =$KN6*15 -> 15 | DD6: =$KN6*15 -> 15 | DE6: =$KN6*0 -> 0 | DF6: 0 | DH6: =$KN6*15 -> 15 | DI6: =$KN6*15 -> 15 | DJ6: =$KN6*0 -> 0 | DK6: 0 | DM6: =$KN6*15 -> 15 | DN6: 15 | DO6: =$KN6*0 -> 0 | DP6: 0 | DR6: 15 | DS6: 15 | DT6: 0 | DU6: 0 | DW6: {=SUMPRODUCT(--(MOD(COLUMN($BO6:$DV6),5)=MOD(COLUMN($BO6),5)),$BO6:$DV6)} -> 155 | DX6: =DW6*$J6 -> 11573.333 | DY6: {=SUMPRODUCT(--(MOD(COLUMN($BO6:$DV6),5)=MOD(COLUMN($BP6),5)),$BO6:$DV6)} -> 150 | DZ6: =DY6*$J6 -> 11200 | EA6: {=SUMPRODUCT(--(MOD(COLUMN($BO6:$DV6),5)=MOD(COLUMN($BQ6),5)),$BO6:$DV6)} -> 0 | EB6: =EA6*$J6 -> 0 | EC6: {=SUMPRODUCT(--(MOD(COLUMN($BO6:$DV6),5)=MOD(COLUMN($BR6),5)),$BO6:$DV6)} -> 0 | ED6: =EC6*$J6 -> 0 | EE6: =$KN6*8 -> 8 | EF6: 8 | EG6: 0 | EI6: =$KN6*9 -> 9 | EJ6: 50 | EK6: 0 | EM6: =$KN6*9 -> 9 | EN6: 0 | EQ6: =$KN6*15 -> 15 | ER6: 1 | EU6: =$KN6*15 -> 15 | EV6: 0 | EY6: =$KN6*15 -> 15 | EZ6: 45 | FC6: =$KN6*15 -> 15 | FD6: 15 | FG6: =$KN6*15 -> 15 | FH6: 15 | FK6: =$KN6*15 -> 15 | FL6: 15 | FO6: =$KN6*15 -> 15 | FP6: 15 | FS6: =$KN6*14 -> 14 | FT6: 14 | FW6: =$KN6*10 -> 10 | FX6: 10 | GA6: =SUMPRODUCT(--(MOD(COLUMN($EE6:$FZ6),4)=MOD(COLUMN($EE6),4)),$EE6:$FZ6) -> 155 | GB6: =GA6*$J6 -> 11573.333 | GC6: =SUMPRODUCT(--(MOD(COLUMN($EE6:$FZ6),4)=MOD(COLUMN($EF6),4)),$EE6:$FZ6) -> 188 | GD6: =GC6*$J6 -> 14037.333 | GE6: =SUMPRODUCT(--(MOD(COLUMN($EE6:$FZ6),4)=MOD(COLUMN($EG6),4)),$EE6:$FZ6) -> 0 | GF6: =GE6*$J6 -> 0 | GG6: =$KN6*10 -> 10 | GK6: =$KN6*10 -> 10 | GO6: =$KN6*15 -> 15 | GS6: =$KN6*20 -> 20 | GW6: =$KN6*20 -> 20 | HA6: =$KN6*20 -> 20 | HE6: =$KN6*20 -> 20 | HI6: =$KN6*20 -> 20 | HM6: =$KN6*20 -> 20 | HQ6: =$KN6*20 -> 20 | HU6: =$KN6*20 -> 20 | HY6: 20 | IC6: {=SUMPRODUCT(--(MOD(COLUMN($GG6:$IB6),4)=MOD(COLUMN($GG6),4)),$GG6:$IB6)} -> 215 | ID6: =IC6*$J6 -> 16053.333 | IE6: {=SUMPRODUCT(--(MOD(COLUMN($GG6:$IB6),4)=MOD(COLUMN($GH6),4)),$GG6:$IB6)} -> 0 | IF6: =IE6*$J6 -> 0 | IG6: {=SUMPRODUCT(--(MOD(COLUMN($GG6:$IB6),4)=MOD(COLUMN($GI6),4)),$GG6:$IB6)} -> 0 | IH6: =IG6*$J6 -> 0 | II6: =$KN6*15 -> 15 | IM6: =$KN6*15 -> 15 | IQ6: =$KN6*20 -> 20 | IU6: =$KN6*25 -> 25 | IY6: =$KN6*25 -> 25 | JC6: =$KN6*25 -> 25 | JG6: =$KN6*30 -> 30 | JK6: =$KN6*30 -> 30 | JO6: =$KN6*30 -> 30 | JS6: =$KN6*30 -> 30 | JW6: =$KN6*30 -> 30 | KA6: 30 | KE6: {=SUMPRODUCT(--(MOD(COLUMN($II6:$KD6),4)=MOD(COLUMN($II6),4)),$II6:$KD6)} -> 305 | KF6: =KE6*$J6 -> 22773.333 | KG6: {=SUMPRODUCT(--(MOD(COLUMN($II6:$KD6),4)=MOD(COLUMN($IJ6),4)),$II6:$KD6)} -> 0 | KH6: =KG6*$J6 -> 0 | KI6: {=SUMPRODUCT(--(MOD(COLUMN($II6:$KD6),4)=MOD(COLUMN($IK6),4)),$II6:$KD6)} -> 0 | KJ6: =KI6*$J6 -> 0 | KN6: 1 | KO6: TEBS 2s/2m 12м
E7: 2 | F7: 1 | G7: 9522010020 | H7: Головка соединительная (питающая) | I7: =89.6/1.2 -> 74.666667 | J7: =89.6/1.2 -> 74.666667 | M7: 102 | N7: 102 | O7: 0 | Q7: 50 | R7: 32 | S7: 32 | U7: 0 | V7: 50 | W7: 50 | Y7: 40 | Z7: 50 | AA7: 50 | AC7: 40 | AD7: 40 | AE7: 0 | AG7: 40 | AH7: 25 | AI7: 25 | AK7: 40 | AL7: 25 | AM7: 25 | AO7: 40 | AP7: 0 | AQ7: 0 | AS7: 40 | AT7: 0 | AU7: 0 | AW7: 40 | AX7: 0 | AY7: 0 | BA7: 40 | BB7: 0 | BC7: 0 | BE7: 40 | BF7: =$KN7*0 -> 0 | BG7: 0 | BI7: =SUMPRODUCT(--(MOD(COLUMN($M7:$BH7),4)=MOD(COLUMN($M7),4)),$M7:$BH7) -> 512 | BJ7: =BI7*$I7 -> 38229.333 | BK7: =SUMPRODUCT(--(MOD(COLUMN($M7:$BH7),4)=MOD(COLUMN($M7)+1,4)),$M7:$BH7) -> 324 | BL7: =BK7*$I7 -> 24192 | BM7: =SUMPRODUCT(--(MOD(COLUMN($M7:$BH7),4)=MOD(COLUMN($M7)+2,4)),$M7:$BH7) -> 182 | BN7: =BM7*$I7 -> 13589.333 | BO7: =$KN7*0 -> 0 | BP7: =$KN7*0 -> 0 | BQ7: =$KN7*0 -> 0 | BR7: 0 | BT7: =$KN7*5 -> 5 | BU7: =$KN7*0 -> 0 | BV7: =$KN7*0 -> 0 | BW7: 0 | BY7: =$KN7*15 -> 15 | BZ7: =$KN7*15 -> 15 | CA7: =$KN7*0 -> 0 | CB7: 0 | CD7: =$KN7*15 -> 15 | CE7: =$KN7*15 -> 15 | CF7: =$KN7*0 -> 0 | CG7: 0 | CI7: =$KN7*15 -> 15 | CJ7: =$KN7*15 -> 15 | CK7: =$KN7*0 -> 0 | CL7: 0 | CN7: =$KN7*15 -> 15 | CO7: =$KN7*15 -> 15 | CP7: =$KN7*0 -> 0 | CQ7: 0 | CS7: =$KN7*15 -> 15 | CT7: =$KN7*15 -> 15 | CU7: =$KN7*0 -> 0 | CV7: 0 | CX7: =$KN7*15 -> 15 | CY7: =$KN7*15 -> 15 | CZ7: =$KN7*0 -> 0 | DA7: 0 | DC7: =$KN7*15 -> 15 | DD7: =$KN7*15 -> 15 | DE7: =$KN7*0 -> 0 | DF7: 0 | DH7: =$KN7*15 -> 15 | DI7: =$KN7*15 -> 15 | DJ7: =$KN7*0 -> 0 | DK7: 0 | DM7: =$KN7*15 -> 15 | DN7: =$KN7*15 -> 15 | DO7: =$KN7*0 -> 0 | DP7: 0 | DR7: =$KN7*15 -> 15 | DS7: =$KN7*15 -> 15 | DT7: =$KN7*0 -> 0 | DU7: 0 | DW7: {=SUMPRODUCT(--(MOD(COLUMN($BO7:$DV7),5)=MOD(COLUMN($BO7),5)),$BO7:$DV7)} -> 155 | DX7: =DW7*$J7 -> 11573.333 | DY7: {=SUMPRODUCT(--(MOD(COLUMN($BO7:$DV7),5)=MOD(COLUMN($BP7),5)),$BO7:$DV7)} -> 150 | DZ7: =DY7*$J7 -> 11200 | EA7: {=SUMPRODUCT(--(MOD(COLUMN($BO7:$DV7),5)=MOD(COLUMN($BQ7),5)),$BO7:$DV7)} -> 0 | EB7: =EA7*$J7 -> 0 | EC7: {=SUMPRODUCT(--(MOD(COLUMN($BO7:$DV7),5)=MOD(COLUMN($BR7),5)),$BO7:$DV7)} -> 0 | ED7: =EC7*$J7 -> 0 | EE7: =$KN7*8 -> 8 | EF7: 8 | EG7: 0 | EI7: =$KN7*9 -> 9 | EJ7: 50 | EK7: 0 | EM7: =$KN7*9 -> 9 | EN7: 0 | EQ7: =$KN7*15 -> 15 | ER7: 1 | EU7: =$KN7*15 -> 15 | EV7: 0 | EY7: =$KN7*15 -> 15 | EZ7: 45 | FC7: =$KN7*15 -> 15 | FD7: 15 | FG7: =$KN7*15 -> 15 | FH7: 15 | FK7: =$KN7*15 -> 15 | FL7: 15 | FO7: =$KN7*15 -> 15 | FP7: 15 | FS7: =$KN7*14 -> 14 | FT7: 14 | FW7: =$KN7*10 -> 10 | FX7: 10 | GA7: =SUMPRODUCT(--(MOD(COLUMN($EE7:$FZ7),4)=MOD(COLUMN($EE7),4)),$EE7:$FZ7) -> 155 | GB7: =GA7*$J7 -> 11573.333 | GC7: =SUMPRODUCT(--(MOD(COLUMN($EE7:$FZ7),4)=MOD(COLUMN($EF7),4)),$EE7:$FZ7) -> 188 | GD7: =GC7*$J7 -> 14037.333 | GE7: =SUMPRODUCT(--(MOD(COLUMN($EE7:$FZ7),4)=MOD(COLUMN($EG7),4)),$EE7:$FZ7) -> 0 | GF7: =GE7*$J7 -> 0 | GG7: =$KN7*10 -> 10 | GK7: =$KN7*10 -> 10 | GO7: =$KN7*15 -> 15 | GS7: =$KN7*20 -> 20 | GW7: =$KN7*20 -> 20 | HA7: =$KN7*20 -> 20 | HE7: =$KN7*20 -> 20 | HI7: =$KN7*20 -> 20 | HM7: =$KN7*20 -> 20 | HQ7: =$KN7*20 -> 20 | HU7: =$KN7*20 -> 20 | HY7: =$KN7*20 -> 20 | IC7: {=SUMPRODUCT(--(MOD(COLUMN($GG7:$IB7),4)=MOD(COLUMN($GG7),4)),$GG7:$IB7)} -> 215 | ID7: =IC7*$J7 -> 16053.333 | IE7: {=SUMPRODUCT(--(MOD(COLUMN($GG7:$IB7),4)=MOD(COLUMN($GH7),4)),$GG7:$IB7)} -> 0 | IF7: =IE7*$J7 -> 0 | IG7: {=SUMPRODUCT(--(MOD(COLUMN($GG7:$IB7),4)=MOD(COLUMN($GI7),4)),$GG7:$IB7)} -> 0 | IH7: =IG7*$J7 -> 0 | II7: =$KN7*15 -> 15 | IM7: =$KN7*15 -> 15 | IQ7: =$KN7*20 -> 20 | IU7: =$KN7*25 -> 25 | IY7: =$KN7*25 -> 25 | JC7: =$KN7*25 -> 25 | JG7: =$KN7*30 -> 30 | JK7: =$KN7*30 -> 30 | JO7: =$KN7*30 -> 30 | JS7: =$KN7*30 -> 30 | JW7: =$KN7*30 -> 30 | KA7: 30 | KE7: {=SUMPRODUCT(--(MOD(COLUMN($II7:$KD7),4)=MOD(COLUMN($II7),4)),$II7:$KD7)} -> 305 | KF7: =KE7*$J7 -> 22773.333 | KG7: {=SUMPRODUCT(--(MOD(COLUMN($II7:$KD7),4)=MOD(COLUMN($IJ7),4)),$II7:$KD7)} -> 0 | KH7: =KG7*$J7 -> 0 | KI7: {=SUMPRODUCT(--(MOD(COLUMN($II7:$KD7),4)=MOD(COLUMN($IK7),4)),$II7:$KD7)} -> 0 | KJ7: =KI7*$J7 -> 0 | KN7: 1
E8: 3 | F8: 1 | G8: 9710029000 | H8: Воздухораспределитель с клапаном растормаживания | I8: =639/1.2 -> 532.5 | J8: =639/1.2 -> 532.5 | M8: 102 | N8: 102 | O8: 0 | Q8: 50 | R8: 32 | S8: 32 | U8: 0 | V8: 50 | W8: 50 | Y8: 40 | Z8: 50 | AA8: 50 | AC8: 40 | AD8: 40 | AE8: 0 | AG8: 40 | AH8: 25 | AI8: 25 | AK8: 40 | AL8: 25 | AM8: 25 | AO8: 40 | AP8: 0 | AQ8: 0 | AS8: 40 | AT8: 0 | AU8: 0 | AW8: 40 | AX8: 0 | AY8: 0 | BA8: 40 | BB8: 0 | BC8: 0 | BE8: 40 | BF8: =$KN8*0 -> 0 | BG8: 0 | BI8: =SUMPRODUCT(--(MOD(COLUMN($M8:$BH8),4)=MOD(COLUMN($M8),4)),$M8:$BH8) -> 512 | BJ8: =BI8*$I8 -> 272640 | BK8: =SUMPRODUCT(--(MOD(COLUMN($M8:$BH8),4)=MOD(COLUMN($M8)+1,4)),$M8:$BH8) -> 324 | BL8: =BK8*$I8 -> 172530 | BM8: =SUMPRODUCT(--(MOD(COLUMN($M8:$BH8),4)=MOD(COLUMN($M8)+2,4)),$M8:$BH8) -> 182 | BN8: =BM8*$I8 -> 96915 | BO8: =$KN8*0 -> 0 | BP8: =$KN8*0 -> 0 | BQ8: =$KN8*0 -> 0 | BR8: 0 | BT8: =$KN8*5 -> 5 | BU8: =$KN8*0 -> 0 | BV8: =$KN8*0 -> 0 | BW8: 0 | BY8: =$KN8*15 -> 15 | BZ8: =$KN8*15 -> 15 | CA8: =$KN8*0 -> 0 | CB8: 0 | CD8: =$KN8*15 -> 15 | CE8: =$KN8*15 -> 15 | CF8: =$KN8*0 -> 0 | CG8: 0 | CI8: =$KN8*15 -> 15 | CJ8: =$KN8*15 -> 15 | CK8: =$KN8*0 -> 0 | CL8: 0 | CN8: =$KN8*15 -> 15 | CO8: =$KN8*15 -> 15 | CP8: =$KN8*0 -> 0 | CQ8: 0 | CS8: =$KN8*15 -> 15 | CT8: =$KN8*15 -> 15 | CU8: =$KN8*0 -> 0 | CV8: 0 | CX8: =$KN8*15 -> 15 | CY8: =$KN8*15 -> 15 | CZ8: =$KN8*0 -> 0 | DA8: 0 | DC8: =$KN8*15 -> 15 | DD8: =$KN8*15 -> 15 | DE8: =$KN8*0 -> 0 | DF8: 0 | DH8: =$KN8*15 -> 15 | DI8: =$KN8*15 -> 15 | DJ8: =$KN8*0 -> 0 | DK8: 0 | DM8: =$KN8*15 -> 15 | DN8: =$KN8*15 -> 15 | DO8: =$KN8*0 -> 0 | DP8: 0 | DR8: =$KN8*15 -> 15 | DS8: =$KN8*15 -> 15 | DT8: =$KN8*0 -> 0 | DU8: 0 | DW8: {=SUMPRODUCT(--(MOD(COLUMN($BO8:$DV8),5)=MOD(COLUMN($BO8),5)),$BO8:$DV8)} -> 155 | DX8: =DW8*$J8 -> 82537.5 | DY8: {=SUMPRODUCT(--(MOD(COLUMN($BO8:$DV8),5)=MOD(COLUMN($BP8),5)),$BO8:$DV8)} -> 150 | DZ8: =DY8*$J8 -> 79875 | EA8: {=SUMPRODUCT(--(MOD(COLUMN($BO8:$DV8),5)=MOD(COLUMN($BQ8),5)),$BO8:$DV8)} -> 0 | EB8: =EA8*$J8 -> 0 | EC8: {=SUMPRODUCT(--(MOD(COLUMN($BO8:$DV8),5)=MOD(COLUMN($BR8),5)),$BO8:$DV8)} -> 0 | ED8: =EC8*$J8 -> 0 | EE8: =$KN8*8 -> 8 | EF8: 8 | EG8: 0 | EI8: =$KN8*9 -> 9 | EJ8: 50 | EK8: 0 | EM8: =$KN8*9 -> 9 | EN8: 0 | EQ8: =$KN8*15 -> 15 | ER8: 1 | EU8: =$KN8*15 -> 15 | EV8: 0 | EY8: =$KN8*15 -> 15 | EZ8: 45 | FC8: =$KN8*15 -> 15 | FD8: 15 | FG8: =$KN8*15 -> 15 | FH8: 15 | FK8: =$KN8*15 -> 15 | FL8: 15 | FO8: =$KN8*15 -> 15 | FP8: 15 | FS8: =$KN8*14 -> 14 | FT8: 14 | FW8: =$KN8*10 -> 10 | FX8: 10 | GA8: =SUMPRODUCT(--(MOD(COLUMN($EE8:$FZ8),4)=MOD(COLUMN($EE8),4)),$EE8:$FZ8) -> 155 | GB8: =GA8*$J8 -> 82537.5 | GC8: =SUMPRODUCT(--(MOD(COLUMN($EE8:$FZ8),4)=MOD(COLUMN($EF8),4)),$EE8:$FZ8) -> 188 | GD8: =GC8*$J8 -> 100110 | GE8: =SUMPRODUCT(--(MOD(COLUMN($EE8:$FZ8),4)=MOD(COLUMN($EG8),4)),$EE8:$FZ8) -> 0 | GF8: =GE8*$J8 -> 0 | GG8: =$KN8*10 -> 10 | GK8: =$KN8*10 -> 10 | GO8: =$KN8*15 -> 15 | GS8: =$KN8*20 -> 20 | GW8: =$KN8*20 -> 20 | HA8: =$KN8*20 -> 20 | HE8: =$KN8*20 -> 20 | HI8: =$KN8*20 -> 20 | HM8: =$KN8*20 -> 20 | HQ8: =$KN8*20 -> 20 | HU8: =$KN8*20 -> 20 | HY8: =$KN8*20 -> 20 | IC8: {=SUMPRODUCT(--(MOD(COLUMN($GG8:$IB8),4)=MOD(COLUMN($GG8),4)),$GG8:$IB8)} -> 215 | ID8: =IC8*$J8 -> 114487.5 | IE8: {=SUMPRODUCT(--(MOD(COLUMN($GG8:$IB8),4)=MOD(COLUMN($GH8),4)),$GG8:$IB8)} -> 0 | IF8: =IE8*$J8 -> 0 | IG8: {=SUMPRODUCT(--(MOD(COLUMN($GG8:$IB8),4)=MOD(COLUMN($GI8),4)),$GG8:$IB8)} -> 0 | IH8: =IG8*$J8 -> 0 | II8: =$KN8*15 -> 15 | IM8: =$KN8*15 -> 15 | IQ8: =$KN8*20 -> 20 | IU8: =$KN8*25 -> 25 | IY8: =$KN8*25 -> 25 | JC8: =$KN8*25 -> 25 | JG8: =$KN8*30 -> 30 | JK8: =$KN8*30 -> 30 | JO8: =$KN8*30 -> 30 | JS8: =$KN8*30 -> 30 | JW8: =$KN8*30 -> 30 | KA8: 30 | KE8: {=SUMPRODUCT(--(MOD(COLUMN($II8:$KD8),4)=MOD(COLUMN($II8),4)),$II8:$KD8)} -> 305 | KF8: =KE8*$J8 -> 162412.5 | KG8: {=SUMPRODUCT(--(MOD(COLUMN($II8:$KD8),4)=MOD(COLUMN($IJ8),4)),$II8:$KD8)} -> 0 | KH8: =KG8*$J8 -> 0 | KI8: {=SUMPRODUCT(--(MOD(COLUMN($II8:$KD8),4)=MOD(COLUMN($IK8),4)),$II8:$KD8)} -> 0 | KJ8: =KI8*$J8 -> 0 | KN8: 1
E9: 4 | F9: 1 | G9: 4801020640 | H9: Модулятор EBS, с PEM, без фит. | I9: =4169.1/1.2*1.048 -> 3641.014 | J9: =4169/1.2*1.048*1.05 -> 3822.973 | M9: 102 | N9: 102 | O9: 0 | Q9: 50 | R9: 32 | S9: 32 | U9: 0 | V9: 50 | W9: 50 | Y9: 40 | Z9: 50 | AA9: 50 | AC9: 40 | AD9: 40 | AE9: 0 | AG9: 40 | AH9: 25 | AI9: 25 | AK9: 40 | AL9: 25 | AM9: 25 | AO9: 40 | AP9: 0 | AQ9: 0 | AS9: 40 | AT9: 0 | AU9: 0 | AW9: 40 | AX9: 0 | AY9: 0 | BA9: 40 | BB9: 0 | BC9: 0 | BE9: 40 | BF9: =$KN9*0 -> 0 | BG9: 0 | BI9: =SUMPRODUCT(--(MOD(COLUMN($M9:$BH9),4)=MOD(COLUMN($M9),4)),$M9:$BH9) -> 512 | BJ9: =BI9*$I9 -> 1864199.2 | BK9: =SUMPRODUCT(--(MOD(COLUMN($M9:$BH9),4)=MOD(COLUMN($M9)+1,4)),$M9:$BH9) -> 324 | BL9: =BK9*$I9 -> 1179688.5 | BM9: =SUMPRODUCT(--(MOD(COLUMN($M9:$BH9),4)=MOD(COLUMN($M9)+2,4)),$M9:$BH9) -> 182 | BN9: =BM9*$I9 -> 662664.55 | BO9: =$KN9*0 -> 0 | BP9: =$KN9*0 -> 0 | BQ9: =$KN9*0 -> 0 | BR9: 0 | BT9: =$KN9*5 -> 5 | BU9: =$KN9*0 -> 0 | BV9: =$KN9*0 -> 0 | BW9: 0 | BY9: =$KN9*15 -> 15 | BZ9: =$KN9*15 -> 15 | CA9: =$KN9*0 -> 0 | CB9: 0 | CD9: =$KN9*15 -> 15 | CE9: =$KN9*15 -> 15 | CF9: =$KN9*0 -> 0 | CG9: 0 | CI9: =$KN9*15 -> 15 | CJ9: =$KN9*15 -> 15 | CK9: =$KN9*0 -> 0 | CL9: 0 | CN9: =$KN9*15 -> 15 | CO9: =$KN9*15 -> 15 | CP9: =$KN9*0 -> 0 | CQ9: 0 | CS9: =$KN9*15 -> 15 | CT9: =$KN9*15 -> 15 | CU9: =$KN9*0 -> 0 | CV9: 0 | CX9: =$KN9*15 -> 15 | CY9: =$KN9*15 -> 15 | CZ9: =$KN9*0 -> 0 | DA9: 0 | DC9: =$KN9*15 -> 15 | DD9: =$KN9*15 -> 15 | DE9: =$KN9*0 -> 0 | DF9: 0 | DH9: =$KN9*15 -> 15 | DI9: =$KN9*15 -> 15 | DJ9: =$KN9*0 -> 0 | DK9: 0 | DM9: =$KN9*15 -> 15 | DN9: =$KN9*15 -> 15 | DO9: =$KN9*0 -> 0 | DP9: 0 | DR9: =$KN9*15 -> 15 | DS9: =$KN9*15 -> 15 | DT9: =$KN9*0 -> 0 | DU9: 0 | DW9: {=SUMPRODUCT(--(MOD(COLUMN($BO9:$DV9),5)=MOD(COLUMN($BO9),5)),$BO9:$DV9)} -> 155 | DX9: =DW9*$J9 -> 592560.82 | DY9: {=SUMPRODUCT(--(MOD(COLUMN($BO9:$DV9),5)=MOD(COLUMN($BP9),5)),$BO9:$DV9)} -> 150 | DZ9: =DY9*$J9 -> 573445.95 | EA9: {=SUMPRODUCT(--(MOD(COLUMN($BO9:$DV9),5)=MOD(COLUMN($BQ9),5)),$BO9:$DV9)} -> 0 | EB9: =EA9*$J9 -> 0 | EC9: {=SUMPRODUCT(--(MOD(COLUMN($BO9:$DV9),5)=MOD(COLUMN($BR9),5)),$BO9:$DV9)} -> 0 | ED9: =EC9*$J9 -> 0 | EE9: =$KN9*8 -> 8 | EF9: 8 | EG9: 0 | EI9: =$KN9*9 -> 9 | EJ9: 50 | EK9: 0 | EM9: =$KN9*9 -> 9 | EN9: 0 | EP9: Требуется перезаключение договора. Заказы смещены на 2 месяца | EQ9: =$KN9*15 -> 15 | ER9: 2 | ES9: 1 | EU9: =$KN9*15 -> 15 | EV9: 3 | EW9: 1 | EY9: =$KN9*15 -> 15 | EZ9: 45 | FC9: =$KN9*15 -> 15 | FD9: 15 | FG9: =$KN9*15 -> 15 | FH9: 15 | FK9: =$KN9*15 -> 15 | FL9: 15 | FO9: =$KN9*15 -> 15 | FP9: 15 | FS9: =$KN9*14 -> 14 | FT9: 14 | FW9: =$KN9*10 -> 10 | FX9: 10 | GA9: =SUMPRODUCT(--(MOD(COLUMN($EE9:$FZ9),4)=MOD(COLUMN($EE9),4)),$EE9:$FZ9) -> 155 | GB9: =GA9*$J9 -> 592560.82 | GC9: =SUMPRODUCT(--(MOD(COLUMN($EE9:$FZ9),4)=MOD(COLUMN($EF9),4)),$EE9:$FZ9) -> 192 | GD9: =GC9*$J9 -> 734010.82 | GE9: =SUMPRODUCT(--(MOD(COLUMN($EE9:$FZ9),4)=MOD(COLUMN($EG9),4)),$EE9:$FZ9) -> 2 | GF9: =GE9*$J9 -> 7645.946 | GG9: =$KN9*10 -> 10 | GK9: =$KN9*10 -> 10 | GO9: =$KN9*15 -> 15 | GS9: =$KN9*20 -> 20 | GW9: =$KN9*20 -> 20 | HA9: =$KN9*20 -> 20 | HE9: =$KN9*20 -> 20 | HI9: =$KN9*20 -> 20 | HM9: =$KN9*20 -> 20 | HQ9: =$KN9*20 -> 20 | HU9: =$KN9*20 -> 20 | HY9: =$KN9*20 -> 20 | IC9: {=SUMPRODUCT(--(MOD(COLUMN($GG9:$IB9),4)=MOD(COLUMN($GG9),4)),$GG9:$IB9)} -> 215 | ID9: =IC9*$J9 -> 821939.2 | IE9: {=SUMPRODUCT(--(MOD(COLUMN($GG9:$IB9),4)=MOD(COLUMN($GH9),4)),$GG9:$IB9)} -> 0 | IF9: =IE9*$J9 -> 0 | IG9: {=SUMPRODUCT(--(MOD(COLUMN($GG9:$IB9),4)=MOD(COLUMN($GI9),4)),$GG9:$IB9)} -> 0 | IH9: =IG9*$J9 -> 0 | II9: =$KN9*15 -> 15 | IM9: =$KN9*15 -> 15 | IQ9: =$KN9*20 -> 20 | IU9: =$KN9*25 -> 25 | IY9: =$KN9*25 -> 25 | JC9: =$KN9*25 -> 25 | JG9: =$KN9*30 -> 30 | JK9: =$KN9*30 -> 30 | JO9: =$KN9*30 -> 30 | JS9: =$KN9*30 -> 30 | JW9: =$KN9*30 -> 30 | KA9: 30 | KE9: {=SUMPRODUCT(--(MOD(COLUMN($II9:$KD9),4)=MOD(COLUMN($II9),4)),$II9:$KD9)} -> 305 | KF9: =KE9*$J9 -> 1166006.8 | KG9: {=SUMPRODUCT(--(MOD(COLUMN($II9:$KD9),4)=MOD(COLUMN($IJ9),4)),$II9:$KD9)} -> 0 | KH9: =KG9*$J9 -> 0 | KI9: {=SUMPRODUCT(--(MOD(COLUMN($II9:$KD9),4)=MOD(COLUMN($IK9),4)),$II9:$KD9)} -> 0 | KJ9: =KI9*$J9 -> 0 | KN9: 1
E10: 5 | F10: 1 | G10: 4491731200 | H10: Кабель питания, 12 м | I10: =842.2/1.2 -> 701.83333 | J10: =842.2/1.2 -> 701.83333 | M10: 102 | N10: 102 | O10: 0 | Q10: 50 | R10: 32 | S10: 32 | U10: 0 | V10: 50 | W10: 50 | Y10: 40 | Z10: 50 | AA10: 50 | AC10: 40 | AD10: 40 | AE10: 0 | AG10: 40 | AH10: 25 | AI10: 25 | AK10: 40 | AL10: 25 | AM10: 25 | AO10: 40 | AP10: 0 | AQ10: 0 | AS10: 40 | AT10: 0 | AU10: 0 | AW10: 40 | AX10: 0 | AY10: 0 | BA10: 40 | BB10: 0 | BC10: 0 | BE10: 40 | BF10: =$KN10*0 -> 0 | BG10: 0 | BI10: =SUMPRODUCT(--(MOD(COLUMN($M10:$BH10),4)=MOD(COLUMN($M10),4)),$M10:$BH10) -> 512 | BJ10: =BI10*$I10 -> 359338.67 | BK10: =SUMPRODUCT(--(MOD(COLUMN($M10:$BH10),4)=MOD(COLUMN($M10)+1,4)),$M10:$BH10) -> 324 | BL10: =BK10*$I10 -> 227394 | BM10: =SUMPRODUCT(--(MOD(COLUMN($M10:$BH10),4)=MOD(COLUMN($M10)+2,4)),$M10:$BH10) -> 182 | BN10: =BM10*$I10 -> 127733.67 | BO10: =$KN10*0 -> 0 | BP10: =$KN10*0 -> 0 | BQ10: =$KN10*0 -> 0 | BR10: 0 | BT10: =$KN10*5 -> 5 | BU10: =$KN10*0 -> 0 | BV10: =$KN10*0 -> 0 | BW10: 0 | BY10: =$KN10*15 -> 15 | BZ10: =$KN10*15 -> 15 | CA10: =$KN10*0 -> 0 | CB10: 0 | CD10: =$KN10*15 -> 15 | CE10: =$KN10*15 -> 15 | CF10: =$KN10*0 -> 0 | CG10: 0 | CI10: =$KN10*15 -> 15 | CJ10: =$KN10*15 -> 15 | CK10: =$KN10*0 -> 0 | CL10: 0 | CN10: =$KN10*15 -> 15 | CO10: =$KN10*15 -> 15 | CP10: =$KN10*0 -> 0 | CQ10: 0 | CS10: =$KN10*15 -> 15 | CT10: =$KN10*15 -> 15 | CU10: =$KN10*0 -> 0 | CV10: 0 | CX10: =$KN10*15 -> 15 | CY10: =$KN10*15 -> 15 | CZ10: =$KN10*0 -> 0 | DA10: 0 | DC10: =$KN10*15 -> 15 | DD10: =$KN10*15 -> 15 | DE10: =$KN10*0 -> 0 | DF10: 0 | DH10: =$KN10*15 -> 15 | DI10: =$KN10*15 -> 15 | DJ10: =$KN10*0 -> 0 | DK10: 0 | DM10: =$KN10*15 -> 15 | DN10: =$KN10*15 -> 15 | DO10: =$KN10*0 -> 0 | DP10: 0 | DR10: =$KN10*15 -> 15 | DS10: =$KN10*15 -> 15 | DT10: =$KN10*0 -> 0 | DU10: 0 | DW10: {=SUMPRODUCT(--(MOD(COLUMN($BO10:$DV10),5)=MOD(COLUMN($BO10),5)),$BO10:$DV10)} -> 155 | DX10: =DW10*$J10 -> 108784.17 | DY10: {=SUMPRODUCT(--(MOD(COLUMN($BO10:$DV10),5)=MOD(COLUMN($BP10),5)),$BO10:$DV10)} -> 150 | DZ10: =DY10*$J10 -> 105275 | EA10: {=SUMPRODUCT(--(MOD(COLUMN($BO10:$DV10),5)=MOD(COLUMN($BQ10),5)),$BO10:$DV10)} -> 0 | EB10: =EA10*$J10 -> 0 | EC10: {=SUMPRODUCT(--(MOD(COLUMN($BO10:$DV10),5)=MOD(COLUMN($BR10),5)),$BO10:$DV10)} -> 0 | ED10: =EC10*$J10 -> 0 | EE10: =$KN10*8 -> 8 | EF10: 8 | EG10: 0 | EI10: =$KN10*9 -> 9 | EJ10: 50 | EK10: 0 | EM10: =$KN10*9 -> 9 | EN10: 0 | EQ10: =$KN10*15 -> 15 | ER10: 1 | EU10: =$KN10*15 -> 15 | EV10: 0 | EY10: =$KN10*15 -> 15 | EZ10: 45 | FC10: =$KN10*15 -> 15 | FD10: 15 | FG10: =$KN10*15 -> 15 | FH10: 15 | FK10: =$KN10*15 -> 15 | FL10: 15 | FO10: =$KN10*15 -> 15 | FP10: 15 | FS10: =$KN10*14 -> 14 | FT10: 14 | FW10: =$KN10*10 -> 10 | FX10: 10 | GA10: =SUMPRODUCT(--(MOD(COLUMN($EE10:$FZ10),4)=MOD(COLUMN($EE10),4)),$EE10:$FZ10) -> 155 | GB10: =GA10*$J10 -> 108784.17 | GC10: =SUMPRODUCT(--(MOD(COLUMN($EE10:$FZ10),4)=MOD(COLUMN($EF10),4)),$EE10:$FZ10) -> 188 | GD10: =GC10*$J10 -> 131944.67 | GE10: =SUMPRODUCT(--(MOD(COLUMN($EE10:$FZ10),4)=MOD(COLUMN($EG10),4)),$EE10:$FZ10) -> 0 | GF10: =GE10*$J10 -> 0 | GG10: =$KN10*10 -> 10 | GK10: =$KN10*10 -> 10 | GO10: =$KN10*15 -> 15 | GS10: =$KN10*20 -> 20 | GW10: =$KN10*20 -> 20 | HA10: =$KN10*20 -> 20 | HE10: =$KN10*20 -> 20 | HI10: =$KN10*20 -> 20 | HM10: =$KN10*20 -> 20 | HQ10: =$KN10*20 -> 20 | HU10: =$KN10*20 -> 20 | HY10: =$KN10*20 -> 20 | IC10: {=SUMPRODUCT(--(MOD(COLUMN($GG10:$IB10),4)=MOD(COLUMN($GG10),4)),$GG10:$IB10)} -> 215 | ID10: =IC10*$J10 -> 150894.17 | IE10: {=SUMPRODUCT(--(MOD(COLUMN($GG10:$IB10),4)=MOD(COLUMN($GH10),4)),$GG10:$IB10)} -> 0 | IF10: =IE10*$J10 -> 0 | IG10: {=SUMPRODUCT(--(MOD(COLUMN($GG10:$IB10),4)=MOD(COLUMN($GI10),4)),$GG10:$IB10)} -> 0 | IH10: =IG10*$J10 -> 0 | II10: =$KN10*15 -> 15 | IM10: =$KN10*15 -> 15 | IQ10: =$KN10*20 -> 20 | IU10: =$KN10*25 -> 25 | IY10: =$KN10*25 -> 25 | JC10: =$KN10*25 -> 25 | JG10: =$KN10*30 -> 30 | JK10: =$KN10*30 -> 30 | JO10: =$KN10*30 -> 30 | JS10: =$KN10*30 -> 30 | JW10: =$KN10*30 -> 30 | KA10: 30 | KE10: {=SUMPRODUCT(--(MOD(COLUMN($II10:$KD10),4)=MOD(COLUMN($II10),4)),$II10:$KD10)} -> 305 | KF10: =KE10*$J10 -> 214059.17 | KG10: {=SUMPRODUCT(--(MOD(COLUMN($II10:$KD10),4)=MOD(COLUMN($IJ10),4)),$II10:$KD10)} -> 0 | KH10: =KG10*$J10 -> 0 | KI10: {=SUMPRODUCT(--(MOD(COLUMN($II10:$KD10),4)=MOD(COLUMN($IK10),4)),$II10:$KD10)} -> 0 | KJ10: =KI10*$J10 -> 0 | KN10: 1
E11: 6 | F11: 1 | G11: 4497230500 | H11: Кабель датчика, 5 м | I11: =71.7/1.2 -> 59.75 | J11: =71.7/1.2 -> 59.75 | M11: 204 | N11: 204 | O11: 0 | Q11: 50 | R11: 64 | S11: 64 | U11: 0 | V11: 100 | W11: 100 | Y11: 80 | Z11: 100 | AA11: 100 | AC11: 80 | AD11: 80 | AE11: 0 | AG11: 80 | AH11: 50 | AI11: 25 | AK11: 80 | AL11: 50 | AM11: 50 | AO11: 80 | AP11: 0 | AQ11: 0 | AS11: 80 | AT11: 0 | AU11: 0 | AW11: 80 | AX11: 0 | AY11: 0 | BA11: 80 | BB11: 0 | BC11: 0 | BE11: 80 | BF11: =$KN11*0 -> 0 | BG11: 0 | BI11: =SUMPRODUCT(--(MOD(COLUMN($M11:$BH11),4)=MOD(COLUMN($M11),4)),$M11:$BH11) -> 974 | BJ11: =BI11*$I11 -> 58196.5 | BK11: =SUMPRODUCT(--(MOD(COLUMN($M11:$BH11),4)=MOD(COLUMN($M11)+1,4)),$M11:$BH11) -> 648 | BL11: =BK11*$I11 -> 38718 | BM11: =SUMPRODUCT(--(MOD(COLUMN($M11:$BH11),4)=MOD(COLUMN($M11)+2,4)),$M11:$BH11) -> 339 | BN11: =BM11*$I11 -> 20255.25 | BO11: =$KN11*0 -> 0 | BP11: =$KN11*0 -> 0 | BQ11: =$KN11*0 -> 0 | BR11: 0 | BT11: =$KN11*5 -> 10 | BU11: =$KN11*0 -> 0 | BV11: =$KN11*0 -> 0 | BW11: 0 | BY11: =$KN11*15 -> 30 | BZ11: =$KN11*15 -> 30 | CA11: =$KN11*0 -> 0 | CB11: 0 | CD11: =$KN11*15 -> 30 | CE11: =$KN11*15 -> 30 | CF11: =$KN11*0 -> 0 | CG11: 0 | CI11: =$KN11*15 -> 30 | CJ11: =$KN11*15 -> 30 | CK11: =$KN11*0 -> 0 | CL11: 0 | CN11: =$KN11*15 -> 30 | CO11: =$KN11*15 -> 30 | CP11: =$KN11*0 -> 0 | CQ11: 0 | CS11: =$KN11*15 -> 30 | CT11: =$KN11*15 -> 30 | CU11: =$KN11*0 -> 0 | CV11: 0 | CX11: =$KN11*15 -> 30 | CY11: =$KN11*15 -> 30 | CZ11: =$KN11*0 -> 0 | DA11: 0 | DC11: =$KN11*15 -> 30 | DD11: =$KN11*15 -> 30 | DE11: =$KN11*0 -> 0 | DF11: 0 | DH11: =$KN11*15 -> 30 | DI11: =$KN11*15 -> 30 | DJ11: =$KN11*0 -> 0 | DK11: 0 | DM11: =$KN11*15 -> 30 | DN11: =$KN11*15 -> 30 | DO11: =$KN11*0 -> 0 | DP11: 0 | DR11: =$KN11*15 -> 30 | DS11: =$KN11*15 -> 30 | DT11: =$KN11*0 -> 0 | DU11: 0 | DW11: {=SUMPRODUCT(--(MOD(COLUMN($BO11:$DV11),5)=MOD(COLUMN($BO11),5)),$BO11:$DV11)} -> 310 | DX11: =DW11*$J11 -> 18522.5 | DY11: {=SUMPRODUCT(--(MOD(COLUMN($BO11:$DV11),5)=MOD(COLUMN($BP11),5)),$BO11:$DV11)} -> 300 | DZ11: =DY11*$J11 -> 17925 | EA11: {=SUMPRODUCT(--(MOD(COLUMN($BO11:$DV11),5)=MOD(COLUMN($BQ11),5)),$BO11:$DV11)} -> 0 | EB11: =EA11*$J11 -> 0 | EC11: {=SUMPRODUCT(--(MOD(COLUMN($BO11:$DV11),5)=MOD(COLUMN($BR11),5)),$BO11:$DV11)} -> 0 | ED11: =EC11*$J11 -> 0 | EE11: =$KN11*8+100 -> 116 | EF11: 16 | EG11: 0 | EI11: =$KN11*9 -> 18 | EJ11: 100 | EK11: 0 | EM11: =$KN11*9 -> 18 | EN11: 0 | EQ11: =$KN11*15 -> 30 | ER11: 2 | EU11: =$KN11*15 -> 30 | EV11: 0 | EY11: =$KN11*15 -> 30 | EZ11: 90 | FC11: =$KN11*15 -> 30 | FD11: 30 | FG11: =$KN11*15 -> 30 | FH11: 30 | FK11: =$KN11*15 -> 30 | FL11: 30 | FO11: =$KN11*15 -> 30 | FP11: 30 | FS11: =$KN11*14 -> 28 | FT11: 28 | FW11: =$KN11*10 -> 20 | FX11: 20 | GA11: =SUMPRODUCT(--(MOD(COLUMN($EE11:$FZ11),4)=MOD(COLUMN($EE11),4)),$EE11:$FZ11) -> 410 | GB11: =GA11*$J11 -> 24497.5 | GC11: =SUMPRODUCT(--(MOD(COLUMN($EE11:$FZ11),4)=MOD(COLUMN($EF11),4)),$EE11:$FZ11) -> 376 | GD11: =GC11*$J11 -> 22466 | GE11: =SUMPRODUCT(--(MOD(COLUMN($EE11:$FZ11),4)=MOD(COLUMN($EG11),4)),$EE11:$FZ11) -> 0 | GF11: =GE11*$J11 -> 0 | GG11: =$KN11*10 -> 20 | GK11: =$KN11*10 -> 20 | GO11: =$KN11*15 -> 30 | GS11: =$KN11*20 -> 40 | GW11: =$KN11*20 -> 40 | HA11: =$KN11*20 -> 40 | HE11: =$KN11*20 -> 40 | HI11: =$KN11*20 -> 40 | HM11: =$KN11*20 -> 40 | HQ11: =$KN11*20 -> 40 | HU11: =$KN11*20 -> 40 | HY11: =$KN11*20 -> 40 | IC11: {=SUMPRODUCT(--(MOD(COLUMN($GG11:$IB11),4)=MOD(COLUMN($GG11),4)),$GG11:$IB11)} -> 430 | ID11: =IC11*$J11 -> 25692.5 | IE11: {=SUMPRODUCT(--(MOD(COLUMN($GG11:$IB11),4)=MOD(COLUMN($GH11),4)),$GG11:$IB11)} -> 0 | IF11: =IE11*$J11 -> 0 | IG11: {=SUMPRODUCT(--(MOD(COLUMN($GG11:$IB11),4)=MOD(COLUMN($GI11),4)),$GG11:$IB11)} -> 0 | IH11: =IG11*$J11 -> 0 | II11: =$KN11*15 -> 30 | IM11: =$KN11*15 -> 30 | IQ11: =$KN11*20 -> 40 | IU11: =$KN11*25 -> 50 | IY11: =$KN11*25 -> 50 | JC11: =$KN11*25 -> 50 | JG11: =$KN11*30 -> 60 | JK11: =$KN11*30 -> 60 | JO11: =$KN11*30 -> 60 | JS11: =$KN11*30 -> 60 | JW11: =$KN11*30 -> 60 | KA11: 30 | KE11: {=SUMPRODUCT(--(MOD(COLUMN($II11:$KD11),4)=MOD(COLUMN($II11),4)),$II11:$KD11)} -> 580 | KF11: =KE11*$J11 -> 34655 | KG11: {=SUMPRODUCT(--(MOD(COLUMN($II11:$KD11),4)=MOD(COLUMN($IJ11),4)),$II11:$KD11)} -> 0 | KH11: =KG11*$J11 -> 0 | KI11: {=SUMPRODUCT(--(MOD(COLUMN($II11:$KD11),4)=MOD(COLUMN($IK11),4)),$II11:$KD11)} -> 0 | KJ11: =KI11*$J11 -> 0 | KN11: 2
E12: 7 | F12: 1 | G12: 4640061000 | H12: Кран уровня пола, 5-ти портовый | I12: =584/1.2 -> 486.66667 | J12: =584/1.2 -> 486.66667 | M12: 102 | N12: 102 | O12: 0 | Q12: 50 | R12: 32 | S12: 32 | U12: 0 | V12: 50 | W12: 50 | Y12: 40 | Z12: 50 | AA12: 50 | AC12: 40 | AD12: 40 | AE12: 0 | AG12: 40 | AH12: 25 | AI12: 25 | AK12: 40 | AL12: 25 | AM12: 25 | AO12: 40 | AP12: 0 | AQ12: 0 | AS12: 40 | AT12: 0 | AU12: 0 | AW12: 40 | AX12: 0 | AY12: 0 | BA12: 40 | BB12: 0 | BC12: 0 | BE12: 40 | BF12: =$KN12*0 -> 0 | BG12: 0 | BI12: =SUMPRODUCT(--(MOD(COLUMN($M12:$BH12),4)=MOD(COLUMN($M12),4)),$M12:$BH12) -> 512 | BJ12: =BI12*$I12 -> 249173.33 | BK12: =SUMPRODUCT(--(MOD(COLUMN($M12:$BH12),4)=MOD(COLUMN($M12)+1,4)),$M12:$BH12) -> 324 | BL12: =BK12*$I12 -> 157680 | BM12: =SUMPRODUCT(--(MOD(COLUMN($M12:$BH12),4)=MOD(COLUMN($M12)+2,4)),$M12:$BH12) -> 182 | BN12: =BM12*$I12 -> 88573.333 | BO12: =$KN12*0 -> 0 | BP12: =$KN12*0 -> 0 | BQ12: =$KN12*0 -> 0 | BR12: 0 | BT12: =$KN12*5 -> 5 | BU12: =$KN12*0 -> 0 | BV12: =$KN12*0 -> 0 | BW12: 0 | BY12: =$KN12*15 -> 15 | BZ12: =$KN12*15 -> 15 | CA12: =$KN12*0 -> 0 | CB12: 0 | CD12: =$KN12*15 -> 15 | CE12: =$KN12*15 -> 15 | CF12: =$KN12*0 -> 0 | CG12: 0 | CI12: =$KN12*15 -> 15 | CJ12: =$KN12*15 -> 15 | CK12: =$KN12*0 -> 0 | CL12: 0 | CN12: =$KN12*15 -> 15 | CO12: =$KN12*15 -> 15 | CP12: =$KN12*0 -> 0 | CQ12: 0 | CS12: =$KN12*15 -> 15 | CT12: =$KN12*15 -> 15 | CU12: =$KN12*0 -> 0 | CV12: 0 | CX12: =$KN12*15 -> 15 | CY12: =$KN12*15 -> 15 | CZ12: =$KN12*0 -> 0 | DA12: 0 | DC12: =$KN12*15 -> 15 | DD12: =$KN12*15 -> 15 | DE12: =$KN12*0 -> 0 | DF12: 0 | DH12: =$KN12*15 -> 15 | DI12: =$KN12*15 -> 15 | DJ12: =$KN12*0 -> 0 | DK12: 0 | DM12: =$KN12*15 -> 15 | DN12: =$KN12*15 -> 15 | DO12: =$KN12*0 -> 0 | DP12: 0 | DR12: =$KN12*15 -> 15 | DS12: =$KN12*15 -> 15 | DT12: =$KN12*0 -> 0 | DU12: 0 | DW12: {=SUMPRODUCT(--(MOD(COLUMN($BO12:$DV12),5)=MOD(COLUMN($BO12),5)),$BO12:$DV12)} -> 155 | DX12: =DW12*$J12 -> 75433.333 | DY12: {=SUMPRODUCT(--(MOD(COLUMN($BO12:$DV12),5)=MOD(COLUMN($BP12),5)),$BO12:$DV12)} -> 150 | DZ12: =DY12*$J12 -> 73000 | EA12: {=SUMPRODUCT(--(MOD(COLUMN($BO12:$DV12),5)=MOD(COLUMN($BQ12),5)),$BO12:$DV12)} -> 0 | EB12: =EA12*$J12 -> 0 | EC12: {=SUMPRODUCT(--(MOD(COLUMN($BO12:$DV12),5)=MOD(COLUMN($BR12),5)),$BO12:$DV12)} -> 0 | ED12: =EC12*$J12 -> 0 | EE12: =$KN12*8 -> 8 | EF12: 8 | EG12: 0 | EI12: =$KN12*9 -> 9 | EJ12: 50 | EK12: 0 | EM12: =$KN12*9 -> 9 | EN12: 0 | EQ12: =$KN12*15 -> 15 | ER12: 1 | EU12: =$KN12*15 -> 15 | EV12: 0 | EY12: =$KN12*15 -> 15 | EZ12: 45 | FC12: =$KN12*15 -> 15 | FD12: 15 | FG12: =$KN12*15 -> 15 | FH12: 15 | FK12: =$KN12*15 -> 15 | FL12: 15 | FO12: =$KN12*15 -> 15 | FP12: 15 | FS12: =$KN12*14 -> 14 | FT12: 14 | FW12: =$KN12*10 -> 10 | FX12: 10 | GA12: =SUMPRODUCT(--(MOD(COLUMN($EE12:$FZ12),4)=MOD(COLUMN($EE12),4)),$EE12:$FZ12) -> 155 | GB12: =GA12*$J12 -> 75433.333 | GC12: =SUMPRODUCT(--(MOD(COLUMN($EE12:$FZ12),4)=MOD(COLUMN($EF12),4)),$EE12:$FZ12) -> 188 | GD12: =GC12*$J12 -> 91493.333 | GE12: =SUMPRODUCT(--(MOD(COLUMN($EE12:$FZ12),4)=MOD(COLUMN($EG12),4)),$EE12:$FZ12) -> 0 | GF12: =GE12*$J12 -> 0 | GG12: =$KN12*10 -> 10 | GK12: =$KN12*10 -> 10 | GO12: =$KN12*15 -> 15 | GS12: =$KN12*20 -> 20 | GW12: =$KN12*20 -> 20 | HA12: =$KN12*20 -> 20 | HE12: =$KN12*20 -> 20 | HI12: =$KN12*20 -> 20 | HM12: =$KN12*20 -> 20 | HQ12: =$KN12*20 -> 20 | HU12: =$KN12*20 -> 20 | HY12: =$KN12*20 -> 20 | IC12: {=SUMPRODUCT(--(MOD(COLUMN($GG12:$IB12),4)=MOD(COLUMN($GG12),4)),$GG12:$IB12)} -> 215 | ID12: =IC12*$J12 -> 104633.33 | IE12: {=SUMPRODUCT(--(MOD(COLUMN($GG12:$IB12),4)=MOD(COLUMN($GH12),4)),$GG12:$IB12)} -> 0 | IF12: =IE12*$J12 -> 0 | IG12: {=SUMPRODUCT(--(MOD(COLUMN($GG12:$IB12),4)=MOD(COLUMN($GI12),4)),$GG12:$IB12)} -> 0 | IH12: =IG12*$J12 -> 0 | II12: =$KN12*15 -> 15 | IM12: =$KN12*15 -> 15 | IQ12: =$KN12*20 -> 20 | IU12: =$KN12*25 -> 25 | IY12: =$KN12*25 -> 25 | JC12: =$KN12*25 -> 25 | JG12: =$KN12*30 -> 30 | JK12: =$KN12*30 -> 30 | JO12: =$KN12*30 -> 30 | JS12: =$KN12*30 -> 30 | JW12: =$KN12*30 -> 30 | KA12: 30 | KE12: {=SUMPRODUCT(--(MOD(COLUMN($II12:$KD12),4)=MOD(COLUMN($II12),4)),$II12:$KD12)} -> 305 | KF12: =KE12*$J12 -> 148433.33 | KG12: {=SUMPRODUCT(--(MOD(COLUMN($II12:$KD12),4)=MOD(COLUMN($IJ12),4)),$II12:$KD12)} -> 0 | KH12: =KG12*$J12 -> 0 | KI12: {=SUMPRODUCT(--(MOD(COLUMN($II12:$KD12),4)=MOD(COLUMN($IK12),4)),$II12:$KD12)} -> 0 | KJ12: =KI12*$J12 -> 0 | KN12: 1
E13: 8 | F13: 1 | G13: 4630320200 | H13: Кран ручного управления | I13: =537.4/1.2 -> 447.83333 | J13: =537.4/1.2 -> 447.83333 | M13: 102 | N13: 102 | O13: 0 | Q13: 50 | R13: 32 | S13: 32 | U13: 0 | V13: 50 | W13: 50 | Y13: 40 | Z13: 50 | AA13: 50 | AC13: 40 | AD13: 40 | AE13: 0 | AG13: 40 | AH13: 25 | AI13: 25 | AK13: 40 | AL13: 25 | AM13: 25 | AO13: 40 | AP13: 0 | AQ13: 0 | AS13: 40 | AT13: 0 | AU13: 0 | AW13: 40 | AX13: 0 | AY13: 0 | BA13: 40 | BB13: 0 | BC13: 0 | BE13: 40 | BF13: =$KN13*0 -> 0 | BG13: 0 | BI13: =SUMPRODUCT(--(MOD(COLUMN($M13:$BH13),4)=MOD(COLUMN($M13),4)),$M13:$BH13) -> 512 | BJ13: =BI13*$I13 -> 229290.67 | BK13: =SUMPRODUCT(--(MOD(COLUMN($M13:$BH13),4)=MOD(COLUMN($M13)+1,4)),$M13:$BH13) -> 324 | BL13: =BK13*$I13 -> 145098 | BM13: =SUMPRODUCT(--(MOD(COLUMN($M13:$BH13),4)=MOD(COLUMN($M13)+2,4)),$M13:$BH13) -> 182 | BN13: =BM13*$I13 -> 81505.667 | BO13: =$KN13*0 -> 0 | BP13: =$KN13*0 -> 0 | BQ13: =$KN13*0 -> 0 | BR13: 0 | BT13: =$KN13*5 -> 5 | BU13: =$KN13*0 -> 0 | BV13: =$KN13*0 -> 0 | BW13: 0 | BY13: =$KN13*15 -> 15 | BZ13: =$KN13*15 -> 15 | CA13: =$KN13*0 -> 0 | CB13: 0 | CD13: =$KN13*15 -> 15 | CE13: =$KN13*15 -> 15 | CF13: =$KN13*0 -> 0 | CG13: 0 | CI13: =$KN13*15 -> 15 | CJ13: =$KN13*15 -> 15 | CK13: =$KN13*0 -> 0 | CL13: 0 | CN13: =$KN13*15 -> 15 | CO13: =$KN13*15 -> 15 | CP13: =$KN13*0 -> 0 | CQ13: 0 | CS13: =$KN13*15 -> 15 | CT13: =$KN13*15 -> 15 | CU13: =$KN13*0 -> 0 | CV13: 0 | CX13: =$KN13*15 -> 15 | CY13: =$KN13*15 -> 15 | CZ13: =$KN13*0 -> 0 | DA13: 0 | DC13: =$KN13*15 -> 15 | DD13: =$KN13*15 -> 15 | DE13: =$KN13*0 -> 0 | DF13: 0 | DH13: =$KN13*15 -> 15 | DI13: =$KN13*15 -> 15 | DJ13: =$KN13*0 -> 0 | DK13: 0 | DM13: =$KN13*15 -> 15 | DN13: =$KN13*15 -> 15 | DO13: =$KN13*0 -> 0 | DP13: 0 | DR13: =$KN13*15 -> 15 | DS13: =$KN13*15 -> 15 | DT13: =$KN13*0 -> 0 | DU13: 0 | DW13: {=SUMPRODUCT(--(MOD(COLUMN($BO13:$DV13),5)=MOD(COLUMN($BO13),5)),$BO13:$DV13)} -> 155 | DX13: =DW13*$J13 -> 69414.167 | DY13: {=SUMPRODUCT(--(MOD(COLUMN($BO13:$DV13),5)=MOD(COLUMN($BP13),5)),$BO13:$DV13)} -> 150 | DZ13: =DY13*$J13 -> 67175 | EA13: {=SUMPRODUCT(--(MOD(COLUMN($BO13:$DV13),5)=MOD(COLUMN($BQ13),5)),$BO13:$DV13)} -> 0 | EB13: =EA13*$J13 -> 0 | EC13: {=SUMPRODUCT(--(MOD(COLUMN($BO13:$DV13),5)=MOD(COLUMN($BR13),5)),$BO13:$DV13)} -> 0 | ED13: =EC13*$J13 -> 0 | EE13: =$KN13*8 -> 8 | EF13: 8 | EG13: 0 | EI13: =$KN13*9 -> 9 | EJ13: 50 | EK13: 0 | EM13: =$KN13*9 -> 9 | EN13: 0 | EQ13: =$KN13*15 -> 15 | ER13: 1 | EU13: =$KN13*15 -> 15 | EV13: 0 | EY13: =$KN13*15 -> 15 | EZ13: 45 | FC13: =$KN13*15 -> 15 | FD13: 15 | FG13: =$KN13*15 -> 15 | FH13: 15 | FK13: =$KN13*15 -> 15 | FL13: 15 | FO13: =$KN13*15 -> 15 | FP13: 15 | FS13: =$KN13*14 -> 14 | FT13: 14 | FW13: =$KN13*10 -> 10 | FX13: 10 | GA13: =SUMPRODUCT(--(MOD(COLUMN($EE13:$FZ13),4)=MOD(COLUMN($EE13),4)),$EE13:$FZ13) -> 155 | GB13: =GA13*$J13 -> 69414.167 | GC13: =SUMPRODUCT(--(MOD(COLUMN($EE13:$FZ13),4)=MOD(COLUMN($EF13),4)),$EE13:$FZ13) -> 188 | GD13: =GC13*$J13 -> 84192.667 | GE13: =SUMPRODUCT(--(MOD(COLUMN($EE13:$FZ13),4)=MOD(COLUMN($EG13),4)),$EE13:$FZ13) -> 0 | GF13: =GE13*$J13 -> 0 | GG13: =$KN13*10 -> 10 | GK13: =$KN13*10 -> 10 | GO13: =$KN13*15 -> 15 | GS13: =$KN13*20 -> 20 | GW13: =$KN13*20 -> 20 | HA13: =$KN13*20 -> 20 | HE13: =$KN13*20 -> 20 | HI13: =$KN13*20 -> 20 | HM13: =$KN13*20 -> 20 | HQ13: =$KN13*20 -> 20 | HU13: =$KN13*20 -> 20 | HY13: =$KN13*20 -> 20 | IC13: {=SUMPRODUCT(--(MOD(COLUMN($GG13:$IB13),4)=MOD(COLUMN($GG13),4)),$GG13:$IB13)} -> 215 | ID13: =IC13*$J13 -> 96284.167 | IE13: {=SUMPRODUCT(--(MOD(COLUMN($GG13:$IB13),4)=MOD(COLUMN($GH13),4)),$GG13:$IB13)} -> 0 | IF13: =IE13*$J13 -> 0 | IG13: {=SUMPRODUCT(--(MOD(COLUMN($GG13:$IB13),4)=MOD(COLUMN($GI13),4)),$GG13:$IB13)} -> 0 | IH13: =IG13*$J13 -> 0 | II13: =$KN13*15 -> 15 | IM13: =$KN13*15 -> 15 | IQ13: =$KN13*20 -> 20 | IU13: =$KN13*25 -> 25 | IY13: =$KN13*25 -> 25 | JC13: =$KN13*25 -> 25 | JG13: =$KN13*30 -> 30 | JK13: =$KN13*30 -> 30 | JO13: =$KN13*30 -> 30 | JS13: =$KN13*30 -> 30 | JW13: =$KN13*30 -> 30 | KA13: 30 | KE13: {=SUMPRODUCT(--(MOD(COLUMN($II13:$KD13),4)=MOD(COLUMN($II13),4)),$II13:$KD13)} -> 305 | KF13: =KE13*$J13 -> 136589.17 | KG13: {=SUMPRODUCT(--(MOD(COLUMN($II13:$KD13),4)=MOD(COLUMN($IJ13),4)),$II13:$KD13)} -> 0 | KH13: =KG13*$J13 -> 0 | KI13: {=SUMPRODUCT(--(MOD(COLUMN($II13:$KD13),4)=MOD(COLUMN($IK13),4)),$II13:$KD13)} -> 0 | KJ13: =KI13*$J13 -> 0 | KN13: 1
E14: 9 | F14: 1 | G14: 4334010030 | H14: Упругий элемент | I14: =41.9/1.2 -> 34.916667 | J14: =41.9/1.2 -> 34.916667 | M14: 102 | N14: 102 | O14: 0 | Q14: 50 | R14: 32 | S14: 32 | U14: 0 | V14: 50 | W14: 50 | Y14: 40 | Z14: 50 | AA14: 50 | AC14: 40 | AD14: 40 | AE14: 0 | AG14: 40 | AH14: 25 | AI14: 25 | AK14: 40 | AL14: 25 | AM14: 25 | AO14: 40 | AP14: 0 | AQ14: 0 | AS14: 40 | AT14: 0 | AU14: 0 | AW14: 40 | AX14: 0 | AY14: 0 | BA14: 40 | BB14: 0 | BC14: 0 | BE14: 40 | BF14: =$KN14*0 -> 0 | BG14: 0 | BI14: =SUMPRODUCT(--(MOD(COLUMN($M14:$BH14),4)=MOD(COLUMN($M14),4)),$M14:$BH14) -> 512 | BJ14: =BI14*$I14 -> 17877.333 | BK14: =SUMPRODUCT(--(MOD(COLUMN($M14:$BH14),4)=MOD(COLUMN($M14)+1,4)),$M14:$BH14) -> 324 | BL14: =BK14*$I14 -> 11313 | BM14: =SUMPRODUCT(--(MOD(COLUMN($M14:$BH14),4)=MOD(COLUMN($M14)+2,4)),$M14:$BH14) -> 182 | BN14: =BM14*$I14 -> 6354.8333 | BO14: =$KN14*0 -> 0 | BP14: =$KN14*0 -> 0 | BQ14: =$KN14*0 -> 0 | BR14: 0 | BT14: =$KN14*5 -> 5 | BU14: =$KN14*0 -> 0 | BV14: =$KN14*0 -> 0 | BW14: 0 | BY14: =$KN14*15 -> 15 | BZ14: =$KN14*15 -> 15 | CA14: =$KN14*0 -> 0 | CB14: 0 | CD14: =$KN14*15 -> 15 | CE14: =$KN14*15 -> 15 | CF14: =$KN14*0 -> 0 | CG14: 0 | CI14: =$KN14*15 -> 15 | CJ14: =$KN14*15 -> 15 | CK14: =$KN14*0 -> 0 | CL14: 0 | CN14: =$KN14*15 -> 15 | CO14: =$KN14*15 -> 15 | CP14: =$KN14*0 -> 0 | CQ14: 0 | CS14: =$KN14*15 -> 15 | CT14: =$KN14*15 -> 15 | CU14: =$KN14*0 -> 0 | CV14: 0 | CX14: =$KN14*15 -> 15 | CY14: =$KN14*15 -> 15 | CZ14: =$KN14*0 -> 0 | DA14: 0 | DC14: =$KN14*15 -> 15 | DD14: =$KN14*15 -> 15 | DE14: =$KN14*0 -> 0 | DF14: 0 | DH14: =$KN14*15 -> 15 | DI14: =$KN14*15 -> 15 | DJ14: =$KN14*0 -> 0 | DK14: 0 | DM14: =$KN14*15 -> 15 | DN14: =$KN14*15 -> 15 | DO14: =$KN14*0 -> 0 | DP14: 0 | DR14: =$KN14*15 -> 15 | DS14: =$KN14*15 -> 15 | DT14: =$KN14*0 -> 0 | DU14: 0 | DW14: {=SUMPRODUCT(--(MOD(COLUMN($BO14:$DV14),5)=MOD(COLUMN($BO14),5)),$BO14:$DV14)} -> 155 | DX14: =DW14*$J14 -> 5412.0833 | DY14: {=SUMPRODUCT(--(MOD(COLUMN($BO14:$DV14),5)=MOD(COLUMN($BP14),5)),$BO14:$DV14)} -> 150 | DZ14: =DY14*$J14 -> 5237.5 | EA14: {=SUMPRODUCT(--(MOD(COLUMN($BO14:$DV14),5)=MOD(COLUMN($BQ14),5)),$BO14:$DV14)} -> 0 | EB14: =EA14*$J14 -> 0 | EC14: {=SUMPRODUCT(--(MOD(COLUMN($BO14:$DV14),5)=MOD(COLUMN($BR14),5)),$BO14:$DV14)} -> 0 | ED14: =EC14*$J14 -> 0 | EE14: =$KN14*8 -> 8 | EF14: 8 | EG14: 0 | EI14: =$KN14*9 -> 9 | EJ14: 50 | EK14: 0 | EM14: =$KN14*9 -> 9 | EN14: 0 | EQ14: =$KN14*15 -> 15 | ER14: 1 | EU14: =$KN14*15 -> 15 | EV14: 0 | EY14: =$KN14*15 -> 15 | EZ14: 45 | FC14: =$KN14*15 -> 15 | FD14: 15 | FG14: =$KN14*15 -> 15 | FH14: 15 | FK14: =$KN14*15 -> 15 | FL14: 15 | FO14: =$KN14*15 -> 15 | FP14: 15 | FS14: =$KN14*14 -> 14 | FT14: 14 | FW14: =$KN14*10 -> 10 | FX14: 10 | GA14: =SUMPRODUCT(--(MOD(COLUMN($EE14:$FZ14),4)=MOD(COLUMN($EE14),4)),$EE14:$FZ14) -> 155 | GB14: =GA14*$J14 -> 5412.0833 | GC14: =SUMPRODUCT(--(MOD(COLUMN($EE14:$FZ14),4)=MOD(COLUMN($EF14),4)),$EE14:$FZ14) -> 188 | GD14: =GC14*$J14 -> 6564.3333 | GE14: =SUMPRODUCT(--(MOD(COLUMN($EE14:$FZ14),4)=MOD(COLUMN($EG14),4)),$EE14:$FZ14) -> 0 | GF14: =GE14*$J14 -> 0 | GG14: =$KN14*10 -> 10 | GK14: =$KN14*10 -> 10 | GO14: =$KN14*15 -> 15 | GS14: =$KN14*20 -> 20 | GW14: =$KN14*20 -> 20 | HA14: =$KN14*20 -> 20 | HE14: =$KN14*20 -> 20 | HI14: =$KN14*20 -> 20 | HM14: =$KN14*20 -> 20 | HQ14: =$KN14*20 -> 20 | HU14: =$KN14*20 -> 20 | HY14: =$KN14*20 -> 20 | IC14: {=SUMPRODUCT(--(MOD(COLUMN($GG14:$IB14),4)=MOD(COLUMN($GG14),4)),$GG14:$IB14)} -> 215 | ID14: =IC14*$J14 -> 7507.0833 | IE14: {=SUMPRODUCT(--(MOD(COLUMN($GG14:$IB14),4)=MOD(COLUMN($GH14),4)),$GG14:$IB14)} -> 0 | IF14: =IE14*$J14 -> 0 | IG14: {=SUMPRODUCT(--(MOD(COLUMN($GG14:$IB14),4)=MOD(COLUMN($GI14),4)),$GG14:$IB14)} -> 0 | IH14: =IG14*$J14 -> 0 | II14: =$KN14*15 -> 15 | IM14: =$KN14*15 -> 15 | IQ14: =$KN14*20 -> 20 | IU14: =$KN14*25 -> 25 | IY14: =$KN14*25 -> 25 | JC14: =$KN14*25 -> 25 | JG14: =$KN14*30 -> 30 | JK14: =$KN14*30 -> 30 | JO14: =$KN14*30 -> 30 | JS14: =$KN14*30 -> 30 | JW14: =$KN14*30 -> 30 | KA14: 30 | KE14: {=SUMPRODUCT(--(MOD(COLUMN($II14:$KD14),4)=MOD(COLUMN($II14),4)),$II14:$KD14)} -> 305 | KF14: =KE14*$J14 -> 10649.583 | KG14: {=SUMPRODUCT(--(MOD(COLUMN($II14:$KD14),4)=MOD(COLUMN($IJ14),4)),$II14:$KD14)} -> 0 | KH14: =KG14*$J14 -> 0 | KI14: {=SUMPRODUCT(--(MOD(COLUMN($II14:$KD14),4)=MOD(COLUMN($IK14),4)),$II14:$KD14)} -> 0 | KJ14: =KI14*$J14 -> 0 | KN14: 1
E15: 10 | F15: 1 | G15: 4630840310 | H15: Клапан управления подъемом оси (LACV) | I15: =657.1/1.2 -> 547.58333 | J15: =657.1/1.2 -> 547.58333 | M15: 102 | N15: 102 | O15: 0 | Q15: 50 | R15: 32 | S15: 32 | U15: 0 | V15: 50 | W15: 50 | Y15: 40 | Z15: 50 | AA15: 50 | AC15: 40 | AD15: 40 | AE15: 0 | AG15: 40 | AH15: 25 | AI15: 25 | AK15: 40 | AL15: 25 | AM15: 25 | AO15: 40 | AP15: 0 | AQ15: 0 | AS15: 40 | AT15: 0 | AU15: 0 | AW15: 40 | AX15: 0 | AY15: 0 | BA15: 40 | BB15: 0 | BC15: 0 | BE15: 40 | BF15: =$KN15*0 -> 0 | BG15: 0 | BI15: =SUMPRODUCT(--(MOD(COLUMN($M15:$BH15),4)=MOD(COLUMN($M15),4)),$M15:$BH15) -> 512 | BJ15: =BI15*$I15 -> 280362.67 | BK15: =SUMPRODUCT(--(MOD(COLUMN($M15:$BH15),4)=MOD(COLUMN($M15)+1,4)),$M15:$BH15) -> 324 | BL15: =BK15*$I15 -> 177417 | BM15: =SUMPRODUCT(--(MOD(COLUMN($M15:$BH15),4)=MOD(COLUMN($M15)+2,4)),$M15:$BH15) -> 182 | BN15: =BM15*$I15 -> 99660.167 | BO15: =$KN15*0 -> 0 | BP15: =$KN15*0 -> 0 | BQ15: =$KN15*0 -> 0 | BR15: 0 | BT15: =$KN15*5 -> 5 | BU15: =$KN15*0 -> 0 | BV15: =$KN15*0 -> 0 | BW15: 0 | BY15: =$KN15*15 -> 15 | BZ15: =$KN15*15 -> 15 | CA15: =$KN15*0 -> 0 | CB15: 0 | CD15: =$KN15*15 -> 15 | CE15: =$KN15*15 -> 15 | CF15: =$KN15*0 -> 0 | CG15: 0 | CI15: =$KN15*15 -> 15 | CJ15: =$KN15*15 -> 15 | CK15: =$KN15*0 -> 0 | CL15: 0 | CN15: =$KN15*15 -> 15 | CO15: =$KN15*15 -> 15 | CP15: =$KN15*0 -> 0 | CQ15: 0 | CS15: =$KN15*15 -> 15 | CT15: =$KN15*15 -> 15 | CU15: =$KN15*0 -> 0 | CV15: 0 | CX15: =$KN15*15 -> 15 | CY15: =$KN15*15 -> 15 | CZ15: =$KN15*0 -> 0 | DA15: 0 | DC15: =$KN15*15 -> 15 | DD15: =$KN15*15 -> 15 | DE15: =$KN15*0 -> 0 | DF15: 0 | DH15: =$KN15*15 -> 15 | DI15: =$KN15*15 -> 15 | DJ15: =$KN15*0 -> 0 | DK15: 0 | DM15: =$KN15*15 -> 15 | DN15: =$KN15*15 -> 15 | DO15: =$KN15*0 -> 0 | DP15: 0 | DR15: =$KN15*15 -> 15 | DS15: =$KN15*15 -> 15 | DT15: =$KN15*0 -> 0 | DU15: 0 | DW15: {=SUMPRODUCT(--(MOD(COLUMN($BO15:$DV15),5)=MOD(COLUMN($BO15),5)),$BO15:$DV15)} -> 155 | DX15: =DW15*$J15 -> 84875.417 | DY15: {=SUMPRODUCT(--(MOD(COLUMN($BO15:$DV15),5)=MOD(COLUMN($BP15),5)),$BO15:$DV15)} -> 150 | DZ15: =DY15*$J15 -> 82137.5 | EA15: {=SUMPRODUCT(--(MOD(COLUMN($BO15:$DV15),5)=MOD(COLUMN($BQ15),5)),$BO15:$DV15)} -> 0 | EB15: =EA15*$J15 -> 0 | EC15: {=SUMPRODUCT(--(MOD(COLUMN($BO15:$DV15),5)=MOD(COLUMN($BR15),5)),$BO15:$DV15)} -> 0 | ED15: =EC15*$J15 -> 0 | EE15: =$KN15*8 -> 8 | EF15: 8 | EG15: 0 | EI15: =$KN15*9 -> 9 | EJ15: 50 | EK15: 0 | EM15: =$KN15*9 -> 9 | EN15: 0 | EQ15: =$KN15*15 -> 15 | ER15: 1 | EU15: =$KN15*15 -> 15 | EV15: 0 | EY15: =$KN15*15 -> 15 | EZ15: 45 | FC15: =$KN15*15 -> 15 | FD15: 15 | FG15: =$KN15*15 -> 15 | FH15: 15 | FK15: =$KN15*15 -> 15 | FL15: 15 | FO15: =$KN15*15 -> 15 | FP15: 15 | FS15: =$KN15*14 -> 14 | FT15: 14 | FW15: =$KN15*10 -> 10 | FX15: 10 | GA15: =SUMPRODUCT(--(MOD(COLUMN($EE15:$FZ15),4)=MOD(COLUMN($EE15),4)),$EE15:$FZ15) -> 155 | GB15: =GA15*$J15 -> 84875.417 | GC15: =SUMPRODUCT(--(MOD(COLUMN($EE15:$FZ15),4)=MOD(COLUMN($EF15),4)),$EE15:$FZ15) -> 188 | GD15: =GC15*$J15 -> 102945.67 | GE15: =SUMPRODUCT(--(MOD(COLUMN($EE15:$FZ15),4)=MOD(COLUMN($EG15),4)),$EE15:$FZ15) -> 0 | GF15: =GE15*$J15 -> 0 | GG15: =$KN15*10 -> 10 | GK15: =$KN15*10 -> 10 | GO15: =$KN15*15 -> 15 | GS15: =$KN15*20 -> 20 | GW15: =$KN15*20 -> 20 | HA15: =$KN15*20 -> 20 | HE15: =$KN15*20 -> 20 | HI15: =$KN15*20 -> 20 | HM15: =$KN15*20 -> 20 | HQ15: =$KN15*20 -> 20 | HU15: =$KN15*20 -> 20 | HY15: =$KN15*20 -> 20 | IC15: {=SUMPRODUCT(--(MOD(COLUMN($GG15:$IB15),4)=MOD(COLUMN($GG15),4)),$GG15:$IB15)} -> 215 | ID15: =IC15*$J15 -> 117730.42 | IE15: {=SUMPRODUCT(--(MOD(COLUMN($GG15:$IB15),4)=MOD(COLUMN($GH15),4)),$GG15:$IB15)} -> 0 | IF15: =IE15*$J15 -> 0 | IG15: {=SUMPRODUCT(--(MOD(COLUMN($GG15:$IB15),4)=MOD(COLUMN($GI15),4)),$GG15:$IB15)} -> 0 | IH15: =IG15*$J15 -> 0 | II15: =$KN15*15 -> 15 | IM15: =$KN15*15 -> 15 | IQ15: =$KN15*20 -> 20 | IU15: =$KN15*25 -> 25 | IY15: =$KN15*25 -> 25 | JC15: =$KN15*25 -> 25 | JG15: =$KN15*30 -> 30 | JK15: =$KN15*30 -> 30 | JO15: =$KN15*30 -> 30 | JS15: =$KN15*30 -> 30 | JW15: =$KN15*30 -> 30 | KA15: 30 | KE15: {=SUMPRODUCT(--(MOD(COLUMN($II15:$KD15),4)=MOD(COLUMN($II15),4)),$II15:$KD15)} -> 305 | KF15: =KE15*$J15 -> 167012.92 | KG15: {=SUMPRODUCT(--(MOD(COLUMN($II15:$KD15),4)=MOD(COLUMN($IJ15),4)),$II15:$KD15)} -> 0 | KH15: =KG15*$J15 -> 0 | KI15: {=SUMPRODUCT(--(MOD(COLUMN($II15:$KD15),4)=MOD(COLUMN($IK15),4)),$II15:$KD15)} -> 0 | KJ15: =KI15*$J15 -> 0 | KN15: 1 | KO15: LACV
E16: 11 | F16: 1 | G16: 4494430600 | H16: Кабель клапана управления подъемом оси, 6 м | I16: =164.2/1.2 -> 136.83333 | J16: =164.2/1.2 -> 136.83333 | M16: 102 | N16: 102 | O16: 0 | Q16: 50 | R16: 32 | S16: 32 | U16: 0 | V16: 50 | W16: 50 | Y16: 40 | Z16: 50 | AA16: 50 | AC16: 40 | AD16: 40 | AE16: 0 | AG16: 40 | AH16: 25 | AI16: 25 | AK16: 40 | AL16: 25 | AM16: 25 | AO16: 40 | AP16: 0 | AQ16: 0 | AS16: 40 | AT16: 0 | AU16: 0 | AW16: 40 | AX16: 0 | AY16: 0 | BA16: 40 | BB16: 0 | BC16: 0 | BE16: 40 | BF16: =$KN16*0 -> 0 | BG16: 0 | BI16: =SUMPRODUCT(--(MOD(COLUMN($M16:$BH16),4)=MOD(COLUMN($M16),4)),$M16:$BH16) -> 512 | BJ16: =BI16*$I16 -> 70058.667 | BK16: =SUMPRODUCT(--(MOD(COLUMN($M16:$BH16),4)=MOD(COLUMN($M16)+1,4)),$M16:$BH16) -> 324 | BL16: =BK16*$I16 -> 44334 | BM16: =SUMPRODUCT(--(MOD(COLUMN($M16:$BH16),4)=MOD(COLUMN($M16)+2,4)),$M16:$BH16) -> 182 | BN16: =BM16*$I16 -> 24903.667 | BO16: =$KN16*0 -> 0 | BP16: =$KN16*0 -> 0 | BQ16: =$KN16*0 -> 0 | BR16: 0 | BT16: =$KN16*5 -> 5 | BU16: =$KN16*0 -> 0 | BV16: =$KN16*0 -> 0 | BW16: 0 | BY16: =$KN16*15 -> 15 | BZ16: =$KN16*15 -> 15 | CA16: =$KN16*0 -> 0 | CB16: 0 | CD16: =$KN16*15 -> 15 | CE16: =$KN16*15 -> 15 | CF16: =$KN16*0 -> 0 | CG16: 0 | CI16: =$KN16*15 -> 15 | CJ16: =$KN16*15 -> 15 | CK16: =$KN16*0 -> 0 | CL16: 0 | CN16: =$KN16*15 -> 15 | CO16: =$KN16*15 -> 15 | CP16: =$KN16*0 -> 0 | CQ16: 0 | CS16: =$KN16*15 -> 15 | CT16: =$KN16*15 -> 15 | CU16: =$KN16*0 -> 0 | CV16: 0 | CX16: =$KN16*15 -> 15 | CY16: =$KN16*15 -> 15 | CZ16: =$KN16*0 -> 0 | DA16: 0 | DC16: =$KN16*15 -> 15 | DD16: =$KN16*15 -> 15 | DE16: =$KN16*0 -> 0 | DF16: 0 | DH16: =$KN16*15 -> 15 | DI16: =$KN16*15 -> 15 | DJ16: =$KN16*0 -> 0 | DK16: 0 | DM16: =$KN16*15 -> 15 | DN16: =$KN16*15 -> 15 | DO16: =$KN16*0 -> 0 | DP16: 0 | DR16: =$KN16*15 -> 15 | DS16: =$KN16*15 -> 15 | DT16: =$KN16*0 -> 0 | DU16: 0 | DW16: {=SUMPRODUCT(--(MOD(COLUMN($BO16:$DV16),5)=MOD(COLUMN($BO16),5)),$BO16:$DV16)} -> 155 | DX16: =DW16*$J16 -> 21209.167 | DY16: {=SUMPRODUCT(--(MOD(COLUMN($BO16:$DV16),5)=MOD(COLUMN($BP16),5)),$BO16:$DV16)} -> 150 | DZ16: =DY16*$J16 -> 20525 | EA16: {=SUMPRODUCT(--(MOD(COLUMN($BO16:$DV16),5)=MOD(COLUMN($BQ16),5)),$BO16:$DV16)} -> 0 | EB16: =EA16*$J16 -> 0 | EC16: {=SUMPRODUCT(--(MOD(COLUMN($BO16:$DV16),5)=MOD(COLUMN($BR16),5)),$BO16:$DV16)} -> 0 | ED16: =EC16*$J16 -> 0 | EE16: =$KN16*8 -> 8 | EF16: 8 | EG16: 0 | EI16: =$KN16*9 -> 9 | EJ16: 50 | EK16: 0 | EM16: =$KN16*9 -> 9 | EN16: 0 | EQ16: =$KN16*15 -> 15 | ER16: 1 | EU16: =$KN16*15 -> 15 | EV16: 0 | EY16: =$KN16*15 -> 15 | EZ16: 45 | FC16: =$KN16*15 -> 15 | FD16: 15 | FG16: =$KN16*15 -> 15 | FH16: 15 | FK16: =$KN16*15 -> 15 | FL16: 15 | FO16: =$KN16*15 -> 15 | FP16: 15 | FS16: =$KN16*14 -> 14 | FT16: 14 | FW16: =$KN16*10 -> 10 | FX16: 10 | GA16: =SUMPRODUCT(--(MOD(COLUMN($EE16:$FZ16),4)=MOD(COLUMN($EE16),4)),$EE16:$FZ16) -> 155 | GB16: =GA16*$J16 -> 21209.167 | GC16: =SUMPRODUCT(--(MOD(COLUMN($EE16:$FZ16),4)=MOD(COLUMN($EF16),4)),$EE16:$FZ16) -> 188 | GD16: =GC16*$J16 -> 25724.667 | GE16: =SUMPRODUCT(--(MOD(COLUMN($EE16:$FZ16),4)=MOD(COLUMN($EG16),4)),$EE16:$FZ16) -> 0 | GF16: =GE16*$J16 -> 0 | GG16: =$KN16*10 -> 10 | GK16: =$KN16*10 -> 10 | GO16: =$KN16*15 -> 15 | GS16: =$KN16*20 -> 20 | GW16: =$KN16*20 -> 20 | HA16: =$KN16*20 -> 20 | HE16: =$KN16*20 -> 20 | HI16: =$KN16*20 -> 20 | HM16: =$KN16*20 -> 20 | HQ16: =$KN16*20 -> 20 | HU16: =$KN16*20 -> 20 | HY16: =$KN16*20 -> 20 | IC16: {=SUMPRODUCT(--(MOD(COLUMN($GG16:$IB16),4)=MOD(COLUMN($GG16),4)),$GG16:$IB16)} -> 215 | ID16: =IC16*$J16 -> 29419.167 | IE16: {=SUMPRODUCT(--(MOD(COLUMN($GG16:$IB16),4)=MOD(COLUMN($GH16),4)),$GG16:$IB16)} -> 0 | IF16: =IE16*$J16 -> 0 | IG16: {=SUMPRODUCT(--(MOD(COLUMN($GG16:$IB16),4)=MOD(COLUMN($GI16),4)),$GG16:$IB16)} -> 0 | IH16: =IG16*$J16 -> 0 | II16: =$KN16*15 -> 15 | IM16: =$KN16*15 -> 15 | IQ16: =$KN16*20 -> 20 | IU16: =$KN16*25 -> 25 | IY16: =$KN16*25 -> 25 | JC16: =$KN16*25 -> 25 | JG16: =$KN16*30 -> 30 | JK16: =$KN16*30 -> 30 | JO16: =$KN16*30 -> 30 | JS16: =$KN16*30 -> 30 | JW16: =$KN16*30 -> 30 | KA16: 30 | KE16: {=SUMPRODUCT(--(MOD(COLUMN($II16:$KD16),4)=MOD(COLUMN($II16),4)),$II16:$KD16)} -> 305 | KF16: =KE16*$J16 -> 41734.167 | KG16: {=SUMPRODUCT(--(MOD(COLUMN($II16:$KD16),4)=MOD(COLUMN($IJ16),4)),$II16:$KD16)} -> 0 | KH16: =KG16*$J16 -> 0 | KI16: {=SUMPRODUCT(--(MOD(COLUMN($II16:$KD16),4)=MOD(COLUMN($IK16),4)),$II16:$KD16)} -> 0 | KJ16: =KI16*$J16 -> 0 | KN16: 1
E17: 12 | F17: 1 | G17: 4492731200 | H17: Кабель питания для прицепа, 12 м | I17: 1037 | J17: 1037 | EH17: Новый артикул | EJ17: 1 | EK17: 0 | EN17: 1 | EO17: 1 | EP17: Заказ февраля перенесена на март
E18: 13 | F18: 1 | G18: 4802070600 | H18: Ускорительный клапан EBS | I18: 1056 | J18: 1056 | EJ18: 1 | EK18: 0 | EN18: 1 | EO18: 1
E19: 14 | F19: 1 | G19: 4494301200 | H19: Кабель клапана ускорительного TEBS, 12 м | I19: 811 | J19: 811 | EJ19: 1 | EK19: 0 | EN19: 1 | EO19: 1
E20: 15 | F20: 1 | G20: 4497230800 | H20: Кабель датчика АБС, 8 м | I20: 210 | J20: 210 | EJ20: 2 | EK20: 0 | EN20: 2 | EO20: 2
E21: 16 | F21: 1 | G21: 4497230500 | H21: Кабель датчика АБС, 5 м | I21: 162 | J21: 162 | EJ21: 2 | EK21: 0 | EN21: 2 | EO21: 2
E22: 17 | F22: 1 | G22: 4640060020 | H22: Кран уровня пола | I22: 325 | J22: 325 | EJ22: 2 | EK22: 0 | EN22: 2 | EO22: 2
E23: 18 | F23: 2 | G23: 9522010010 | H23: Головка соединительная, с фильтром, управляющая | J23: =138.5/1.2 -> 115.41667 | BF23: =$KN23*0 -> 0 | DK23: 0 | DO23: =$KN23*0 -> 0 | DP23: 0 | DQ23: Новая номенклатура | DU23: 0 | DW23: {=SUMPRODUCT(--(MOD(COLUMN($BO23:$DV23),5)=MOD(COLUMN($BO23),5)),$BO23:$DV23)} -> 0 | DX23: =DW23*$J23 -> 0 | DY23: {=SUMPRODUCT(--(MOD(COLUMN($BO23:$DV23),5)=MOD(COLUMN($BP23),5)),$BO23:$DV23)} -> 0 | DZ23: =DY23*$J23 -> 0 | EA23: {=SUMPRODUCT(--(MOD(COLUMN($BO23:$DV23),5)=MOD(COLUMN($BQ23),5)),$BO23:$DV23)} -> 0 | EB23: =EA23*$J23 -> 0 | EC23: {=SUMPRODUCT(--(MOD(COLUMN($BO23:$DV23),5)=MOD(COLUMN($BR23),5)),$BO23:$DV23)} -> 0 | ED23: =EC23*$J23 -> 0 | EE23: 50 | EF23: 0 | EG23: 0 | EV23: 0 | GA23: =SUMPRODUCT(--(MOD(COLUMN($EE23:$FZ23),4)=MOD(COLUMN($EE23),4)),$EE23:$FZ23) -> 50 | GB23: =GA23*$J23 -> 5770.8333 | GC23: =SUMPRODUCT(--(MOD(COLUMN($EE23:$FZ23),4)=MOD(COLUMN($EF23),4)),$EE23:$FZ23) -> 0 | GD23: =GC23*$J23 -> 0 | GE23: =SUMPRODUCT(--(MOD(COLUMN($EE23:$FZ23),4)=MOD(COLUMN($EG23),4)),$EE23:$FZ23) -> 0 | GF23: =GE23*$J23 -> 0 | IC23: {=SUMPRODUCT(--(MOD(COLUMN($GG23:$IB23),4)=MOD(COLUMN($GG23),4)),$GG23:$IB23)} -> 0 | ID23: =IC23*$J23 -> 0 | IE23: {=SUMPRODUCT(--(MOD(COLUMN($GG23:$IB23),4)=MOD(COLUMN($GH23),4)),$GG23:$IB23)} -> 0 | IF23: =IE23*$J23 -> 0 | IG23: {=SUMPRODUCT(--(MOD(COLUMN($GG23:$IB23),4)=MOD(COLUMN($GI23),4)),$GG23:$IB23)} -> 0 | IH23: =IG23*$J23 -> 0 | KE23: {=SUMPRODUCT(--(MOD(COLUMN($II23:$KD23),4)=MOD(COLUMN($II23),4)),$II23:$KD23)} -> 0 | KF23: =KE23*$J23 -> 0 | KG23: {=SUMPRODUCT(--(MOD(COLUMN($II23:$KD23),4)=MOD(COLUMN($IJ23),4)),$II23:$KD23)} -> 0 | KH23: =KG23*$J23 -> 0 | KI23: {=SUMPRODUCT(--(MOD(COLUMN($II23:$KD23),4)=MOD(COLUMN($IK23),4)),$II23:$KD23)} -> 0 | KJ23: =KI23*$J23 -> 0 | KN23: 1 | KO23: Wabco 4s/3m 15m
E24: 19 | F24: 2 | G24: 9522010020 | H24: Головка соединительная, с фильтром, питающая | J24: =138.5/1.2 -> 115.41667 | BF24: =$KN24*0 -> 0 | DK24: 0 | DO24: =$KN24*0 -> 0 | DP24: 0 | DU24: 0 | DW24: {=SUMPRODUCT(--(MOD(COLUMN($BO24:$DV24),5)=MOD(COLUMN($BO24),5)),$BO24:$DV24)} -> 0 | DX24: =DW24*$J24 -> 0 | DY24: {=SUMPRODUCT(--(MOD(COLUMN($BO24:$DV24),5)=MOD(COLUMN($BP24),5)),$BO24:$DV24)} -> 0 | DZ24: =DY24*$J24 -> 0 | EA24: {=SUMPRODUCT(--(MOD(COLUMN($BO24:$DV24),5)=MOD(COLUMN($BQ24),5)),$BO24:$DV24)} -> 0 | EB24: =EA24*$J24 -> 0 | EC24: {=SUMPRODUCT(--(MOD(COLUMN($BO24:$DV24),5)=MOD(COLUMN($BR24),5)),$BO24:$DV24)} -> 0 | ED24: =EC24*$J24 -> 0 | EE24: 50 | EF24: 0 | EG24: 0 | EV24: 0 | GA24: =SUMPRODUCT(--(MOD(COLUMN($EE24:$FZ24),4)=MOD(COLUMN($EE24),4)),$EE24:$FZ24) -> 50 | GB24: =GA24*$J24 -> 5770.8333 | GC24: =SUMPRODUCT(--(MOD(COLUMN($EE24:$FZ24),4)=MOD(COLUMN($EF24),4)),$EE24:$FZ24) -> 0 | GD24: =GC24*$J24 -> 0 | GE24: =SUMPRODUCT(--(MOD(COLUMN($EE24:$FZ24),4)=MOD(COLUMN($EG24),4)),$EE24:$FZ24) -> 0 | GF24: =GE24*$J24 -> 0 | IC24: {=SUMPRODUCT(--(MOD(COLUMN($GG24:$IB24),4)=MOD(COLUMN($GG24),4)),$GG24:$IB24)} -> 0 | ID24: =IC24*$J24 -> 0 | IE24: {=SUMPRODUCT(--(MOD(COLUMN($GG24:$IB24),4)=MOD(COLUMN($GH24),4)),$GG24:$IB24)} -> 0 | IF24: =IE24*$J24 -> 0 | IG24: {=SUMPRODUCT(--(MOD(COLUMN($GG24:$IB24),4)=MOD(COLUMN($GI24),4)),$GG24:$IB24)} -> 0 | IH24: =IG24*$J24 -> 0 | KE24: {=SUMPRODUCT(--(MOD(COLUMN($II24:$KD24),4)=MOD(COLUMN($II24),4)),$II24:$KD24)} -> 0 | KF24: =KE24*$J24 -> 0 | KG24: {=SUMPRODUCT(--(MOD(COLUMN($II24:$KD24),4)=MOD(COLUMN($IJ24),4)),$II24:$KD24)} -> 0 | KH24: =KG24*$J24 -> 0 | KI24: {=SUMPRODUCT(--(MOD(COLUMN($II24:$KD24),4)=MOD(COLUMN($IK24),4)),$II24:$KD24)} -> 0 | KJ24: =KI24*$J24 -> 0 | KN24: 1
E25: 20 | F25: 2 | G25: 9630010510 | H25: Клапан растормаживания, сдвоенный | J25: =451/1.2 -> 375.83333 | BF25: =$KN25*0 -> 0 | DK25: 0 | DO25: =$KN25*0 -> 0 | DP25: 0 | DU25: 0 | DW25: {=SUMPRODUCT(--(MOD(COLUMN($BO25:$DV25),5)=MOD(COLUMN($BO25),5)),$BO25:$DV25)} -> 0 | DX25: =DW25*$J25 -> 0 | DY25: {=SUMPRODUCT(--(MOD(COLUMN($BO25:$DV25),5)=MOD(COLUMN($BP25),5)),$BO25:$DV25)} -> 0 | DZ25: =DY25*$J25 -> 0 | EA25: {=SUMPRODUCT(--(MOD(COLUMN($BO25:$DV25),5)=MOD(COLUMN($BQ25),5)),$BO25:$DV25)} -> 0 | EB25: =EA25*$J25 -> 0 | EC25: {=SUMPRODUCT(--(MOD(COLUMN($BO25:$DV25),5)=MOD(COLUMN($BR25),5)),$BO25:$DV25)} -> 0 | ED25: =EC25*$J25 -> 0 | EE25: 50 | EF25: 0 | EG25: 0 | EV25: 0 | GA25: =SUMPRODUCT(--(MOD(COLUMN($EE25:$FZ25),4)=MOD(COLUMN($EE25),4)),$EE25:$FZ25) -> 50 | GB25: =GA25*$J25 -> 18791.667 | GC25: =SUMPRODUCT(--(MOD(COLUMN($EE25:$FZ25),4)=MOD(COLUMN($EF25),4)),$EE25:$FZ25) -> 0 | GD25: =GC25*$J25 -> 0 | GE25: =SUMPRODUCT(--(MOD(COLUMN($EE25:$FZ25),4)=MOD(COLUMN($EG25),4)),$EE25:$FZ25) -> 0 | GF25: =GE25*$J25 -> 0 | IC25: {=SUMPRODUCT(--(MOD(COLUMN($GG25:$IB25),4)=MOD(COLUMN($GG25),4)),$GG25:$IB25)} -> 0 | ID25: =IC25*$J25 -> 0 | IE25: {=SUMPRODUCT(--(MOD(COLUMN($GG25:$IB25),4)=MOD(COLUMN($GH25),4)),$GG25:$IB25)} -> 0 | IF25: =IE25*$J25 -> 0 | IG25: {=SUMPRODUCT(--(MOD(COLUMN($GG25:$IB25),4)=MOD(COLUMN($GI25),4)),$GG25:$IB25)} -> 0 | IH25: =IG25*$J25 -> 0 | KE25: {=SUMPRODUCT(--(MOD(COLUMN($II25:$KD25),4)=MOD(COLUMN($II25),4)),$II25:$KD25)} -> 0 | KF25: =KE25*$J25 -> 0 | KG25: {=SUMPRODUCT(--(MOD(COLUMN($II25:$KD25),4)=MOD(COLUMN($IJ25),4)),$II25:$KD25)} -> 0 | KH25: =KG25*$J25 -> 0 | KI25: {=SUMPRODUCT(--(MOD(COLUMN($II25:$KD25),4)=MOD(COLUMN($IK25),4)),$II25:$KD25)} -> 0 | KJ25: =KI25*$J25 -> 0 | KN25: 1
E26: 21 | F26: 2 | G26: 9710020400 | H26: Воздухораспределитель | J26: =587.5/1.2 -> 489.58333 | BF26: =$KN26*0 -> 0 | DK26: 0 | DO26: =$KN26*0 -> 0 | DP26: 0 | DU26: 0 | DW26: {=SUMPRODUCT(--(MOD(COLUMN($BO26:$DV26),5)=MOD(COLUMN($BO26),5)),$BO26:$DV26)} -> 0 | DX26: =DW26*$J26 -> 0 | DY26: {=SUMPRODUCT(--(MOD(COLUMN($BO26:$DV26),5)=MOD(COLUMN($BP26),5)),$BO26:$DV26)} -> 0 | DZ26: =DY26*$J26 -> 0 | EA26: {=SUMPRODUCT(--(MOD(COLUMN($BO26:$DV26),5)=MOD(COLUMN($BQ26),5)),$BO26:$DV26)} -> 0 | EB26: =EA26*$J26 -> 0 | EC26: {=SUMPRODUCT(--(MOD(COLUMN($BO26:$DV26),5)=MOD(COLUMN($BR26),5)),$BO26:$DV26)} -> 0 | ED26: =EC26*$J26 -> 0 | EE26: 50 | EF26: 0 | EG26: 0 | EV26: 0 | GA26: =SUMPRODUCT(--(MOD(COLUMN($EE26:$FZ26),4)=MOD(COLUMN($EE26),4)),$EE26:$FZ26) -> 50 | GB26: =GA26*$J26 -> 24479.167 | GC26: =SUMPRODUCT(--(MOD(COLUMN($EE26:$FZ26),4)=MOD(COLUMN($EF26),4)),$EE26:$FZ26) -> 0 | GD26: =GC26*$J26 -> 0 | GE26: =SUMPRODUCT(--(MOD(COLUMN($EE26:$FZ26),4)=MOD(COLUMN($EG26),4)),$EE26:$FZ26) -> 0 | GF26: =GE26*$J26 -> 0 | IC26: {=SUMPRODUCT(--(MOD(COLUMN($GG26:$IB26),4)=MOD(COLUMN($GG26),4)),$GG26:$IB26)} -> 0 | ID26: =IC26*$J26 -> 0 | IE26: {=SUMPRODUCT(--(MOD(COLUMN($GG26:$IB26),4)=MOD(COLUMN($GH26),4)),$GG26:$IB26)} -> 0 | IF26: =IE26*$J26 -> 0 | IG26: {=SUMPRODUCT(--(MOD(COLUMN($GG26:$IB26),4)=MOD(COLUMN($GI26),4)),$GG26:$IB26)} -> 0 | IH26: =IG26*$J26 -> 0 | KE26: {=SUMPRODUCT(--(MOD(COLUMN($II26:$KD26),4)=MOD(COLUMN($II26),4)),$II26:$KD26)} -> 0 | KF26: =KE26*$J26 -> 0 | KG26: {=SUMPRODUCT(--(MOD(COLUMN($II26:$KD26),4)=MOD(COLUMN($IJ26),4)),$II26:$KD26)} -> 0 | KH26: =KG26*$J26 -> 0 | KI26: {=SUMPRODUCT(--(MOD(COLUMN($II26:$KD26),4)=MOD(COLUMN($IK26),4)),$II26:$KD26)} -> 0 | KJ26: =KI26*$J26 -> 0 | KN26: 1
E27: 22 | F27: 2 | G27: 4801020640 | H27: Блок TEBS-E, 4S3M Premium | J27: =8797.5/1.2 -> 7331.25 | BF27: =$KN27*0 -> 0 | DK27: 0 | DO27: =$KN27*0 -> 0 | DP27: 0 | DU27: 0 | DW27: {=SUMPRODUCT(--(MOD(COLUMN($BO27:$DV27),5)=MOD(COLUMN($BO27),5)),$BO27:$DV27)} -> 0 | DX27: =DW27*$J27 -> 0 | DY27: {=SUMPRODUCT(--(MOD(COLUMN($BO27:$DV27),5)=MOD(COLUMN($BP27),5)),$BO27:$DV27)} -> 0 | DZ27: =DY27*$J27 -> 0 | EA27: {=SUMPRODUCT(--(MOD(COLUMN($BO27:$DV27),5)=MOD(COLUMN($BQ27),5)),$BO27:$DV27)} -> 0 | EB27: =EA27*$J27 -> 0 | EC27: {=SUMPRODUCT(--(MOD(COLUMN($BO27:$DV27),5)=MOD(COLUMN($BR27),5)),$BO27:$DV27)} -> 0 | ED27: =EC27*$J27 -> 0 | EE27: 50 | EF27: 0 | EG27: 0 | EV27: 0 | GA27: =SUMPRODUCT(--(MOD(COLUMN($EE27:$FZ27),4)=MOD(COLUMN($EE27),4)),$EE27:$FZ27) -> 50 | GB27: =GA27*$J27 -> 366562.5 | GC27: =SUMPRODUCT(--(MOD(COLUMN($EE27:$FZ27),4)=MOD(COLUMN($EF27),4)),$EE27:$FZ27) -> 0 | GD27: =GC27*$J27 -> 0 | GE27: =SUMPRODUCT(--(MOD(COLUMN($EE27:$FZ27),4)=MOD(COLUMN($EG27),4)),$EE27:$FZ27) -> 0 | GF27: =GE27*$J27 -> 0 | IC27: {=SUMPRODUCT(--(MOD(COLUMN($GG27:$IB27),4)=MOD(COLUMN($GG27),4)),$GG27:$IB27)} -> 0 | ID27: =IC27*$J27 -> 0 | IE27: {=SUMPRODUCT(--(MOD(COLUMN($GG27:$IB27),4)=MOD(COLUMN($GH27),4)),$GG27:$IB27)} -> 0 | IF27: =IE27*$J27 -> 0 | IG27: {=SUMPRODUCT(--(MOD(COLUMN($GG27:$IB27),4)=MOD(COLUMN($GI27),4)),$GG27:$IB27)} -> 0 | IH27: =IG27*$J27 -> 0 | KE27: {=SUMPRODUCT(--(MOD(COLUMN($II27:$KD27),4)=MOD(COLUMN($II27),4)),$II27:$KD27)} -> 0 | KF27: =KE27*$J27 -> 0 | KG27: {=SUMPRODUCT(--(MOD(COLUMN($II27:$KD27),4)=MOD(COLUMN($IJ27),4)),$II27:$KD27)} -> 0 | KH27: =KG27*$J27 -> 0 | KI27: {=SUMPRODUCT(--(MOD(COLUMN($II27:$KD27),4)=MOD(COLUMN($IK27),4)),$II27:$KD27)} -> 0 | KJ27: =KI27*$J27 -> 0 | KN27: 1
E28: 23 | F28: 1 | G28: 4491731500 | H28: Кабель питания для прицепа, 15 м | J28: =1204.8/1.2 -> 1004 | BF28: =$KN28*0 -> 0 | DK28: 0 | DO28: =$KN28*0 -> 0 | DP28: 0 | DU28: 0 | DW28: {=SUMPRODUCT(--(MOD(COLUMN($BO28:$DV28),5)=MOD(COLUMN($BO28),5)),$BO28:$DV28)} -> 0 | DX28: =DW28*$J28 -> 0 | DY28: {=SUMPRODUCT(--(MOD(COLUMN($BO28:$DV28),5)=MOD(COLUMN($BP28),5)),$BO28:$DV28)} -> 0 | DZ28: =DY28*$J28 -> 0 | EA28: {=SUMPRODUCT(--(MOD(COLUMN($BO28:$DV28),5)=MOD(COLUMN($BQ28),5)),$BO28:$DV28)} -> 0 | EB28: =EA28*$J28 -> 0 | EC28: {=SUMPRODUCT(--(MOD(COLUMN($BO28:$DV28),5)=MOD(COLUMN($BR28),5)),$BO28:$DV28)} -> 0 | ED28: =EC28*$J28 -> 0 | EE28: 50 | EF28: 0 | EG28: 0 | EV28: 0 | GA28: =SUMPRODUCT(--(MOD(COLUMN($EE28:$FZ28),4)=MOD(COLUMN($EE28),4)),$EE28:$FZ28) -> 50 | GB28: =GA28*$J28 -> 50200 | GC28: =SUMPRODUCT(--(MOD(COLUMN($EE28:$FZ28),4)=MOD(COLUMN($EF28),4)),$EE28:$FZ28) -> 0 | GD28: =GC28*$J28 -> 0 | GE28: =SUMPRODUCT(--(MOD(COLUMN($EE28:$FZ28),4)=MOD(COLUMN($EG28),4)),$EE28:$FZ28) -> 0 | GF28: =GE28*$J28 -> 0 | IC28: {=SUMPRODUCT(--(MOD(COLUMN($GG28:$IB28),4)=MOD(COLUMN($GG28),4)),$GG28:$IB28)} -> 0 | ID28: =IC28*$J28 -> 0 | IE28: {=SUMPRODUCT(--(MOD(COLUMN($GG28:$IB28),4)=MOD(COLUMN($GH28),4)),$GG28:$IB28)} -> 0 | IF28: =IE28*$J28 -> 0 | IG28: {=SUMPRODUCT(--(MOD(COLUMN($GG28:$IB28),4)=MOD(COLUMN($GI28),4)),$GG28:$IB28)} -> 0 | IH28: =IG28*$J28 -> 0 | KE28: {=SUMPRODUCT(--(MOD(COLUMN($II28:$KD28),4)=MOD(COLUMN($II28),4)),$II28:$KD28)} -> 0 | KF28: =KE28*$J28 -> 0 | KG28: {=SUMPRODUCT(--(MOD(COLUMN($II28:$KD28),4)=MOD(COLUMN($IJ28),4)),$II28:$KD28)} -> 0 | KH28: =KG28*$J28 -> 0 | KI28: {=SUMPRODUCT(--(MOD(COLUMN($II28:$KD28),4)=MOD(COLUMN($IK28),4)),$II28:$KD28)} -> 0 | KJ28: =KI28*$J28 -> 0 | KN28: 1
E29: 24 | F29: 2 | G29: 4802070010 | H29: Модулятор EBS | J29: =4618.8/1.2 -> 3849 | BF29: =$KN29*0 -> 0 | DK29: 0 | DO29: =$KN29*0 -> 0 | DP29: 0 | DU29: 0 | DW29: {=SUMPRODUCT(--(MOD(COLUMN($BO29:$DV29),5)=MOD(COLUMN($BO29),5)),$BO29:$DV29)} -> 0 | DX29: =DW29*$J29 -> 0 | DY29: {=SUMPRODUCT(--(MOD(COLUMN($BO29:$DV29),5)=MOD(COLUMN($BP29),5)),$BO29:$DV29)} -> 0 | DZ29: =DY29*$J29 -> 0 | EA29: {=SUMPRODUCT(--(MOD(COLUMN($BO29:$DV29),5)=MOD(COLUMN($BQ29),5)),$BO29:$DV29)} -> 0 | EB29: =EA29*$J29 -> 0 | EC29: {=SUMPRODUCT(--(MOD(COLUMN($BO29:$DV29),5)=MOD(COLUMN($BR29),5)),$BO29:$DV29)} -> 0 | ED29: =EC29*$J29 -> 0 | EE29: 50 | EF29: 0 | EG29: 0 | EV29: 0 | GA29: =SUMPRODUCT(--(MOD(COLUMN($EE29:$FZ29),4)=MOD(COLUMN($EE29),4)),$EE29:$FZ29) -> 50 | GB29: =GA29*$J29 -> 192450 | GC29: =SUMPRODUCT(--(MOD(COLUMN($EE29:$FZ29),4)=MOD(COLUMN($EF29),4)),$EE29:$FZ29) -> 0 | GD29: =GC29*$J29 -> 0 | GE29: =SUMPRODUCT(--(MOD(COLUMN($EE29:$FZ29),4)=MOD(COLUMN($EG29),4)),$EE29:$FZ29) -> 0 | GF29: =GE29*$J29 -> 0 | IC29: {=SUMPRODUCT(--(MOD(COLUMN($GG29:$IB29),4)=MOD(COLUMN($GG29),4)),$GG29:$IB29)} -> 0 | ID29: =IC29*$J29 -> 0 | IE29: {=SUMPRODUCT(--(MOD(COLUMN($GG29:$IB29),4)=MOD(COLUMN($GH29),4)),$GG29:$IB29)} -> 0 | IF29: =IE29*$J29 -> 0 | IG29: {=SUMPRODUCT(--(MOD(COLUMN($GG29:$IB29),4)=MOD(COLUMN($GI29),4)),$GG29:$IB29)} -> 0 | IH29: =IG29*$J29 -> 0 | KE29: {=SUMPRODUCT(--(MOD(COLUMN($II29:$KD29),4)=MOD(COLUMN($II29),4)),$II29:$KD29)} -> 0 | KF29: =KE29*$J29 -> 0 | KG29: {=SUMPRODUCT(--(MOD(COLUMN($II29:$KD29),4)=MOD(COLUMN($IJ29),4)),$II29:$KD29)} -> 0 | KH29: =KG29*$J29 -> 0 | KI29: {=SUMPRODUCT(--(MOD(COLUMN($II29:$KD29),4)=MOD(COLUMN($IK29),4)),$II29:$KD29)} -> 0 | KJ29: =KI29*$J29 -> 0 | KN29: 1
E30: 25 | F30: 2 | G30: 4494290800 | H30: Кабель модулятора EBS, 8 м | J30: =1568.4/1.2 -> 1307 | BF30: =$KN30*0 -> 0 | DK30: 0 | DO30: =$KN30*0 -> 0 | DP30: 0 | DU30: 0 | DW30: {=SUMPRODUCT(--(MOD(COLUMN($BO30:$DV30),5)=MOD(COLUMN($BO30),5)),$BO30:$DV30)} -> 0 | DX30: =DW30*$J30 -> 0 | DY30: {=SUMPRODUCT(--(MOD(COLUMN($BO30:$DV30),5)=MOD(COLUMN($BP30),5)),$BO30:$DV30)} -> 0 | DZ30: =DY30*$J30 -> 0 | EA30: {=SUMPRODUCT(--(MOD(COLUMN($BO30:$DV30),5)=MOD(COLUMN($BQ30),5)),$BO30:$DV30)} -> 0 | EB30: =EA30*$J30 -> 0 | EC30: {=SUMPRODUCT(--(MOD(COLUMN($BO30:$DV30),5)=MOD(COLUMN($BR30),5)),$BO30:$DV30)} -> 0 | ED30: =EC30*$J30 -> 0 | EE30: 50 | EF30: 0 | EG30: 0 | EV30: 0 | GA30: =SUMPRODUCT(--(MOD(COLUMN($EE30:$FZ30),4)=MOD(COLUMN($EE30),4)),$EE30:$FZ30) -> 50 | GB30: =GA30*$J30 -> 65350 | GC30: =SUMPRODUCT(--(MOD(COLUMN($EE30:$FZ30),4)=MOD(COLUMN($EF30),4)),$EE30:$FZ30) -> 0 | GD30: =GC30*$J30 -> 0 | GE30: =SUMPRODUCT(--(MOD(COLUMN($EE30:$FZ30),4)=MOD(COLUMN($EG30),4)),$EE30:$FZ30) -> 0 | GF30: =GE30*$J30 -> 0 | IC30: {=SUMPRODUCT(--(MOD(COLUMN($GG30:$IB30),4)=MOD(COLUMN($GG30),4)),$GG30:$IB30)} -> 0 | ID30: =IC30*$J30 -> 0 | IE30: {=SUMPRODUCT(--(MOD(COLUMN($GG30:$IB30),4)=MOD(COLUMN($GH30),4)),$GG30:$IB30)} -> 0 | IF30: =IE30*$J30 -> 0 | IG30: {=SUMPRODUCT(--(MOD(COLUMN($GG30:$IB30),4)=MOD(COLUMN($GI30),4)),$GG30:$IB30)} -> 0 | IH30: =IG30*$J30 -> 0 | KE30: {=SUMPRODUCT(--(MOD(COLUMN($II30:$KD30),4)=MOD(COLUMN($II30),4)),$II30:$KD30)} -> 0 | KF30: =KE30*$J30 -> 0 | KG30: {=SUMPRODUCT(--(MOD(COLUMN($II30:$KD30),4)=MOD(COLUMN($IJ30),4)),$II30:$KD30)} -> 0 | KH30: =KG30*$J30 -> 0 | KI30: {=SUMPRODUCT(--(MOD(COLUMN($II30:$KD30),4)=MOD(COLUMN($IK30),4)),$II30:$KD30)} -> 0 | KJ30: =KI30*$J30 -> 0 | KN30: 1
E31: 26 | F31: 2 | G31: 4640061000 | H31: Кран уровня пола | J31: =973.1/1.2 -> 810.91667 | BF31: =$KN31*0 -> 0 | DK31: 0 | DO31: =$KN31*0 -> 0 | DP31: 0 | DU31: 0 | DW31: {=SUMPRODUCT(--(MOD(COLUMN($BO31:$DV31),5)=MOD(COLUMN($BO31),5)),$BO31:$DV31)} -> 0 | DX31: =DW31*$J31 -> 0 | DY31: {=SUMPRODUCT(--(MOD(COLUMN($BO31:$DV31),5)=MOD(COLUMN($BP31),5)),$BO31:$DV31)} -> 0 | DZ31: =DY31*$J31 -> 0 | EA31: {=SUMPRODUCT(--(MOD(COLUMN($BO31:$DV31),5)=MOD(COLUMN($BQ31),5)),$BO31:$DV31)} -> 0 | EB31: =EA31*$J31 -> 0 | EC31: {=SUMPRODUCT(--(MOD(COLUMN($BO31:$DV31),5)=MOD(COLUMN($BR31),5)),$BO31:$DV31)} -> 0 | ED31: =EC31*$J31 -> 0 | EE31: 50 | EF31: 0 | EG31: 0 | EV31: 0 | GA31: =SUMPRODUCT(--(MOD(COLUMN($EE31:$FZ31),4)=MOD(COLUMN($EE31),4)),$EE31:$FZ31) -> 50 | GB31: =GA31*$J31 -> 40545.833 | GC31: =SUMPRODUCT(--(MOD(COLUMN($EE31:$FZ31),4)=MOD(COLUMN($EF31),4)),$EE31:$FZ31) -> 0 | GD31: =GC31*$J31 -> 0 | GE31: =SUMPRODUCT(--(MOD(COLUMN($EE31:$FZ31),4)=MOD(COLUMN($EG31),4)),$EE31:$FZ31) -> 0 | GF31: =GE31*$J31 -> 0 | IC31: {=SUMPRODUCT(--(MOD(COLUMN($GG31:$IB31),4)=MOD(COLUMN($GG31),4)),$GG31:$IB31)} -> 0 | ID31: =IC31*$J31 -> 0 | IE31: {=SUMPRODUCT(--(MOD(COLUMN($GG31:$IB31),4)=MOD(COLUMN($GH31),4)),$GG31:$IB31)} -> 0 | IF31: =IE31*$J31 -> 0 | IG31: {=SUMPRODUCT(--(MOD(COLUMN($GG31:$IB31),4)=MOD(COLUMN($GI31),4)),$GG31:$IB31)} -> 0 | IH31: =IG31*$J31 -> 0 | KE31: {=SUMPRODUCT(--(MOD(COLUMN($II31:$KD31),4)=MOD(COLUMN($II31),4)),$II31:$KD31)} -> 0 | KF31: =KE31*$J31 -> 0 | KG31: {=SUMPRODUCT(--(MOD(COLUMN($II31:$KD31),4)=MOD(COLUMN($IJ31),4)),$II31:$KD31)} -> 0 | KH31: =KG31*$J31 -> 0 | KI31: {=SUMPRODUCT(--(MOD(COLUMN($II31:$KD31),4)=MOD(COLUMN($IK31),4)),$II31:$KD31)} -> 0 | KJ31: =KI31*$J31 -> 0 | KN31: 1
E32: 27 | F32: 2 | G32: 4630320200 | H32: Кран ручного управления | J32: =981.5/1.2 -> 817.91667 | BF32: =$KN32*0 -> 0 | DK32: 0 | DO32: =$KN32*0 -> 0 | DP32: 0 | DU32: 0 | DW32: {=SUMPRODUCT(--(MOD(COLUMN($BO32:$DV32),5)=MOD(COLUMN($BO32),5)),$BO32:$DV32)} -> 0 | DX32: =DW32*$J32 -> 0 | DY32: {=SUMPRODUCT(--(MOD(COLUMN($BO32:$DV32),5)=MOD(COLUMN($BP32),5)),$BO32:$DV32)} -> 0 | DZ32: =DY32*$J32 -> 0 | EA32: {=SUMPRODUCT(--(MOD(COLUMN($BO32:$DV32),5)=MOD(COLUMN($BQ32),5)),$BO32:$DV32)} -> 0 | EB32: =EA32*$J32 -> 0 | EC32: {=SUMPRODUCT(--(MOD(COLUMN($BO32:$DV32),5)=MOD(COLUMN($BR32),5)),$BO32:$DV32)} -> 0 | ED32: =EC32*$J32 -> 0 | EE32: 50 | EF32: 0 | EG32: 0 | EV32: 0 | GA32: =SUMPRODUCT(--(MOD(COLUMN($EE32:$FZ32),4)=MOD(COLUMN($EE32),4)),$EE32:$FZ32) -> 50 | GB32: =GA32*$J32 -> 40895.833 | GC32: =SUMPRODUCT(--(MOD(COLUMN($EE32:$FZ32),4)=MOD(COLUMN($EF32),4)),$EE32:$FZ32) -> 0 | GD32: =GC32*$J32 -> 0 | GE32: =SUMPRODUCT(--(MOD(COLUMN($EE32:$FZ32),4)=MOD(COLUMN($EG32),4)),$EE32:$FZ32) -> 0 | GF32: =GE32*$J32 -> 0 | IC32: {=SUMPRODUCT(--(MOD(COLUMN($GG32:$IB32),4)=MOD(COLUMN($GG32),4)),$GG32:$IB32)} -> 0 | ID32: =IC32*$J32 -> 0 | IE32: {=SUMPRODUCT(--(MOD(COLUMN($GG32:$IB32),4)=MOD(COLUMN($GH32),4)),$GG32:$IB32)} -> 0 | IF32: =IE32*$J32 -> 0 | IG32: {=SUMPRODUCT(--(MOD(COLUMN($GG32:$IB32),4)=MOD(COLUMN($GI32),4)),$GG32:$IB32)} -> 0 | IH32: =IG32*$J32 -> 0 | KE32: {=SUMPRODUCT(--(MOD(COLUMN($II32:$KD32),4)=MOD(COLUMN($II32),4)),$II32:$KD32)} -> 0 | KF32: =KE32*$J32 -> 0 | KG32: {=SUMPRODUCT(--(MOD(COLUMN($II32:$KD32),4)=MOD(COLUMN($IJ32),4)),$II32:$KD32)} -> 0 | KH32: =KG32*$J32 -> 0 | KI32: {=SUMPRODUCT(--(MOD(COLUMN($II32:$KD32),4)=MOD(COLUMN($IK32),4)),$II32:$KD32)} -> 0 | KJ32: =KI32*$J32 -> 0 | KN32: 1
E33: 28 | F33: 2 | G33: 4334010030 | H33: Упругий элемент | J33: =77/1.2 -> 64.166667 | BF33: =$KN33*0 -> 0 | DK33: 0 | DO33: =$KN33*0 -> 0 | DP33: 0 | DU33: 0 | DW33: {=SUMPRODUCT(--(MOD(COLUMN($BO33:$DV33),5)=MOD(COLUMN($BO33),5)),$BO33:$DV33)} -> 0 | DX33: =DW33*$J33 -> 0 | DY33: {=SUMPRODUCT(--(MOD(COLUMN($BO33:$DV33),5)=MOD(COLUMN($BP33),5)),$BO33:$DV33)} -> 0 | DZ33: =DY33*$J33 -> 0 | EA33: {=SUMPRODUCT(--(MOD(COLUMN($BO33:$DV33),5)=MOD(COLUMN($BQ33),5)),$BO33:$DV33)} -> 0 | EB33: =EA33*$J33 -> 0 | EC33: {=SUMPRODUCT(--(MOD(COLUMN($BO33:$DV33),5)=MOD(COLUMN($BR33),5)),$BO33:$DV33)} -> 0 | ED33: =EC33*$J33 -> 0 | EE33: 50 | EF33: 0 | EG33: 0 | EV33: 0 | GA33: =SUMPRODUCT(--(MOD(COLUMN($EE33:$FZ33),4)=MOD(COLUMN($EE33),4)),$EE33:$FZ33) -> 50 | GB33: =GA33*$J33 -> 3208.3333 | GC33: =SUMPRODUCT(--(MOD(COLUMN($EE33:$FZ33),4)=MOD(COLUMN($EF33),4)),$EE33:$FZ33) -> 0 | GD33: =GC33*$J33 -> 0 | GE33: =SUMPRODUCT(--(MOD(COLUMN($EE33:$FZ33),4)=MOD(COLUMN($EG33),4)),$EE33:$FZ33) -> 0 | GF33: =GE33*$J33 -> 0 | IC33: {=SUMPRODUCT(--(MOD(COLUMN($GG33:$IB33),4)=MOD(COLUMN($GG33),4)),$GG33:$IB33)} -> 0 | ID33: =IC33*$J33 -> 0 | IE33: {=SUMPRODUCT(--(MOD(COLUMN($GG33:$IB33),4)=MOD(COLUMN($GH33),4)),$GG33:$IB33)} -> 0 | IF33: =IE33*$J33 -> 0 | IG33: {=SUMPRODUCT(--(MOD(COLUMN($GG33:$IB33),4)=MOD(COLUMN($GI33),4)),$GG33:$IB33)} -> 0 | IH33: =IG33*$J33 -> 0 | KE33: {=SUMPRODUCT(--(MOD(COLUMN($II33:$KD33),4)=MOD(COLUMN($II33),4)),$II33:$KD33)} -> 0 | KF33: =KE33*$J33 -> 0 | KG33: {=SUMPRODUCT(--(MOD(COLUMN($II33:$KD33),4)=MOD(COLUMN($IJ33),4)),$II33:$KD33)} -> 0 | KH33: =KG33*$J33 -> 0 | KI33: {=SUMPRODUCT(--(MOD(COLUMN($II33:$KD33),4)=MOD(COLUMN($IK33),4)),$II33:$KD33)} -> 0 | KJ33: =KI33*$J33 -> 0 | KN33: 1
E34: 29 | F34: 2 | G34: 4520021320 | H34: Запорный кран | J34: =456/1.2 -> 380 | BF34: =$KN34*0 -> 0 | DK34: 0 | DO34: =$KN34*0 -> 0 | DP34: 0 | DU34: 0 | DW34: {=SUMPRODUCT(--(MOD(COLUMN($BO34:$DV34),5)=MOD(COLUMN($BO34),5)),$BO34:$DV34)} -> 0 | DX34: =DW34*$J34 -> 0 | DY34: {=SUMPRODUCT(--(MOD(COLUMN($BO34:$DV34),5)=MOD(COLUMN($BP34),5)),$BO34:$DV34)} -> 0 | DZ34: =DY34*$J34 -> 0 | EA34: {=SUMPRODUCT(--(MOD(COLUMN($BO34:$DV34),5)=MOD(COLUMN($BQ34),5)),$BO34:$DV34)} -> 0 | EB34: =EA34*$J34 -> 0 | EC34: {=SUMPRODUCT(--(MOD(COLUMN($BO34:$DV34),5)=MOD(COLUMN($BR34),5)),$BO34:$DV34)} -> 0 | ED34: =EC34*$J34 -> 0 | EE34: 50 | EF34: 0 | EG34: 0 | EV34: 0 | GA34: =SUMPRODUCT(--(MOD(COLUMN($EE34:$FZ34),4)=MOD(COLUMN($EE34),4)),$EE34:$FZ34) -> 50 | GB34: =GA34*$J34 -> 19000 | GC34: =SUMPRODUCT(--(MOD(COLUMN($EE34:$FZ34),4)=MOD(COLUMN($EF34),4)),$EE34:$FZ34) -> 0 | GD34: =GC34*$J34 -> 0 | GE34: =SUMPRODUCT(--(MOD(COLUMN($EE34:$FZ34),4)=MOD(COLUMN($EG34),4)),$EE34:$FZ34) -> 0 | GF34: =GE34*$J34 -> 0 | IC34: {=SUMPRODUCT(--(MOD(COLUMN($GG34:$IB34),4)=MOD(COLUMN($GG34),4)),$GG34:$IB34)} -> 0 | ID34: =IC34*$J34 -> 0 | IE34: {=SUMPRODUCT(--(MOD(COLUMN($GG34:$IB34),4)=MOD(COLUMN($GH34),4)),$GG34:$IB34)} -> 0 | IF34: =IE34*$J34 -> 0 | IG34: {=SUMPRODUCT(--(MOD(COLUMN($GG34:$IB34),4)=MOD(COLUMN($GI34),4)),$GG34:$IB34)} -> 0 | IH34: =IG34*$J34 -> 0 | KE34: {=SUMPRODUCT(--(MOD(COLUMN($II34:$KD34),4)=MOD(COLUMN($II34),4)),$II34:$KD34)} -> 0 | KF34: =KE34*$J34 -> 0 | KG34: {=SUMPRODUCT(--(MOD(COLUMN($II34:$KD34),4)=MOD(COLUMN($IJ34),4)),$II34:$KD34)} -> 0 | KH34: =KG34*$J34 -> 0 | KI34: {=SUMPRODUCT(--(MOD(COLUMN($II34:$KD34),4)=MOD(COLUMN($IK34),4)),$II34:$KD34)} -> 0 | KJ34: =KI34*$J34 -> 0 | KN34: 1
H35: Итого | BI35: =SUMPRODUCT(--(MOD(COLUMN($M35:$BH35),4)=MOD(COLUMN($M35),4)),$M35:$BH35) -> 0 | BJ35: =BI35*$I35 -> 0 | BK35: =SUMPRODUCT(--(MOD(COLUMN($M35:$BH35),4)=MOD(COLUMN($M35)+1,4)),$M35:$BH35) -> 0 | BL35: =BK35*$I35 -> 0 | BM35: =SUMPRODUCT(--(MOD(COLUMN($M35:$BH35),4)=MOD(COLUMN($M35)+2,4)),$M35:$BH35) -> 0 | BN35: =BM35*$I35 -> 0 | DF35: 0
A36: НЕФАЗ ПАО | BI36: =SUMPRODUCT(--(MOD(COLUMN($M36:$BH36),4)=MOD(COLUMN($M36),4)),$M36:$BH36) -> 0 | BJ36: =BI36*$I36 -> 0 | BK36: =SUMPRODUCT(--(MOD(COLUMN($M36:$BH36),4)=MOD(COLUMN($M36)+1,4)),$M36:$BH36) -> 0 | BL36: =BK36*$I36 -> 0 | BM36: =SUMPRODUCT(--(MOD(COLUMN($M36:$BH36),4)=MOD(COLUMN($M36)+2,4)),$M36:$BH36) -> 0 | BN36: =BM36*$I36 -> 0 | DW36: =SUMPRODUCT(--(MOD(COLUMN($BO36:$DV36),5)=MOD(COLUMN($BO36),5)),$BO36:$DV36) -> 0 | DX36: =DW36*$J36 -> 0 | DY36: =SUMPRODUCT(--(MOD(COLUMN($BO36:$DV36),5)=MOD(COLUMN($BO36),5)+1),$BO36:$DV36) -> 0 | DZ36: =DY36*$J36 -> 0 | EA36: =SUMPRODUCT(--(MOD(COLUMN($BO36:$DV36),5)=MOD(COLUMN($BO36),5)+2),$BO36:$DV36) -> 0 | EB36: =EA36*$J36 -> 0 | EC36: =SUMPRODUCT(--(MOD(COLUMN($BO36:$DV36),5)=MOD(COLUMN($BO36),5)+3),$BO36:$DV36) -> 0 | ED36: =EC36*$J36 -> 0
A37: ПАО «ТЗА» | B37: Отсрочка 30 дней | C37: ВБК РУС | D37: Мустафин Ринат | E37: 1 | F37: 1 | G37: 9522010010 | H37: Головка соединительная (управляющая) | I37: =89.6/1.2/0.98 -> 76.190476 | J37: =89.6/1.2 -> 74.666667 | M37: 0 | N37: 0 | O37: 0 | Q37: 0 | R37: 0 | S37: 0 | U37: 0 | V37: 0 | W37: 0 | Y37: 5 | Z37: 0 | AA37: 0 | AB37: У клиента запаздывает подготовка производства | AC37: 20 | AD37: 0 | AE37: 0 | AF37: У клиента запаздывает подготовка производства в конце месяца ожидается сборка опытного полуприцепа, компоненты закуплены в 2023 г. | AG37: 20 | AH37: 0 | AI37: 0 | AJ37: У клиента запаздывает подготовка производства в конце месяца ожидается сборка опытного полуприцепа, компоненты закуплены в 2023 г. | AK37: 20 | AL37: 0 | AM37: 0 | AN37: Клиент пока не запускает производство полуприцепов | AO37: 20 | AP37: 0 | AQ37: 0 | AR37: Клиент пока не запускает производство полуприцепов | AS37: 20 | AT37: 0 | AU37: 0 | AV37: Клиент пока не запускает производство полуприцепов | AW37: 20 | AX37: 0 | AY37: 0 | AZ37: Клиент пока не запускает производство полуприцепов | BA37: 20 | BB37: 0 | BC37: 0 | BE37: 20 | BF37: =$KN37*0 -> 0 | BG37: 0 | BI37: =SUMPRODUCT(--(MOD(COLUMN($M37:$BH37),4)=MOD(COLUMN($M37),4)),$M37:$BH37) -> 165 | BJ37: =BI37*$I37 -> 12571.429 | BK37: =SUMPRODUCT(--(MOD(COLUMN($M37:$BH37),4)=MOD(COLUMN($M37)+1,4)),$M37:$BH37) -> 0 | BL37: =BK37*$I37 -> 0 | BM37: =SUMPRODUCT(--(MOD(COLUMN($M37:$BH37),4)=MOD(COLUMN($M37)+2,4)),$M37:$BH37) -> 0 | BN37: =BM37*$I37 -> 0 | BO37: =$KN37*5 -> 5 | BP37: =$KN37*0 -> 0 | BQ37: =$KN37*5 -> 5 | BR37: 0 | BT37: =$KN37*5 -> 5 | BU37: =$KN37*1 -> 1 | BV37: =$KN37*0 -> 0 | BW37: 0 | BY37: =$KN37*5 -> 5 | BZ37: =$KN37*0 -> 0 | CA37: 0 | CB37: 0 | CD37: =$KN37*5 -> 5 | CE37: =$KN37*0 -> 0 | CF37: =$KN37*0 -> 0 | CG37: 0 | CI37: =$KN37*5 -> 5 | CJ37: =$KN37*5 -> 5 | CK37: 0 | CL37: 0 | CN37: =$KN37*5 -> 5 | CO37: =$KN37*5 -> 5 | CP37: =$KN37*0 -> 0 | CQ37: 0 | CS37: =$KN37*20 -> 20 | CT37: =$KN37*20 -> 20 | CU37: =$KN37*0 -> 0 | CV37: 0 | CX37: =$KN37*20 -> 20 | CY37: =$KN37*20 -> 20 | CZ37: =$KN37*0 -> 0 | DA37: 0 | DC37: =$KN37*20 -> 20 | DD37: =$KN37*20 -> 20 | DE37: =$KN37*0 -> 0 | DF37: 0 | DH37: =$KN37*20 -> 20 | DI37: =$KN37*20 -> 20 | DJ37: =$KN37*0 -> 0 | DK37: 0 | DM37: =$KN37*20 -> 20 | DN37: =$KN37*20 -> 20 | DO37: =$KN37*0 -> 0 | DP37: 0 | DQ37: Заказ ноября перенесен на декабрь | DR37: =$KN37*20 -> 20 | DS37: =$KN37*20 -> 20 | DT37: =$KN37*0 -> 0 | DU37: 0 | DW37: {=SUMPRODUCT(--(MOD(COLUMN($BO37:$DV37),5)=MOD(COLUMN($BO37),5)),$BO37:$DV37)} -> 150 | DX37: =DW37*$J37 -> 11200 | DY37: {=SUMPRODUCT(--(MOD(COLUMN($BO37:$DV37),5)=MOD(COLUMN($BP37),5)),$BO37:$DV37)} -> 131 | DZ37: =DY37*$J37 -> 9781.3333 | EA37: {=SUMPRODUCT(--(MOD(COLUMN($BO37:$DV37),5)=MOD(COLUMN($BQ37),5)),$BO37:$DV37)} -> 5 | EB37: =EA37*$J37 -> 373.33333 | EC37: {=SUMPRODUCT(--(MOD(COLUMN($BO37:$DV37),5)=MOD(COLUMN($BR37),5)),$BO37:$DV37)} -> 0 | ED37: =EC37*$J37 -> 0 | EE37: =$KN37*0 -> 0 | EF37: 2 | EG37: 0 | EI37: 5 | EJ37: 2 | EK37: 2 | EM37: 5 | EN37: 0 | EO37: 0 | EQ37: =$KN37*10 -> 10 | ER37: 0 | ET37: Заказ апреля перенесен на май | EU37: =$KN37*15 -> 15 | EV37: 2 | EY37: =$KN37*20 -> 20 | EZ37: 16 | FC37: =$KN37*25 -> 25 | FD37: 18 | FG37: =$KN37*30 -> 30 | FH37: 10 | FK37: =$KN37*35 -> 35 | FL37: 10 | FO37: =$KN37*40 -> 40 | FP37: 15 | FS37: =$KN37*45 -> 45 | FT37: 15 | FW37: =$KN37*50 -> 50 | FX37: 15 | GA37: {=SUMPRODUCT(--(MOD(COLUMN($EE37:$FZ37),4)=MOD(COLUMN($EE37),4)),$EE37:$FZ37)} -> 280 | GB37: =GA37*$J37 -> 20906.667 | GC37: {=SUMPRODUCT(--(MOD(COLUMN($EE37:$FZ37),4)=MOD(COLUMN($EF37),4)),$EE37:$FZ37)} -> 105 | GD37: =GC37*$J37 -> 7840 | GE37: {=SUMPRODUCT(--(MOD(COLUMN($EE37:$FZ37),4)=MOD(COLUMN($EG37),4)),$EE37:$FZ37)} -> 2 | GF37: =GE37*$J37 -> 149.33333 | GG37: =$KN37*40 -> 40 | GK37: =$KN37*40 -> 40 | GO37: =$KN37*45 -> 45 | GS37: =$KN37*50 -> 50 | GW37: =$KN37*50 -> 50 | HA37: =$KN37*50 -> 50 | HE37: =$KN37*50 -> 50 | HI37: =$KN37*50 -> 50 | HM37: =$KN37*50 -> 50 | HQ37: =$KN37*50 -> 50 | HU37: =$KN37*50 -> 50 | HY37: =$KN37*50 -> 50 | IC37: {=SUMPRODUCT(--(MOD(COLUMN($GG37:$IB37),4)=MOD(COLUMN($GG37),4)),$GG37:$IB37)} -> 575 | ID37: =IC37*$J37 -> 42933.333 | IE37: {=SUMPRODUCT(--(MOD(COLUMN($GG37:$IB37),4)=MOD(COLUMN($GH37),4)),$GG37:$IB37)} -> 0 | IF37: =IE37*$J37 -> 0 | IG37: {=SUMPRODUCT(--(MOD(COLUMN($GG37:$IB37),4)=MOD(COLUMN($GI37),4)),$GG37:$IB37)} -> 0 | IH37: =IG37*$J37 -> 0 | II37: =$KN37*45 -> 45 | IM37: =$KN37*45 -> 45 | IQ37: =$KN37*50 -> 50 | IU37: =$KN37*55 -> 55 | IY37: =$KN37*55 -> 55 | JC37: =$KN37*55 -> 55 | JG37: =$KN37*60 -> 60 | JK37: =$KN37*60 -> 60 | JO37: =$KN37*60 -> 60 | JS37: =$KN37*60 -> 60 | JW37: =$KN37*60 -> 60 | KA37: =$KN37*60 -> 60 | KE37: {=SUMPRODUCT(--(MOD(COLUMN($II37:$KD37),4)=MOD(COLUMN($II37),4)),$II37:$KD37)} -> 665 | KF37: =KE37*$J37 -> 49653.333 | KG37: {=SUMPRODUCT(--(MOD(COLUMN($II37:$KD37),4)=MOD(COLUMN($IJ37),4)),$II37:$KD37)} -> 0 | KH37: =KG37*$J37 -> 0 | KI37: {=SUMPRODUCT(--(MOD(COLUMN($II37:$KD37),4)=MOD(COLUMN($IK37),4)),$II37:$KD37)} -> 0 | KJ37: =KI37*$J37 -> 0 | KN37: 1 | KO37: TEBS 2s/2m 12м
E38: 2 | F38: 1 | G38: 9522010020 | H38: Головка соединительная (питающая) | I38: =89.6/1.2/0.98 -> 76.190476 | J38: =89.6/1.2 -> 74.666667 | M38: 0 | N38: 0 | O38: 0 | Q38: 0 | R38: 0 | S38: 0 | U38: 0 | V38: 0 | W38: 0 | Y38: 5 | Z38: 0 | AA38: 0 | AC38: 20 | AD38: 0 | AE38: 0 | AG38: 20 | AH38: 0 | AI38: 0 | AK38: 20 | AL38: 0 | AM38: 0 | AO38: 20 | AP38: 0 | AQ38: 0 | AS38: 20 | AT38: 0 | AU38: 0 | AW38: 20 | AX38: 0 | AY38: 0 | BA38: 20 | BB38: 0 | BC38: 0 | BE38: 20 | BF38: =$KN38*0 -> 0 | BG38: 0 | BI38: =SUMPRODUCT(--(MOD(COLUMN($M38:$BH38),4)=MOD(COLUMN($M38),4)),$M38:$BH38) -> 165 | BJ38: =BI38*$I38 -> 12571.429 | BK38: =SUMPRODUCT(--(MOD(COLUMN($M38:$BH38),4)=MOD(COLUMN($M38)+1,4)),$M38:$BH38) -> 0 | BL38: =BK38*$I38 -> 0 | BM38: =SUMPRODUCT(--(MOD(COLUMN($M38:$BH38),4)=MOD(COLUMN($M38)+2,4)),$M38:$BH38) -> 0 | BN38: =BM38*$I38 -> 0 | BO38: =$KN38*5 -> 5 | BP38: =$KN38*0 -> 0 | BQ38: =$KN38*5 -> 5 | BR38: 0 | BT38: =$KN38*5 -> 5 | BU38: =$KN38*1 -> 1 | BV38: =$KN38*0 -> 0 | BW38: 0 | BY38: =$KN38*5 -> 5 | BZ38: =$KN38*0 -> 0 | CA38: =$KN38*0 -> 0 | CB38: 0 | CD38: =$KN38*5 -> 5 | CE38: =$KN38*0 -> 0 | CF38: =$KN38*0 -> 0 | CG38: 0 | CI38: =$KN38*5 -> 5 | CJ38: =$KN38*5 -> 5 | CK38: =$KN38*0 -> 0 | CL38: 0 | CN38: =$KN38*5 -> 5 | CO38: =$KN38*5 -> 5 | CP38: =$KN38*0 -> 0 | CQ38: 0 | CS38: =$KN38*20 -> 20 | CT38: =$KN38*20 -> 20 | CU38: =$KN38*0 -> 0 | CV38: 0 | CX38: =$KN38*20 -> 20 | CY38: =$KN38*20 -> 20 | CZ38: =$KN38*0 -> 0 | DA38: 0 | DC38: =$KN38*20 -> 20 | DD38: =$KN38*20 -> 20 | DE38: =$KN38*0 -> 0 | DF38: 0 | DH38: =$KN38*20 -> 20 | DI38: =$KN38*20 -> 20 | DJ38: =$KN38*0 -> 0 | DK38: 0 | DM38: =$KN38*20 -> 20 | DN38: =$KN38*20 -> 20 | DO38: =$KN38*0 -> 0 | DP38: 0 | DR38: =$KN38*20 -> 20 | DS38: =$KN38*20 -> 20 | DT38: =$KN38*0 -> 0 | DU38: 0 | DW38: {=SUMPRODUCT(--(MOD(COLUMN($BO38:$DV38),5)=MOD(COLUMN($BO38),5)),$BO38:$DV38)} -> 150 | DX38: =DW38*$J38 -> 11200 | DY38: {=SUMPRODUCT(--(MOD(COLUMN($BO38:$DV38),5)=MOD(COLUMN($BP38),5)),$BO38:$DV38)} -> 131 | DZ38: =DY38*$J38 -> 9781.3333 | EA38: {=SUMPRODUCT(--(MOD(COLUMN($BO38:$DV38),5)=MOD(COLUMN($BQ38),5)),$BO38:$DV38)} -> 5 | EB38: =EA38*$J38 -> 373.33333 | EC38: {=SUMPRODUCT(--(MOD(COLUMN($BO38:$DV38),5)=MOD(COLUMN($BR38),5)),$BO38:$DV38)} -> 0 | ED38: =EC38*$J38 -> 0 | EE38: =$KN38*0 -> 0 | EF38: 2 | EG38: 0 | EI38: 5 | EJ38: 2 | EK38: 2 | EM38: 5 | EN38: 0 | EO38: 0 | EQ38: =$KN38*10 -> 10 | ER38: 0 | EU38: =$KN38*15 -> 15 | EV38: 2 | EY38: =$KN38*20 -> 20 | EZ38: 16 | FC38: =$KN38*25 -> 25 | FD38: 18 | FG38: =$KN38*30 -> 30 | FH38: 10 | FK38: =$KN38*35 -> 35 | FL38: 10 | FO38: =$KN38*40 -> 40 | FP38: 15 | FS38: =$KN38*45 -> 45 | FT38: 15 | FW38: =$KN38*50 -> 50 | FX38: 15 | GA38: {=SUMPRODUCT(--(MOD(COLUMN($EE38:$FZ38),4)=MOD(COLUMN($EE38),4)),$EE38:$FZ38)} -> 280 | GB38: =GA38*$J38 -> 20906.667 | GC38: {=SUMPRODUCT(--(MOD(COLUMN($EE38:$FZ38),4)=MOD(COLUMN($EF38),4)),$EE38:$FZ38)} -> 105 | GD38: =GC38*$J38 -> 7840 | GE38: {=SUMPRODUCT(--(MOD(COLUMN($EE38:$FZ38),4)=MOD(COLUMN($EG38),4)),$EE38:$FZ38)} -> 2 | GF38: =GE38*$J38 -> 149.33333 | GG38: =$KN38*40 -> 40 | GK38: =$KN38*40 -> 40 | GO38: =$KN38*45 -> 45 | GS38: =$KN38*50 -> 50 | GW38: =$KN38*50 -> 50 | HA38: =$KN38*50 -> 50 | HE38: =$KN38*50 -> 50 | HI38: =$KN38*50 -> 50 | HM38: =$KN38*50 -> 50 | HQ38: =$KN38*50 -> 50 | HU38: =$KN38*50 -> 50 | HY38: =$KN38*50 -> 50 | IC38: {=SUMPRODUCT(--(MOD(COLUMN($GG38:$IB38),4)=MOD(COLUMN($GG38),4)),$GG38:$IB38)} -> 575 | ID38: =IC38*$J38 -> 42933.333 | IE38: {=SUMPRODUCT(--(MOD(COLUMN($GG38:$IB38),4)=MOD(COLUMN($GH38),4)),$GG38:$IB38)} -> 0 | IF38: =IE38*$J38 -> 0 | IG38: {=SUMPRODUCT(--(MOD(COLUMN($GG38:$IB38),4)=MOD(COLUMN($GI38),4)),$GG38:$IB38)} -> 0 | IH38: =IG38*$J38 -> 0 | II38: =$KN38*45 -> 45 | IM38: =$KN38*45 -> 45 | IQ38: =$KN38*50 -> 50 | IU38: =$KN38*55 -> 55 | IY38: =$KN38*55 -> 55 | JC38: =$KN38*55 -> 55 | JG38: =$KN38*60 -> 60 | JK38: =$KN38*60 -> 60 | JO38: =$KN38*60 -> 60 | JS38: =$KN38*60 -> 60 | JW38: =$KN38*60 -> 60 | KA38: =$KN38*60 -> 60 | KE38: {=SUMPRODUCT(--(MOD(COLUMN($II38:$KD38),4)=MOD(COLUMN($II38),4)),$II38:$KD38)} -> 665 | KF38: =KE38*$J38 -> 49653.333 | KG38: {=SUMPRODUCT(--(MOD(COLUMN($II38:$KD38),4)=MOD(COLUMN($IJ38),4)),$II38:$KD38)} -> 0 | KH38: =KG38*$J38 -> 0 | KI38: {=SUMPRODUCT(--(MOD(COLUMN($II38:$KD38),4)=MOD(COLUMN($IK38),4)),$II38:$KD38)} -> 0 | KJ38: =KI38*$J38 -> 0 | KN38: 1
E39: 3 | F39: 1 | G39: 9710029000 | H39: Воздухораспределитель с клапаном растормаживания | I39: =639/1.2/0.98 -> 543.36735 | J39: =639/1.2 -> 532.5 | M39: 0 | N39: 0 | O39: 0 | Q39: 0 | R39: 0 | S39: 0 | U39: 0 | V39: 0 | W39: 0 | Y39: 5 | Z39: 0 | AA39: 0 | AC39: 20 | AD39: 0 | AE39: 0 | AG39: 20 | AH39: 0 | AI39: 0 | AK39: 20 | AL39: 0 | AM39: 0 | AO39: 20 | AP39: 0 | AQ39: 0 | AS39: 20 | AT39: 0 | AU39: 0 | AW39: 20 | AX39: 0 | AY39: 0 | BA39: 20 | BB39: 0 | BC39: 0 | BE39: 20 | BF39: =$KN39*0 -> 0 | BG39: 0 | BI39: =SUMPRODUCT(--(MOD(COLUMN($M39:$BH39),4)=MOD(COLUMN($M39),4)),$M39:$BH39) -> 165 | BJ39: =BI39*$I39 -> 89655.612 | BK39: =SUMPRODUCT(--(MOD(COLUMN($M39:$BH39),4)=MOD(COLUMN($M39)+1,4)),$M39:$BH39) -> 0 | BL39: =BK39*$I39 -> 0 | BM39: =SUMPRODUCT(--(MOD(COLUMN($M39:$BH39),4)=MOD(COLUMN($M39)+2,4)),$M39:$BH39) -> 0 | BN39: =BM39*$I39 -> 0 | BO39: =$KN39*5 -> 5 | BP39: =$KN39*0 -> 0 | BQ39: =$KN39*5 -> 5 | BR39: 0 | BT39: =$KN39*5 -> 5 | BU39: =$KN39*1 -> 1 | BV39: =$KN39*0 -> 0 | BW39: 0 | BY39: =$KN39*5 -> 5 | BZ39: =$KN39*0 -> 0 | CA39: =$KN39*0 -> 0 | CB39: 0 | CD39: =$KN39*5 -> 5 | CE39: =$KN39*0 -> 0 | CF39: =$KN39*0 -> 0 | CG39: 0 | CI39: =$KN39*5 -> 5 | CJ39: =$KN39*5 -> 5 | CK39: =$KN39*0 -> 0 | CL39: 0 | CN39: =$KN39*5 -> 5 | CO39: =$KN39*5 -> 5 | CP39: =$KN39*0 -> 0 | CQ39: 0 | CS39: =$KN39*20 -> 20 | CT39: =$KN39*20 -> 20 | CU39: =$KN39*0 -> 0 | CV39: 0 | CX39: =$KN39*20 -> 20 | CY39: =$KN39*20 -> 20 | CZ39: =$KN39*0 -> 0 | DA39: 0 | DC39: =$KN39*20 -> 20 | DD39: =$KN39*20 -> 20 | DE39: =$KN39*0 -> 0 | DF39: 0 | DH39: =$KN39*20 -> 20 | DI39: =$KN39*20 -> 20 | DJ39: =$KN39*0 -> 0 | DK39: 0 | DM39: =$KN39*20 -> 20 | DN39: =$KN39*20 -> 20 | DO39: =$KN39*0 -> 0 | DP39: 0 | DR39: =$KN39*20 -> 20 | DS39: =$KN39*20 -> 20 | DT39: =$KN39*0 -> 0 | DU39: 0 | DW39: {=SUMPRODUCT(--(MOD(COLUMN($BO39:$DV39),5)=MOD(COLUMN($BO39),5)),$BO39:$DV39)} -> 150 | DX39: =DW39*$J39 -> 79875 | DY39: {=SUMPRODUCT(--(MOD(COLUMN($BO39:$DV39),5)=MOD(COLUMN($BP39),5)),$BO39:$DV39)} -> 131 | DZ39: =DY39*$J39 -> 69757.5 | EA39: {=SUMPRODUCT(--(MOD(COLUMN($BO39:$DV39),5)=MOD(COLUMN($BQ39),5)),$BO39:$DV39)} -> 5 | EB39: =EA39*$J39 -> 2662.5 | EC39: {=SUMPRODUCT(--(MOD(COLUMN($BO39:$DV39),5)=MOD(COLUMN($BR39),5)),$BO39:$DV39)} -> 0 | ED39: =EC39*$J39 -> 0 | EE39: =$KN39*0 -> 0 | EF39: 2 | EG39: 0 | EI39: 5 | EJ39: 2 | EK39: 2 | EM39: 5 | EN39: 0 | EO39: 0 | EQ39: =$KN39*10 -> 10 | ER39: 0 | EU39: =$KN39*15 -> 15 | EV39: 2 | EY39: =$KN39*20 -> 20 | EZ39: 0 | FC39: =$KN39*25 -> 25 | FD39: 0 | FG39: =$KN39*30 -> 30 | FH39: 10 | FK39: =$KN39*35 -> 35 | FL39: 10 | FO39: =$KN39*40 -> 40 | FP39: 15 | FS39: =$KN39*45 -> 45 | FT39: 15 | FW39: =$KN39*50 -> 50 | FX39: 15 | GA39: {=SUMPRODUCT(--(MOD(COLUMN($EE39:$FZ39),4)=MOD(COLUMN($EE39),4)),$EE39:$FZ39)} -> 280 | GB39: =GA39*$J39 -> 149100 | GC39: {=SUMPRODUCT(--(MOD(COLUMN($EE39:$FZ39),4)=MOD(COLUMN($EF39),4)),$EE39:$FZ39)} -> 71 | GD39: =GC39*$J39 -> 37807.5 | GE39: {=SUMPRODUCT(--(MOD(COLUMN($EE39:$FZ39),4)=MOD(COLUMN($EG39),4)),$EE39:$FZ39)} -> 2 | GF39: =GE39*$J39 -> 1065 | GG39: =$KN39*40 -> 40 | GK39: =$KN39*40 -> 40 | GO39: =$KN39*45 -> 45 | GS39: =$KN39*50 -> 50 | GW39: =$KN39*50 -> 50 | HA39: =$KN39*50 -> 50 | HE39: =$KN39*50 -> 50 | HI39: =$KN39*50 -> 50 | HM39: =$KN39*50 -> 50 | HQ39: =$KN39*50 -> 50 | HU39: =$KN39*50 -> 50 | HY39: =$KN39*50 -> 50 | IC39: {=SUMPRODUCT(--(MOD(COLUMN($GG39:$IB39),4)=MOD(COLUMN($GG39),4)),$GG39:$IB39)} -> 575 | ID39: =IC39*$J39 -> 306187.5 | IE39: {=SUMPRODUCT(--(MOD(COLUMN($GG39:$IB39),4)=MOD(COLUMN($GH39),4)),$GG39:$IB39)} -> 0 | IF39: =IE39*$J39 -> 0 | IG39: {=SUMPRODUCT(--(MOD(COLUMN($GG39:$IB39),4)=MOD(COLUMN($GI39),4)),$GG39:$IB39)} -> 0 | IH39: =IG39*$J39 -> 0 | II39: =$KN39*45 -> 45 | IM39: =$KN39*45 -> 45 | IQ39: =$KN39*50 -> 50 | IU39: =$KN39*55 -> 55 | IY39: =$KN39*55 -> 55 | JC39: =$KN39*55 -> 55 | JG39: =$KN39*60 -> 60 | JK39: =$KN39*60 -> 60 | JO39: =$KN39*60 -> 60 | JS39: =$KN39*60 -> 60 | JW39: =$KN39*60 -> 60 | KA39: =$KN39*60 -> 60 | KE39: {=SUMPRODUCT(--(MOD(COLUMN($II39:$KD39),4)=MOD(COLUMN($II39),4)),$II39:$KD39)} -> 665 | KF39: =KE39*$J39 -> 354112.5 | KG39: {=SUMPRODUCT(--(MOD(COLUMN($II39:$KD39),4)=MOD(COLUMN($IJ39),4)),$II39:$KD39)} -> 0 | KH39: =KG39*$J39 -> 0 | KI39: {=SUMPRODUCT(--(MOD(COLUMN($II39:$KD39),4)=MOD(COLUMN($IK39),4)),$II39:$KD39)} -> 0 | KJ39: =KI39*$J39 -> 0 | KN39: 1
E40: 4 | F40: 1 | G40: 4801020640 | H40: Модулятор EBS, с PEM, без фит. | I40: =4169.1/1.2*1.048 -> 3641.014 | J40: =4169/1.2*1.048*1.05 -> 3822.973 | M40: 0 | N40: 0 | O40: 0 | Q40: 0 | R40: 0 | S40: 0 | U40: 0 | V40: 0 | W40: 0 | Y40: 5 | Z40: 0 | AA40: 0 | AC40: 20 | AD40: 0 | AE40: 0 | AG40: 20 | AH40: 0 | AI40: 0 | AK40: 20 | AL40: 0 | AM40: 0 | AO40: 20 | AP40: 0 | AQ40: 0 | AS40: 20 | AT40: 0 | AU40: 0 | AW40: 20 | AX40: 0 | AY40: 0 | BA40: 20 | BB40: 0 | BC40: 0 | BE40: 20 | BF40: =$KN40*0 -> 0 | BG40: 0 | BI40: =SUMPRODUCT(--(MOD(COLUMN($M40:$BH40),4)=MOD(COLUMN($M40),4)),$M40:$BH40) -> 165 | BJ40: =BI40*$I40 -> 600767.31 | BK40: =SUMPRODUCT(--(MOD(COLUMN($M40:$BH40),4)=MOD(COLUMN($M40)+1,4)),$M40:$BH40) -> 0 | BL40: =BK40*$I40 -> 0 | BM40: =SUMPRODUCT(--(MOD(COLUMN($M40:$BH40),4)=MOD(COLUMN($M40)+2,4)),$M40:$BH40) -> 0 | BN40: =BM40*$I40 -> 0 | BO40: =$KN40*5 -> 5 | BP40: =$KN40*0 -> 0 | BQ40: =$KN40*5 -> 5 | BR40: 0 | BT40: =$KN40*5 -> 5 | BU40: =$KN40*1 -> 1 | BV40: =$KN40*0 -> 0 | BW40: 0 | BY40: =$KN40*5 -> 5 | BZ40: =$KN40*0 -> 0 | CA40: =$KN40*0 -> 0 | CB40: 0 | CD40: =$KN40*5 -> 5 | CE40: =$KN40*0 -> 0 | CF40: =$KN40*0 -> 0 | CG40: 0 | CI40: =$KN40*5 -> 5 | CJ40: =$KN40*5 -> 5 | CK40: =$KN40*0 -> 0 | CL40: 0 | CN40: =$KN40*5 -> 5 | CO40: =$KN40*5 -> 5 | CP40: =$KN40*0 -> 0 | CQ40: 0 | CS40: =$KN40*20 -> 20 | CT40: =$KN40*20 -> 20 | CU40: =$KN40*0 -> 0 | CV40: 0 | CX40: =$KN40*20 -> 20 | CY40: =$KN40*20 -> 20 | CZ40: =$KN40*0 -> 0 | DA40: 0 | DC40: =$KN40*20 -> 20 | DD40: =$KN40*20 -> 20 | DE40: =$KN40*0 -> 0 | DF40: 0 | DH40: =$KN40*20 -> 20 | DI40: =$KN40*20 -> 20 | DJ40: =$KN40*0 -> 0 | DK40: 0 | DM40: =$KN40*20 -> 20 | DN40: =$KN40*20 -> 20 | DO40: =$KN40*0 -> 0 | DP40: 0 | DR40: =$KN40*20 -> 20 | DS40: =$KN40*20 -> 20 | DT40: =$KN40*0 -> 0 | DU40: 0 | DW40: {=SUMPRODUCT(--(MOD(COLUMN($BO40:$DV40),5)=MOD(COLUMN($BO40),5)),$BO40:$DV40)} -> 150 | DX40: =DW40*$J40 -> 573445.95 | DY40: {=SUMPRODUCT(--(MOD(COLUMN($BO40:$DV40),5)=MOD(COLUMN($BP40),5)),$BO40:$DV40)} -> 131 | DZ40: =DY40*$J40 -> 500809.46 | EA40: {=SUMPRODUCT(--(MOD(COLUMN($BO40:$DV40),5)=MOD(COLUMN($BQ40),5)),$BO40:$DV40)} -> 5 | EB40: =EA40*$J40 -> 19114.865 | EC40: {=SUMPRODUCT(--(MOD(COLUMN($BO40:$DV40),5)=MOD(COLUMN($BR40),5)),$BO40:$DV40)} -> 0 | ED40: =EC40*$J40 -> 0 | EE40: =$KN40*0 -> 0 | EF40: 2 | EG40: 0 | EI40: 5 | EJ40: 2 | EK40: 2 | EM40: 5 | EN40: 0 | EO40: 0 | EQ40: =$KN40*10 -> 10 | ER40: 0 | EU40: =$KN40*15 -> 15 | EV40: 2 | EY40: =$KN40*20 -> 20 | EZ40: 16 | FC40: =$KN40*25 -> 25 | FD40: 18 | FG40: =$KN40*30 -> 30 | FH40: 10 | FK40: =$KN40*35 -> 35 | FL40: 10 | FO40: =$KN40*40 -> 40 | FP40: 15 | FS40: =$KN40*45 -> 45 | FT40: 15 | FW40: =$KN40*50 -> 50 | FX40: 15 | GA40: {=SUMPRODUCT(--(MOD(COLUMN($EE40:$FZ40),4)=MOD(COLUMN($EE40),4)),$EE40:$FZ40)} -> 280 | GB40: =GA40*$J40 -> 1070432.4 | GC40: {=SUMPRODUCT(--(MOD(COLUMN($EE40:$FZ40),4)=MOD(COLUMN($EF40),4)),$EE40:$FZ40)} -> 105 | GD40: =GC40*$J40 -> 401412.17 | GE40: {=SUMPRODUCT(--(MOD(COLUMN($EE40:$FZ40),4)=MOD(COLUMN($EG40),4)),$EE40:$FZ40)} -> 2 | GF40: =GE40*$J40 -> 7645.946 | GG40: =$KN40*40 -> 40 | GK40: =$KN40*40 -> 40 | GO40: =$KN40*45 -> 45 | GS40: =$KN40*50 -> 50 | GW40: =$KN40*50 -> 50 | HA40: =$KN40*50 -> 50 | HE40: =$KN40*50 -> 50 | HI40: =$KN40*50 -> 50 | HM40: =$KN40*50 -> 50 | HQ40: =$KN40*50 -> 50 | HU40: =$KN40*50 -> 50 | HY40: =$KN40*50 -> 50 | IC40: {=SUMPRODUCT(--(MOD(COLUMN($GG40:$IB40),4)=MOD(COLUMN($GG40),4)),$GG40:$IB40)} -> 575 | ID40: =IC40*$J40 -> 2198209.5 | IE40: {=SUMPRODUCT(--(MOD(COLUMN($GG40:$IB40),4)=MOD(COLUMN($GH40),4)),$GG40:$IB40)} -> 0 | IF40: =IE40*$J40 -> 0 | IG40: {=SUMPRODUCT(--(MOD(COLUMN($GG40:$IB40),4)=MOD(COLUMN($GI40),4)),$GG40:$IB40)} -> 0 | IH40: =IG40*$J40 -> 0 | II40: =$KN40*45 -> 45 | IM40: =$KN40*45 -> 45 | IQ40: =$KN40*50 -> 50 | IU40: =$KN40*55 -> 55 | IY40: =$KN40*55 -> 55 | JC40: =$KN40*55 -> 55 | JG40: =$KN40*60 -> 60 | JK40: =$KN40*60 -> 60 | JO40: =$KN40*60 -> 60 | JS40: =$KN40*60 -> 60 | JW40: =$KN40*60 -> 60 | KA40: =$KN40*60 -> 60 | KE40: {=SUMPRODUCT(--(MOD(COLUMN($II40:$KD40),4)=MOD(COLUMN($II40),4)),$II40:$KD40)} -> 665 | KF40: =KE40*$J40 -> 2542277 | KG40: {=SUMPRODUCT(--(MOD(COLUMN($II40:$KD40),4)=MOD(COLUMN($IJ40),4)),$II40:$KD40)} -> 0 | KH40: =KG40*$J40 -> 0 | KI40: {=SUMPRODUCT(--(MOD(COLUMN($II40:$KD40),4)=MOD(COLUMN($IK40),4)),$II40:$KD40)} -> 0 | KJ40: =KI40*$J40 -> 0 | KN40: 1
E41: 5 | F41: 1 | G41: 4491731200 | H41: Кабель питания, 12 м | I41: =842.2/1.2/0.98 -> 716.15646 | J41: =842.2/1.2 -> 701.83333 | M41: 0 | N41: 0 | O41: 0 | Q41: 0 | R41: 0 | S41: 0 | U41: 0 | V41: 0 | W41: 0 | Y41: 5 | Z41: 0 | AA41: 0 | AC41: 20 | AD41: 0 | AE41: 0 | AG41: 20 | AH41: 0 | AI41: 0 | AK41: 20 | AL41: 0 | AM41: 0 | AO41: 20 | AP41: 0 | AQ41: 0 | AS41: 20 | AT41: 0 | AU41: 0 | AW41: 20 | AX41: 0 | AY41: 0 | BA41: 20 | BB41: 0 | BC41: 0 | BE41: 20 | BF41: =$KN41*0 -> 0 | BG41: 0 | BI41: =SUMPRODUCT(--(MOD(COLUMN($M41:$BH41),4)=MOD(COLUMN($M41),4)),$M41:$BH41) -> 165 | BJ41: =BI41*$I41 -> 118165.82 | BK41: =SUMPRODUCT(--(MOD(COLUMN($M41:$BH41),4)=MOD(COLUMN($M41)+1,4)),$M41:$BH41) -> 0 | BL41: =BK41*$I41 -> 0 | BM41: =SUMPRODUCT(--(MOD(COLUMN($M41:$BH41),4)=MOD(COLUMN($M41)+2,4)),$M41:$BH41) -> 0 | BN41: =BM41*$I41 -> 0 | BO41: =$KN41*5 -> 5 | BP41: =$KN41*0 -> 0 | BQ41: =$KN41*5 -> 5 | BR41: 0 | BT41: =$KN41*5 -> 5 | BU41: =$KN41*1 -> 1 | BV41: =$KN41*0 -> 0 | BW41: 0 | BY41: =$KN41*5 -> 5 | BZ41: =$KN41*0 -> 0 | CA41: =$KN41*0 -> 0 | CB41: 0 | CD41: =$KN41*5 -> 5 | CE41: =$KN41*0 -> 0 | CF41: =$KN41*0 -> 0 | CG41: 0 | CI41: =$KN41*5 -> 5 | CJ41: =$KN41*5 -> 5 | CK41: =$KN41*0 -> 0 | CL41: 0 | CN41: =$KN41*5 -> 5 | CO41: =$KN41*5 -> 5 | CP41: =$KN41*0 -> 0 | CQ41: 0 | CS41: =$KN41*20 -> 20 | CT41: =$KN41*20 -> 20 | CU41: =$KN41*0 -> 0 | CV41: 0 | CX41: =$KN41*20 -> 20 | CY41: =$KN41*20 -> 20 | CZ41: =$KN41*0 -> 0 | DA41: 0 | DC41: =$KN41*20 -> 20 | DD41: =$KN41*20 -> 20 | DE41: =$KN41*0 -> 0 | DF41: 0 | DH41: =$KN41*20 -> 20 | DI41: =$KN41*20 -> 20 | DJ41: =$KN41*0 -> 0 | DK41: 0 | DM41: =$KN41*20 -> 20 | DN41: =$KN41*20 -> 20 | DO41: =$KN41*0 -> 0 | DP41: 0 | DR41: =$KN41*20 -> 20 | DS41: =$KN41*20 -> 20 | DT41: =$KN41*0 -> 0 | DU41: 0 | DW41: {=SUMPRODUCT(--(MOD(COLUMN($BO41:$DV41),5)=MOD(COLUMN($BO41),5)),$BO41:$DV41)} -> 150 | DX41: =DW41*$J41 -> 105275 | DY41: {=SUMPRODUCT(--(MOD(COLUMN($BO41:$DV41),5)=MOD(COLUMN($BP41),5)),$BO41:$DV41)} -> 131 | DZ41: =DY41*$J41 -> 91940.167 | EA41: {=SUMPRODUCT(--(MOD(COLUMN($BO41:$DV41),5)=MOD(COLUMN($BQ41),5)),$BO41:$DV41)} -> 5 | EB41: =EA41*$J41 -> 3509.1667 | EC41: {=SUMPRODUCT(--(MOD(COLUMN($BO41:$DV41),5)=MOD(COLUMN($BR41),5)),$BO41:$DV41)} -> 0 | ED41: =EC41*$J41 -> 0 | EE41: =$KN41*0 -> 0 | EF41: 0 | EG41: 0 | EI41: 5 | EM41: 5 | EN41: 0 | EO41: 0 | EQ41: =$KN41*10 -> 10 | ER41: 0 | EU41: =$KN41*15 -> 15 | EV41: 0 | EY41: =$KN41*20 -> 20 | EZ41: 0 | FC41: =$KN41*25 -> 25 | FD41: 0 | FG41: =$KN41*30 -> 30 | FH41: 10 | FK41: =$KN41*35 -> 35 | FL41: 10 | FO41: =$KN41*40 -> 40 | FP41: 15 | FS41: =$KN41*45 -> 45 | FT41: 15 | FW41: =$KN41*50 -> 50 | FX41: 15 | GA41: {=SUMPRODUCT(--(MOD(COLUMN($EE41:$FZ41),4)=MOD(COLUMN($EE41),4)),$EE41:$FZ41)} -> 280 | GB41: =GA41*$J41 -> 196513.33 | GC41: {=SUMPRODUCT(--(MOD(COLUMN($EE41:$FZ41),4)=MOD(COLUMN($EF41),4)),$EE41:$FZ41)} -> 65 | GD41: =GC41*$J41 -> 45619.167 | GE41: {=SUMPRODUCT(--(MOD(COLUMN($EE41:$FZ41),4)=MOD(COLUMN($EG41),4)),$EE41:$FZ41)} -> 0 | GF41: =GE41*$J41 -> 0 | GG41: =$KN41*40 -> 40 | GK41: =$KN41*40 -> 40 | GO41: =$KN41*45 -> 45 | GS41: =$KN41*50 -> 50 | GW41: =$KN41*50 -> 50 | HA41: =$KN41*50 -> 50 | HE41: =$KN41*50 -> 50 | HI41: =$KN41*50 -> 50 | HM41: =$KN41*50 -> 50 | HQ41: =$KN41*50 -> 50 | HU41: =$KN41*50 -> 50 | HY41: =$KN41*50 -> 50 | IC41: {=SUMPRODUCT(--(MOD(COLUMN($GG41:$IB41),4)=MOD(COLUMN($GG41),4)),$GG41:$IB41)} -> 575 | ID41: =IC41*$J41 -> 403554.17 | IE41: {=SUMPRODUCT(--(MOD(COLUMN($GG41:$IB41),4)=MOD(COLUMN($GH41),4)),$GG41:$IB41)} -> 0 | IF41: =IE41*$J41 -> 0 | IG41: {=SUMPRODUCT(--(MOD(COLUMN($GG41:$IB41),4)=MOD(COLUMN($GI41),4)),$GG41:$IB41)} -> 0 | IH41: =IG41*$J41 -> 0 | II41: =$KN41*45 -> 45 | IM41: =$KN41*45 -> 45 | IQ41: =$KN41*50 -> 50 | IU41: =$KN41*55 -> 55 | IY41: =$KN41*55 -> 55 | JC41: =$KN41*55 -> 55 | JG41: =$KN41*60 -> 60 | JK41: =$KN41*60 -> 60 | JO41: =$KN41*60 -> 60 | JS41: =$KN41*60 -> 60 | JW41: =$KN41*60 -> 60 | KA41: =$KN41*60 -> 60 | KE41: {=SUMPRODUCT(--(MOD(COLUMN($II41:$KD41),4)=MOD(COLUMN($II41),4)),$II41:$KD41)} -> 665 | KF41: =KE41*$J41 -> 466719.17 | KG41: {=SUMPRODUCT(--(MOD(COLUMN($II41:$KD41),4)=MOD(COLUMN($IJ41),4)),$II41:$KD41)} -> 0 | KH41: =KG41*$J41 -> 0 | KI41: {=SUMPRODUCT(--(MOD(COLUMN($II41:$KD41),4)=MOD(COLUMN($IK41),4)),$II41:$KD41)} -> 0 | KJ41: =KI41*$J41 -> 0 | KN41: 1
E42: 6 | F42: 1 | G42: 4492731200 | H42: Кабель питания, 12 м | I42: 1037 | J42: 1037 | EO42: 0 | ER42: 0 | EV42: 1 | GA42: {=SUMPRODUCT(--(MOD(COLUMN($EE42:$FZ42),4)=MOD(COLUMN($EE42),4)),$EE42:$FZ42)} -> 0 | GB42: =GA42*$J42 -> 0 | GC42: {=SUMPRODUCT(--(MOD(COLUMN($EE42:$FZ42),4)=MOD(COLUMN($EF42),4)),$EE42:$FZ42)} -> 1 | GD42: =GC42*$J42 -> 1037 | GE42: {=SUMPRODUCT(--(MOD(COLUMN($EE42:$FZ42),4)=MOD(COLUMN($EG42),4)),$EE42:$FZ42)} -> 0 | GF42: =GE42*$J42 -> 0 | IC42: {=SUMPRODUCT(--(MOD(COLUMN($GG42:$IB42),4)=MOD(COLUMN($GG42),4)),$GG42:$IB42)} -> 0 | ID42: =IC42*$J42 -> 0 | IE42: {=SUMPRODUCT(--(MOD(COLUMN($GG42:$IB42),4)=MOD(COLUMN($GH42),4)),$GG42:$IB42)} -> 0 | IF42: =IE42*$J42 -> 0 | IG42: {=SUMPRODUCT(--(MOD(COLUMN($GG42:$IB42),4)=MOD(COLUMN($GI42),4)),$GG42:$IB42)} -> 0 | IH42: =IG42*$J42 -> 0 | KE42: {=SUMPRODUCT(--(MOD(COLUMN($II42:$KD42),4)=MOD(COLUMN($II42),4)),$II42:$KD42)} -> 0 | KF42: =KE42*$J42 -> 0 | KG42: {=SUMPRODUCT(--(MOD(COLUMN($II42:$KD42),4)=MOD(COLUMN($IJ42),4)),$II42:$KD42)} -> 0 | KH42: =KG42*$J42 -> 0 | KI42: {=SUMPRODUCT(--(MOD(COLUMN($II42:$KD42),4)=MOD(COLUMN($IK42),4)),$II42:$KD42)} -> 0 | KJ42: =KI42*$J42 -> 0
E43: 7 | F43: 1 | G43: 4491731500 | H43: Кабель питания, 15 м | I43: 762.4 | J43: 762.4 | DU43: 0 | DW43: {=SUMPRODUCT(--(MOD(COLUMN($BO43:$DV43),5)=MOD(COLUMN($BO43),5)),$BO43:$DV43)} -> 0 | DX43: =DW43*$J43 -> 0 | DY43: {=SUMPRODUCT(--(MOD(COLUMN($BO43:$DV43),5)=MOD(COLUMN($BP43),5)),$BO43:$DV43)} -> 0 | DZ43: =DY43*$J43 -> 0 | EA43: {=SUMPRODUCT(--(MOD(COLUMN($BO43:$DV43),5)=MOD(COLUMN($BQ43),5)),$BO43:$DV43)} -> 0 | EB43: =EA43*$J43 -> 0 | EC43: {=SUMPRODUCT(--(MOD(COLUMN($BO43:$DV43),5)=MOD(COLUMN($BR43),5)),$BO43:$DV43)} -> 0 | ED43: =EC43*$J43 -> 0 | EE43: =$KN43*0 -> 0 | EF43: 1 | EG43: 0 | EH43: Новый артикул | EJ43: 1 | EK43: 1 | EN43: 0 | EO43: 0 | ER43: 0 | EV43: 1 | EZ43: 16 | FD43: 18 | GA43: {=SUMPRODUCT(--(MOD(COLUMN($EE43:$FZ43),4)=MOD(COLUMN($EE43),4)),$EE43:$FZ43)} -> 0 | GB43: =GA43*$J43 -> 0 | GC43: {=SUMPRODUCT(--(MOD(COLUMN($EE43:$FZ43),4)=MOD(COLUMN($EF43),4)),$EE43:$FZ43)} -> 37 | GD43: =GC43*$J43 -> 28208.8 | GE43: {=SUMPRODUCT(--(MOD(COLUMN($EE43:$FZ43),4)=MOD(COLUMN($EG43),4)),$EE43:$FZ43)} -> 1 | GF43: =GE43*$J43 -> 762.4 | IC43: {=SUMPRODUCT(--(MOD(COLUMN($GG43:$IB43),4)=MOD(COLUMN($GG43),4)),$GG43:$IB43)} -> 0 | ID43: =IC43*$J43 -> 0 | IE43: {=SUMPRODUCT(--(MOD(COLUMN($GG43:$IB43),4)=MOD(COLUMN($GH43),4)),$GG43:$IB43)} -> 0 | IF43: =IE43*$J43 -> 0 | IG43: {=SUMPRODUCT(--(MOD(COLUMN($GG43:$IB43),4)=MOD(COLUMN($GI43),4)),$GG43:$IB43)} -> 0 | IH43: =IG43*$J43 -> 0 | KE43: {=SUMPRODUCT(--(MOD(COLUMN($II43:$KD43),4)=MOD(COLUMN($II43),4)),$II43:$KD43)} -> 0 | KF43: =KE43*$J43 -> 0 | KG43: {=SUMPRODUCT(--(MOD(COLUMN($II43:$KD43),4)=MOD(COLUMN($IJ43),4)),$II43:$KD43)} -> 0 | KH43: =KG43*$J43 -> 0 | KI43: {=SUMPRODUCT(--(MOD(COLUMN($II43:$KD43),4)=MOD(COLUMN($IK43),4)),$II43:$KD43)} -> 0 | KJ43: =KI43*$J43 -> 0 | KN43: 1
E44: 8 | F44: 1 | G44: 4497230300 | H44: Кабель датчика, 3 м | J44: =68.4/1.2 -> 57 | CP44: 4 | CQ44: 4 | CV44: 0 | DA44: 0 | DE44: =$KN44*0 -> 0 | DF44: 0 | DJ44: =$KN44*0 -> 0 | DK44: 0 | DO44: =$KN44*0 -> 0 | DP44: 0 | DT44: =$KN44*0 -> 0 | DU44: 0 | DW44: {=SUMPRODUCT(--(MOD(COLUMN($BO44:$DV44),5)=MOD(COLUMN($BO44),5)),$BO44:$DV44)} -> 0 | DX44: =DW44*$J44 -> 0 | DY44: {=SUMPRODUCT(--(MOD(COLUMN($BO44:$DV44),5)=MOD(COLUMN($BP44),5)),$BO44:$DV44)} -> 0 | DZ44: =DY44*$J44 -> 0 | EA44: {=SUMPRODUCT(--(MOD(COLUMN($BO44:$DV44),5)=MOD(COLUMN($BQ44),5)),$BO44:$DV44)} -> 4 | EB44: =EA44*$J44 -> 228 | EC44: {=SUMPRODUCT(--(MOD(COLUMN($BO44:$DV44),5)=MOD(COLUMN($BR44),5)),$BO44:$DV44)} -> 4 | ED44: =EC44*$J44 -> 228 | EE44: =$KN44*0 -> 0 | EF44: 6 | EG44: 0 | EI44: 0 | EJ44: 6 | EK44: 6 | EM44: 0 | EN44: 0 | EO44: 0 | EQ44: =$KN44*10 -> 0 | ER44: 0 | EU44: =$KN44*15 -> 0 | EV44: 0 | EY44: =$KN44*20 -> 0 | EZ44: 64 | FC44: =$KN44*25 -> 0 | FD44: 66 | FG44: =$KN44*30 -> 0 | FH44: 0 | FL44: 0 | FP44: 0 | FT44: 0 | FX44: 0 | GA44: {=SUMPRODUCT(--(MOD(COLUMN($EE44:$FZ44),4)=MOD(COLUMN($EE44),4)),$EE44:$FZ44)} -> 0 | GB44: =GA44*$J44 -> 0 | GC44: {=SUMPRODUCT(--(MOD(COLUMN($EE44:$FZ44),4)=MOD(COLUMN($EF44),4)),$EE44:$FZ44)} -> 142 | GD44: =GC44*$J44 -> 8094 | GE44: {=SUMPRODUCT(--(MOD(COLUMN($EE44:$FZ44),4)=MOD(COLUMN($EG44),4)),$EE44:$FZ44)} -> 6 | GF44: =GE44*$J44 -> 342 | IC44: {=SUMPRODUCT(--(MOD(COLUMN($GG44:$IB44),4)=MOD(COLUMN($GG44),4)),$GG44:$IB44)} -> 0 | ID44: =IC44*$J44 -> 0 | IE44: {=SUMPRODUCT(--(MOD(COLUMN($GG44:$IB44),4)=MOD(COLUMN($GH44),4)),$GG44:$IB44)} -> 0 | IF44: =IE44*$J44 -> 0 | IG44: {=SUMPRODUCT(--(MOD(COLUMN($GG44:$IB44),4)=MOD(COLUMN($GI44),4)),$GG44:$IB44)} -> 0 | IH44: =IG44*$J44 -> 0 | KE44: {=SUMPRODUCT(--(MOD(COLUMN($II44:$KD44),4)=MOD(COLUMN($II44),4)),$II44:$KD44)} -> 0 | KF44: =KE44*$J44 -> 0 | KG44: {=SUMPRODUCT(--(MOD(COLUMN($II44:$KD44),4)=MOD(COLUMN($IJ44),4)),$II44:$KD44)} -> 0 | KH44: =KG44*$J44 -> 0 | KI44: {=SUMPRODUCT(--(MOD(COLUMN($II44:$KD44),4)=MOD(COLUMN($IK44),4)),$II44:$KD44)} -> 0 | KJ44: =KI44*$J44 -> 0
E45: 9 | F45: 1 | G45: 4497230500 | H45: Кабель датчика, 5 м | I45: =71.7/1.2/0.98 -> 60.969388 | J45: =71.7/1.2 -> 59.75 | M45: 0 | N45: 0 | O45: 0 | Q45: 0 | R45: 0 | S45: 0 | U45: 0 | V45: 0 | W45: 0 | Y45: 10 | Z45: 0 | AA45: 0 | AC45: 40 | AD45: 0 | AE45: 0 | AG45: 40 | AH45: 0 | AI45: 0 | AK45: 40 | AL45: 0 | AM45: 0 | AO45: 40 | AP45: 0 | AQ45: 0 | AS45: 40 | AT45: 0 | AU45: 0 | AW45: 40 | AX45: 0 | AY45: 0 | BA45: 40 | BB45: 0 | BC45: 0 | BE45: 40 | BF45: =$KN45*0 -> 0 | BG45: 0 | BI45: =SUMPRODUCT(--(MOD(COLUMN($M45:$BH45),4)=MOD(COLUMN($M45),4)),$M45:$BH45) -> 330 | BJ45: =BI45*$I45 -> 20119.898 | BK45: =SUMPRODUCT(--(MOD(COLUMN($M45:$BH45),4)=MOD(COLUMN($M45)+1,4)),$M45:$BH45) -> 0 | BL45: =BK45*$I45 -> 0 | BM45: =SUMPRODUCT(--(MOD(COLUMN($M45:$BH45),4)=MOD(COLUMN($M45)+2,4)),$M45:$BH45) -> 0 | BN45: =BM45*$I45 -> 0 | BO45: =$KN45*5 -> 10 | BP45: =$KN45*0 -> 0 | BQ45: =$KN45*5 -> 10 | BR45: 0 | BT45: =$KN45*5 -> 10 | BU45: =$KN45*1 -> 2 | BV45: =$KN45*0 -> 0 | BW45: 0 | BY45: =$KN45*5 -> 10 | BZ45: =$KN45*0 -> 0 | CA45: =$KN45*0 -> 0 | CB45: 0 | CD45: =$KN45*5 -> 10 | CE45: =$KN45*0 -> 0 | CF45: =$KN45*0 -> 0 | CG45: 0 | CI45: =$KN45*5 -> 10 | CJ45: =$KN45*5 -> 10 | CK45: =$KN45*0 -> 0 | CL45: 0 | CN45: =$KN45*5 -> 10 | CO45: =$KN45*5 -> 10 | CP45: =$KN45*0 -> 0 | CQ45: 0 | CS45: =$KN45*20 -> 40 | CT45: =$KN45*20 -> 40 | CU45: =$KN45*0 -> 0 | CV45: 0 | CX45: =$KN45*20 -> 40 | CY45: =$KN45*20 -> 40 | CZ45: =$KN45*0 -> 0 | DA45: 0 | DC45: =$KN45*20 -> 40 | DD45: =$KN45*20 -> 40 | DE45: =$KN45*0 -> 0 | DF45: 0 | DH45: =$KN45*20 -> 40 | DI45: =$KN45*20 -> 40 | DJ45: =$KN45*0 -> 0 | DK45: 0 | DM45: =$KN45*20 -> 40 | DN45: =$KN45*20 -> 40 | DO45: =$KN45*0 -> 0 | DP45: 0 | DR45: =$KN45*20 -> 40 | DS45: =$KN45*20 -> 40 | DT45: =$KN45*0 -> 0 | DU45: 0 | DW45: {=SUMPRODUCT(--(MOD(COLUMN($BO45:$DV45),5)=MOD(COLUMN($BO45),5)),$BO45:$DV45)} -> 300 | DX45: =DW45*$J45 -> 17925 | DY45: {=SUMPRODUCT(--(MOD(COLUMN($BO45:$DV45),5)=MOD(COLUMN($BP45),5)),$BO45:$DV45)} -> 262 | DZ45: =DY45*$J45 -> 15654.5 | EA45: {=SUMPRODUCT(--(MOD(COLUMN($BO45:$DV45),5)=MOD(COLUMN($BQ45),5)),$BO45:$DV45)} -> 10 | EB45: =EA45*$J45 -> 597.5 | EC45: {=SUMPRODUCT(--(MOD(COLUMN($BO45:$DV45),5)=MOD(COLUMN($BR45),5)),$BO45:$DV45)} -> 0 | ED45: =EC45*$J45 -> 0 | EE45: =$KN45*0 -> 0 | EF45: 0 | EG45: 0 | EI45: 10 | EM45: 10 | EN45: 0 | EO45: 0 | EQ45: =$KN45*10 -> 20 | ER45: 0 | EU45: =$KN45*15 -> 30 | EV45: 4 | EY45: =$KN45*20 -> 40 | EZ45: 0 | FC45: =$KN45*25 -> 50 | FD45: 0 | FG45: =$KN45*30 -> 60 | FH45: 20 | FK45: =$KN45*35 -> 70 | FL45: 20 | FO45: =$KN45*40 -> 80 | FP45: 30 | FS45: =$KN45*45 -> 90 | FT45: 30 | FW45: =$KN45*50 -> 100 | FX45: 30 | GA45: {=SUMPRODUCT(--(MOD(COLUMN($EE45:$FZ45),4)=MOD(COLUMN($EE45),4)),$EE45:$FZ45)} -> 560 | GB45: =GA45*$J45 -> 33460 | GC45: {=SUMPRODUCT(--(MOD(COLUMN($EE45:$FZ45),4)=MOD(COLUMN($EF45),4)),$EE45:$FZ45)} -> 134 | GD45: =GC45*$J45 -> 8006.5 | GE45: {=SUMPRODUCT(--(MOD(COLUMN($EE45:$FZ45),4)=MOD(COLUMN($EG45),4)),$EE45:$FZ45)} -> 0 | GF45: =GE45*$J45 -> 0 | GG45: =$KN45*40 -> 80 | GK45: =$KN45*40 -> 80 | GO45: =$KN45*45 -> 90 | GS45: =$KN45*50 -> 100 | GW45: =$KN45*50 -> 100 | HA45: =$KN45*50 -> 100 | HE45: =$KN45*50 -> 100 | HI45: =$KN45*50 -> 100 | HM45: =$KN45*50 -> 100 | HQ45: =$KN45*50 -> 100 | HU45: =$KN45*50 -> 100 | HY45: =$KN45*50 -> 100 | IC45: {=SUMPRODUCT(--(MOD(COLUMN($GG45:$IB45),4)=MOD(COLUMN($GG45),4)),$GG45:$IB45)} -> 1150 | ID45: =IC45*$J45 -> 68712.5 | IE45: {=SUMPRODUCT(--(MOD(COLUMN($GG45:$IB45),4)=MOD(COLUMN($GH45),4)),$GG45:$IB45)} -> 0 | IF45: =IE45*$J45 -> 0 | IG45: {=SUMPRODUCT(--(MOD(COLUMN($GG45:$IB45),4)=MOD(COLUMN($GI45),4)),$GG45:$IB45)} -> 0 | IH45: =IG45*$J45 -> 0 | II45: =$KN45*45 -> 90 | IM45: =$KN45*45 -> 90 | IQ45: =$KN45*50 -> 100 | IU45: =$KN45*55 -> 110 | IY45: =$KN45*55 -> 110 | JC45: =$KN45*55 -> 110 | JG45: =$KN45*60 -> 120 | JK45: =$KN45*60 -> 120 | JO45: =$KN45*60 -> 120 | JS45: =$KN45*60 -> 120 | JW45: =$KN45*60 -> 120 | KA45: =$KN45*60 -> 120 | KE45: {=SUMPRODUCT(--(MOD(COLUMN($II45:$KD45),4)=MOD(COLUMN($II45),4)),$II45:$KD45)} -> 1330 | KF45: =KE45*$J45 -> 79467.5 | KG45: {=SUMPRODUCT(--(MOD(COLUMN($II45:$KD45),4)=MOD(COLUMN($IJ45),4)),$II45:$KD45)} -> 0 | KH45: =KG45*$J45 -> 0 | KI45: {=SUMPRODUCT(--(MOD(COLUMN($II45:$KD45),4)=MOD(COLUMN($IK45),4)),$II45:$KD45)} -> 0 | KJ45: =KI45*$J45 -> 0 | KN45: 2
E46: 10 | F46: 1 | G46: 4497230800 | H46: Кабель датчика, 8 м | I46: 209.6 | J46: 209.6 | EO46: 0 | ER46: 0 | EV46: 2 | GA46: {=SUMPRODUCT(--(MOD(COLUMN($EE46:$FZ46),4)=MOD(COLUMN($EE46),4)),$EE46:$FZ46)} -> 0 | GB46: =GA46*$J46 -> 0 | GC46: {=SUMPRODUCT(--(MOD(COLUMN($EE46:$FZ46),4)=MOD(COLUMN($EF46),4)),$EE46:$FZ46)} -> 2 | GD46: =GC46*$J46 -> 419.2 | GE46: {=SUMPRODUCT(--(MOD(COLUMN($EE46:$FZ46),4)=MOD(COLUMN($EG46),4)),$EE46:$FZ46)} -> 0 | GF46: =GE46*$J46 -> 0 | IC46: {=SUMPRODUCT(--(MOD(COLUMN($GG46:$IB46),4)=MOD(COLUMN($GG46),4)),$GG46:$IB46)} -> 0 | ID46: =IC46*$J46 -> 0 | IE46: {=SUMPRODUCT(--(MOD(COLUMN($GG46:$IB46),4)=MOD(COLUMN($GH46),4)),$GG46:$IB46)} -> 0 | IF46: =IE46*$J46 -> 0 | IG46: {=SUMPRODUCT(--(MOD(COLUMN($GG46:$IB46),4)=MOD(COLUMN($GI46),4)),$GG46:$IB46)} -> 0 | IH46: =IG46*$J46 -> 0 | KE46: {=SUMPRODUCT(--(MOD(COLUMN($II46:$KD46),4)=MOD(COLUMN($II46),4)),$II46:$KD46)} -> 0 | KF46: =KE46*$J46 -> 0 | KG46: {=SUMPRODUCT(--(MOD(COLUMN($II46:$KD46),4)=MOD(COLUMN($IJ46),4)),$II46:$KD46)} -> 0 | KH46: =KG46*$J46 -> 0 | KI46: {=SUMPRODUCT(--(MOD(COLUMN($II46:$KD46),4)=MOD(COLUMN($IK46),4)),$II46:$KD46)} -> 0 | KJ46: =KI46*$J46 -> 0
E47: 11 | F47: 1 | G47: 4640061000 | H47: Кран уровня пола, 5-ти портовый | I47: =584/1.2/0.98 -> 496.59864 | J47: =584/1.2 -> 486.66667 | M47: 0 | N47: 0 | O47: 0 | Q47: 0 | R47: 0 | S47: 0 | U47: 0 | V47: 0 | W47: 0 | Y47: 5 | Z47: 0 | AA47: 0 | AC47: 20 | AD47: 0 | AE47: 0 | AG47: 20 | AH47: 0 | AI47: 0 | AK47: 20 | AL47: 0 | AM47: 0 | AO47: 20 | AP47: 0 | AQ47: 0 | AS47: 20 | AT47: 0 | AU47: 0 | AW47: 20 | AX47: 0 | AY47: 0 | BA47: 20 | BB47: 0 | BC47: 0 | BE47: 20 | BF47: =$KN47*0 -> 0 | BG47: 0 | BI47: =SUMPRODUCT(--(MOD(COLUMN($M47:$BH47),4)=MOD(COLUMN($M47),4)),$M47:$BH47) -> 165 | BJ47: =BI47*$I47 -> 81938.776 | BK47: =SUMPRODUCT(--(MOD(COLUMN($M47:$BH47),4)=MOD(COLUMN($M47)+1,4)),$M47:$BH47) -> 0 | BL47: =BK47*$I47 -> 0 | BM47: =SUMPRODUCT(--(MOD(COLUMN($M47:$BH47),4)=MOD(COLUMN($M47)+2,4)),$M47:$BH47) -> 0 | BN47: =BM47*$I47 -> 0 | BO47: =$KN47*5 -> 5 | BP47: =$KN47*0 -> 0 | BQ47: =$KN47*5 -> 5 | BR47: 0 | BT47: =$KN47*5 -> 5 | BU47: =$KN47*1 -> 1 | BV47: =$KN47*0 -> 0 | BW47: 0 | BY47: =$KN47*5 -> 5 | BZ47: =$KN47*0 -> 0 | CA47: =$KN47*0 -> 0 | CB47: 0 | CD47: =$KN47*5 -> 5 | CE47: =$KN47*0 -> 0 | CF47: =$KN47*0 -> 0 | CG47: 0 | CI47: =$KN47*5 -> 5 | CJ47: =$KN47*5 -> 5 | CK47: =$KN47*0 -> 0 | CL47: 0 | CN47: =$KN47*5 -> 5 | CO47: =$KN47*5 -> 5 | CP47: =$KN47*0 -> 0 | CQ47: 0 | CS47: =$KN47*20 -> 20 | CT47: =$KN47*20 -> 20 | CU47: =$KN47*0 -> 0 | CV47: 0 | CX47: =$KN47*20 -> 20 | CY47: =$KN47*20 -> 20 | CZ47: =$KN47*0 -> 0 | DA47: 0 | DC47: =$KN47*20 -> 20 | DD47: =$KN47*20 -> 20 | DE47: =$KN47*0 -> 0 | DF47: 0 | DH47: =$KN47*20 -> 20 | DI47: =$KN47*20 -> 20 | DJ47: =$KN47*0 -> 0 | DK47: 0 | DM47: =$KN47*20 -> 20 | DN47: =$KN47*20 -> 20 | DO47: =$KN47*0 -> 0 | DP47: 0 | DR47: =$KN47*20 -> 20 | DS47: =$KN47*20 -> 20 | DT47: =$KN47*0 -> 0 | DU47: 0 | DW47: {=SUMPRODUCT(--(MOD(COLUMN($BO47:$DV47),5)=MOD(COLUMN($BO47),5)),$BO47:$DV47)} -> 150 | DX47: =DW47*$J47 -> 73000 | DY47: {=SUMPRODUCT(--(MOD(COLUMN($BO47:$DV47),5)=MOD(COLUMN($BP47),5)),$BO47:$DV47)} -> 131 | DZ47: =DY47*$J47 -> 63753.333 | EA47: {=SUMPRODUCT(--(MOD(COLUMN($BO47:$DV47),5)=MOD(COLUMN($BQ47),5)),$BO47:$DV47)} -> 5 | EB47: =EA47*$J47 -> 2433.3333 | EC47: {=SUMPRODUCT(--(MOD(COLUMN($BO47:$DV47),5)=MOD(COLUMN($BR47),5)),$BO47:$DV47)} -> 0 | ED47: =EC47*$J47 -> 0 | EE47: =$KN47*0 -> 0 | EF47: 2 | EG47: 0 | EI47: 5 | EJ47: 2 | EK47: 2 | EM47: 5 | EN47: 0 | EO47: 0 | EQ47: =$KN47*10 -> 10 | ER47: 0 | EU47: =$KN47*15 -> 15 | EV47: 1 | EY47: =$KN47*20 -> 20 | EZ47: 16 | FC47: =$KN47*25 -> 25 | FD47: 18 | FG47: =$KN47*30 -> 30 | FH47: 10 | FK47: =$KN47*35 -> 35 | FL47: 10 | FO47: =$KN47*40 -> 40 | FP47: 15 | FS47: =$KN47*45 -> 45 | FT47: 15 | FW47: =$KN47*50 -> 50 | FX47: 15 | GA47: {=SUMPRODUCT(--(MOD(COLUMN($EE47:$FZ47),4)=MOD(COLUMN($EE47),4)),$EE47:$FZ47)} -> 280 | GB47: =GA47*$J47 -> 136266.67 | GC47: {=SUMPRODUCT(--(MOD(COLUMN($EE47:$FZ47),4)=MOD(COLUMN($EF47),4)),$EE47:$FZ47)} -> 104 | GD47: =GC47*$J47 -> 50613.333 | GE47: {=SUMPRODUCT(--(MOD(COLUMN($EE47:$FZ47),4)=MOD(COLUMN($EG47),4)),$EE47:$FZ47)} -> 2 | GF47: =GE47*$J47 -> 973.33333 | GG47: =$KN47*40 -> 40 | GK47: =$KN47*40 -> 40 | GO47: =$KN47*45 -> 45 | GS47: =$KN47*50 -> 50 | GW47: =$KN47*50 -> 50 | HA47: =$KN47*50 -> 50 | HE47: =$KN47*50 -> 50 | HI47: =$KN47*50 -> 50 | HM47: =$KN47*50 -> 50 | HQ47: =$KN47*50 -> 50 | HU47: =$KN47*50 -> 50 | HY47: =$KN47*50 -> 50 | IC47: {=SUMPRODUCT(--(MOD(COLUMN($GG47:$IB47),4)=MOD(COLUMN($GG47),4)),$GG47:$IB47)} -> 575 | ID47: =IC47*$J47 -> 279833.33 | IE47: {=SUMPRODUCT(--(MOD(COLUMN($GG47:$IB47),4)=MOD(COLUMN($GH47),4)),$GG47:$IB47)} -> 0 | IF47: =IE47*$J47 -> 0 | IG47: {=SUMPRODUCT(--(MOD(COLUMN($GG47:$IB47),4)=MOD(COLUMN($GI47),4)),$GG47:$IB47)} -> 0 | IH47: =IG47*$J47 -> 0 | II47: =$KN47*45 -> 45 | IM47: =$KN47*45 -> 45 | IQ47: =$KN47*50 -> 50 | IU47: =$KN47*55 -> 55 | IY47: =$KN47*55 -> 55 | JC47: =$KN47*55 -> 55 | JG47: =$KN47*60 -> 60 | JK47: =$KN47*60 -> 60 | JO47: =$KN47*60 -> 60 | JS47: =$KN47*60 -> 60 | JW47: =$KN47*60 -> 60 | KA47: =$KN47*60 -> 60 | KE47: {=SUMPRODUCT(--(MOD(COLUMN($II47:$KD47),4)=MOD(COLUMN($II47),4)),$II47:$KD47)} -> 665 | KF47: =KE47*$J47 -> 323633.33 | KG47: {=SUMPRODUCT(--(MOD(COLUMN($II47:$KD47),4)=MOD(COLUMN($IJ47),4)),$II47:$KD47)} -> 0 | KH47: =KG47*$J47 -> 0 | KI47: {=SUMPRODUCT(--(MOD(COLUMN($II47:$KD47),4)=MOD(COLUMN($IK47),4)),$II47:$KD47)} -> 0 | KJ47: =KI47*$J47 -> 0 | KN47: 1
E48: 12 | F48: 1 | G48: 4630320200 | H48: Кран ручного управления | I48: =537.4/1.2/0.98 -> 456.97279 | J48: =537.4/1.2 -> 447.83333 | M48: 0 | N48: 0 | O48: 0 | Q48: 0 | R48: 0 | S48: 0 | U48: 0 | V48: 0 | W48: 0 | Y48: 5 | Z48: 0 | AA48: 0 | AC48: 20 | AD48: 0 | AE48: 0 | AG48: 20 | AH48: 0 | AI48: 0 | AK48: 20 | AL48: 0 | AM48: 0 | AO48: 20 | AP48: 0 | AQ48: 0 | AS48: 20 | AT48: 0 | AU48: 0 | AW48: 20 | AX48: 0 | AY48: 0 | BA48: 20 | BB48: 0 | BC48: 0 | BE48: 20 | BF48: =$KN48*0 -> 0 | BG48: 0 | BI48: =SUMPRODUCT(--(MOD(COLUMN($M48:$BH48),4)=MOD(COLUMN($M48),4)),$M48:$BH48) -> 165 | BJ48: =BI48*$I48 -> 75400.51 | BK48: =SUMPRODUCT(--(MOD(COLUMN($M48:$BH48),4)=MOD(COLUMN($M48)+1,4)),$M48:$BH48) -> 0 | BL48: =BK48*$I48 -> 0 | BM48: =SUMPRODUCT(--(MOD(COLUMN($M48:$BH48),4)=MOD(COLUMN($M48)+2,4)),$M48:$BH48) -> 0 | BN48: =BM48*$I48 -> 0 | BO48: =$KN48*5 -> 5 | BP48: =$KN48*0 -> 0 | BQ48: =$KN48*5 -> 5 | BR48: 0 | BT48: =$KN48*5 -> 5 | BU48: =$KN48*1 -> 1 | BV48: =$KN48*0 -> 0 | BW48: 0 | BY48: =$KN48*5 -> 5 | BZ48: =$KN48*0 -> 0 | CA48: =$KN48*0 -> 0 | CB48: 0 | CD48: =$KN48*5 -> 5 | CE48: =$KN48*0 -> 0 | CF48: =$KN48*0 -> 0 | CG48: 0 | CI48: =$KN48*5 -> 5 | CJ48: =$KN48*5 -> 5 | CK48: =$KN48*0 -> 0 | CL48: 0 | CN48: =$KN48*5 -> 5 | CO48: =$KN48*5 -> 5 | CP48: =$KN48*0 -> 0 | CQ48: 0 | CS48: =$KN48*20 -> 20 | CT48: =$KN48*20 -> 20 | CU48: =$KN48*0 -> 0 | CV48: 0 | CX48: =$KN48*20 -> 20 | CY48: =$KN48*20 -> 20 | CZ48: =$KN48*0 -> 0 | DA48: 0 | DC48: =$KN48*20 -> 20 | DD48: =$KN48*20 -> 20 | DE48: =$KN48*0 -> 0 | DF48: 0 | DH48: =$KN48*20 -> 20 | DI48: =$KN48*20 -> 20 | DJ48: =$KN48*0 -> 0 | DK48: 0 | DM48: =$KN48*20 -> 20 | DN48: =$KN48*20 -> 20 | DO48: =$KN48*0 -> 0 | DP48: 0 | DR48: =$KN48*20 -> 20 | DS48: =$KN48*20 -> 20 | DT48: =$KN48*0 -> 0 | DU48: 0 | DW48: {=SUMPRODUCT(--(MOD(COLUMN($BO48:$DV48),5)=MOD(COLUMN($BO48),5)),$BO48:$DV48)} -> 150 | DX48: =DW48*$J48 -> 67175 | DY48: {=SUMPRODUCT(--(MOD(COLUMN($BO48:$DV48),5)=MOD(COLUMN($BP48),5)),$BO48:$DV48)} -> 131 | DZ48: =DY48*$J48 -> 58666.167 | EA48: {=SUMPRODUCT(--(MOD(COLUMN($BO48:$DV48),5)=MOD(COLUMN($BQ48),5)),$BO48:$DV48)} -> 5 | EB48: =EA48*$J48 -> 2239.1667 | EC48: {=SUMPRODUCT(--(MOD(COLUMN($BO48:$DV48),5)=MOD(COLUMN($BR48),5)),$BO48:$DV48)} -> 0 | ED48: =EC48*$J48 -> 0 | EE48: =$KN48*0 -> 0 | EF48: 2 | EG48: 0 | EI48: 5 | EJ48: 3 | EK48: 2 | EM48: 5 | EN48: 1 | EO48: 0 | EQ48: =$KN48*10 -> 10 | ER48: 0 | EU48: =$KN48*15 -> 15 | EV48: 2 | EY48: =$KN48*20 -> 20 | EZ48: 16 | FC48: =$KN48*25 -> 25 | FD48: 18 | FG48: =$KN48*30 -> 30 | FH48: 10 | FK48: =$KN48*35 -> 35 | FL48: 10 | FO48: =$KN48*40 -> 40 | FP48: 15 | FS48: =$KN48*45 -> 45 | FT48: 15 | FW48: =$KN48*50 -> 50 | FX48: 15 | GA48: {=SUMPRODUCT(--(MOD(COLUMN($EE48:$FZ48),4)=MOD(COLUMN($EE48),4)),$EE48:$FZ48)} -> 280 | GB48: =GA48*$J48 -> 125393.33 | GC48: {=SUMPRODUCT(--(MOD(COLUMN($EE48:$FZ48),4)=MOD(COLUMN($EF48),4)),$EE48:$FZ48)} -> 107 | GD48: =GC48*$J48 -> 47918.167 | GE48: {=SUMPRODUCT(--(MOD(COLUMN($EE48:$FZ48),4)=MOD(COLUMN($EG48),4)),$EE48:$FZ48)} -> 2 | GF48: =GE48*$J48 -> 895.66667 | GG48: =$KN48*40 -> 40 | GK48: =$KN48*40 -> 40 | GO48: =$KN48*45 -> 45 | GS48: =$KN48*50 -> 50 | GW48: =$KN48*50 -> 50 | HA48: =$KN48*50 -> 50 | HE48: =$KN48*50 -> 50 | HI48: =$KN48*50 -> 50 | HM48: =$KN48*50 -> 50 | HQ48: =$KN48*50 -> 50 | HU48: =$KN48*50 -> 50 | HY48: =$KN48*50 -> 50 | IC48: {=SUMPRODUCT(--(MOD(COLUMN($GG48:$IB48),4)=MOD(COLUMN($GG48),4)),$GG48:$IB48)} -> 575 | ID48: =IC48*$J48 -> 257504.17 | IE48: {=SUMPRODUCT(--(MOD(COLUMN($GG48:$IB48),4)=MOD(COLUMN($GH48),4)),$GG48:$IB48)} -> 0 | IF48: =IE48*$J48 -> 0 | IG48: {=SUMPRODUCT(--(MOD(COLUMN($GG48:$IB48),4)=MOD(COLUMN($GI48),4)),$GG48:$IB48)} -> 0 | IH48: =IG48*$J48 -> 0 | II48: =$KN48*45 -> 45 | IM48: =$KN48*45 -> 45 | IQ48: =$KN48*50 -> 50 | IU48: =$KN48*55 -> 55 | IY48: =$KN48*55 -> 55 | JC48: =$KN48*55 -> 55 | JG48: =$KN48*60 -> 60 | JK48: =$KN48*60 -> 60 | JO48: =$KN48*60 -> 60 | JS48: =$KN48*60 -> 60 | JW48: =$KN48*60 -> 60 | KA48: =$KN48*60 -> 60 | KE48: {=SUMPRODUCT(--(MOD(COLUMN($II48:$KD48),4)=MOD(COLUMN($II48),4)),$II48:$KD48)} -> 665 | KF48: =KE48*$J48 -> 297809.17 | KG48: {=SUMPRODUCT(--(MOD(COLUMN($II48:$KD48),4)=MOD(COLUMN($IJ48),4)),$II48:$KD48)} -> 0 | KH48: =KG48*$J48 -> 0 | KI48: {=SUMPRODUCT(--(MOD(COLUMN($II48:$KD48),4)=MOD(COLUMN($IK48),4)),$II48:$KD48)} -> 0 | KJ48: =KI48*$J48 -> 0 | KN48: 1
E49: 13 | F49: 1 | G49: 4334010030 | H49: Упругий элемент | I49: =41.9/1.2/0.98 -> 35.629252 | J49: =41.9/1.2 -> 34.916667 | M49: 0 | N49: 0 | O49: 0 | Q49: 0 | R49: 0 | S49: 0 | U49: 0 | V49: 0 | W49: 0 | Y49: 5 | Z49: 0 | AA49: 0 | AC49: 20 | AD49: 0 | AE49: 0 | AG49: 20 | AH49: 0 | AI49: 0 | AK49: 20 | AL49: 0 | AM49: 0 | AO49: 20 | AP49: 0 | AQ49: 0 | AS49: 20 | AT49: 0 | AU49: 0 | AW49: 20 | AX49: 0 | AY49: 0 | BA49: 20 | BB49: 0 | BC49: 0 | BE49: 20 | BF49: =$KN49*0 -> 0 | BG49: 0 | BI49: =SUMPRODUCT(--(MOD(COLUMN($M49:$BH49),4)=MOD(COLUMN($M49),4)),$M49:$BH49) -> 165 | BJ49: =BI49*$I49 -> 5878.8265 | BK49: =SUMPRODUCT(--(MOD(COLUMN($M49:$BH49),4)=MOD(COLUMN($M49)+1,4)),$M49:$BH49) -> 0 | BL49: =BK49*$I49 -> 0 | BM49: =SUMPRODUCT(--(MOD(COLUMN($M49:$BH49),4)=MOD(COLUMN($M49)+2,4)),$M49:$BH49) -> 0 | BN49: =BM49*$I49 -> 0 | BO49: =$KN49*5 -> 5 | BP49: =$KN49*0 -> 0 | BQ49: =$KN49*5 -> 5 | BR49: 0 | BT49: =$KN49*5 -> 5 | BU49: =$KN49*1 -> 1 | BV49: =$KN49*0 -> 0 | BW49: 0 | BY49: =$KN49*5 -> 5 | BZ49: =$KN49*0 -> 0 | CA49: =$KN49*0 -> 0 | CB49: 0 | CD49: =$KN49*5 -> 5 | CE49: =$KN49*0 -> 0 | CF49: =$KN49*0 -> 0 | CG49: 0 | CI49: =$KN49*5 -> 5 | CJ49: =$KN49*5 -> 5 | CK49: =$KN49*0 -> 0 | CL49: 0 | CN49: =$KN49*5 -> 5 | CO49: =$KN49*5 -> 5 | CP49: =$KN49*0 -> 0 | CQ49: 0 | CS49: =$KN49*20 -> 20 | CT49: =$KN49*20 -> 20 | CU49: =$KN49*0 -> 0 | CV49: 0 | CX49: =$KN49*20 -> 20 | CY49: =$KN49*20 -> 20 | CZ49: =$KN49*0 -> 0 | DA49: 0 | DC49: =$KN49*20 -> 20 | DD49: =$KN49*20 -> 20 | DE49: =$KN49*0 -> 0 | DF49: 0 | DH49: =$KN49*20 -> 20 | DI49: =$KN49*20 -> 20 | DJ49: =$KN49*0 -> 0 | DK49: 0 | DM49: =$KN49*20 -> 20 | DN49: =$KN49*20 -> 20 | DO49: =$KN49*0 -> 0 | DP49: 0 | DR49: =$KN49*20 -> 20 | DS49: =$KN49*20 -> 20 | DT49: =$KN49*0 -> 0 | DU49: 0 | DW49: {=SUMPRODUCT(--(MOD(COLUMN($BO49:$DV49),5)=MOD(COLUMN($BO49),5)),$BO49:$DV49)} -> 150 | DX49: =DW49*$J49 -> 5237.5 | DY49: {=SUMPRODUCT(--(MOD(COLUMN($BO49:$DV49),5)=MOD(COLUMN($BP49),5)),$BO49:$DV49)} -> 131 | DZ49: =DY49*$J49 -> 4574.0833 | EA49: {=SUMPRODUCT(--(MOD(COLUMN($BO49:$DV49),5)=MOD(COLUMN($BQ49),5)),$BO49:$DV49)} -> 5 | EB49: =EA49*$J49 -> 174.58333 | EC49: {=SUMPRODUCT(--(MOD(COLUMN($BO49:$DV49),5)=MOD(COLUMN($BR49),5)),$BO49:$DV49)} -> 0 | ED49: =EC49*$J49 -> 0 | EE49: =$KN49*0 -> 0 | EF49: 2 | EG49: 0 | EI49: 5 | EJ49: 3 | EK49: 2 | EM49: 5 | EN49: 1 | EO49: 0 | EQ49: =$KN49*10 -> 10 | ER49: 0 | EU49: =$KN49*15 -> 15 | EV49: 4 | EY49: =$KN49*20 -> 20 | EZ49: 16 | FC49: =$KN49*25 -> 25 | FD49: 18 | FG49: =$KN49*30 -> 30 | FH49: 10 | FK49: =$KN49*35 -> 35 | FL49: 10 | FO49: =$KN49*40 -> 40 | FP49: 15 | FS49: =$KN49*45 -> 45 | FT49: 15 | FW49: =$KN49*50 -> 50 | FX49: 15 | GA49: {=SUMPRODUCT(--(MOD(COLUMN($EE49:$FZ49),4)=MOD(COLUMN($EE49),4)),$EE49:$FZ49)} -> 280 | GB49: =GA49*$J49 -> 9776.6667 | GC49: {=SUMPRODUCT(--(MOD(COLUMN($EE49:$FZ49),4)=MOD(COLUMN($EF49),4)),$EE49:$FZ49)} -> 109 | GD49: =GC49*$J49 -> 3805.9167 | GE49: {=SUMPRODUCT(--(MOD(COLUMN($EE49:$FZ49),4)=MOD(COLUMN($EG49),4)),$EE49:$FZ49)} -> 2 | GF49: =GE49*$J49 -> 69.833333 | GG49: =$KN49*40 -> 40 | GK49: =$KN49*40 -> 40 | GO49: =$KN49*45 -> 45 | GS49: =$KN49*50 -> 50 | GW49: =$KN49*50 -> 50 | HA49: =$KN49*50 -> 50 | HE49: =$KN49*50 -> 50 | HI49: =$KN49*50 -> 50 | HM49: =$KN49*50 -> 50 | HQ49: =$KN49*50 -> 50 | HU49: =$KN49*50 -> 50 | HY49: =$KN49*50 -> 50 | IC49: {=SUMPRODUCT(--(MOD(COLUMN($GG49:$IB49),4)=MOD(COLUMN($GG49),4)),$GG49:$IB49)} -> 575 | ID49: =IC49*$J49 -> 20077.083 | IE49: {=SUMPRODUCT(--(MOD(COLUMN($GG49:$IB49),4)=MOD(COLUMN($GH49),4)),$GG49:$IB49)} -> 0 | IF49: =IE49*$J49 -> 0 | IG49: {=SUMPRODUCT(--(MOD(COLUMN($GG49:$IB49),4)=MOD(COLUMN($GI49),4)),$GG49:$IB49)} -> 0 | IH49: =IG49*$J49 -> 0 | II49: =$KN49*45 -> 45 | IM49: =$KN49*45 -> 45 | IQ49: =$KN49*50 -> 50 | IU49: =$KN49*55 -> 55 | IY49: =$KN49*55 -> 55 | JC49: =$KN49*55 -> 55 | JG49: =$KN49*60 -> 60 | JK49: =$KN49*60 -> 60 | JO49: =$KN49*60 -> 60 | JS49: =$KN49*60 -> 60 | JW49: =$KN49*60 -> 60 | KA49: =$KN49*60 -> 60 | KE49: {=SUMPRODUCT(--(MOD(COLUMN($II49:$KD49),4)=MOD(COLUMN($II49),4)),$II49:$KD49)} -> 665 | KF49: =KE49*$J49 -> 23219.583 | KG49: {=SUMPRODUCT(--(MOD(COLUMN($II49:$KD49),4)=MOD(COLUMN($IJ49),4)),$II49:$KD49)} -> 0 | KH49: =KG49*$J49 -> 0 | KI49: {=SUMPRODUCT(--(MOD(COLUMN($II49:$KD49),4)=MOD(COLUMN($IK49),4)),$II49:$KD49)} -> 0 | KJ49: =KI49*$J49 -> 0 | KN49: 1
E50: 14 | F50: 1 | G50: 4630840310 | H50: Клапан управления подъемом оси (LACV) | I50: =657.1/1.2/0.98 -> 558.7585 | J50: =657.1/1.2 -> 547.58333 | M50: 0 | N50: 0 | O50: 0 | Q50: 0 | R50: 0 | S50: 0 | U50: 0 | V50: 0 | W50: 0 | Y50: 5 | Z50: 0 | AA50: 0 | AC50: 20 | AD50: 0 | AE50: 0 | AG50: 20 | AH50: 0 | AI50: 0 | AK50: 20 | AL50: 0 | AM50: 0 | AO50: 20 | AP50: 0 | AQ50: 0 | AS50: 20 | AT50: 0 | AU50: 0 | AW50: 20 | AX50: 0 | AY50: 0 | BA50: 20 | BB50: 0 | BC50: 0 | BE50: 20 | BF50: =$KN50*0 -> 0 | BG50: 0 | BI50: =SUMPRODUCT(--(MOD(COLUMN($M50:$BH50),4)=MOD(COLUMN($M50),4)),$M50:$BH50) -> 165 | BJ50: =BI50*$I50 -> 92195.153 | BK50: =SUMPRODUCT(--(MOD(COLUMN($M50:$BH50),4)=MOD(COLUMN($M50)+1,4)),$M50:$BH50) -> 0 | BL50: =BK50*$I50 -> 0 | BM50: =SUMPRODUCT(--(MOD(COLUMN($M50:$BH50),4)=MOD(COLUMN($M50)+2,4)),$M50:$BH50) -> 0 | BN50: =BM50*$I50 -> 0 | BO50: =$KN50*5 -> 5 | BP50: =$KN50*0 -> 0 | BQ50: =$KN50*5 -> 5 | BR50: 2 | BT50: =$KN50*5 -> 5 | BU50: =$KN50*1 -> 1 | BV50: =$KN50*10 -> 10 | BW50: 10 | BY50: =$KN50*5 -> 5 | BZ50: =$KN50*0 -> 0 | CA50: =$KN50*0 -> 0 | CB50: 0 | CD50: =$KN50*5 -> 5 | CE50: =$KN50*0 -> 0 | CF50: =$KN50*0 -> 0 | CG50: 0 | CI50: =$KN50*5 -> 5 | CJ50: =$KN50*5 -> 5 | CK50: =$KN50*0 -> 0 | CL50: 0 | CN50: =$KN50*5 -> 5 | CO50: =$KN50*5 -> 5 | CP50: =$KN50*0 -> 0 | CQ50: 0 | CS50: =$KN50*20 -> 20 | CT50: =$KN50*20 -> 20 | CU50: =$KN50*0 -> 0 | CV50: 0 | CX50: =$KN50*20 -> 20 | CY50: =$KN50*20 -> 20 | CZ50: =$KN50*0 -> 0 | DA50: 0 | DC50: =$KN50*20 -> 20 | DD50: =$KN50*20 -> 20 | DE50: =$KN50*0 -> 0 | DF50: 0 | DH50: =$KN50*20 -> 20 | DI50: =$KN50*20 -> 20 | DJ50: =$KN50*0 -> 0 | DK50: 0 | DM50: =$KN50*20 -> 20 | DN50: =$KN50*20 -> 20 | DO50: =$KN50*0 -> 0 | DP50: 0 | DR50: =$KN50*20 -> 20 | DS50: =$KN50*20 -> 20 | DT50: =$KN50*0 -> 0 | DU50: 0 | DW50: {=SUMPRODUCT(--(MOD(COLUMN($BO50:$DV50),5)=MOD(COLUMN($BO50),5)),$BO50:$DV50)} -> 150 | DX50: =DW50*$J50 -> 82137.5 | DY50: {=SUMPRODUCT(--(MOD(COLUMN($BO50:$DV50),5)=MOD(COLUMN($BP50),5)),$BO50:$DV50)} -> 131 | DZ50: =DY50*$J50 -> 71733.417 | EA50: {=SUMPRODUCT(--(MOD(COLUMN($BO50:$DV50),5)=MOD(COLUMN($BQ50),5)),$BO50:$DV50)} -> 15 | EB50: =EA50*$J50 -> 8213.75 | EC50: {=SUMPRODUCT(--(MOD(COLUMN($BO50:$DV50),5)=MOD(COLUMN($BR50),5)),$BO50:$DV50)} -> 12 | ED50: =EC50*$J50 -> 6571 | EE50: =$KN50*0 -> 0 | EF50: 1 | EG50: 0 | EI50: 5 | EJ50: 1 | EK50: 1 | EM50: 5 | EN50: 0 | EO50: 0 | EQ50: =$KN50*10 -> 10 | ER50: 0 | ES50: 1 | EU50: =$KN50*15 -> 15 | EV50: 2 | EY50: =$KN50*20 -> 20 | EZ50: 32 | FC50: =$KN50*25 -> 25 | FD50: 33 | FG50: =$KN50*30 -> 30 | FH50: 10 | FK50: =$KN50*35 -> 35 | FL50: 10 | FO50: =$KN50*40 -> 40 | FP50: 15 | FS50: =$KN50*45 -> 45 | FT50: 15 | FW50: =$KN50*50 -> 50 | FX50: 15 | GA50: =SUMPRODUCT(--(MOD(COLUMN($EE50:$FZ50),4)=MOD(COLUMN($EE50),4)),$EE50:$FZ50) -> 280 | GB50: =GA50*$J50 -> 153323.33 | GC50: =SUMPRODUCT(--(MOD(COLUMN($EE50:$FZ50),4)=MOD(COLUMN($EF50),4)),$EE50:$FZ50) -> 134 | GD50: =GC50*$J50 -> 73376.167 | GE50: =SUMPRODUCT(--(MOD(COLUMN($EE50:$FZ50),4)=MOD(COLUMN($EG50),4)),$EE50:$FZ50) -> 2 | GF50: =GE50*$J50 -> 1095.1667 | GG50: =$KN50*40 -> 40 | GK50: =$KN50*40 -> 40 | GO50: =$KN50*45 -> 45 | GS50: =$KN50*50 -> 50 | GW50: =$KN50*50 -> 50 | HA50: =$KN50*50 -> 50 | HE50: =$KN50*50 -> 50 | HI50: =$KN50*50 -> 50 | HM50: =$KN50*50 -> 50 | HQ50: =$KN50*50 -> 50 | HU50: =$KN50*50 -> 50 | HY50: =$KN50*50 -> 50 | IC50: {=SUMPRODUCT(--(MOD(COLUMN($GG50:$IB50),4)=MOD(COLUMN($GG50),4)),$GG50:$IB50)} -> 575 | ID50: =IC50*$J50 -> 314860.42 | IE50: {=SUMPRODUCT(--(MOD(COLUMN($GG50:$IB50),4)=MOD(COLUMN($GH50),4)),$GG50:$IB50)} -> 0 | IF50: =IE50*$J50 -> 0 | IG50: {=SUMPRODUCT(--(MOD(COLUMN($GG50:$IB50),4)=MOD(COLUMN($GI50),4)),$GG50:$IB50)} -> 0 | IH50: =IG50*$J50 -> 0 | II50: =$KN50*45 -> 45 | IM50: =$KN50*45 -> 45 | IQ50: =$KN50*50 -> 50 | IU50: =$KN50*55 -> 55 | IY50: =$KN50*55 -> 55 | JC50: =$KN50*55 -> 55 | JG50: =$KN50*60 -> 60 | JK50: =$KN50*60 -> 60 | JO50: =$KN50*60 -> 60 | JS50: =$KN50*60 -> 60 | JW50: =$KN50*60 -> 60 | KA50: =$KN50*60 -> 60 | KE50: {=SUMPRODUCT(--(MOD(COLUMN($II50:$KD50),4)=MOD(COLUMN($II50),4)),$II50:$KD50)} -> 665 | KF50: =KE50*$J50 -> 364142.92 | KG50: {=SUMPRODUCT(--(MOD(COLUMN($II50:$KD50),4)=MOD(COLUMN($IJ50),4)),$II50:$KD50)} -> 0 | KH50: =KG50*$J50 -> 0 | KI50: {=SUMPRODUCT(--(MOD(COLUMN($II50:$KD50),4)=MOD(COLUMN($IK50),4)),$II50:$KD50)} -> 0 | KJ50: =KI50*$J50 -> 0 | KN50: 1 | KO50: LACV
E51: 15 | F51: 1 | G51: 4494430600 | H51: Кабель клапана управления подъемом оси, 6 м | I51: =164.2/1.2/0.98 -> 139.62585 | J51: =164.2/1.2 -> 136.83333 | M51: 0 | N51: 0 | O51: 0 | Q51: 0 | R51: 0 | S51: 0 | U51: 0 | V51: 0 | W51: 0 | Y51: 5 | Z51: 0 | AA51: 0 | AC51: 20 | AD51: 0 | AE51: 0 | AG51: 20 | AH51: 0 | AI51: 0 | AK51: 20 | AL51: 0 | AO51: 20 | AP51: 0 | AQ51: 0 | AS51: 20 | AT51: 0 | AU51: 0 | AW51: 20 | AX51: 0 | AY51: 0 | BA51: 20 | BB51: 0 | BC51: 0 | BE51: 20 | BF51: =$KN51*0 -> 0 | BG51: 0 | BI51: =SUMPRODUCT(--(MOD(COLUMN($M51:$BH51),4)=MOD(COLUMN($M51),4)),$M51:$BH51) -> 165 | BJ51: =BI51*$I51 -> 23038.265 | BK51: =SUMPRODUCT(--(MOD(COLUMN($M51:$BH51),4)=MOD(COLUMN($M51)+1,4)),$M51:$BH51) -> 0 | BL51: =BK51*$I51 -> 0 | BM51: =SUMPRODUCT(--(MOD(COLUMN($M51:$BH51),4)=MOD(COLUMN($M51)+2,4)),$M51:$BH51) -> 0 | BN51: =BM51*$I51 -> 0 | BO51: =$KN51*5 -> 5 | BP51: =$KN51*0 -> 0 | BQ51: =$KN51*5 -> 5 | BR51: 2 | BT51: =$KN51*5 -> 5 | BU51: =$KN51*1 -> 1 | BV51: =$KN51*10 -> 10 | BW51: 7 | BY51: =$KN51*5 -> 5 | BZ51: =$KN51*0 -> 0 | CA51: =$KN51*0 -> 0 | CB51: 0 | CD51: =$KN51*5 -> 5 | CE51: =$KN51*0 -> 0 | CF51: =$KN51*0 -> 0 | CG51: 0 | CI51: =$KN51*5 -> 5 | CJ51: =$KN51*5 -> 5 | CK51: =$KN51*0 -> 0 | CL51: 0 | CN51: =$KN51*5 -> 5 | CO51: =$KN51*5 -> 5 | CP51: =$KN51*0 -> 0 | CQ51: 0 | CS51: =$KN51*20 -> 20 | CT51: =$KN51*20 -> 20 | CU51: =$KN51*0 -> 0 | CV51: 0 | CX51: =$KN51*20 -> 20 | CY51: =$KN51*20 -> 20 | CZ51: =$KN51*0 -> 0 | DA51: 0 | DC51: =$KN51*20 -> 20 | DD51: =$KN51*20 -> 20 | DE51: =$KN51*0 -> 0 | DF51: 0 | DH51: =$KN51*20 -> 20 | DI51: =$KN51*20 -> 20 | DJ51: =$KN51*0 -> 0 | DK51: 0 | DM51: =$KN51*20 -> 20 | DN51: =$KN51*20 -> 20 | DO51: =$KN51*0 -> 0 | DP51: 0 | DR51: =$KN51*20 -> 20 | DS51: =$KN51*20 -> 20 | DT51: =$KN51*0 -> 0 | DU51: 0 | DW51: {=SUMPRODUCT(--(MOD(COLUMN($BO51:$DV51),5)=MOD(COLUMN($BO51),5)),$BO51:$DV51)} -> 150 | DX51: =DW51*$J51 -> 20525 | DY51: {=SUMPRODUCT(--(MOD(COLUMN($BO51:$DV51),5)=MOD(COLUMN($BP51),5)),$BO51:$DV51)} -> 131 | DZ51: =DY51*$J51 -> 17925.167 | EA51: {=SUMPRODUCT(--(MOD(COLUMN($BO51:$DV51),5)=MOD(COLUMN($BQ51),5)),$BO51:$DV51)} -> 15 | EB51: =EA51*$J51 -> 2052.5 | EC51: {=SUMPRODUCT(--(MOD(COLUMN($BO51:$DV51),5)=MOD(COLUMN($BR51),5)),$BO51:$DV51)} -> 9 | ED51: =EC51*$J51 -> 1231.5 | EE51: =$KN51*0 -> 0 | EF51: 3 | EG51: 0 | EI51: 5 | EJ51: 3 | EK51: 3 | EM51: 5 | EN51: 0 | EO51: 0 | EQ51: =$KN51*10 -> 10 | ER51: 0 | ES51: 1 | EU51: =$KN51*15 -> 15 | EV51: 2 | EY51: =$KN51*20 -> 20 | EZ51: 32 | FC51: =$KN51*25 -> 25 | FD51: 33 | FG51: =$KN51*30 -> 30 | FH51: 10 | FK51: =$KN51*35 -> 35 | FL51: 10 | FO51: =$KN51*40 -> 40 | FP51: 15 | FS51: =$KN51*45 -> 45 | FT51: 15 | FW51: =$KN51*50 -> 50 | FX51: 15 | GA51: =SUMPRODUCT(--(MOD(COLUMN($EE51:$FZ51),4)=MOD(COLUMN($EE51),4)),$EE51:$FZ51) -> 280 | GB51: =GA51*$J51 -> 38313.333 | GC51: =SUMPRODUCT(--(MOD(COLUMN($EE51:$FZ51),4)=MOD(COLUMN($EF51),4)),$EE51:$FZ51) -> 138 | GD51: =GC51*$J51 -> 18883 | GE51: =SUMPRODUCT(--(MOD(COLUMN($EE51:$FZ51),4)=MOD(COLUMN($EG51),4)),$EE51:$FZ51) -> 4 | GF51: =GE51*$J51 -> 547.33333 | GG51: =$KN51*40 -> 40 | GK51: =$KN51*40 -> 40 | GO51: =$KN51*45 -> 45 | GS51: =$KN51*50 -> 50 | GW51: =$KN51*50 -> 50 | HA51: =$KN51*50 -> 50 | HE51: =$KN51*50 -> 50 | HI51: =$KN51*50 -> 50 | HM51: =$KN51*50 -> 50 | HQ51: =$KN51*50 -> 50 | HU51: =$KN51*50 -> 50 | HY51: =$KN51*50 -> 50 | IC51: {=SUMPRODUCT(--(MOD(COLUMN($GG51:$IB51),4)=MOD(COLUMN($GG51),4)),$GG51:$IB51)} -> 575 | ID51: =IC51*$J51 -> 78679.167 | IE51: {=SUMPRODUCT(--(MOD(COLUMN($GG51:$IB51),4)=MOD(COLUMN($GH51),4)),$GG51:$IB51)} -> 0 | IF51: =IE51*$J51 -> 0 | IG51: {=SUMPRODUCT(--(MOD(COLUMN($GG51:$IB51),4)=MOD(COLUMN($GI51),4)),$GG51:$IB51)} -> 0 | IH51: =IG51*$J51 -> 0 | II51: =$KN51*45 -> 45 | IM51: =$KN51*45 -> 45 | IQ51: =$KN51*50 -> 50 | IU51: =$KN51*55 -> 55 | IY51: =$KN51*55 -> 55 | JC51: =$KN51*55 -> 55 | JG51: =$KN51*60 -> 60 | JK51: =$KN51*60 -> 60 | JO51: =$KN51*60 -> 60 | JS51: =$KN51*60 -> 60 | JW51: =$KN51*60 -> 60 | KA51: =$KN51*60 -> 60 | KE51: {=SUMPRODUCT(--(MOD(COLUMN($II51:$KD51),4)=MOD(COLUMN($II51),4)),$II51:$KD51)} -> 665 | KF51: =KE51*$J51 -> 90994.167 | KG51: {=SUMPRODUCT(--(MOD(COLUMN($II51:$KD51),4)=MOD(COLUMN($IJ51),4)),$II51:$KD51)} -> 0 | KH51: =KG51*$J51 -> 0 | KI51: {=SUMPRODUCT(--(MOD(COLUMN($II51:$KD51),4)=MOD(COLUMN($IK51),4)),$II51:$KD51)} -> 0 | KJ51: =KI51*$J51 -> 0 | KN51: 1
E52: 16 | F52: 1 | G52: 4802070100 | H52: Ускорительный клапан TEBS | I52: 3264 | J52: 3264 | N52: 1 | O52: 0 | R52: 1 | S52: 1 | DU52: 0 | DW52: {=SUMPRODUCT(--(MOD(COLUMN($BO52:$DV52),5)=MOD(COLUMN($BO52),5)),$BO52:$DV52)} -> 0 | DX52: =DW52*$J52 -> 0 | DY52: {=SUMPRODUCT(--(MOD(COLUMN($BO52:$DV52),5)=MOD(COLUMN($BP52),5)),$BO52:$DV52)} -> 0 | DZ52: =DY52*$J52 -> 0 | EA52: {=SUMPRODUCT(--(MOD(COLUMN($BO52:$DV52),5)=MOD(COLUMN($BQ52),5)),$BO52:$DV52)} -> 0 | EB52: =EA52*$J52 -> 0 | EC52: {=SUMPRODUCT(--(MOD(COLUMN($BO52:$DV52),5)=MOD(COLUMN($BR52),5)),$BO52:$DV52)} -> 0 | ED52: =EC52*$J52 -> 0 | EF52: 1 | EG52: 0 | EH52: Новый артикул | EJ52: 1 | EK52: 1 | EL52: Изменение артикула | EO52: 0 | ER52: 0 | GA52: {=SUMPRODUCT(--(MOD(COLUMN($EE52:$FZ52),4)=MOD(COLUMN($EE52),4)),$EE52:$FZ52)} -> 0 | GB52: =GA52*$J52 -> 0 | GC52: {=SUMPRODUCT(--(MOD(COLUMN($EE52:$FZ52),4)=MOD(COLUMN($EF52),4)),$EE52:$FZ52)} -> 2 | GD52: =GC52*$J52 -> 6528 | GE52: {=SUMPRODUCT(--(MOD(COLUMN($EE52:$FZ52),4)=MOD(COLUMN($EG52),4)),$EE52:$FZ52)} -> 1 | GF52: =GE52*$J52 -> 3264 | IC52: {=SUMPRODUCT(--(MOD(COLUMN($GG52:$IB52),4)=MOD(COLUMN($GG52),4)),$GG52:$IB52)} -> 0 | ID52: =IC52*$J52 -> 0 | IE52: {=SUMPRODUCT(--(MOD(COLUMN($GG52:$IB52),4)=MOD(COLUMN($GH52),4)),$GG52:$IB52)} -> 0 | IF52: =IE52*$J52 -> 0 | IG52: {=SUMPRODUCT(--(MOD(COLUMN($GG52:$IB52),4)=MOD(COLUMN($GI52),4)),$GG52:$IB52)} -> 0 | IH52: =IG52*$J52 -> 0 | KE52: {=SUMPRODUCT(--(MOD(COLUMN($II52:$KD52),4)=MOD(COLUMN($II52),4)),$II52:$KD52)} -> 0 | KF52: =KE52*$J52 -> 0 | KG52: {=SUMPRODUCT(--(MOD(COLUMN($II52:$KD52),4)=MOD(COLUMN($IJ52),4)),$II52:$KD52)} -> 0 | KH52: =KG52*$J52 -> 0 | KI52: {=SUMPRODUCT(--(MOD(COLUMN($II52:$KD52),4)=MOD(COLUMN($IK52),4)),$II52:$KD52)} -> 0 | KJ52: =KI52*$J52 -> 0
E53: 17 | F53: 1 | G53: 4802070600 | H53: Ускорительный клапан TEBS | I53: 1056 | J53: 1056 | DU53: 0 | DW53: {=SUMPRODUCT(--(MOD(COLUMN($BO53:$DV53),5)=MOD(COLUMN($BO53),5)),$BO53:$DV53)} -> 0 | DX53: =DW53*$J53 -> 0 | DY53: {=SUMPRODUCT(--(MOD(COLUMN($BO53:$DV53),5)=MOD(COLUMN($BP53),5)),$BO53:$DV53)} -> 0 | DZ53: =DY53*$J53 -> 0 | EA53: {=SUMPRODUCT(--(MOD(COLUMN($BO53:$DV53),5)=MOD(COLUMN($BQ53),5)),$BO53:$DV53)} -> 0 | EB53: =EA53*$J53 -> 0 | EC53: {=SUMPRODUCT(--(MOD(COLUMN($BO53:$DV53),5)=MOD(COLUMN($BR53),5)),$BO53:$DV53)} -> 0 | ED53: =EC53*$J53 -> 0 | EF53: 1 | EG53: 0 | EH53: Новый артикул | EJ53: 1 | EK53: 1 | EL53: Изменение артикула | EO53: 0 | ER53: 0 | EV53: 2 | EZ53: 16 | FD53: 15 | GA53: {=SUMPRODUCT(--(MOD(COLUMN($EE53:$FZ53),4)=MOD(COLUMN($EE53),4)),$EE53:$FZ53)} -> 0 | GB53: =GA53*$J53 -> 0 | GC53: {=SUMPRODUCT(--(MOD(COLUMN($EE53:$FZ53),4)=MOD(COLUMN($EF53),4)),$EE53:$FZ53)} -> 35 | GD53: =GC53*$J53 -> 36960 | GE53: {=SUMPRODUCT(--(MOD(COLUMN($EE53:$FZ53),4)=MOD(COLUMN($EG53),4)),$EE53:$FZ53)} -> 1 | GF53: =GE53*$J53 -> 1056 | IC53: {=SUMPRODUCT(--(MOD(COLUMN($GG53:$IB53),4)=MOD(COLUMN($GG53),4)),$GG53:$IB53)} -> 0 | ID53: =IC53*$J53 -> 0 | IE53: {=SUMPRODUCT(--(MOD(COLUMN($GG53:$IB53),4)=MOD(COLUMN($GH53),4)),$GG53:$IB53)} -> 0 | IF53: =IE53*$J53 -> 0 | IG53: {=SUMPRODUCT(--(MOD(COLUMN($GG53:$IB53),4)=MOD(COLUMN($GI53),4)),$GG53:$IB53)} -> 0 | IH53: =IG53*$J53 -> 0 | KE53: {=SUMPRODUCT(--(MOD(COLUMN($II53:$KD53),4)=MOD(COLUMN($II53),4)),$II53:$KD53)} -> 0 | KF53: =KE53*$J53 -> 0 | KG53: {=SUMPRODUCT(--(MOD(COLUMN($II53:$KD53),4)=MOD(COLUMN($IJ53),4)),$II53:$KD53)} -> 0 | KH53: =KG53*$J53 -> 0 | KI53: {=SUMPRODUCT(--(MOD(COLUMN($II53:$KD53),4)=MOD(COLUMN($IK53),4)),$II53:$KD53)} -> 0 | KJ53: =KI53*$J53 -> 0
E54: 18 | F54: 1 | G54: 4494300600 | H54: Кабель клапана ускорительного TEBS, 6 м | I54: 429 | J54: 429 | EO54: 0 | ER54: 0 | EV54: 1 | EZ54: 16 | FD54: 15 | GA54: {=SUMPRODUCT(--(MOD(COLUMN($EE54:$FZ54),4)=MOD(COLUMN($EE54),4)),$EE54:$FZ54)} -> 0 | GB54: =GA54*$J54 -> 0 | GC54: {=SUMPRODUCT(--(MOD(COLUMN($EE54:$FZ54),4)=MOD(COLUMN($EF54),4)),$EE54:$FZ54)} -> 32 | GD54: =GC54*$J54 -> 13728 | GE54: {=SUMPRODUCT(--(MOD(COLUMN($EE54:$FZ54),4)=MOD(COLUMN($EG54),4)),$EE54:$FZ54)} -> 0 | GF54: =GE54*$J54 -> 0 | IC54: {=SUMPRODUCT(--(MOD(COLUMN($GG54:$IB54),4)=MOD(COLUMN($GG54),4)),$GG54:$IB54)} -> 0 | ID54: =IC54*$J54 -> 0 | IE54: {=SUMPRODUCT(--(MOD(COLUMN($GG54:$IB54),4)=MOD(COLUMN($GH54),4)),$GG54:$IB54)} -> 0 | IF54: =IE54*$J54 -> 0 | IG54: {=SUMPRODUCT(--(MOD(COLUMN($GG54:$IB54),4)=MOD(COLUMN($GI54),4)),$GG54:$IB54)} -> 0 | IH54: =IG54*$J54 -> 0 | KE54: {=SUMPRODUCT(--(MOD(COLUMN($II54:$KD54),4)=MOD(COLUMN($II54),4)),$II54:$KD54)} -> 0 | KF54: =KE54*$J54 -> 0 | KG54: {=SUMPRODUCT(--(MOD(COLUMN($II54:$KD54),4)=MOD(COLUMN($IJ54),4)),$II54:$KD54)} -> 0 | KH54: =KG54*$J54 -> 0 | KI54: {=SUMPRODUCT(--(MOD(COLUMN($II54:$KD54),4)=MOD(COLUMN($IK54),4)),$II54:$KD54)} -> 0 | KJ54: =KI54*$J54 -> 0
E55: 19 | F55: 1 | G55: 9522002220 | H55: Головка соединительная тягача (желтая, М16х1,5) | J55: =66.45/1.2 -> 55.375 | DU55: 0 | DW55: {=SUMPRODUCT(--(MOD(COLUMN($BO55:$DV55),5)=MOD(COLUMN($BO55),5)),$BO55:$DV55)} -> 0 | DX55: =DW55*$J55 -> 0 | DY55: {=SUMPRODUCT(--(MOD(COLUMN($BO55:$DV55),5)=MOD(COLUMN($BP55),5)),$BO55:$DV55)} -> 0 | DZ55: =DY55*$J55 -> 0 | EA55: {=SUMPRODUCT(--(MOD(COLUMN($BO55:$DV55),5)=MOD(COLUMN($BQ55),5)),$BO55:$DV55)} -> 0 | EB55: =EA55*$J55 -> 0 | EC55: {=SUMPRODUCT(--(MOD(COLUMN($BO55:$DV55),5)=MOD(COLUMN($BR55),5)),$BO55:$DV55)} -> 0 | ED55: =EC55*$J55 -> 0 | EF55: 1 | EG55: 0 | EH55: Новый артикул | EJ55: 1 | EK55: 1 | EO55: 0 | GA55: {=SUMPRODUCT(--(MOD(COLUMN($EE55:$FZ55),4)=MOD(COLUMN($EE55),4)),$EE55:$FZ55)} -> 0 | GB55: =GA55*$J55 -> 0 | GC55: {=SUMPRODUCT(--(MOD(COLUMN($EE55:$FZ55),4)=MOD(COLUMN($EF55),4)),$EE55:$FZ55)} -> 2 | GD55: =GC55*$J55 -> 110.75 | GE55: {=SUMPRODUCT(--(MOD(COLUMN($EE55:$FZ55),4)=MOD(COLUMN($EG55),4)),$EE55:$FZ55)} -> 1 | GF55: =GE55*$J55 -> 55.375 | IC55: {=SUMPRODUCT(--(MOD(COLUMN($GG55:$IB55),4)=MOD(COLUMN($GG55),4)),$GG55:$IB55)} -> 0 | ID55: =IC55*$J55 -> 0 | IE55: {=SUMPRODUCT(--(MOD(COLUMN($GG55:$IB55),4)=MOD(COLUMN($GH55),4)),$GG55:$IB55)} -> 0 | IF55: =IE55*$J55 -> 0 | IG55: {=SUMPRODUCT(--(MOD(COLUMN($GG55:$IB55),4)=MOD(COLUMN($GI55),4)),$GG55:$IB55)} -> 0 | IH55: =IG55*$J55 -> 0 | KE55: {=SUMPRODUCT(--(MOD(COLUMN($II55:$KD55),4)=MOD(COLUMN($II55),4)),$II55:$KD55)} -> 0 | KF55: =KE55*$J55 -> 0 | KG55: {=SUMPRODUCT(--(MOD(COLUMN($II55:$KD55),4)=MOD(COLUMN($IJ55),4)),$II55:$KD55)} -> 0 | KH55: =KG55*$J55 -> 0 | KI55: {=SUMPRODUCT(--(MOD(COLUMN($II55:$KD55),4)=MOD(COLUMN($IK55),4)),$II55:$KD55)} -> 0 | KJ55: =KI55*$J55 -> 0
E56: 20 | F56: 1 | G56: 9522002210 | H56: Головка соединительная тягача (красная, М16х1,5) | J56: =66.45/1.2 -> 55.375 | DU56: 0 | DW56: {=SUMPRODUCT(--(MOD(COLUMN($BO56:$DV56),5)=MOD(COLUMN($BO56),5)),$BO56:$DV56)} -> 0 | DX56: =DW56*$J56 -> 0 | DY56: {=SUMPRODUCT(--(MOD(COLUMN($BO56:$DV56),5)=MOD(COLUMN($BP56),5)),$BO56:$DV56)} -> 0 | DZ56: =DY56*$J56 -> 0 | EA56: {=SUMPRODUCT(--(MOD(COLUMN($BO56:$DV56),5)=MOD(COLUMN($BQ56),5)),$BO56:$DV56)} -> 0 | EB56: =EA56*$J56 -> 0 | EC56: {=SUMPRODUCT(--(MOD(COLUMN($BO56:$DV56),5)=MOD(COLUMN($BR56),5)),$BO56:$DV56)} -> 0 | ED56: =EC56*$J56 -> 0 | EF56: 1 | EH56: Новый артикул | EJ56: 1 | EK56: 1 | EO56: 0 | GA56: {=SUMPRODUCT(--(MOD(COLUMN($EE56:$FZ56),4)=MOD(COLUMN($EE56),4)),$EE56:$FZ56)} -> 0 | GB56: =GA56*$J56 -> 0 | GC56: {=SUMPRODUCT(--(MOD(COLUMN($EE56:$FZ56),4)=MOD(COLUMN($EF56),4)),$EE56:$FZ56)} -> 2 | GD56: =GC56*$J56 -> 110.75 | GE56: {=SUMPRODUCT(--(MOD(COLUMN($EE56:$FZ56),4)=MOD(COLUMN($EG56),4)),$EE56:$FZ56)} -> 1 | GF56: =GE56*$J56 -> 55.375 | IC56: {=SUMPRODUCT(--(MOD(COLUMN($GG56:$IB56),4)=MOD(COLUMN($GG56),4)),$GG56:$IB56)} -> 0 | ID56: =IC56*$J56 -> 0 | IE56: {=SUMPRODUCT(--(MOD(COLUMN($GG56:$IB56),4)=MOD(COLUMN($GH56),4)),$GG56:$IB56)} -> 0 | IF56: =IE56*$J56 -> 0 | IG56: {=SUMPRODUCT(--(MOD(COLUMN($GG56:$IB56),4)=MOD(COLUMN($GI56),4)),$GG56:$IB56)} -> 0 | IH56: =IG56*$J56 -> 0 | KE56: {=SUMPRODUCT(--(MOD(COLUMN($II56:$KD56),4)=MOD(COLUMN($II56),4)),$II56:$KD56)} -> 0 | KF56: =KE56*$J56 -> 0 | KG56: {=SUMPRODUCT(--(MOD(COLUMN($II56:$KD56),4)=MOD(COLUMN($IJ56),4)),$II56:$KD56)} -> 0 | KH56: =KG56*$J56 -> 0 | KI56: {=SUMPRODUCT(--(MOD(COLUMN($II56:$KD56),4)=MOD(COLUMN($IK56),4)),$II56:$KD56)} -> 0 | KJ56: =KI56*$J56 -> 0
E57: 21 | F57: 1 | G57: 4721950310 | H57: Ускорительный клапан АБС (3-й модулятор) | J57: 258 | EH57: Новый артикул | EJ57: 1 | EN57: 1 | EO57: 0 | EP57: Заказ февраля перенесена на март | EV57: 1 | EW57: 0 | EX57: Заказ марта перенесен на май | GA57: {=SUMPRODUCT(--(MOD(COLUMN($EE57:$FZ57),4)=MOD(COLUMN($EE57),4)),$EE57:$FZ57)} -> 0 | GB57: =GA57*$J57 -> 0 | GC57: {=SUMPRODUCT(--(MOD(COLUMN($EE57:$FZ57),4)=MOD(COLUMN($EF57),4)),$EE57:$FZ57)} -> 3 | GD57: =GC57*$J57 -> 774 | GE57: {=SUMPRODUCT(--(MOD(COLUMN($EE57:$FZ57),4)=MOD(COLUMN($EG57),4)),$EE57:$FZ57)} -> 0 | GF57: =GE57*$J57 -> 0
E58: 22 | F58: 1 | G58: 4496161560 | H58: Кабель ускорительного клапана АБС, 10 м / диагностики, 3 м | J58: 205 | EJ58: 1 | EN58: 1 | EO58: 0 | EV58: 1 | GA58: {=SUMPRODUCT(--(MOD(COLUMN($EE58:$FZ58),4)=MOD(COLUMN($EE58),4)),$EE58:$FZ58)} -> 0 | GB58: =GA58*$J58 -> 0 | GC58: {=SUMPRODUCT(--(MOD(COLUMN($EE58:$FZ58),4)=MOD(COLUMN($EF58),4)),$EE58:$FZ58)} -> 3 | GD58: =GC58*$J58 -> 615 | GE58: {=SUMPRODUCT(--(MOD(COLUMN($EE58:$FZ58),4)=MOD(COLUMN($EG58),4)),$EE58:$FZ58)} -> 0 | GF58: =GE58*$J58 -> 0
E59: 23 | F59: 1 | G59: 9630010510 | H59: Клапан растормаживания сдвоенный | J59: 275 | EJ59: 1 | EN59: 1 | EO59: 0 | EV59: 1 | GA59: {=SUMPRODUCT(--(MOD(COLUMN($EE59:$FZ59),4)=MOD(COLUMN($EE59),4)),$EE59:$FZ59)} -> 0 | GB59: =GA59*$J59 -> 0 | GC59: {=SUMPRODUCT(--(MOD(COLUMN($EE59:$FZ59),4)=MOD(COLUMN($EF59),4)),$EE59:$FZ59)} -> 3 | GD59: =GC59*$J59 -> 825 | GE59: {=SUMPRODUCT(--(MOD(COLUMN($EE59:$FZ59),4)=MOD(COLUMN($EG59),4)),$EE59:$FZ59)} -> 0 | GF59: =GE59*$J59 -> 0
E60: 24 | F60: 1 | G60: 4640060020 | H60: Кран уровня пола | J60: 487 | EJ60: 1 | EN60: 1 | EO60: 0 | EV60: 1 | GA60: {=SUMPRODUCT(--(MOD(COLUMN($EE60:$FZ60),4)=MOD(COLUMN($EE60),4)),$EE60:$FZ60)} -> 0 | GB60: =GA60*$J60 -> 0 | GC60: {=SUMPRODUCT(--(MOD(COLUMN($EE60:$FZ60),4)=MOD(COLUMN($EF60),4)),$EE60:$FZ60)} -> 3 | GD60: =GC60*$J60 -> 1461 | GE60: {=SUMPRODUCT(--(MOD(COLUMN($EE60:$FZ60),4)=MOD(COLUMN($EG60),4)),$EE60:$FZ60)} -> 0 | GF60: =GE60*$J60 -> 0
E61: 25 | F61: 1 | G61: 4757145000 | H61: Регулятор тормозных сил | J61: 528 | EJ61: 1 | EN61: 1 | EO61: 0 | EV61: 1 | GA61: {=SUMPRODUCT(--(MOD(COLUMN($EE61:$FZ61),4)=MOD(COLUMN($EE61),4)),$EE61:$FZ61)} -> 0 | GB61: =GA61*$J61 -> 0 | GC61: {=SUMPRODUCT(--(MOD(COLUMN($EE61:$FZ61),4)=MOD(COLUMN($EF61),4)),$EE61:$FZ61)} -> 3 | GD61: =GC61*$J61 -> 1584 | GE61: {=SUMPRODUCT(--(MOD(COLUMN($EE61:$FZ61),4)=MOD(COLUMN($EG61),4)),$EE61:$FZ61)} -> 0 | GF61: =GE61*$J61 -> 0
E62: 26 | F62: 1 | G62: 4750103050 | H62: Клапан ограничения давления | J62: 104 | EJ62: 1 | EN62: 1 | EO62: 0 | EV62: 2 | GA62: {=SUMPRODUCT(--(MOD(COLUMN($EE62:$FZ62),4)=MOD(COLUMN($EE62),4)),$EE62:$FZ62)} -> 0 | GB62: =GA62*$J62 -> 0 | GC62: {=SUMPRODUCT(--(MOD(COLUMN($EE62:$FZ62),4)=MOD(COLUMN($EF62),4)),$EE62:$FZ62)} -> 4 | GD62: =GC62*$J62 -> 416 | GE62: {=SUMPRODUCT(--(MOD(COLUMN($EE62:$FZ62),4)=MOD(COLUMN($EG62),4)),$EE62:$FZ62)} -> 0 | GF62: =GE62*$J62 -> 0
E63: 27 | F63: 2 | G63: 4493792810 | H63: Кабель питания, часть 1 | J63: 194 | EJ63: 1 | EN63: 1 | EO63: 0 | EV63: 1 | GA63: {=SUMPRODUCT(--(MOD(COLUMN($EE63:$FZ63),4)=MOD(COLUMN($EE63),4)),$EE63:$FZ63)} -> 0 | GB63: =GA63*$J63 -> 0 | GC63: {=SUMPRODUCT(--(MOD(COLUMN($EE63:$FZ63),4)=MOD(COLUMN($EF63),4)),$EE63:$FZ63)} -> 3 | GD63: =GC63*$J63 -> 582 | GE63: {=SUMPRODUCT(--(MOD(COLUMN($EE63:$FZ63),4)=MOD(COLUMN($EG63),4)),$EE63:$FZ63)} -> 0 | GF63: =GE63*$J63 -> 0
E64: 28 | F64: 2 | G64: 4491301200 | H64: Кабель питания, часть 2, 12 м | J64: 580 | EJ64: 1 | EN64: 1 | EO64: 0 | EV64: 1 | GA64: {=SUMPRODUCT(--(MOD(COLUMN($EE64:$FZ64),4)=MOD(COLUMN($EE64),4)),$EE64:$FZ64)} -> 0 | GB64: =GA64*$J64 -> 0 | GC64: {=SUMPRODUCT(--(MOD(COLUMN($EE64:$FZ64),4)=MOD(COLUMN($EF64),4)),$EE64:$FZ64)} -> 3 | GD64: =GC64*$J64 -> 1740 | GE64: {=SUMPRODUCT(--(MOD(COLUMN($EE64:$FZ64),4)=MOD(COLUMN($EG64),4)),$EE64:$FZ64)} -> 0 | GF64: =GE64*$J64 -> 0
E65: 29 | F65: 2 | G65: 4497490300 | H65: Кабель-удлинитель датчика АБС, 3 м | J65: 58 | EJ65: 4 | EN65: 4 | EO65: 0 | EV65: 4 | GA65: {=SUMPRODUCT(--(MOD(COLUMN($EE65:$FZ65),4)=MOD(COLUMN($EE65),4)),$EE65:$FZ65)} -> 0 | GB65: =GA65*$J65 -> 0 | GC65: {=SUMPRODUCT(--(MOD(COLUMN($EE65:$FZ65),4)=MOD(COLUMN($EF65),4)),$EE65:$FZ65)} -> 12 | GD65: =GC65*$J65 -> 696 | GE65: {=SUMPRODUCT(--(MOD(COLUMN($EE65:$FZ65),4)=MOD(COLUMN($EG65),4)),$EE65:$FZ65)} -> 0 | GF65: =GE65*$J65 -> 0
E66: 30 | F66: 2 | G66: 9522010010 | H66: Головка соединительная, с фильтром, управляющая | I66: 96.4 | J66: =138.5/1.2 -> 115.41667 | BF66: =$KN66*0 -> 0 | BR66: 2 | BV66: =$KN66*10 -> 10 | BW66: 5 | BX66: Договор на 10 комплектов, будут забирать в течении года по мере необходимости | CB66: 0 | CG66: 0 | CL66: 0 | CQ66: 0 | CV66: 0 | DA66: 0 | DF66: 0 | DK66: 0 | DO66: =$KN66*0 -> 0 | DP66: 0 | DT66: =$KN66*0 -> 0 | DU66: 0 | DW66: {=SUMPRODUCT(--(MOD(COLUMN($BO66:$DV66),5)=MOD(COLUMN($BO66),5)),$BO66:$DV66)} -> 0 | DX66: =DW66*$J66 -> 0 | DY66: {=SUMPRODUCT(--(MOD(COLUMN($BO66:$DV66),5)=MOD(COLUMN($BP66),5)),$BO66:$DV66)} -> 0 | DZ66: =DY66*$J66 -> 0 | EA66: {=SUMPRODUCT(--(MOD(COLUMN($BO66:$DV66),5)=MOD(COLUMN($BQ66),5)),$BO66:$DV66)} -> 10 | EB66: =EA66*$J66 -> 1154.1667 | EC66: {=SUMPRODUCT(--(MOD(COLUMN($BO66:$DV66),5)=MOD(COLUMN($BR66),5)),$BO66:$DV66)} -> 7 | ED66: =EC66*$J66 -> 807.91667 | EJ66: 1 | EN66: 1 | EO66: 0 | EV66: 1 | GA66: {=SUMPRODUCT(--(MOD(COLUMN($EE66:$FZ66),4)=MOD(COLUMN($EE66),4)),$EE66:$FZ66)} -> 0 | GB66: =GA66*$J66 -> 0 | GC66: {=SUMPRODUCT(--(MOD(COLUMN($EE66:$FZ66),4)=MOD(COLUMN($EF66),4)),$EE66:$FZ66)} -> 3 | GD66: =GC66*$J66 -> 346.25 | GE66: {=SUMPRODUCT(--(MOD(COLUMN($EE66:$FZ66),4)=MOD(COLUMN($EG66),4)),$EE66:$FZ66)} -> 0 | GF66: =GE66*$J66 -> 0 | IC66: {=SUMPRODUCT(--(MOD(COLUMN($GG66:$IB66),4)=MOD(COLUMN($GG66),4)),$GG66:$IB66)} -> 0 | ID66: =IC66*$J66 -> 0 | IE66: {=SUMPRODUCT(--(MOD(COLUMN($GG66:$IB66),4)=MOD(COLUMN($GH66),4)),$GG66:$IB66)} -> 0 | IF66: =IE66*$J66 -> 0 | IG66: {=SUMPRODUCT(--(MOD(COLUMN($GG66:$IB66),4)=MOD(COLUMN($GI66),4)),$GG66:$IB66)} -> 0 | IH66: =IG66*$J66 -> 0 | KE66: {=SUMPRODUCT(--(MOD(COLUMN($II66:$KD66),4)=MOD(COLUMN($II66),4)),$II66:$KD66)} -> 0 | KF66: =KE66*$J66 -> 0 | KG66: {=SUMPRODUCT(--(MOD(COLUMN($II66:$KD66),4)=MOD(COLUMN($IJ66),4)),$II66:$KD66)} -> 0 | KH66: =KG66*$J66 -> 0 | KI66: {=SUMPRODUCT(--(MOD(COLUMN($II66:$KD66),4)=MOD(COLUMN($IK66),4)),$II66:$KD66)} -> 0 | KJ66: =KI66*$J66 -> 0 | KN66: 1 | KO66: TEBS WABCO 2s/2m 12м
E67: 31 | F67: 2 | G67: 9522010020 | H67: Головка соединительная, с фильтром, питающая | I67: 96.4 | J67: =138.5/1.2 -> 115.41667 | BF67: =$KN67*0 -> 0 | BR67: 2 | BV67: =$KN67*10 -> 10 | BW67: 6 | CB67: 0 | CG67: 0 | CL67: 0 | CQ67: 0 | CV67: 0 | DA67: 0 | DF67: 0 | DK67: 0 | DO67: =$KN67*0 -> 0 | DP67: 0 | DT67: =$KN67*0 -> 0 | DU67: 0 | DW67: {=SUMPRODUCT(--(MOD(COLUMN($BO67:$DV67),5)=MOD(COLUMN($BO67),5)),$BO67:$DV67)} -> 0 | DX67: =DW67*$J67 -> 0 | DY67: {=SUMPRODUCT(--(MOD(COLUMN($BO67:$DV67),5)=MOD(COLUMN($BP67),5)),$BO67:$DV67)} -> 0 | DZ67: =DY67*$J67 -> 0 | EA67: {=SUMPRODUCT(--(MOD(COLUMN($BO67:$DV67),5)=MOD(COLUMN($BQ67),5)),$BO67:$DV67)} -> 10 | EB67: =EA67*$J67 -> 1154.1667 | EC67: {=SUMPRODUCT(--(MOD(COLUMN($BO67:$DV67),5)=MOD(COLUMN($BR67),5)),$BO67:$DV67)} -> 8 | ED67: =EC67*$J67 -> 923.33333 | EJ67: 1 | EN67: 1 | EO67: 0 | EV67: 1 | GA67: {=SUMPRODUCT(--(MOD(COLUMN($EE67:$FZ67),4)=MOD(COLUMN($EE67),4)),$EE67:$FZ67)} -> 0 | GB67: =GA67*$J67 -> 0 | GC67: {=SUMPRODUCT(--(MOD(COLUMN($EE67:$FZ67),4)=MOD(COLUMN($EF67),4)),$EE67:$FZ67)} -> 3 | GD67: =GC67*$J67 -> 346.25 | GE67: {=SUMPRODUCT(--(MOD(COLUMN($EE67:$FZ67),4)=MOD(COLUMN($EG67),4)),$EE67:$FZ67)} -> 0 | GF67: =GE67*$J67 -> 0 | IC67: {=SUMPRODUCT(--(MOD(COLUMN($GG67:$IB67),4)=MOD(COLUMN($GG67),4)),$GG67:$IB67)} -> 0 | ID67: =IC67*$J67 -> 0 | IE67: {=SUMPRODUCT(--(MOD(COLUMN($GG67:$IB67),4)=MOD(COLUMN($GH67),4)),$GG67:$IB67)} -> 0 | IF67: =IE67*$J67 -> 0 | IG67: {=SUMPRODUCT(--(MOD(COLUMN($GG67:$IB67),4)=MOD(COLUMN($GI67),4)),$GG67:$IB67)} -> 0 | IH67: =IG67*$J67 -> 0 | KE67: {=SUMPRODUCT(--(MOD(COLUMN($II67:$KD67),4)=MOD(COLUMN($II67),4)),$II67:$KD67)} -> 0 | KF67: =KE67*$J67 -> 0 | KG67: {=SUMPRODUCT(--(MOD(COLUMN($II67:$KD67),4)=MOD(COLUMN($IJ67),4)),$II67:$KD67)} -> 0 | KH67: =KG67*$J67 -> 0 | KI67: {=SUMPRODUCT(--(MOD(COLUMN($II67:$KD67),4)=MOD(COLUMN($IK67),4)),$II67:$KD67)} -> 0 | KJ67: =KI67*$J67 -> 0 | KN67: 1
E68: 32 | F68: 2 | G68: 9630010510 | H68: Клапан растормаживания, сдвоенный | I68: 370.6 | J68: =451/1.2 -> 375.83333 | BF68: =$KN68*0 -> 0 | BR68: 2 | BV68: =$KN68*10 -> 10 | BW68: 10 | CB68: 0 | CG68: 0 | CL68: 0 | CQ68: 0 | CV68: 0 | DA68: 0 | DF68: 0 | DK68: 0 | DO68: =$KN68*4 -> 4 | DP68: 0 | DT68: =$KN68*4 -> 4 | DU68: 0 | DW68: {=SUMPRODUCT(--(MOD(COLUMN($BO68:$DV68),5)=MOD(COLUMN($BO68),5)),$BO68:$DV68)} -> 0 | DX68: =DW68*$J68 -> 0 | DY68: {=SUMPRODUCT(--(MOD(COLUMN($BO68:$DV68),5)=MOD(COLUMN($BP68),5)),$BO68:$DV68)} -> 0 | DZ68: =DY68*$J68 -> 0 | EA68: {=SUMPRODUCT(--(MOD(COLUMN($BO68:$DV68),5)=MOD(COLUMN($BQ68),5)),$BO68:$DV68)} -> 18 | EB68: =EA68*$J68 -> 6765 | EC68: {=SUMPRODUCT(--(MOD(COLUMN($BO68:$DV68),5)=MOD(COLUMN($BR68),5)),$BO68:$DV68)} -> 12 | ED68: =EC68*$J68 -> 4510 | GA68: {=SUMPRODUCT(--(MOD(COLUMN($EE68:$FZ68),4)=MOD(COLUMN($EE68),4)),$EE68:$FZ68)} -> 0 | GB68: =GA68*$J68 -> 0 | GC68: {=SUMPRODUCT(--(MOD(COLUMN($EE68:$FZ68),4)=MOD(COLUMN($EF68),4)),$EE68:$FZ68)} -> 0 | GD68: =GC68*$J68 -> 0 | GE68: {=SUMPRODUCT(--(MOD(COLUMN($EE68:$FZ68),4)=MOD(COLUMN($EG68),4)),$EE68:$FZ68)} -> 0 | GF68: =GE68*$J68 -> 0 | IC68: {=SUMPRODUCT(--(MOD(COLUMN($GG68:$IB68),4)=MOD(COLUMN($GG68),4)),$GG68:$IB68)} -> 0 | ID68: =IC68*$J68 -> 0 | IE68: {=SUMPRODUCT(--(MOD(COLUMN($GG68:$IB68),4)=MOD(COLUMN($GH68),4)),$GG68:$IB68)} -> 0 | IF68: =IE68*$J68 -> 0 | IG68: {=SUMPRODUCT(--(MOD(COLUMN($GG68:$IB68),4)=MOD(COLUMN($GI68),4)),$GG68:$IB68)} -> 0 | IH68: =IG68*$J68 -> 0 | KE68: {=SUMPRODUCT(--(MOD(COLUMN($II68:$KD68),4)=MOD(COLUMN($II68),4)),$II68:$KD68)} -> 0 | KF68: =KE68*$J68 -> 0 | KG68: {=SUMPRODUCT(--(MOD(COLUMN($II68:$KD68),4)=MOD(COLUMN($IJ68),4)),$II68:$KD68)} -> 0 | KH68: =KG68*$J68 -> 0 | KI68: {=SUMPRODUCT(--(MOD(COLUMN($II68:$KD68),4)=MOD(COLUMN($IK68),4)),$II68:$KD68)} -> 0 | KJ68: =KI68*$J68 -> 0 | KN68: 1
E69: 33 | F69: 2 | G69: 9710020400 | H69: Воздухораспределитель | I69: 366.7 | J69: =587.5/1.2 -> 489.58333 | BF69: =$KN69*0 -> 0 | BR69: 2 | BV69: =$KN69*10 -> 10 | BW69: 10 | CB69: 0 | CG69: 0 | CL69: 0 | CQ69: 0 | CV69: 0 | DA69: 0 | DF69: 0 | DK69: 0 | DO69: =$KN69*4 -> 4 | DP69: 0 | DT69: =$KN69*4 -> 4 | DU69: 0 | DW69: {=SUMPRODUCT(--(MOD(COLUMN($BO69:$DV69),5)=MOD(COLUMN($BO69),5)),$BO69:$DV69)} -> 0 | DX69: =DW69*$J69 -> 0 | DY69: {=SUMPRODUCT(--(MOD(COLUMN($BO69:$DV69),5)=MOD(COLUMN($BP69),5)),$BO69:$DV69)} -> 0 | DZ69: =DY69*$J69 -> 0 | EA69: {=SUMPRODUCT(--(MOD(COLUMN($BO69:$DV69),5)=MOD(COLUMN($BQ69),5)),$BO69:$DV69)} -> 18 | EB69: =EA69*$J69 -> 8812.5 | EC69: {=SUMPRODUCT(--(MOD(COLUMN($BO69:$DV69),5)=MOD(COLUMN($BR69),5)),$BO69:$DV69)} -> 12 | ED69: =EC69*$J69 -> 5875 | GA69: {=SUMPRODUCT(--(MOD(COLUMN($EE69:$FZ69),4)=MOD(COLUMN($EE69),4)),$EE69:$FZ69)} -> 0 | GB69: =GA69*$J69 -> 0 | GC69: {=SUMPRODUCT(--(MOD(COLUMN($EE69:$FZ69),4)=MOD(COLUMN($EF69),4)),$EE69:$FZ69)} -> 0 | GD69: =GC69*$J69 -> 0 | GE69: {=SUMPRODUCT(--(MOD(COLUMN($EE69:$FZ69),4)=MOD(COLUMN($EG69),4)),$EE69:$FZ69)} -> 0 | GF69: =GE69*$J69 -> 0 | IC69: {=SUMPRODUCT(--(MOD(COLUMN($GG69:$IB69),4)=MOD(COLUMN($GG69),4)),$GG69:$IB69)} -> 0 | ID69: =IC69*$J69 -> 0 | IE69: {=SUMPRODUCT(--(MOD(COLUMN($GG69:$IB69),4)=MOD(COLUMN($GH69),4)),$GG69:$IB69)} -> 0 | IF69: =IE69*$J69 -> 0 | IG69: {=SUMPRODUCT(--(MOD(COLUMN($GG69:$IB69),4)=MOD(COLUMN($GI69),4)),$GG69:$IB69)} -> 0 | IH69: =IG69*$J69 -> 0 | KE69: {=SUMPRODUCT(--(MOD(COLUMN($II69:$KD69),4)=MOD(COLUMN($II69),4)),$II69:$KD69)} -> 0 | KF69: =KE69*$J69 -> 0 | KG69: {=SUMPRODUCT(--(MOD(COLUMN($II69:$KD69),4)=MOD(COLUMN($IJ69),4)),$II69:$KD69)} -> 0 | KH69: =KG69*$J69 -> 0 | KI69: {=SUMPRODUCT(--(MOD(COLUMN($II69:$KD69),4)=MOD(COLUMN($IK69),4)),$II69:$KD69)} -> 0 | KJ69: =KI69*$J69 -> 0 | KN69: 1
E70: 34 | F70: 2 | G70: 4801020640 | H70: Блок TEBS-E, 4S3M Premium | I70: 7690.4 | J70: =10350/1.2 -> 8625 | BF70: =$KN70*0 -> 0 | BR70: 2 | BV70: =$KN70*10 -> 10 | BW70: 10 | CB70: 0 | CG70: 0 | CL70: 0 | CQ70: 0 | CV70: 0 | DA70: 0 | DF70: 0 | DK70: 0 | DO70: =$KN70*4 -> 4 | DP70: 0 | DT70: =$KN70*4 -> 4 | DU70: 0 | DW70: {=SUMPRODUCT(--(MOD(COLUMN($BO70:$DV70),5)=MOD(COLUMN($BO70),5)),$BO70:$DV70)} -> 0 | DX70: =DW70*$J70 -> 0 | DY70: {=SUMPRODUCT(--(MOD(COLUMN($BO70:$DV70),5)=MOD(COLUMN($BP70),5)),$BO70:$DV70)} -> 0 | DZ70: =DY70*$J70 -> 0 | EA70: {=SUMPRODUCT(--(MOD(COLUMN($BO70:$DV70),5)=MOD(COLUMN($BQ70),5)),$BO70:$DV70)} -> 18 | EB70: =EA70*$J70 -> 155250 | EC70: {=SUMPRODUCT(--(MOD(COLUMN($BO70:$DV70),5)=MOD(COLUMN($BR70),5)),$BO70:$DV70)} -> 12 | ED70: =EC70*$J70 -> 103500 | GA70: {=SUMPRODUCT(--(MOD(COLUMN($EE70:$FZ70),4)=MOD(COLUMN($EE70),4)),$EE70:$FZ70)} -> 0 | GB70: =GA70*$J70 -> 0 | GC70: {=SUMPRODUCT(--(MOD(COLUMN($EE70:$FZ70),4)=MOD(COLUMN($EF70),4)),$EE70:$FZ70)} -> 0 | GD70: =GC70*$J70 -> 0 | GE70: {=SUMPRODUCT(--(MOD(COLUMN($EE70:$FZ70),4)=MOD(COLUMN($EG70),4)),$EE70:$FZ70)} -> 0 | GF70: =GE70*$J70 -> 0 | IC70: {=SUMPRODUCT(--(MOD(COLUMN($GG70:$IB70),4)=MOD(COLUMN($GG70),4)),$GG70:$IB70)} -> 0 | ID70: =IC70*$J70 -> 0 | IE70: {=SUMPRODUCT(--(MOD(COLUMN($GG70:$IB70),4)=MOD(COLUMN($GH70),4)),$GG70:$IB70)} -> 0 | IF70: =IE70*$J70 -> 0 | IG70: {=SUMPRODUCT(--(MOD(COLUMN($GG70:$IB70),4)=MOD(COLUMN($GI70),4)),$GG70:$IB70)} -> 0 | IH70: =IG70*$J70 -> 0 | KE70: {=SUMPRODUCT(--(MOD(COLUMN($II70:$KD70),4)=MOD(COLUMN($II70),4)),$II70:$KD70)} -> 0 | KF70: =KE70*$J70 -> 0 | KG70: {=SUMPRODUCT(--(MOD(COLUMN($II70:$KD70),4)=MOD(COLUMN($IJ70),4)),$II70:$KD70)} -> 0 | KH70: =KG70*$J70 -> 0 | KI70: {=SUMPRODUCT(--(MOD(COLUMN($II70:$KD70),4)=MOD(COLUMN($IK70),4)),$II70:$KD70)} -> 0 | KJ70: =KI70*$J70 -> 0 | KN70: 1
E71: 35 | F71: 2 | G71: 4491731200 | H71: Кабель питания для прицепа, 12 м | I71: 912.4 | J71: =1244.4/1.2 -> 1037 | BF71: =$KN71*0 -> 0 | BR71: 2 | BV71: =$KN71*10 -> 10 | BW71: 10 | CB71: 0 | CG71: 0 | CL71: 0 | CQ71: 0 | CV71: 0 | DA71: 0 | DF71: 0 | DK71: 0 | DO71: =$KN71*0 -> 0 | DP71: 0 | DT71: =$KN71*0 -> 0 | DU71: 0 | DW71: {=SUMPRODUCT(--(MOD(COLUMN($BO71:$DV71),5)=MOD(COLUMN($BO71),5)),$BO71:$DV71)} -> 0 | DX71: =DW71*$J71 -> 0 | DY71: {=SUMPRODUCT(--(MOD(COLUMN($BO71:$DV71),5)=MOD(COLUMN($BP71),5)),$BO71:$DV71)} -> 0 | DZ71: =DY71*$J71 -> 0 | EA71: {=SUMPRODUCT(--(MOD(COLUMN($BO71:$DV71),5)=MOD(COLUMN($BQ71),5)),$BO71:$DV71)} -> 10 | EB71: =EA71*$J71 -> 10370 | EC71: {=SUMPRODUCT(--(MOD(COLUMN($BO71:$DV71),5)=MOD(COLUMN($BR71),5)),$BO71:$DV71)} -> 12 | ED71: =EC71*$J71 -> 12444 | GA71: {=SUMPRODUCT(--(MOD(COLUMN($EE71:$FZ71),4)=MOD(COLUMN($EE71),4)),$EE71:$FZ71)} -> 0 | GB71: =GA71*$J71 -> 0 | GC71: {=SUMPRODUCT(--(MOD(COLUMN($EE71:$FZ71),4)=MOD(COLUMN($EF71),4)),$EE71:$FZ71)} -> 0 | GD71: =GC71*$J71 -> 0 | GE71: {=SUMPRODUCT(--(MOD(COLUMN($EE71:$FZ71),4)=MOD(COLUMN($EG71),4)),$EE71:$FZ71)} -> 0 | GF71: =GE71*$J71 -> 0 | IC71: {=SUMPRODUCT(--(MOD(COLUMN($GG71:$IB71),4)=MOD(COLUMN($GG71),4)),$GG71:$IB71)} -> 0 | ID71: =IC71*$J71 -> 0 | IE71: {=SUMPRODUCT(--(MOD(COLUMN($GG71:$IB71),4)=MOD(COLUMN($GH71),4)),$GG71:$IB71)} -> 0 | IF71: =IE71*$J71 -> 0 | IG71: {=SUMPRODUCT(--(MOD(COLUMN($GG71:$IB71),4)=MOD(COLUMN($GI71),4)),$GG71:$IB71)} -> 0 | IH71: =IG71*$J71 -> 0 | KE71: {=SUMPRODUCT(--(MOD(COLUMN($II71:$KD71),4)=MOD(COLUMN($II71),4)),$II71:$KD71)} -> 0 | KF71: =KE71*$J71 -> 0 | KG71: {=SUMPRODUCT(--(MOD(COLUMN($II71:$KD71),4)=MOD(COLUMN($IJ71),4)),$II71:$KD71)} -> 0 | KH71: =KG71*$J71 -> 0 | KI71: {=SUMPRODUCT(--(MOD(COLUMN($II71:$KD71),4)=MOD(COLUMN($IK71),4)),$II71:$KD71)} -> 0 | KJ71: =KI71*$J71 -> 0 | KN71: 1
E72: 36 | F72: 2 | G72: 4497230300 | H72: Кабель датчика АБС | I72: 82.4 | J72: =213.4/1.2 -> 177.83333 | BF72: =$KN72*0 -> 0 | BR72: 4 | BV72: =$KN72*10 -> 20 | BW72: 20 | CB72: 0 | CG72: 0 | CL72: 0 | CQ72: 0 | CV72: 0 | DA72: 0 | DF72: 0 | DK72: 0 | DO72: =$KN72*4 -> 8 | DP72: 0 | DT72: =$KN72*4 -> 8 | DU72: 0 | DW72: {=SUMPRODUCT(--(MOD(COLUMN($BO72:$DV72),5)=MOD(COLUMN($BO72),5)),$BO72:$DV72)} -> 0 | DX72: =DW72*$J72 -> 0 | DY72: {=SUMPRODUCT(--(MOD(COLUMN($BO72:$DV72),5)=MOD(COLUMN($BP72),5)),$BO72:$DV72)} -> 0 | DZ72: =DY72*$J72 -> 0 | EA72: {=SUMPRODUCT(--(MOD(COLUMN($BO72:$DV72),5)=MOD(COLUMN($BQ72),5)),$BO72:$DV72)} -> 36 | EB72: =EA72*$J72 -> 6402 | EC72: {=SUMPRODUCT(--(MOD(COLUMN($BO72:$DV72),5)=MOD(COLUMN($BR72),5)),$BO72:$DV72)} -> 24 | ED72: =EC72*$J72 -> 4268 | GA72: {=SUMPRODUCT(--(MOD(COLUMN($EE72:$FZ72),4)=MOD(COLUMN($EE72),4)),$EE72:$FZ72)} -> 0 | GB72: =GA72*$J72 -> 0 | GC72: {=SUMPRODUCT(--(MOD(COLUMN($EE72:$FZ72),4)=MOD(COLUMN($EF72),4)),$EE72:$FZ72)} -> 0 | GD72: =GC72*$J72 -> 0 | GE72: {=SUMPRODUCT(--(MOD(COLUMN($EE72:$FZ72),4)=MOD(COLUMN($EG72),4)),$EE72:$FZ72)} -> 0 | GF72: =GE72*$J72 -> 0 | IC72: {=SUMPRODUCT(--(MOD(COLUMN($GG72:$IB72),4)=MOD(COLUMN($GG72),4)),$GG72:$IB72)} -> 0 | ID72: =IC72*$J72 -> 0 | IE72: {=SUMPRODUCT(--(MOD(COLUMN($GG72:$IB72),4)=MOD(COLUMN($GH72),4)),$GG72:$IB72)} -> 0 | IF72: =IE72*$J72 -> 0 | IG72: {=SUMPRODUCT(--(MOD(COLUMN($GG72:$IB72),4)=MOD(COLUMN($GI72),4)),$GG72:$IB72)} -> 0 | IH72: =IG72*$J72 -> 0 | KE72: {=SUMPRODUCT(--(MOD(COLUMN($II72:$KD72),4)=MOD(COLUMN($II72),4)),$II72:$KD72)} -> 0 | KF72: =KE72*$J72 -> 0 | KG72: {=SUMPRODUCT(--(MOD(COLUMN($II72:$KD72),4)=MOD(COLUMN($IJ72),4)),$II72:$KD72)} -> 0 | KH72: =KG72*$J72 -> 0 | KI72: {=SUMPRODUCT(--(MOD(COLUMN($II72:$KD72),4)=MOD(COLUMN($IK72),4)),$II72:$KD72)} -> 0 | KJ72: =KI72*$J72 -> 0 | KN72: 2
E73: 37 | F73: 2 | G73: 4493491000 | H73: Кабель питания от стоп-сигнала (24 N), 10 м | J73: =259.4/1.2 -> 216.16667 | BF73: =$KN73*0 -> 0 | BR73: 2 | BV73: =$KN73*10 -> 10 | BW73: 10 | CB73: 0 | CG73: 0 | CK73: 1 | CL73: 1 | CQ73: 0 | CV73: 0 | DA73: 0 | DF73: 0 | DK73: 0 | DO73: =$KN73*0 -> 0 | DP73: 0 | DT73: =$KN73*0 -> 0 | DU73: 0 | DW73: {=SUMPRODUCT(--(MOD(COLUMN($BO73:$DV73),5)=MOD(COLUMN($BO73),5)),$BO73:$DV73)} -> 0 | DX73: =DW73*$J73 -> 0 | DY73: {=SUMPRODUCT(--(MOD(COLUMN($BO73:$DV73),5)=MOD(COLUMN($BP73),5)),$BO73:$DV73)} -> 0 | DZ73: =DY73*$J73 -> 0 | EA73: {=SUMPRODUCT(--(MOD(COLUMN($BO73:$DV73),5)=MOD(COLUMN($BQ73),5)),$BO73:$DV73)} -> 11 | EB73: =EA73*$J73 -> 2377.8333 | EC73: {=SUMPRODUCT(--(MOD(COLUMN($BO73:$DV73),5)=MOD(COLUMN($BR73),5)),$BO73:$DV73)} -> 13 | ED73: =EC73*$J73 -> 2810.1667 | GA73: {=SUMPRODUCT(--(MOD(COLUMN($EE73:$FZ73),4)=MOD(COLUMN($EE73),4)),$EE73:$FZ73)} -> 0 | GB73: =GA73*$J73 -> 0 | GC73: {=SUMPRODUCT(--(MOD(COLUMN($EE73:$FZ73),4)=MOD(COLUMN($EF73),4)),$EE73:$FZ73)} -> 0 | GD73: =GC73*$J73 -> 0 | GE73: {=SUMPRODUCT(--(MOD(COLUMN($EE73:$FZ73),4)=MOD(COLUMN($EG73),4)),$EE73:$FZ73)} -> 0 | GF73: =GE73*$J73 -> 0 | IC73: {=SUMPRODUCT(--(MOD(COLUMN($GG73:$IB73),4)=MOD(COLUMN($GG73),4)),$GG73:$IB73)} -> 0 | ID73: =IC73*$J73 -> 0 | IE73: {=SUMPRODUCT(--(MOD(COLUMN($GG73:$IB73),4)=MOD(COLUMN($GH73),4)),$GG73:$IB73)} -> 0 | IF73: =IE73*$J73 -> 0 | IG73: {=SUMPRODUCT(--(MOD(COLUMN($GG73:$IB73),4)=MOD(COLUMN($GI73),4)),$GG73:$IB73)} -> 0 | IH73: =IG73*$J73 -> 0 | KE73: {=SUMPRODUCT(--(MOD(COLUMN($II73:$KD73),4)=MOD(COLUMN($II73),4)),$II73:$KD73)} -> 0 | KF73: =KE73*$J73 -> 0 | KG73: {=SUMPRODUCT(--(MOD(COLUMN($II73:$KD73),4)=MOD(COLUMN($IJ73),4)),$II73:$KD73)} -> 0 | KH73: =KG73*$J73 -> 0 | KI73: {=SUMPRODUCT(--(MOD(COLUMN($II73:$KD73),4)=MOD(COLUMN($IK73),4)),$II73:$KD73)} -> 0 | KJ73: =KI73*$J73 -> 0 | KN73: 1
E74: 38 | F74: 2 | G74: 4640061000 | H74: Кран уровня пола | I74: 743.8 | J74: =973.1/1.2 -> 810.91667 | BF74: =$KN74*0 -> 0 | BR74: 2 | BV74: =$KN74*10 -> 10 | BW74: 10 | CB74: 0 | CG74: 0 | CL74: 0 | CQ74: 0 | CV74: 0 | DA74: 0 | DF74: 0 | DK74: 0 | DO74: =$KN74*4 -> 4 | DP74: 0 | DT74: =$KN74*4 -> 4 | DU74: 0 | DW74: {=SUMPRODUCT(--(MOD(COLUMN($BO74:$DV74),5)=MOD(COLUMN($BO74),5)),$BO74:$DV74)} -> 0 | DX74: =DW74*$J74 -> 0 | DY74: {=SUMPRODUCT(--(MOD(COLUMN($BO74:$DV74),5)=MOD(COLUMN($BP74),5)),$BO74:$DV74)} -> 0 | DZ74: =DY74*$J74 -> 0 | EA74: {=SUMPRODUCT(--(MOD(COLUMN($BO74:$DV74),5)=MOD(COLUMN($BQ74),5)),$BO74:$DV74)} -> 18 | EB74: =EA74*$J74 -> 14596.5 | EC74: {=SUMPRODUCT(--(MOD(COLUMN($BO74:$DV74),5)=MOD(COLUMN($BR74),5)),$BO74:$DV74)} -> 12 | ED74: =EC74*$J74 -> 9731 | GA74: {=SUMPRODUCT(--(MOD(COLUMN($EE74:$FZ74),4)=MOD(COLUMN($EE74),4)),$EE74:$FZ74)} -> 0 | GB74: =GA74*$J74 -> 0 | GC74: {=SUMPRODUCT(--(MOD(COLUMN($EE74:$FZ74),4)=MOD(COLUMN($EF74),4)),$EE74:$FZ74)} -> 0 | GD74: =GC74*$J74 -> 0 | GE74: {=SUMPRODUCT(--(MOD(COLUMN($EE74:$FZ74),4)=MOD(COLUMN($EG74),4)),$EE74:$FZ74)} -> 0 | GF74: =GE74*$J74 -> 0 | IC74: {=SUMPRODUCT(--(MOD(COLUMN($GG74:$IB74),4)=MOD(COLUMN($GG74),4)),$GG74:$IB74)} -> 0 | ID74: =IC74*$J74 -> 0 | IE74: {=SUMPRODUCT(--(MOD(COLUMN($GG74:$IB74),4)=MOD(COLUMN($GH74),4)),$GG74:$IB74)} -> 0 | IF74: =IE74*$J74 -> 0 | IG74: {=SUMPRODUCT(--(MOD(COLUMN($GG74:$IB74),4)=MOD(COLUMN($GI74),4)),$GG74:$IB74)} -> 0 | IH74: =IG74*$J74 -> 0 | KE74: {=SUMPRODUCT(--(MOD(COLUMN($II74:$KD74),4)=MOD(COLUMN($II74),4)),$II74:$KD74)} -> 0 | KF74: =KE74*$J74 -> 0 | KG74: {=SUMPRODUCT(--(MOD(COLUMN($II74:$KD74),4)=MOD(COLUMN($IJ74),4)),$II74:$KD74)} -> 0 | KH74: =KG74*$J74 -> 0 | KI74: {=SUMPRODUCT(--(MOD(COLUMN($II74:$KD74),4)=MOD(COLUMN($IK74),4)),$II74:$KD74)} -> 0 | KJ74: =KI74*$J74 -> 0 | KN74: 1 | KO74: WABCO П/П
E75: 39 | F75: 2 | G75: 4630320200 | H75: Кран ручного управления | I75: 775 | J75: =981.5/1.2 -> 817.91667 | BF75: =$KN75*0 -> 0 | BR75: 2 | BV75: =$KN75*10 -> 10 | BW75: 10 | CB75: 0 | CG75: 0 | CL75: 0 | CQ75: 0 | CV75: 0 | DA75: 0 | DF75: 0 | DK75: 0 | DO75: =$KN75*4 -> 4 | DP75: 0 | DT75: =$KN75*4 -> 4 | DU75: 0 | DW75: {=SUMPRODUCT(--(MOD(COLUMN($BO75:$DV75),5)=MOD(COLUMN($BO75),5)),$BO75:$DV75)} -> 0 | DX75: =DW75*$J75 -> 0 | DY75: {=SUMPRODUCT(--(MOD(COLUMN($BO75:$DV75),5)=MOD(COLUMN($BP75),5)),$BO75:$DV75)} -> 0 | DZ75: =DY75*$J75 -> 0 | EA75: {=SUMPRODUCT(--(MOD(COLUMN($BO75:$DV75),5)=MOD(COLUMN($BQ75),5)),$BO75:$DV75)} -> 18 | EB75: =EA75*$J75 -> 14722.5 | EC75: {=SUMPRODUCT(--(MOD(COLUMN($BO75:$DV75),5)=MOD(COLUMN($BR75),5)),$BO75:$DV75)} -> 12 | ED75: =EC75*$J75 -> 9815 | GA75: {=SUMPRODUCT(--(MOD(COLUMN($EE75:$FZ75),4)=MOD(COLUMN($EE75),4)),$EE75:$FZ75)} -> 0 | GB75: =GA75*$J75 -> 0 | GC75: {=SUMPRODUCT(--(MOD(COLUMN($EE75:$FZ75),4)=MOD(COLUMN($EF75),4)),$EE75:$FZ75)} -> 0 | GD75: =GC75*$J75 -> 0 | GE75: {=SUMPRODUCT(--(MOD(COLUMN($EE75:$FZ75),4)=MOD(COLUMN($EG75),4)),$EE75:$FZ75)} -> 0 | GF75: =GE75*$J75 -> 0 | IC75: {=SUMPRODUCT(--(MOD(COLUMN($GG75:$IB75),4)=MOD(COLUMN($GG75),4)),$GG75:$IB75)} -> 0 | ID75: =IC75*$J75 -> 0 | IE75: {=SUMPRODUCT(--(MOD(COLUMN($GG75:$IB75),4)=MOD(COLUMN($GH75),4)),$GG75:$IB75)} -> 0 | IF75: =IE75*$J75 -> 0 | IG75: {=SUMPRODUCT(--(MOD(COLUMN($GG75:$IB75),4)=MOD(COLUMN($GI75),4)),$GG75:$IB75)} -> 0 | IH75: =IG75*$J75 -> 0 | KE75: {=SUMPRODUCT(--(MOD(COLUMN($II75:$KD75),4)=MOD(COLUMN($II75),4)),$II75:$KD75)} -> 0 | KF75: =KE75*$J75 -> 0 | KG75: {=SUMPRODUCT(--(MOD(COLUMN($II75:$KD75),4)=MOD(COLUMN($IJ75),4)),$II75:$KD75)} -> 0 | KH75: =KG75*$J75 -> 0 | KI75: {=SUMPRODUCT(--(MOD(COLUMN($II75:$KD75),4)=MOD(COLUMN($IK75),4)),$II75:$KD75)} -> 0 | KJ75: =KI75*$J75 -> 0 | KN75: 1
E76: 40 | F76: 2 | G76: 4334010030 | H76: Упругий элемент | I76: 67.3 | J76: =77/1.2 -> 64.166667 | BF76: =$KN76*0 -> 0 | BR76: 2 | BV76: =$KN76*10 -> 10 | BW76: 10 | CB76: 0 | CG76: 0 | CL76: 0 | CQ76: 0 | CV76: 0 | DA76: 0 | DF76: 0 | DK76: 0 | DO76: =$KN76*4 -> 4 | DP76: 0 | DT76: =$KN76*4 -> 4 | DU76: 0 | DW76: {=SUMPRODUCT(--(MOD(COLUMN($BO76:$DV76),5)=MOD(COLUMN($BO76),5)),$BO76:$DV76)} -> 0 | DX76: =DW76*$J76 -> 0 | DY76: {=SUMPRODUCT(--(MOD(COLUMN($BO76:$DV76),5)=MOD(COLUMN($BP76),5)),$BO76:$DV76)} -> 0 | DZ76: =DY76*$J76 -> 0 | EA76: {=SUMPRODUCT(--(MOD(COLUMN($BO76:$DV76),5)=MOD(COLUMN($BQ76),5)),$BO76:$DV76)} -> 18 | EB76: =EA76*$J76 -> 1155 | EC76: {=SUMPRODUCT(--(MOD(COLUMN($BO76:$DV76),5)=MOD(COLUMN($BR76),5)),$BO76:$DV76)} -> 12 | ED76: =EC76*$J76 -> 770 | GA76: {=SUMPRODUCT(--(MOD(COLUMN($EE76:$FZ76),4)=MOD(COLUMN($EE76),4)),$EE76:$FZ76)} -> 0 | GB76: =GA76*$J76 -> 0 | GC76: {=SUMPRODUCT(--(MOD(COLUMN($EE76:$FZ76),4)=MOD(COLUMN($EF76),4)),$EE76:$FZ76)} -> 0 | GD76: =GC76*$J76 -> 0 | GE76: {=SUMPRODUCT(--(MOD(COLUMN($EE76:$FZ76),4)=MOD(COLUMN($EG76),4)),$EE76:$FZ76)} -> 0 | GF76: =GE76*$J76 -> 0 | IC76: {=SUMPRODUCT(--(MOD(COLUMN($GG76:$IB76),4)=MOD(COLUMN($GG76),4)),$GG76:$IB76)} -> 0 | ID76: =IC76*$J76 -> 0 | IE76: {=SUMPRODUCT(--(MOD(COLUMN($GG76:$IB76),4)=MOD(COLUMN($GH76),4)),$GG76:$IB76)} -> 0 | IF76: =IE76*$J76 -> 0 | IG76: {=SUMPRODUCT(--(MOD(COLUMN($GG76:$IB76),4)=MOD(COLUMN($GI76),4)),$GG76:$IB76)} -> 0 | IH76: =IG76*$J76 -> 0 | KE76: {=SUMPRODUCT(--(MOD(COLUMN($II76:$KD76),4)=MOD(COLUMN($II76),4)),$II76:$KD76)} -> 0 | KF76: =KE76*$J76 -> 0 | KG76: {=SUMPRODUCT(--(MOD(COLUMN($II76:$KD76),4)=MOD(COLUMN($IJ76),4)),$II76:$KD76)} -> 0 | KH76: =KG76*$J76 -> 0 | KI76: {=SUMPRODUCT(--(MOD(COLUMN($II76:$KD76),4)=MOD(COLUMN($IK76),4)),$II76:$KD76)} -> 0 | KJ76: =KI76*$J76 -> 0 | KN76: 1
E77: 41 | F77: 2 | G77: 4461220500 | H77: CAN Router | J77: 9205.9 | DU77: 0 | DW77: {=SUMPRODUCT(--(MOD(COLUMN($BO77:$DV77),5)=MOD(COLUMN($BO77),5)),$BO77:$DV77)} -> 0 | DX77: =DW77*$J77 -> 0 | DY77: {=SUMPRODUCT(--(MOD(COLUMN($BO77:$DV77),5)=MOD(COLUMN($BP77),5)),$BO77:$DV77)} -> 0 | DZ77: =DY77*$J77 -> 0 | EA77: {=SUMPRODUCT(--(MOD(COLUMN($BO77:$DV77),5)=MOD(COLUMN($BQ77),5)),$BO77:$DV77)} -> 0 | EB77: =EA77*$J77 -> 0 | EC77: {=SUMPRODUCT(--(MOD(COLUMN($BO77:$DV77),5)=MOD(COLUMN($BR77),5)),$BO77:$DV77)} -> 0 | ED77: =EC77*$J77 -> 0 | EF77: 0 | EH77: Новый артикул | ER77: 1 | ES77: 1 | ET77: Заказ мая отгрузили раньше | EV77: 0 | EX77: Отгрузили в апреле | GA77: =SUMPRODUCT(--(MOD(COLUMN($EE77:$FZ77),4)=MOD(COLUMN($EE77),4)),$EE77:$FZ77) -> 0 | GB77: =GA77*$J77 -> 0 | GC77: =SUMPRODUCT(--(MOD(COLUMN($EE77:$FZ77),4)=MOD(COLUMN($EF77),4)),$EE77:$FZ77) -> 1 | GD77: =GC77*$J77 -> 9205.9 | GE77: =SUMPRODUCT(--(MOD(COLUMN($EE77:$FZ77),4)=MOD(COLUMN($EG77),4)),$EE77:$FZ77) -> 1 | GF77: =GE77*$J77 -> 9205.9 | IC77: {=SUMPRODUCT(--(MOD(COLUMN($GG77:$IB77),4)=MOD(COLUMN($GG77),4)),$GG77:$IB77)} -> 0 | ID77: =IC77*$J77 -> 0 | IE77: {=SUMPRODUCT(--(MOD(COLUMN($GG77:$IB77),4)=MOD(COLUMN($GH77),4)),$GG77:$IB77)} -> 0 | IF77: =IE77*$J77 -> 0 | IG77: {=SUMPRODUCT(--(MOD(COLUMN($GG77:$IB77),4)=MOD(COLUMN($GI77),4)),$GG77:$IB77)} -> 0 | IH77: =IG77*$J77 -> 0 | KE77: {=SUMPRODUCT(--(MOD(COLUMN($II77:$KD77),4)=MOD(COLUMN($II77),4)),$II77:$KD77)} -> 0 | KF77: =KE77*$J77 -> 0 | KG77: {=SUMPRODUCT(--(MOD(COLUMN($II77:$KD77),4)=MOD(COLUMN($IJ77),4)),$II77:$KD77)} -> 0 | KH77: =KG77*$J77 -> 0 | KI77: {=SUMPRODUCT(--(MOD(COLUMN($II77:$KD77),4)=MOD(COLUMN($IK77),4)),$II77:$KD77)} -> 0 | KJ77: =KI77*$J77 -> 0
E78: 42 | F78: 2 | G78: 4491331200 | H78: Power Cable | J78: 3400 | DU78: 0 | DW78: {=SUMPRODUCT(--(MOD(COLUMN($BO78:$DV78),5)=MOD(COLUMN($BO78),5)),$BO78:$DV78)} -> 0 | DX78: =DW78*$J78 -> 0 | DY78: {=SUMPRODUCT(--(MOD(COLUMN($BO78:$DV78),5)=MOD(COLUMN($BP78),5)),$BO78:$DV78)} -> 0 | DZ78: =DY78*$J78 -> 0 | EA78: {=SUMPRODUCT(--(MOD(COLUMN($BO78:$DV78),5)=MOD(COLUMN($BQ78),5)),$BO78:$DV78)} -> 0 | EB78: =EA78*$J78 -> 0 | EC78: {=SUMPRODUCT(--(MOD(COLUMN($BO78:$DV78),5)=MOD(COLUMN($BR78),5)),$BO78:$DV78)} -> 0 | ED78: =EC78*$J78 -> 0 | EF78: 0 | EH78: Новый артикул | ER78: 1 | ES78: 1 | EV78: 0 | GA78: =SUMPRODUCT(--(MOD(COLUMN($EE78:$FZ78),4)=MOD(COLUMN($EE78),4)),$EE78:$FZ78) -> 0 | GB78: =GA78*$J78 -> 0 | GC78: =SUMPRODUCT(--(MOD(COLUMN($EE78:$FZ78),4)=MOD(COLUMN($EF78),4)),$EE78:$FZ78) -> 1 | GD78: =GC78*$J78 -> 3400 | GE78: =SUMPRODUCT(--(MOD(COLUMN($EE78:$FZ78),4)=MOD(COLUMN($EG78),4)),$EE78:$FZ78) -> 1 | GF78: =GE78*$J78 -> 3400 | IC78: {=SUMPRODUCT(--(MOD(COLUMN($GG78:$IB78),4)=MOD(COLUMN($GG78),4)),$GG78:$IB78)} -> 0 | ID78: =IC78*$J78 -> 0 | IE78: {=SUMPRODUCT(--(MOD(COLUMN($GG78:$IB78),4)=MOD(COLUMN($GH78),4)),$GG78:$IB78)} -> 0 | IF78: =IE78*$J78 -> 0 | IG78: {=SUMPRODUCT(--(MOD(COLUMN($GG78:$IB78),4)=MOD(COLUMN($GI78),4)),$GG78:$IB78)} -> 0 | IH78: =IG78*$J78 -> 0 | KE78: {=SUMPRODUCT(--(MOD(COLUMN($II78:$KD78),4)=MOD(COLUMN($II78),4)),$II78:$KD78)} -> 0 | KF78: =KE78*$J78 -> 0 | KG78: {=SUMPRODUCT(--(MOD(COLUMN($II78:$KD78),4)=MOD(COLUMN($IJ78),4)),$II78:$KD78)} -> 0 | KH78: =KG78*$J78 -> 0 | KI78: {=SUMPRODUCT(--(MOD(COLUMN($II78:$KD78),4)=MOD(COLUMN($IK78),4)),$II78:$KD78)} -> 0 | KJ78: =KI78*$J78 -> 0
E79: 43 | F79: 2 | G79: 4493470800 | H79: Power Cable | J79: 2150 | DU79: 0 | DW79: {=SUMPRODUCT(--(MOD(COLUMN($BO79:$DV79),5)=MOD(COLUMN($BO79),5)),$BO79:$DV79)} -> 0 | DX79: =DW79*$J79 -> 0 | DY79: {=SUMPRODUCT(--(MOD(COLUMN($BO79:$DV79),5)=MOD(COLUMN($BP79),5)),$BO79:$DV79)} -> 0 | DZ79: =DY79*$J79 -> 0 | EA79: {=SUMPRODUCT(--(MOD(COLUMN($BO79:$DV79),5)=MOD(COLUMN($BQ79),5)),$BO79:$DV79)} -> 0 | EB79: =EA79*$J79 -> 0 | EC79: {=SUMPRODUCT(--(MOD(COLUMN($BO79:$DV79),5)=MOD(COLUMN($BR79),5)),$BO79:$DV79)} -> 0 | ED79: =EC79*$J79 -> 0 | EF79: 0 | EH79: Новый артикул | ER79: 1 | ES79: 1 | EV79: 0 | GA79: =SUMPRODUCT(--(MOD(COLUMN($EE79:$FZ79),4)=MOD(COLUMN($EE79),4)),$EE79:$FZ79) -> 0 | GB79: =GA79*$J79 -> 0 | GC79: =SUMPRODUCT(--(MOD(COLUMN($EE79:$FZ79),4)=MOD(COLUMN($EF79),4)),$EE79:$FZ79) -> 1 | GD79: =GC79*$J79 -> 2150 | GE79: =SUMPRODUCT(--(MOD(COLUMN($EE79:$FZ79),4)=MOD(COLUMN($EG79),4)),$EE79:$FZ79) -> 1 | GF79: =GE79*$J79 -> 2150 | IC79: {=SUMPRODUCT(--(MOD(COLUMN($GG79:$IB79),4)=MOD(COLUMN($GG79),4)),$GG79:$IB79)} -> 0 | ID79: =IC79*$J79 -> 0 | IE79: {=SUMPRODUCT(--(MOD(COLUMN($GG79:$IB79),4)=MOD(COLUMN($GH79),4)),$GG79:$IB79)} -> 0 | IF79: =IE79*$J79 -> 0 | IG79: {=SUMPRODUCT(--(MOD(COLUMN($GG79:$IB79),4)=MOD(COLUMN($GI79),4)),$GG79:$IB79)} -> 0 | IH79: =IG79*$J79 -> 0 | KE79: {=SUMPRODUCT(--(MOD(COLUMN($II79:$KD79),4)=MOD(COLUMN($II79),4)),$II79:$KD79)} -> 0 | KF79: =KE79*$J79 -> 0 | KG79: {=SUMPRODUCT(--(MOD(COLUMN($II79:$KD79),4)=MOD(COLUMN($IJ79),4)),$II79:$KD79)} -> 0 | KH79: =KG79*$J79 -> 0 | KI79: {=SUMPRODUCT(--(MOD(COLUMN($II79:$KD79),4)=MOD(COLUMN($IK79),4)),$II79:$KD79)} -> 0 | KJ79: =KI79*$J79 -> 0
E80: 44 | F80: 2 | G80: 4491350600 | H80: Power Cable | J80: 1960 | DU80: 0 | DW80: {=SUMPRODUCT(--(MOD(COLUMN($BO80:$DV80),5)=MOD(COLUMN($BO80),5)),$BO80:$DV80)} -> 0 | DX80: =DW80*$J80 -> 0 | DY80: {=SUMPRODUCT(--(MOD(COLUMN($BO80:$DV80),5)=MOD(COLUMN($BP80),5)),$BO80:$DV80)} -> 0 | DZ80: =DY80*$J80 -> 0 | EA80: {=SUMPRODUCT(--(MOD(COLUMN($BO80:$DV80),5)=MOD(COLUMN($BQ80),5)),$BO80:$DV80)} -> 0 | EB80: =EA80*$J80 -> 0 | EC80: {=SUMPRODUCT(--(MOD(COLUMN($BO80:$DV80),5)=MOD(COLUMN($BR80),5)),$BO80:$DV80)} -> 0 | ED80: =EC80*$J80 -> 0 | EF80: 0 | EH80: Новый артикул | ER80: 1 | ES80: 1 | EV80: 0 | GA80: =SUMPRODUCT(--(MOD(COLUMN($EE80:$FZ80),4)=MOD(COLUMN($EE80),4)),$EE80:$FZ80) -> 0 | GB80: =GA80*$J80 -> 0 | GC80: =SUMPRODUCT(--(MOD(COLUMN($EE80:$FZ80),4)=MOD(COLUMN($EF80),4)),$EE80:$FZ80) -> 1 | GD80: =GC80*$J80 -> 1960 | GE80: =SUMPRODUCT(--(MOD(COLUMN($EE80:$FZ80),4)=MOD(COLUMN($EG80),4)),$EE80:$FZ80) -> 1 | GF80: =GE80*$J80 -> 1960 | IC80: {=SUMPRODUCT(--(MOD(COLUMN($GG80:$IB80),4)=MOD(COLUMN($GG80),4)),$GG80:$IB80)} -> 0 | ID80: =IC80*$J80 -> 0 | IE80: {=SUMPRODUCT(--(MOD(COLUMN($GG80:$IB80),4)=MOD(COLUMN($GH80),4)),$GG80:$IB80)} -> 0 | IF80: =IE80*$J80 -> 0 | IG80: {=SUMPRODUCT(--(MOD(COLUMN($GG80:$IB80),4)=MOD(COLUMN($GI80),4)),$GG80:$IB80)} -> 0 | IH80: =IG80*$J80 -> 0 | KE80: {=SUMPRODUCT(--(MOD(COLUMN($II80:$KD80),4)=MOD(COLUMN($II80),4)),$II80:$KD80)} -> 0 | KF80: =KE80*$J80 -> 0 | KG80: {=SUMPRODUCT(--(MOD(COLUMN($II80:$KD80),4)=MOD(COLUMN($IJ80),4)),$II80:$KD80)} -> 0 | KH80: =KG80*$J80 -> 0 | KI80: {=SUMPRODUCT(--(MOD(COLUMN($II80:$KD80),4)=MOD(COLUMN($IK80),4)),$II80:$KD80)} -> 0 | KJ80: =KI80*$J80 -> 0
E81: 45 | F81: 2 | G81: 4340140000 | H81: Клапан обратный | J81: 480 | DU81: 0 | DW81: {=SUMPRODUCT(--(MOD(COLUMN($BO81:$DV81),5)=MOD(COLUMN($BO81),5)),$BO81:$DV81)} -> 0 | DX81: =DW81*$J81 -> 0 | DY81: {=SUMPRODUCT(--(MOD(COLUMN($BO81:$DV81),5)=MOD(COLUMN($BP81),5)),$BO81:$DV81)} -> 0 | DZ81: =DY81*$J81 -> 0 | EA81: {=SUMPRODUCT(--(MOD(COLUMN($BO81:$DV81),5)=MOD(COLUMN($BQ81),5)),$BO81:$DV81)} -> 0 | EB81: =EA81*$J81 -> 0 | EC81: {=SUMPRODUCT(--(MOD(COLUMN($BO81:$DV81),5)=MOD(COLUMN($BR81),5)),$BO81:$DV81)} -> 0 | ED81: =EC81*$J81 -> 0 | EF81: 0 | EH81: Новый артикул | ER81: 1 | ES81: 1 | EV81: 0 | GA81: =SUMPRODUCT(--(MOD(COLUMN($EE81:$FZ81),4)=MOD(COLUMN($EE81),4)),$EE81:$FZ81) -> 0 | GB81: =GA81*$J81 -> 0 | GC81: =SUMPRODUCT(--(MOD(COLUMN($EE81:$FZ81),4)=MOD(COLUMN($EF81),4)),$EE81:$FZ81) -> 1 | GD81: =GC81*$J81 -> 480 | GE81: =SUMPRODUCT(--(MOD(COLUMN($EE81:$FZ81),4)=MOD(COLUMN($EG81),4)),$EE81:$FZ81) -> 1 | GF81: =GE81*$J81 -> 480 | IC81: {=SUMPRODUCT(--(MOD(COLUMN($GG81:$IB81),4)=MOD(COLUMN($GG81),4)),$GG81:$IB81)} -> 0 | ID81: =IC81*$J81 -> 0 | IE81: {=SUMPRODUCT(--(MOD(COLUMN($GG81:$IB81),4)=MOD(COLUMN($GH81),4)),$GG81:$IB81)} -> 0 | IF81: =IE81*$J81 -> 0 | IG81: {=SUMPRODUCT(--(MOD(COLUMN($GG81:$IB81),4)=MOD(COLUMN($GI81),4)),$GG81:$IB81)} -> 0 | IH81: =IG81*$J81 -> 0 | KE81: {=SUMPRODUCT(--(MOD(COLUMN($II81:$KD81),4)=MOD(COLUMN($II81),4)),$II81:$KD81)} -> 0 | KF81: =KE81*$J81 -> 0 | KG81: {=SUMPRODUCT(--(MOD(COLUMN($II81:$KD81),4)=MOD(COLUMN($IJ81),4)),$II81:$KD81)} -> 0 | KH81: =KG81*$J81 -> 0 | KI81: {=SUMPRODUCT(--(MOD(COLUMN($II81:$KD81),4)=MOD(COLUMN($IK81),4)),$II81:$KD81)} -> 0 | KJ81: =KI81*$J81 -> 0
E82: 46 | F82: 2 | G82: 4345000030 | H82: Клапан двойной, запорный | J82: 730 | DU82: 0 | DW82: {=SUMPRODUCT(--(MOD(COLUMN($BO82:$DV82),5)=MOD(COLUMN($BO82),5)),$BO82:$DV82)} -> 0 | DX82: =DW82*$J82 -> 0 | DY82: {=SUMPRODUCT(--(MOD(COLUMN($BO82:$DV82),5)=MOD(COLUMN($BP82),5)),$BO82:$DV82)} -> 0 | DZ82: =DY82*$J82 -> 0 | EA82: {=SUMPRODUCT(--(MOD(COLUMN($BO82:$DV82),5)=MOD(COLUMN($BQ82),5)),$BO82:$DV82)} -> 0 | EB82: =EA82*$J82 -> 0 | EC82: {=SUMPRODUCT(--(MOD(COLUMN($BO82:$DV82),5)=MOD(COLUMN($BR82),5)),$BO82:$DV82)} -> 0 | ED82: =EC82*$J82 -> 0 | EF82: 0 | EH82: Новый артикул | ER82: 1 | ES82: 1 | EV82: 0 | GA82: =SUMPRODUCT(--(MOD(COLUMN($EE82:$FZ82),4)=MOD(COLUMN($EE82),4)),$EE82:$FZ82) -> 0 | GB82: =GA82*$J82 -> 0 | GC82: =SUMPRODUCT(--(MOD(COLUMN($EE82:$FZ82),4)=MOD(COLUMN($EF82),4)),$EE82:$FZ82) -> 1 | GD82: =GC82*$J82 -> 730 | GE82: =SUMPRODUCT(--(MOD(COLUMN($EE82:$FZ82),4)=MOD(COLUMN($EG82),4)),$EE82:$FZ82) -> 1 | GF82: =GE82*$J82 -> 730 | IC82: {=SUMPRODUCT(--(MOD(COLUMN($GG82:$IB82),4)=MOD(COLUMN($GG82),4)),$GG82:$IB82)} -> 0 | ID82: =IC82*$J82 -> 0 | IE82: {=SUMPRODUCT(--(MOD(COLUMN($GG82:$IB82),4)=MOD(COLUMN($GH82),4)),$GG82:$IB82)} -> 0 | IF82: =IE82*$J82 -> 0 | IG82: {=SUMPRODUCT(--(MOD(COLUMN($GG82:$IB82),4)=MOD(COLUMN($GI82),4)),$GG82:$IB82)} -> 0 | IH82: =IG82*$J82 -> 0 | KE82: {=SUMPRODUCT(--(MOD(COLUMN($II82:$KD82),4)=MOD(COLUMN($II82),4)),$II82:$KD82)} -> 0 | KF82: =KE82*$J82 -> 0 | KG82: {=SUMPRODUCT(--(MOD(COLUMN($II82:$KD82),4)=MOD(COLUMN($IJ82),4)),$II82:$KD82)} -> 0 | KH82: =KG82*$J82 -> 0 | KI82: {=SUMPRODUCT(--(MOD(COLUMN($II82:$KD82),4)=MOD(COLUMN($IK82),4)),$II82:$KD82)} -> 0 | KJ82: =KI82*$J82 -> 0
E83: 47 | F83: 2 | G83: 4342080290 | H83: Клапан 2х магистральный | J83: 485 | DU83: 0 | DW83: {=SUMPRODUCT(--(MOD(COLUMN($BO83:$DV83),5)=MOD(COLUMN($BO83),5)),$BO83:$DV83)} -> 0 | DX83: =DW83*$J83 -> 0 | DY83: {=SUMPRODUCT(--(MOD(COLUMN($BO83:$DV83),5)=MOD(COLUMN($BP83),5)),$BO83:$DV83)} -> 0 | DZ83: =DY83*$J83 -> 0 | EA83: {=SUMPRODUCT(--(MOD(COLUMN($BO83:$DV83),5)=MOD(COLUMN($BQ83),5)),$BO83:$DV83)} -> 0 | EB83: =EA83*$J83 -> 0 | EC83: {=SUMPRODUCT(--(MOD(COLUMN($BO83:$DV83),5)=MOD(COLUMN($BR83),5)),$BO83:$DV83)} -> 0 | ED83: =EC83*$J83 -> 0 | EF83: 0 | EH83: Новый артикул | ER83: 1 | ES83: 1 | EV83: 0 | GA83: =SUMPRODUCT(--(MOD(COLUMN($EE83:$FZ83),4)=MOD(COLUMN($EE83),4)),$EE83:$FZ83) -> 0 | GB83: =GA83*$J83 -> 0 | GC83: =SUMPRODUCT(--(MOD(COLUMN($EE83:$FZ83),4)=MOD(COLUMN($EF83),4)),$EE83:$FZ83) -> 1 | GD83: =GC83*$J83 -> 485 | GE83: =SUMPRODUCT(--(MOD(COLUMN($EE83:$FZ83),4)=MOD(COLUMN($EG83),4)),$EE83:$FZ83) -> 1 | GF83: =GE83*$J83 -> 485 | IC83: {=SUMPRODUCT(--(MOD(COLUMN($GG83:$IB83),4)=MOD(COLUMN($GG83),4)),$GG83:$IB83)} -> 0 | ID83: =IC83*$J83 -> 0 | IE83: {=SUMPRODUCT(--(MOD(COLUMN($GG83:$IB83),4)=MOD(COLUMN($GH83),4)),$GG83:$IB83)} -> 0 | IF83: =IE83*$J83 -> 0 | IG83: {=SUMPRODUCT(--(MOD(COLUMN($GG83:$IB83),4)=MOD(COLUMN($GI83),4)),$GG83:$IB83)} -> 0 | IH83: =IG83*$J83 -> 0 | KE83: {=SUMPRODUCT(--(MOD(COLUMN($II83:$KD83),4)=MOD(COLUMN($II83),4)),$II83:$KD83)} -> 0 | KF83: =KE83*$J83 -> 0 | KG83: {=SUMPRODUCT(--(MOD(COLUMN($II83:$KD83),4)=MOD(COLUMN($IJ83),4)),$II83:$KD83)} -> 0 | KH83: =KG83*$J83 -> 0 | KI83: {=SUMPRODUCT(--(MOD(COLUMN($II83:$KD83),4)=MOD(COLUMN($IK83),4)),$II83:$KD83)} -> 0 | KJ83: =KI83*$J83 -> 0
E84: 48 | F84: 2 | G84: 9730090010 | H84: Клапан управления тормозами прицепа | J84: 1590 | DU84: 0 | DW84: {=SUMPRODUCT(--(MOD(COLUMN($BO84:$DV84),5)=MOD(COLUMN($BO84),5)),$BO84:$DV84)} -> 0 | DX84: =DW84*$J84 -> 0 | DY84: {=SUMPRODUCT(--(MOD(COLUMN($BO84:$DV84),5)=MOD(COLUMN($BP84),5)),$BO84:$DV84)} -> 0 | DZ84: =DY84*$J84 -> 0 | EA84: {=SUMPRODUCT(--(MOD(COLUMN($BO84:$DV84),5)=MOD(COLUMN($BQ84),5)),$BO84:$DV84)} -> 0 | EB84: =EA84*$J84 -> 0 | EC84: {=SUMPRODUCT(--(MOD(COLUMN($BO84:$DV84),5)=MOD(COLUMN($BR84),5)),$BO84:$DV84)} -> 0 | ED84: =EC84*$J84 -> 0 | EF84: 0 | EH84: Новый артикул | ER84: 1 | ES84: 1 | EV84: 0 | GA84: =SUMPRODUCT(--(MOD(COLUMN($EE84:$FZ84),4)=MOD(COLUMN($EE84),4)),$EE84:$FZ84) -> 0 | GB84: =GA84*$J84 -> 0 | GC84: =SUMPRODUCT(--(MOD(COLUMN($EE84:$FZ84),4)=MOD(COLUMN($EF84),4)),$EE84:$FZ84) -> 1 | GD84: =GC84*$J84 -> 1590 | GE84: =SUMPRODUCT(--(MOD(COLUMN($EE84:$FZ84),4)=MOD(COLUMN($EG84),4)),$EE84:$FZ84) -> 1 | GF84: =GE84*$J84 -> 1590 | IC84: {=SUMPRODUCT(--(MOD(COLUMN($GG84:$IB84),4)=MOD(COLUMN($GG84),4)),$GG84:$IB84)} -> 0 | ID84: =IC84*$J84 -> 0 | IE84: {=SUMPRODUCT(--(MOD(COLUMN($GG84:$IB84),4)=MOD(COLUMN($GH84),4)),$GG84:$IB84)} -> 0 | IF84: =IE84*$J84 -> 0 | IG84: {=SUMPRODUCT(--(MOD(COLUMN($GG84:$IB84),4)=MOD(COLUMN($GI84),4)),$GG84:$IB84)} -> 0 | IH84: =IG84*$J84 -> 0 | KE84: {=SUMPRODUCT(--(MOD(COLUMN($II84:$KD84),4)=MOD(COLUMN($II84),4)),$II84:$KD84)} -> 0 | KF84: =KE84*$J84 -> 0 | KG84: {=SUMPRODUCT(--(MOD(COLUMN($II84:$KD84),4)=MOD(COLUMN($IJ84),4)),$II84:$KD84)} -> 0 | KH84: =KG84*$J84 -> 0 | KI84: {=SUMPRODUCT(--(MOD(COLUMN($II84:$KD84),4)=MOD(COLUMN($IK84),4)),$II84:$KD84)} -> 0 | KJ84: =KI84*$J84 -> 0
E85: 49 | F85: 2 | G85: 4462907000 | H85: OptiLink ECU | J85: =1818/1.2 -> 1515 | BF85: =$KN85*0 -> 0 | CK85: 1 | CL85: 1 | CM85: Новая номенклатура | CQ85: 0 | CV85: 0 | DA85: 0 | DF85: 0 | DK85: 0 | DU85: 0 | DW85: {=SUMPRODUCT(--(MOD(COLUMN($BO85:$DV85),5)=MOD(COLUMN($BO85),5)),$BO85:$DV85)} -> 0 | DX85: =DW85*$J85 -> 0 | DY85: {=SUMPRODUCT(--(MOD(COLUMN($BO85:$DV85),5)=MOD(COLUMN($BP85),5)),$BO85:$DV85)} -> 0 | DZ85: =DY85*$J85 -> 0 | EA85: {=SUMPRODUCT(--(MOD(COLUMN($BO85:$DV85),5)=MOD(COLUMN($BQ85),5)),$BO85:$DV85)} -> 1 | EB85: =EA85*$J85 -> 1515 | EC85: {=SUMPRODUCT(--(MOD(COLUMN($BO85:$DV85),5)=MOD(COLUMN($BR85),5)),$BO85:$DV85)} -> 1 | ED85: =EC85*$J85 -> 1515 | GA85: {=SUMPRODUCT(--(MOD(COLUMN($EE85:$FZ85),4)=MOD(COLUMN($EE85),4)),$EE85:$FZ85)} -> 0 | GB85: =GA85*$J85 -> 0 | GC85: {=SUMPRODUCT(--(MOD(COLUMN($EE85:$FZ85),4)=MOD(COLUMN($EF85),4)),$EE85:$FZ85)} -> 0 | GD85: =GC85*$J85 -> 0 | GE85: {=SUMPRODUCT(--(MOD(COLUMN($EE85:$FZ85),4)=MOD(COLUMN($EG85),4)),$EE85:$FZ85)} -> 0 | GF85: =GE85*$J85 -> 0 | IC85: {=SUMPRODUCT(--(MOD(COLUMN($GG85:$IB85),4)=MOD(COLUMN($GG85),4)),$GG85:$IB85)} -> 0 | ID85: =IC85*$J85 -> 0 | IE85: {=SUMPRODUCT(--(MOD(COLUMN($GG85:$IB85),4)=MOD(COLUMN($GH85),4)),$GG85:$IB85)} -> 0 | IF85: =IE85*$J85 -> 0 | IG85: {=SUMPRODUCT(--(MOD(COLUMN($GG85:$IB85),4)=MOD(COLUMN($GI85),4)),$GG85:$IB85)} -> 0 | IH85: =IG85*$J85 -> 0 | KE85: {=SUMPRODUCT(--(MOD(COLUMN($II85:$KD85),4)=MOD(COLUMN($II85),4)),$II85:$KD85)} -> 0 | KF85: =KE85*$J85 -> 0 | KG85: {=SUMPRODUCT(--(MOD(COLUMN($II85:$KD85),4)=MOD(COLUMN($IJ85),4)),$II85:$KD85)} -> 0 | KH85: =KG85*$J85 -> 0 | KI85: {=SUMPRODUCT(--(MOD(COLUMN($II85:$KD85),4)=MOD(COLUMN($IK85),4)),$II85:$KD85)} -> 0 | KJ85: =KI85*$J85 -> 0 | KN85: 1
E86: 50 | F86: 2 | G86: 4499271200 | H86: Кабель Электронного блока-передатчика OptiLink, 12 м | J86: =504/1.2 -> 420 | CP86: 1 | CQ86: 1 | CV86: 0 | DA86: 0 | DF86: 0 | DK86: 0 | DU86: 0 | DW86: {=SUMPRODUCT(--(MOD(COLUMN($BO86:$DV86),5)=MOD(COLUMN($BO86),5)),$BO86:$DV86)} -> 0 | DX86: =DW86*$J86 -> 0 | DY86: {=SUMPRODUCT(--(MOD(COLUMN($BO86:$DV86),5)=MOD(COLUMN($BP86),5)),$BO86:$DV86)} -> 0 | DZ86: =DY86*$J86 -> 0 | EA86: {=SUMPRODUCT(--(MOD(COLUMN($BO86:$DV86),5)=MOD(COLUMN($BQ86),5)),$BO86:$DV86)} -> 1 | EB86: =EA86*$J86 -> 420 | EC86: {=SUMPRODUCT(--(MOD(COLUMN($BO86:$DV86),5)=MOD(COLUMN($BR86),5)),$BO86:$DV86)} -> 1 | ED86: =EC86*$J86 -> 420 | GA86: {=SUMPRODUCT(--(MOD(COLUMN($EE86:$FZ86),4)=MOD(COLUMN($EE86),4)),$EE86:$FZ86)} -> 0 | GB86: =GA86*$J86 -> 0 | GC86: {=SUMPRODUCT(--(MOD(COLUMN($EE86:$FZ86),4)=MOD(COLUMN($EF86),4)),$EE86:$FZ86)} -> 0 | GD86: =GC86*$J86 -> 0 | GE86: {=SUMPRODUCT(--(MOD(COLUMN($EE86:$FZ86),4)=MOD(COLUMN($EG86),4)),$EE86:$FZ86)} -> 0 | GF86: =GE86*$J86 -> 0 | IC86: {=SUMPRODUCT(--(MOD(COLUMN($GG86:$IB86),4)=MOD(COLUMN($GG86),4)),$GG86:$IB86)} -> 0 | ID86: =IC86*$J86 -> 0 | IE86: {=SUMPRODUCT(--(MOD(COLUMN($GG86:$IB86),4)=MOD(COLUMN($GH86),4)),$GG86:$IB86)} -> 0 | IF86: =IE86*$J86 -> 0 | IG86: {=SUMPRODUCT(--(MOD(COLUMN($GG86:$IB86),4)=MOD(COLUMN($GI86),4)),$GG86:$IB86)} -> 0 | IH86: =IG86*$J86 -> 0 | KE86: {=SUMPRODUCT(--(MOD(COLUMN($II86:$KD86),4)=MOD(COLUMN($II86),4)),$II86:$KD86)} -> 0 | KF86: =KE86*$J86 -> 0 | KG86: {=SUMPRODUCT(--(MOD(COLUMN($II86:$KD86),4)=MOD(COLUMN($IJ86),4)),$II86:$KD86)} -> 0 | KH86: =KG86*$J86 -> 0 | KI86: {=SUMPRODUCT(--(MOD(COLUMN($II86:$KD86),4)=MOD(COLUMN($IK86),4)),$II86:$KD86)} -> 0 | KJ86: =KI86*$J86 -> 0
E87: 51 | F87: 2 | G87: 4630905020 | H87: Кран ручного управления уровнем пола eTASC | J87: =2730/1.2 -> 2275 | BF87: =$KN87*0 -> 0 | CK87: 1 | CL87: 1 | CQ87: 0 | CV87: 0 | DA87: 0 | DF87: 0 | DK87: 0 | DU87: 0 | DW87: {=SUMPRODUCT(--(MOD(COLUMN($BO87:$DV87),5)=MOD(COLUMN($BO87),5)),$BO87:$DV87)} -> 0 | DX87: =DW87*$J87 -> 0 | DY87: {=SUMPRODUCT(--(MOD(COLUMN($BO87:$DV87),5)=MOD(COLUMN($BP87),5)),$BO87:$DV87)} -> 0 | DZ87: =DY87*$J87 -> 0 | EA87: {=SUMPRODUCT(--(MOD(COLUMN($BO87:$DV87),5)=MOD(COLUMN($BQ87),5)),$BO87:$DV87)} -> 1 | EB87: =EA87*$J87 -> 2275 | EC87: {=SUMPRODUCT(--(MOD(COLUMN($BO87:$DV87),5)=MOD(COLUMN($BR87),5)),$BO87:$DV87)} -> 1 | ED87: =EC87*$J87 -> 2275 | GA87: {=SUMPRODUCT(--(MOD(COLUMN($EE87:$FZ87),4)=MOD(COLUMN($EE87),4)),$EE87:$FZ87)} -> 0 | GB87: =GA87*$J87 -> 0 | GC87: {=SUMPRODUCT(--(MOD(COLUMN($EE87:$FZ87),4)=MOD(COLUMN($EF87),4)),$EE87:$FZ87)} -> 0 | GD87: =GC87*$J87 -> 0 | GE87: {=SUMPRODUCT(--(MOD(COLUMN($EE87:$FZ87),4)=MOD(COLUMN($EG87),4)),$EE87:$FZ87)} -> 0 | GF87: =GE87*$J87 -> 0 | IC87: {=SUMPRODUCT(--(MOD(COLUMN($GG87:$IB87),4)=MOD(COLUMN($GG87),4)),$GG87:$IB87)} -> 0 | ID87: =IC87*$J87 -> 0 | IE87: {=SUMPRODUCT(--(MOD(COLUMN($GG87:$IB87),4)=MOD(COLUMN($GH87),4)),$GG87:$IB87)} -> 0 | IF87: =IE87*$J87 -> 0 | IG87: {=SUMPRODUCT(--(MOD(COLUMN($GG87:$IB87),4)=MOD(COLUMN($GI87),4)),$GG87:$IB87)} -> 0 | IH87: =IG87*$J87 -> 0 | KE87: {=SUMPRODUCT(--(MOD(COLUMN($II87:$KD87),4)=MOD(COLUMN($II87),4)),$II87:$KD87)} -> 0 | KF87: =KE87*$J87 -> 0 | KG87: {=SUMPRODUCT(--(MOD(COLUMN($II87:$KD87),4)=MOD(COLUMN($IJ87),4)),$II87:$KD87)} -> 0 | KH87: =KG87*$J87 -> 0 | KI87: {=SUMPRODUCT(--(MOD(COLUMN($II87:$KD87),4)=MOD(COLUMN($IK87),4)),$II87:$KD87)} -> 0 | KJ87: =KI87*$J87 -> 0 | KN87: 1
E88: 52 | F88: 2 | G88: 4410501000 | H88: Датчик положения | J88: =690/1.2 -> 575 | BF88: =$KN88*0 -> 0 | CK88: 1 | CL88: 1 | CQ88: 0 | CV88: 0 | DA88: 0 | DF88: 0 | DK88: 0 | DU88: 0 | DW88: {=SUMPRODUCT(--(MOD(COLUMN($BO88:$DV88),5)=MOD(COLUMN($BO88),5)),$BO88:$DV88)} -> 0 | DX88: =DW88*$J88 -> 0 | DY88: {=SUMPRODUCT(--(MOD(COLUMN($BO88:$DV88),5)=MOD(COLUMN($BP88),5)),$BO88:$DV88)} -> 0 | DZ88: =DY88*$J88 -> 0 | EA88: {=SUMPRODUCT(--(MOD(COLUMN($BO88:$DV88),5)=MOD(COLUMN($BQ88),5)),$BO88:$DV88)} -> 1 | EB88: =EA88*$J88 -> 575 | EC88: {=SUMPRODUCT(--(MOD(COLUMN($BO88:$DV88),5)=MOD(COLUMN($BR88),5)),$BO88:$DV88)} -> 1 | ED88: =EC88*$J88 -> 575 | GA88: {=SUMPRODUCT(--(MOD(COLUMN($EE88:$FZ88),4)=MOD(COLUMN($EE88),4)),$EE88:$FZ88)} -> 0 | GB88: =GA88*$J88 -> 0 | GC88: {=SUMPRODUCT(--(MOD(COLUMN($EE88:$FZ88),4)=MOD(COLUMN($EF88),4)),$EE88:$FZ88)} -> 0 | GD88: =GC88*$J88 -> 0 | GE88: {=SUMPRODUCT(--(MOD(COLUMN($EE88:$FZ88),4)=MOD(COLUMN($EG88),4)),$EE88:$FZ88)} -> 0 | GF88: =GE88*$J88 -> 0 | IC88: {=SUMPRODUCT(--(MOD(COLUMN($GG88:$IB88),4)=MOD(COLUMN($GG88),4)),$GG88:$IB88)} -> 0 | ID88: =IC88*$J88 -> 0 | IE88: {=SUMPRODUCT(--(MOD(COLUMN($GG88:$IB88),4)=MOD(COLUMN($GH88),4)),$GG88:$IB88)} -> 0 | IF88: =IE88*$J88 -> 0 | IG88: {=SUMPRODUCT(--(MOD(COLUMN($GG88:$IB88),4)=MOD(COLUMN($GI88),4)),$GG88:$IB88)} -> 0 | IH88: =IG88*$J88 -> 0 | KE88: {=SUMPRODUCT(--(MOD(COLUMN($II88:$KD88),4)=MOD(COLUMN($II88),4)),$II88:$KD88)} -> 0 | KF88: =KE88*$J88 -> 0 | KG88: {=SUMPRODUCT(--(MOD(COLUMN($II88:$KD88),4)=MOD(COLUMN($IJ88),4)),$II88:$KD88)} -> 0 | KH88: =KG88*$J88 -> 0 | KI88: {=SUMPRODUCT(--(MOD(COLUMN($II88:$KD88),4)=MOD(COLUMN($IK88),4)),$II88:$KD88)} -> 0 | KJ88: =KI88*$J88 -> 0 | KN88: 1
E89: 53 | F89: 2 | G89: 4410507182 | H89: Рычаг удлиннитель датчика положения | J89: =174/1.2 -> 145 | BF89: =$KN89*0 -> 0 | CK89: 1 | CL89: 1 | CQ89: 0 | CV89: 0 | DA89: 0 | DF89: 0 | DK89: 0 | DU89: 0 | DW89: {=SUMPRODUCT(--(MOD(COLUMN($BO89:$DV89),5)=MOD(COLUMN($BO89),5)),$BO89:$DV89)} -> 0 | DX89: =DW89*$J89 -> 0 | DY89: {=SUMPRODUCT(--(MOD(COLUMN($BO89:$DV89),5)=MOD(COLUMN($BP89),5)),$BO89:$DV89)} -> 0 | DZ89: =DY89*$J89 -> 0 | EA89: {=SUMPRODUCT(--(MOD(COLUMN($BO89:$DV89),5)=MOD(COLUMN($BQ89),5)),$BO89:$DV89)} -> 1 | EB89: =EA89*$J89 -> 145 | EC89: {=SUMPRODUCT(--(MOD(COLUMN($BO89:$DV89),5)=MOD(COLUMN($BR89),5)),$BO89:$DV89)} -> 1 | ED89: =EC89*$J89 -> 145 | GA89: {=SUMPRODUCT(--(MOD(COLUMN($EE89:$FZ89),4)=MOD(COLUMN($EE89),4)),$EE89:$FZ89)} -> 0 | GB89: =GA89*$J89 -> 0 | GC89: {=SUMPRODUCT(--(MOD(COLUMN($EE89:$FZ89),4)=MOD(COLUMN($EF89),4)),$EE89:$FZ89)} -> 0 | GD89: =GC89*$J89 -> 0 | GE89: {=SUMPRODUCT(--(MOD(COLUMN($EE89:$FZ89),4)=MOD(COLUMN($EG89),4)),$EE89:$FZ89)} -> 0 | GF89: =GE89*$J89 -> 0 | IC89: {=SUMPRODUCT(--(MOD(COLUMN($GG89:$IB89),4)=MOD(COLUMN($GG89),4)),$GG89:$IB89)} -> 0 | ID89: =IC89*$J89 -> 0 | IE89: {=SUMPRODUCT(--(MOD(COLUMN($GG89:$IB89),4)=MOD(COLUMN($GH89),4)),$GG89:$IB89)} -> 0 | IF89: =IE89*$J89 -> 0 | IG89: {=SUMPRODUCT(--(MOD(COLUMN($GG89:$IB89),4)=MOD(COLUMN($GI89),4)),$GG89:$IB89)} -> 0 | IH89: =IG89*$J89 -> 0 | KE89: {=SUMPRODUCT(--(MOD(COLUMN($II89:$KD89),4)=MOD(COLUMN($II89),4)),$II89:$KD89)} -> 0 | KF89: =KE89*$J89 -> 0 | KG89: {=SUMPRODUCT(--(MOD(COLUMN($II89:$KD89),4)=MOD(COLUMN($IJ89),4)),$II89:$KD89)} -> 0 | KH89: =KG89*$J89 -> 0 | KI89: {=SUMPRODUCT(--(MOD(COLUMN($II89:$KD89),4)=MOD(COLUMN($IK89),4)),$II89:$KD89)} -> 0 | KJ89: =KI89*$J89 -> 0 | KN89: 1
E90: 54 | F90: 2 | G90: 4494450500 | H90: Кабель, 5 м | J90: =648/1.2 -> 540 | BF90: =$KN90*0 -> 0 | CK90: 1 | CL90: 1 | CQ90: 0 | CV90: 0 | DA90: 0 | DF90: 0 | DK90: 0 | DU90: 0 | DW90: {=SUMPRODUCT(--(MOD(COLUMN($BO90:$DV90),5)=MOD(COLUMN($BO90),5)),$BO90:$DV90)} -> 0 | DX90: =DW90*$J90 -> 0 | DY90: {=SUMPRODUCT(--(MOD(COLUMN($BO90:$DV90),5)=MOD(COLUMN($BP90),5)),$BO90:$DV90)} -> 0 | DZ90: =DY90*$J90 -> 0 | EA90: {=SUMPRODUCT(--(MOD(COLUMN($BO90:$DV90),5)=MOD(COLUMN($BQ90),5)),$BO90:$DV90)} -> 1 | EB90: =EA90*$J90 -> 540 | EC90: {=SUMPRODUCT(--(MOD(COLUMN($BO90:$DV90),5)=MOD(COLUMN($BR90),5)),$BO90:$DV90)} -> 1 | ED90: =EC90*$J90 -> 540 | GA90: {=SUMPRODUCT(--(MOD(COLUMN($EE90:$FZ90),4)=MOD(COLUMN($EE90),4)),$EE90:$FZ90)} -> 0 | GB90: =GA90*$J90 -> 0 | GC90: {=SUMPRODUCT(--(MOD(COLUMN($EE90:$FZ90),4)=MOD(COLUMN($EF90),4)),$EE90:$FZ90)} -> 0 | GD90: =GC90*$J90 -> 0 | GE90: {=SUMPRODUCT(--(MOD(COLUMN($EE90:$FZ90),4)=MOD(COLUMN($EG90),4)),$EE90:$FZ90)} -> 0 | GF90: =GE90*$J90 -> 0 | IC90: {=SUMPRODUCT(--(MOD(COLUMN($GG90:$IB90),4)=MOD(COLUMN($GG90),4)),$GG90:$IB90)} -> 0 | ID90: =IC90*$J90 -> 0 | IE90: {=SUMPRODUCT(--(MOD(COLUMN($GG90:$IB90),4)=MOD(COLUMN($GH90),4)),$GG90:$IB90)} -> 0 | IF90: =IE90*$J90 -> 0 | IG90: {=SUMPRODUCT(--(MOD(COLUMN($GG90:$IB90),4)=MOD(COLUMN($GI90),4)),$GG90:$IB90)} -> 0 | IH90: =IG90*$J90 -> 0 | KE90: {=SUMPRODUCT(--(MOD(COLUMN($II90:$KD90),4)=MOD(COLUMN($II90),4)),$II90:$KD90)} -> 0 | KF90: =KE90*$J90 -> 0 | KG90: {=SUMPRODUCT(--(MOD(COLUMN($II90:$KD90),4)=MOD(COLUMN($IJ90),4)),$II90:$KD90)} -> 0 | KH90: =KG90*$J90 -> 0 | KI90: {=SUMPRODUCT(--(MOD(COLUMN($II90:$KD90),4)=MOD(COLUMN($IK90),4)),$II90:$KD90)} -> 0 | KJ90: =KI90*$J90 -> 0 | KN90: 1
E91: 55 | F91: 2 | G91: 4498110300 | H91: Кабель датчика положения, 3м | J91: =756/1.2 -> 630 | BF91: =$KN91*0 -> 0 | CK91: 1 | CL91: 1 | CQ91: 0 | CV91: 0 | DA91: 0 | DF91: 0 | DK91: 0 | DU91: 0 | DW91: {=SUMPRODUCT(--(MOD(COLUMN($BO91:$DV91),5)=MOD(COLUMN($BO91),5)),$BO91:$DV91)} -> 0 | DX91: =DW91*$J91 -> 0 | DY91: {=SUMPRODUCT(--(MOD(COLUMN($BO91:$DV91),5)=MOD(COLUMN($BP91),5)),$BO91:$DV91)} -> 0 | DZ91: =DY91*$J91 -> 0 | EA91: {=SUMPRODUCT(--(MOD(COLUMN($BO91:$DV91),5)=MOD(COLUMN($BQ91),5)),$BO91:$DV91)} -> 1 | EB91: =EA91*$J91 -> 630 | EC91: {=SUMPRODUCT(--(MOD(COLUMN($BO91:$DV91),5)=MOD(COLUMN($BR91),5)),$BO91:$DV91)} -> 1 | ED91: =EC91*$J91 -> 630 | GA91: {=SUMPRODUCT(--(MOD(COLUMN($EE91:$FZ91),4)=MOD(COLUMN($EE91),4)),$EE91:$FZ91)} -> 0 | GB91: =GA91*$J91 -> 0 | GC91: {=SUMPRODUCT(--(MOD(COLUMN($EE91:$FZ91),4)=MOD(COLUMN($EF91),4)),$EE91:$FZ91)} -> 0 | GD91: =GC91*$J91 -> 0 | GE91: {=SUMPRODUCT(--(MOD(COLUMN($EE91:$FZ91),4)=MOD(COLUMN($EG91),4)),$EE91:$FZ91)} -> 0 | GF91: =GE91*$J91 -> 0 | IC91: {=SUMPRODUCT(--(MOD(COLUMN($GG91:$IB91),4)=MOD(COLUMN($GG91),4)),$GG91:$IB91)} -> 0 | ID91: =IC91*$J91 -> 0 | IE91: {=SUMPRODUCT(--(MOD(COLUMN($GG91:$IB91),4)=MOD(COLUMN($GH91),4)),$GG91:$IB91)} -> 0 | IF91: =IE91*$J91 -> 0 | IG91: {=SUMPRODUCT(--(MOD(COLUMN($GG91:$IB91),4)=MOD(COLUMN($GI91),4)),$GG91:$IB91)} -> 0 | IH91: =IG91*$J91 -> 0 | KE91: {=SUMPRODUCT(--(MOD(COLUMN($II91:$KD91),4)=MOD(COLUMN($II91),4)),$II91:$KD91)} -> 0 | KF91: =KE91*$J91 -> 0 | KG91: {=SUMPRODUCT(--(MOD(COLUMN($II91:$KD91),4)=MOD(COLUMN($IJ91),4)),$II91:$KD91)} -> 0 | KH91: =KG91*$J91 -> 0 | KI91: {=SUMPRODUCT(--(MOD(COLUMN($II91:$KD91),4)=MOD(COLUMN($IK91),4)),$II91:$KD91)} -> 0 | KJ91: =KI91*$J91 -> 0 | KN91: 1
E92: 56 | F92: 2 | G92: 4802070010 | H92: Модулятор EBS | J92: =4618.8/1.2 -> 3849 | BF92: =$KN92*0 -> 0 | DK92: 0 | DO92: =$KN92*3 -> 3 | DT92: =$KN92*3 -> 3 | DU92: 0 | DW92: {=SUMPRODUCT(--(MOD(COLUMN($BO92:$DV92),5)=MOD(COLUMN($BO92),5)),$BO92:$DV92)} -> 0 | DX92: =DW92*$J92 -> 0 | DY92: {=SUMPRODUCT(--(MOD(COLUMN($BO92:$DV92),5)=MOD(COLUMN($BP92),5)),$BO92:$DV92)} -> 0 | DZ92: =DY92*$J92 -> 0 | EA92: {=SUMPRODUCT(--(MOD(COLUMN($BO92:$DV92),5)=MOD(COLUMN($BQ92),5)),$BO92:$DV92)} -> 6 | EB92: =EA92*$J92 -> 23094 | EC92: {=SUMPRODUCT(--(MOD(COLUMN($BO92:$DV92),5)=MOD(COLUMN($BR92),5)),$BO92:$DV92)} -> 0 | ED92: =EC92*$J92 -> 0 | GA92: {=SUMPRODUCT(--(MOD(COLUMN($EE92:$FZ92),4)=MOD(COLUMN($EE92),4)),$EE92:$FZ92)} -> 0 | GB92: =GA92*$J92 -> 0 | GC92: {=SUMPRODUCT(--(MOD(COLUMN($EE92:$FZ92),4)=MOD(COLUMN($EF92),4)),$EE92:$FZ92)} -> 0 | GD92: =GC92*$J92 -> 0 | GE92: {=SUMPRODUCT(--(MOD(COLUMN($EE92:$FZ92),4)=MOD(COLUMN($EG92),4)),$EE92:$FZ92)} -> 0 | GF92: =GE92*$J92 -> 0 | IC92: {=SUMPRODUCT(--(MOD(COLUMN($GG92:$IB92),4)=MOD(COLUMN($GG92),4)),$GG92:$IB92)} -> 0 | ID92: =IC92*$J92 -> 0 | IE92: {=SUMPRODUCT(--(MOD(COLUMN($GG92:$IB92),4)=MOD(COLUMN($GH92),4)),$GG92:$IB92)} -> 0 | IF92: =IE92*$J92 -> 0 | IG92: {=SUMPRODUCT(--(MOD(COLUMN($GG92:$IB92),4)=MOD(COLUMN($GI92),4)),$GG92:$IB92)} -> 0 | IH92: =IG92*$J92 -> 0 | KE92: {=SUMPRODUCT(--(MOD(COLUMN($II92:$KD92),4)=MOD(COLUMN($II92),4)),$II92:$KD92)} -> 0 | KF92: =KE92*$J92 -> 0 | KG92: {=SUMPRODUCT(--(MOD(COLUMN($II92:$KD92),4)=MOD(COLUMN($IJ92),4)),$II92:$KD92)} -> 0 | KH92: =KG92*$J92 -> 0 | KI92: {=SUMPRODUCT(--(MOD(COLUMN($II92:$KD92),4)=MOD(COLUMN($IK92),4)),$II92:$KD92)} -> 0 | KJ92: =KI92*$J92 -> 0 | KN92: 1
E93: 57 | F93: 2 | G93: 4494290800 | H93: Кабель модулятора EBS, 8 м | J93: =1568.4/1.2 -> 1307 | BF93: =$KN93*0 -> 0 | DK93: 0 | DO93: =$KN93*3 -> 3 | DT93: =$KN93*3 -> 3 | DU93: 0 | DW93: {=SUMPRODUCT(--(MOD(COLUMN($BO93:$DV93),5)=MOD(COLUMN($BO93),5)),$BO93:$DV93)} -> 0 | DX93: =DW93*$J93 -> 0 | DY93: {=SUMPRODUCT(--(MOD(COLUMN($BO93:$DV93),5)=MOD(COLUMN($BP93),5)),$BO93:$DV93)} -> 0 | DZ93: =DY93*$J93 -> 0 | EA93: {=SUMPRODUCT(--(MOD(COLUMN($BO93:$DV93),5)=MOD(COLUMN($BQ93),5)),$BO93:$DV93)} -> 6 | EB93: =EA93*$J93 -> 7842 | EC93: {=SUMPRODUCT(--(MOD(COLUMN($BO93:$DV93),5)=MOD(COLUMN($BR93),5)),$BO93:$DV93)} -> 0 | ED93: =EC93*$J93 -> 0 | GA93: {=SUMPRODUCT(--(MOD(COLUMN($EE93:$FZ93),4)=MOD(COLUMN($EE93),4)),$EE93:$FZ93)} -> 0 | GB93: =GA93*$J93 -> 0 | GC93: {=SUMPRODUCT(--(MOD(COLUMN($EE93:$FZ93),4)=MOD(COLUMN($EF93),4)),$EE93:$FZ93)} -> 0 | GD93: =GC93*$J93 -> 0 | GE93: {=SUMPRODUCT(--(MOD(COLUMN($EE93:$FZ93),4)=MOD(COLUMN($EG93),4)),$EE93:$FZ93)} -> 0 | GF93: =GE93*$J93 -> 0 | IC93: {=SUMPRODUCT(--(MOD(COLUMN($GG93:$IB93),4)=MOD(COLUMN($GG93),4)),$GG93:$IB93)} -> 0 | ID93: =IC93*$J93 -> 0 | IE93: {=SUMPRODUCT(--(MOD(COLUMN($GG93:$IB93),4)=MOD(COLUMN($GH93),4)),$GG93:$IB93)} -> 0 | IF93: =IE93*$J93 -> 0 | IG93: {=SUMPRODUCT(--(MOD(COLUMN($GG93:$IB93),4)=MOD(COLUMN($GI93),4)),$GG93:$IB93)} -> 0 | IH93: =IG93*$J93 -> 0 | KE93: {=SUMPRODUCT(--(MOD(COLUMN($II93:$KD93),4)=MOD(COLUMN($II93),4)),$II93:$KD93)} -> 0 | KF93: =KE93*$J93 -> 0 | KG93: {=SUMPRODUCT(--(MOD(COLUMN($II93:$KD93),4)=MOD(COLUMN($IJ93),4)),$II93:$KD93)} -> 0 | KH93: =KG93*$J93 -> 0 | KI93: {=SUMPRODUCT(--(MOD(COLUMN($II93:$KD93),4)=MOD(COLUMN($IK93),4)),$II93:$KD93)} -> 0 | KJ93: =KI93*$J93 -> 0 | KN93: 1
H94: Итого | BI94: =SUMPRODUCT(--(MOD(COLUMN($M94:$BH94),4)=MOD(COLUMN($M94),4)),$M94:$BH94) -> 0 | BJ94: =BI94*$I94 -> 0 | BK94: =SUMPRODUCT(--(MOD(COLUMN($M94:$BH94),4)=MOD(COLUMN($M94)+1,4)),$M94:$BH94) -> 0 | BL94: =BK94*$I94 -> 0 | BM94: =SUMPRODUCT(--(MOD(COLUMN($M94:$BH94),4)=MOD(COLUMN($M94)+2,4)),$M94:$BH94) -> 0 | BN94: =BM94*$I94 -> 0
A95: ПАО «ТЗА» | BI95: =SUMPRODUCT(--(MOD(COLUMN($M95:$BH95),4)=MOD(COLUMN($M95),4)),$M95:$BH95) -> 0 | BJ95: =BI95*$I95 -> 0 | BK95: =SUMPRODUCT(--(MOD(COLUMN($M95:$BH95),4)=MOD(COLUMN($M95)+1,4)),$M95:$BH95) -> 0 | BL95: =BK95*$I95 -> 0 | BM95: =SUMPRODUCT(--(MOD(COLUMN($M95:$BH95),4)=MOD(COLUMN($M95)+2,4)),$M95:$BH95) -> 0 | BN95: =BM95*$I95 -> 0 | DW95: =SUMPRODUCT(--(MOD(COLUMN($BO95:$DV95),5)=MOD(COLUMN($BO95),5)),$BO95:$DV95) -> 0 | DX95: =DW95*$J95 -> 0 | DY95: =SUMPRODUCT(--(MOD(COLUMN($BO95:$DV95),5)=MOD(COLUMN($BO95),5)+1),$BO95:$DV95) -> 0 | DZ95: =DY95*$J95 -> 0 | EA95: =SUMPRODUCT(--(MOD(COLUMN($BO95:$DV95),5)=MOD(COLUMN($BO95),5)+2),$BO95:$DV95) -> 0 | EB95: =EA95*$J95 -> 0 | EC95: =SUMPRODUCT(--(MOD(COLUMN($BO95:$DV95),5)=MOD(COLUMN($BO95),5)+3),$BO95:$DV95) -> 0 | ED95: =EC95*$J95 -> 0
A96: СпецАвтоКам | B96: Предоплата 100% | C96: ВБК РУС | D96: Мустафин Ринат | E96: 1 | F96: 1 | G96: 9522010010 | H96: Головка соединительная (управляющая) | I96: =89.6/1.2/0.98 -> 76.190476 | J96: =89.6/1.2*1.0863 -> 81.1104 | CL96: 0 | CQ96: 0 | CV96: 0 | DA96: 0 | DF96: 0 | DK96: 0 | DP96: 0 | DW96: {=SUMPRODUCT(--(MOD(COLUMN($BO96:$DV96),5)=MOD(COLUMN($BO96),5)),$BO96:$DV96)} -> 0 | DX96: =DW96*$J96 -> 0 | DY96: {=SUMPRODUCT(--(MOD(COLUMN($BO96:$DV96),5)=MOD(COLUMN($BP96),5)),$BO96:$DV96)} -> 0 | DZ96: =DY96*$J96 -> 0 | EA96: {=SUMPRODUCT(--(MOD(COLUMN($BO96:$DV96),5)=MOD(COLUMN($BQ96),5)),$BO96:$DV96)} -> 0 | EB96: =EA96*$J96 -> 0 | EC96: {=SUMPRODUCT(--(MOD(COLUMN($BO96:$DV96),5)=MOD(COLUMN($BR96),5)),$BO96:$DV96)} -> 0 | ED96: =EC96*$J96 -> 0 | EE96: 0 | EF96: 0 | EG96: 0 | EI96: 0 | EJ96: 0 | EK96: 0 | EO96: 0 | EQ96: =$KN96*5 -> 5 | ER96: 0 | EU96: =$KN96*5 -> 5 | EV96: 0 | EW96: 0 | EY96: =$KN96*5 -> 5 | EZ96: 0 | FC96: =$KN96*10 -> 10 | FD96: 5 | FG96: =$KN96*10 -> 10 | FH96: 5 | FK96: =$KN96*10 -> 10 | FL96: 10 | FO96: =$KN96*10 -> 10 | FP96: 10 | FS96: =$KN96*10 -> 10 | FT96: 10 | FW96: =$KN96*10 -> 10 | FX96: 10 | GA96: {=SUMPRODUCT(--(MOD(COLUMN($EE96:$FZ96),4)=MOD(COLUMN($EE96),4)),$EE96:$FZ96)} -> 75 | GB96: =GA96*$J96 -> 6083.28 | GC96: {=SUMPRODUCT(--(MOD(COLUMN($EE96:$FZ96),4)=MOD(COLUMN($EF96),4)),$EE96:$FZ96)} -> 50 | GD96: =GC96*$J96 -> 4055.52 | GE96: {=SUMPRODUCT(--(MOD(COLUMN($EE96:$FZ96),4)=MOD(COLUMN($EG96),4)),$EE96:$FZ96)} -> 0 | GF96: =GE96*$J96 -> 0 | GG96: =$KN96*10 -> 10 | GK96: =$KN96*10 -> 10 | GO96: =$KN96*15 -> 15 | GS96: =$KN96*20 -> 20 | GW96: =$KN96*20 -> 20 | HA96: =$KN96*20 -> 20 | HE96: =$KN96*20 -> 20 | HI96: =$KN96*20 -> 20 | HM96: =$KN96*20 -> 20 | HQ96: =$KN96*20 -> 20 | HU96: =$KN96*20 -> 20 | HY96: =$KN96*20 -> 20 | IC96: {=SUMPRODUCT(--(MOD(COLUMN($GG96:$IB96),4)=MOD(COLUMN($GG96),4)),$GG96:$IB96)} -> 215 | ID96: =IC96*$J96 -> 17438.736 | IE96: {=SUMPRODUCT(--(MOD(COLUMN($GG96:$IB96),4)=MOD(COLUMN($GH96),4)),$GG96:$IB96)} -> 0 | IF96: =IE96*$J96 -> 0 | IG96: {=SUMPRODUCT(--(MOD(COLUMN($GG96:$IB96),4)=MOD(COLUMN($GI96),4)),$GG96:$IB96)} -> 0 | IH96: =IG96*$J96 -> 0 | II96: =$KN96*10 -> 10 | IM96: =$KN96*10 -> 10 | IQ96: =$KN96*15 -> 15 | IU96: =$KN96*20 -> 20 | IY96: =$KN96*20 -> 20 | JC96: =$KN96*20 -> 20 | JG96: =$KN96*20 -> 20 | JK96: =$KN96*20 -> 20 | JO96: =$KN96*20 -> 20 | JS96: =$KN96*20 -> 20 | JW96: =$KN96*20 -> 20 | KA96: =$KN96*20 -> 20 | KE96: {=SUMPRODUCT(--(MOD(COLUMN($II96:$KD96),4)=MOD(COLUMN($II96),4)),$II96:$KD96)} -> 215 | KF96: =KE96*$J96 -> 17438.736 | KG96: {=SUMPRODUCT(--(MOD(COLUMN($II96:$KD96),4)=MOD(COLUMN($IJ96),4)),$II96:$KD96)} -> 0 | KH96: =KG96*$J96 -> 0 | KI96: {=SUMPRODUCT(--(MOD(COLUMN($II96:$KD96),4)=MOD(COLUMN($IK96),4)),$II96:$KD96)} -> 0 | KJ96: =KI96*$J96 -> 0 | KN96: 1 | KO96: TEBS 4s/3m 12м
