Workbook
Name ЕВРО: ПНЕВМАТИКА!$A$1
Name ЕВРО_2025_08_29: 93.49
Name НДС: 1.22
Name НДС_20: 1.2
Name Список_артикулов: База[Артикул]
Name Список_комплектов: Комплекты[Комплект]
Name Список_Сводная_Пневматика_2026: Пневматика_СВОДНАЯ_2026[Ключ]
Name Список_Сводная_Тормоз_2026: Тормоз_СВОДНАЯ_2026[Ключ]
Name ЮАНЬ: ПНЕВМАТИКА!$A$2
Name ЮАНЬ_2025_08_29: 11.25

Sheet ТОРМОЗ
A1: 93.49 | B1: - курс евро/рубль | E1: Дата | G1: 46171 | K1: НДС_20 Проверка
A2: 11.25 | B2: - курс юань/рубль | K2: НДС Проверка
F3: Подсветить артикул: | G3: ъ | I3: 2026-I | N3: 2026 | BS3: 2027 _ НЕ АКТУАЛИЗИРУЕТСЯ | DT3: 2028 _ НЕ АКТУАЛИЗИРУЕТСЯ
A4: Клиент | B4: Условия оплаты | C4: Поставщик | D4: Менеджер | E4: п\п | F4: 2 - продукт WABCO | G4: Номер изделия/ артикул | H4: Наименование | I4: Цена для плана, CNY, без НДС | J4: Цена в валюте, без НДС | K4: Валюта | L4: Цена от курса, CNY, без НДС | N4: ПР 26 | O4: 46023 | S4: 46054 | W4: 46082 | AA4: 46113 | AE4: 46143 | AI4: 46174 | AM4: 46204 | AQ4: 46235 | AU4: 46266 | AY4: 46296 | BC4: 46327 | BG4: 46357 | BL4: ИТОГО, 2026 | BS4: ПР 27 | BT4: 46388 | BX4: 46419 | CB4: 46447 | CF4: 46478 | CJ4: 46508 | CN4: 46539 | CR4: 46569 | CV4: 46600 | CZ4: 46631 | DD4: 46661 | DH4: 46692 | DL4: 46722 | DQ4: ИТОГО, 2027 | DT4: ПР 28 | DU4: 46753 | DY4: 46784 | EC4: 46813 | EG4: 46844 | EK4: 46874 | EO4: 46905 | ES4: 46935 | EW4: 46966 | FA4: 46997 | FE4: 47027 | FI4: 47058 | FM4: 47088 | FR4: ИТОГО, 2028
O5: AOP, шт | P5: Прогноз, шт | Q5: Факт, шт | R5: Коментарий | S5: AOP, шт | T5: Прогноз, шт | U5: Факт, шт | V5: Коментарий | W5: AOP, шт | X5: Прогноз, шт | Y5: Факт, шт | Z5: Коментарий | AA5: AOP, шт | AB5: Прогноз, шт | AC5: Факт, шт | AD5: Коментарий | AE5: AOP, шт | AF5: Прогноз, шт | AG5: Факт, шт | AH5: Коментарий | AI5: AOP, шт | AJ5: Прогноз, шт | AK5: Факт, шт | AL5: Коментарий | AM5: AOP, шт | AN5: Прогноз, шт | AO5: Факт, шт | AP5: Коментарий | AQ5: AOP, шт | AR5: Прогноз, шт | AS5: Факт, шт | AT5: Коментарий | AU5: AOP, шт | AV5: Прогноз, шт | AW5: Факт, шт | AX5: Коментарий | AY5: AOP, шт | AZ5: Прогноз, шт | BA5: Факт, шт | BB5: Коментарий | BC5: AOP, шт | BD5: Прогноз, шт | BE5: Факт, шт | BF5: Коментарий | BG5: AOP, шт | BH5: Прогноз, шт | BI5: Факт, шт | BJ5: Коментарий | BL5: AOP, шт | BM5: Продажи AOP, CNY | BN5: Прогноз, шт | BO5: Продажи Прогноз, CNY | BP5: Факт, шт | BQ5: Продажи Факт, CNY | BT5: AOP, шт | BU5: Прогноз, шт | BV5: Факт, шт | BW5: Коментарий | BX5: AOP, шт | BY5: Прогноз, шт | BZ5: Факт, шт | CA5: Коментарий | CB5: AOP, шт | CC5: Прогноз, шт | CD5: Факт, шт | CE5: Коментарий | CF5: AOP, шт | CG5: Прогноз, шт | CH5: Факт, шт | CI5: Коментарий | CJ5: AOP, шт | CK5: Прогноз, шт | CL5: Факт, шт | CM5: Коментарий | CN5: AOP, шт | CO5: Прогноз, шт | CP5: Факт, шт | CQ5: Коментарий | CR5: AOP, шт | CS5: Прогноз, шт | CT5: Факт, шт | CU5: Коментарий | CV5: AOP, шт | CW5: Прогноз, шт | CX5: Факт, шт | CY5: Коментарий | CZ5: AOP, шт | DA5: Прогноз, шт | DB5: Факт, шт | DC5: Коментарий | DD5: AOP, шт | DE5: Прогноз, шт | DF5: Факт, шт | DG5: Коментарий | DH5: AOP, шт | DI5: Прогноз, шт | DJ5: Факт, шт | DK5: Коментарий | DL5: AOP, шт | DM5: Прогноз, шт | DN5: Факт, шт | DO5: Коментарий | DQ5: AOP, шт | DR5: Продажи AOP, CNY | DU5: AOP, шт | DV5: Прогноз, шт | DW5: Факт, шт | DX5: Коментарий | DY5: AOP, шт | DZ5: Прогноз, шт | EA5: Факт, шт | EB5: Коментарий | EC5: AOP, шт | ED5: Прогноз, шт | EE5: Факт, шт | EF5: Коментарий | EG5: AOP, шт | EH5: Прогноз, шт | EI5: Факт, шт | EJ5: Коментарий | EK5: AOP, шт | EL5: Прогноз, шт | EM5: Факт, шт | EN5: Коментарий | EO5: AOP, шт | EP5: Прогноз, шт | EQ5: Факт, шт | ER5: Коментарий | ES5: AOP, шт | ET5: Прогноз, шт | EU5: Факт, шт | EV5: Коментарий | EW5: AOP, шт | EX5: Прогноз, шт | EY5: Факт, шт | EZ5: Коментарий | FA5: AOP, шт | FB5: Прогноз, шт | FC5: Факт, шт | FD5: Коментарий | FE5: AOP, шт | FF5: Прогноз, шт | FG5: Факт, шт | FH5: Коментарий | FI5: AOP, шт | FJ5: Прогноз, шт | FK5: Факт, шт | FL5: Коментарий | FM5: AOP, шт | FN5: Прогноз, шт | FO5: Факт, шт | FP5: Коментарий | FR5: AOP, шт | FS5: Продажи AOP, CNY
A6: АВТОКОМПОНЕНТ НАО | B6: Предоплата 50% | C6: ВБК Восток | D6: Прасолов, Соловьёв | E6: =IF(ISBLANK(G6),"",IF($A$6:$A$64=$A6,COUNTIF($A$6:A6,$A6),"")) -> 1 | F6: 1 | G6: 6402250560 | H6: 6402250560 AD Тормоз дисковый ( левый ) | I6: 2048 | L6: =IF(K6="RUB",J6/ЮАНЬ,IF(K6="EUR",J6*ЕВРО/ЮАНЬ,"")) | N6: =IF(BP6>0,1,IF(BN6>0,2,)) -> 2 | U6: 0 | AA6: 9 | AE6: 9 | AG6: 0 | AI6: 60 | AM6: 120 | AQ6: 120 | AU6: 120 | AV6: 60 | AY6: 240 | AZ6: 60 | BC6: 240 | BD6: 120 | BG6: 240 | BH6: 240 | BL6: =SUMPRODUCT(--(MOD(COLUMN($O6:$AL6),4)=MOD(COLUMN($O6)+0,4)),$O6:$AL6) +SUMPRODUCT(--(MOD(COLUMN($AM6:$BJ6),4)=MOD(COLUMN($AM6)+0,4)),$AM6:$BJ6) -> 1158 | BM6: =SUMPRODUCT(--(MOD(COLUMN($O6:$AL6),4)=MOD(COLUMN($O6)+0,4)),$O6:$AL6)*$I6 +SUMPRODUCT(--(MOD(COLUMN($AM6:$BJ6),4)=MOD(COLUMN($AM6)+0,4)),$AM6:$BJ6)*$I6 -> 2371584 | BN6: =SUMPRODUCT(--(MOD(COLUMN($O6:$AL6),4)=MOD(COLUMN($O6)+1,4)),$O6:$AL6) +SUMPRODUCT(--(MOD(COLUMN($AM6:$BJ6),4)=MOD(COLUMN($AM6)+1,4)),$AM6:$BJ6) -> 480 | BO6: =SUMPRODUCT(--(MOD(COLUMN($O6:$AL6),4)=MOD(COLUMN($O6)+1,4)),$O6:$AL6)*$I6 +SUMPRODUCT(--(MOD(COLUMN($AM6:$BJ6),4)=MOD(COLUMN($AM6)+1,4)),$AM6:$BJ6)*$I6 -> 983040 | BP6: =SUMPRODUCT(--(MOD(COLUMN($O6:$AL6),4)=MOD(COLUMN($O6)+2,4)),$O6:$AL6) +SUMPRODUCT(--(MOD(COLUMN($AM6:$BJ6),4)=MOD(COLUMN($AM6)+2,4)),$AM6:$BJ6) -> 0 | BQ6: =SUMPRODUCT(--(MOD(COLUMN($O6:$AL6),4)=MOD(COLUMN($O6)+2,4)),$O6:$AL6)*$I6 +SUMPRODUCT(--(MOD(COLUMN($AM6:$BJ6),4)=MOD(COLUMN($AM6)+2,4)),$AM6:$BJ6)*$I6 -> 0 | BT6: 1041 | BX6: 1041 | CB6: 1041 | CF6: 1041 | CJ6: 1041 | CN6: 1041 | CR6: 1041 | CV6: 1041 | CZ6: 1041 | DD6: 1041 | DH6: 1041 | DL6: 1041 | DQ6: =SUMPRODUCT(--(MOD(COLUMN(BT6:CQ6),4)=MOD(COLUMN(BT6),4)),BT6:CQ6)+SUMPRODUCT(--(MOD(COLUMN(CR6:DO6),4)=MOD(COLUMN(CR6),4)),CR6:DO6) -> 12492 | DR6: =SUMPRODUCT(--(MOD(COLUMN(BT6:CQ6),4)=MOD(COLUMN(BT6),4)),BT6:CQ6)*#REF!+SUMPRODUCT(--(MOD(COLUMN(CR6:DO6),4)=MOD(COLUMN(CR6),4)),CR6:DO6)*#REF! -> #REF! | DU6: 2082 | DY6: 2082 | EC6: 2082 | EG6: 2082 | EK6: 2082 | EO6: 2082 | ES6: 2082 | EW6: 2082 | FA6: 2082 | FE6: 2082 | FI6: 2082 | FM6: 2082 | FR6: =SUMPRODUCT(--(MOD(COLUMN(DU6:ER6),4)=MOD(COLUMN(DU6),4)),DU6:ER6)+SUMPRODUCT(--(MOD(COLUMN(ES6:FP6),4)=MOD(COLUMN(ES6),4)),ES6:FP6) -> 24984 | FS6: =SUMPRODUCT(--(MOD(COLUMN(DU6:ER6),4)=MOD(COLUMN(DU6),4)),DU6:ER6)*#REF!+SUMPRODUCT(--(MOD(COLUMN(ES6:FP6),4)=MOD(COLUMN(ES6),4)),ES6:FP6)*#REF! -> #REF!
A7: АВТОКОМПОНЕНТ НАО | B7: Предоплата 50% | C7: ВБК Восток | D7: Прасолов, Соловьёв | E7: =IF(ISBLANK(G7),"",IF($A$6:$A$64=$A7,COUNTIF($A$6:A7,$A7),"")) -> 2 | F7: 1 | G7: 6402250570 | H7: 6402250570 AD Тормоз дисковый ( правый ) | I7: =I6 -> 2048 | L7: =IF(K7="RUB",J7/ЮАНЬ,IF(K7="EUR",J7*ЕВРО/ЮАНЬ,"")) | N7: =IF(BP7>0,1,IF(BN7>0,2,)) -> 2 | U7: 0 | AA7: 9 | AE7: 9 | AG7: 0 | AI7: 60 | AM7: 120 | AQ7: 120 | AU7: 120 | AV7: =AV6 -> 60 | AY7: 240 | AZ7: =AZ6 -> 60 | BC7: 240 | BD7: =BD6 -> 120 | BG7: 240 | BH7: =BH6 -> 240 | BL7: =SUMPRODUCT(--(MOD(COLUMN($O7:$AL7),4)=MOD(COLUMN($O7)+0,4)),$O7:$AL7) +SUMPRODUCT(--(MOD(COLUMN($AM7:$BJ7),4)=MOD(COLUMN($AM7)+0,4)),$AM7:$BJ7) -> 1158 | BM7: =SUMPRODUCT(--(MOD(COLUMN($O7:$AL7),4)=MOD(COLUMN($O7)+0,4)),$O7:$AL7)*$I7 +SUMPRODUCT(--(MOD(COLUMN($AM7:$BJ7),4)=MOD(COLUMN($AM7)+0,4)),$AM7:$BJ7)*$I7 -> 2371584 | BN7: =SUMPRODUCT(--(MOD(COLUMN($O7:$AL7),4)=MOD(COLUMN($O7)+1,4)),$O7:$AL7) +SUMPRODUCT(--(MOD(COLUMN($AM7:$BJ7),4)=MOD(COLUMN($AM7)+1,4)),$AM7:$BJ7) -> 480 | BO7: =SUMPRODUCT(--(MOD(COLUMN($O7:$AL7),4)=MOD(COLUMN($O7)+1,4)),$O7:$AL7)*$I7 +SUMPRODUCT(--(MOD(COLUMN($AM7:$BJ7),4)=MOD(COLUMN($AM7)+1,4)),$AM7:$BJ7)*$I7 -> 983040 | BP7: =SUMPRODUCT(--(MOD(COLUMN($O7:$AL7),4)=MOD(COLUMN($O7)+2,4)),$O7:$AL7) +SUMPRODUCT(--(MOD(COLUMN($AM7:$BJ7),4)=MOD(COLUMN($AM7)+2,4)),$AM7:$BJ7) -> 0 | BQ7: =SUMPRODUCT(--(MOD(COLUMN($O7:$AL7),4)=MOD(COLUMN($O7)+2,4)),$O7:$AL7)*$I7 +SUMPRODUCT(--(MOD(COLUMN($AM7:$BJ7),4)=MOD(COLUMN($AM7)+2,4)),$AM7:$BJ7)*$I7 -> 0 | BT7: 1041 | BX7: 1041 | CB7: 1041 | CF7: 1041 | CJ7: 1041 | CN7: 1041 | CR7: 1041 | CV7: 1041 | CZ7: 1041 | DD7: 1041 | DH7: 1041 | DL7: 1041 | DQ7: =SUMPRODUCT(--(MOD(COLUMN(BT7:CQ7),4)=MOD(COLUMN(BT7),4)),BT7:CQ7)+SUMPRODUCT(--(MOD(COLUMN(CR7:DO7),4)=MOD(COLUMN(CR7),4)),CR7:DO7) -> 12492 | DR7: =SUMPRODUCT(--(MOD(COLUMN(BT7:CQ7),4)=MOD(COLUMN(BT7),4)),BT7:CQ7)*#REF!+SUMPRODUCT(--(MOD(COLUMN(CR7:DO7),4)=MOD(COLUMN(CR7),4)),CR7:DO7)*#REF! -> #REF! | DU7: 2082 | DY7: 2082 | EC7: 2082 | EG7: 2082 | EK7: 2082 | EO7: 2082 | ES7: 2082 | EW7: 2082 | FA7: 2082 | FE7: 2082 | FI7: 2082 | FM7: 2082 | FR7: =SUMPRODUCT(--(MOD(COLUMN(DU7:ER7),4)=MOD(COLUMN(DU7),4)),DU7:ER7)+SUMPRODUCT(--(MOD(COLUMN(ES7:FP7),4)=MOD(COLUMN(ES7),4)),ES7:FP7) -> 24984 | FS7: =SUMPRODUCT(--(MOD(COLUMN(DU7:ER7),4)=MOD(COLUMN(DU7),4)),DU7:ER7)*#REF!+SUMPRODUCT(--(MOD(COLUMN(ES7:FP7),4)=MOD(COLUMN(ES7),4)),ES7:FP7)*#REF! -> #REF!
A8: АВТОКОМПОНЕНТ НАО | B8: Предоплата 50% | C8: ВБК Восток | D8: Прасолов, Соловьёв | E8: =IF(ISBLANK(G8),"",IF($A$6:$A$64=$A8,COUNTIF($A$6:A8,$A8),"")) -> 3 | F8: 1 | G8: 4410328790 | H8: Датчик АБС, 1 м | I8: =90/НДС_20 -> 75 | L8: =IF(K8="RUB",J8/ЮАНЬ,IF(K8="EUR",J8*ЕВРО/ЮАНЬ,"")) | N8: =IF(BP8>0,1,IF(BN8>0,2,)) -> 1 | S8: 1000 | U8: 0 | AA8: 6 | AB8: =1000 -> 1000 | AC8: 1000 | AE8: 6 | AG8: 0 | AI8: 40 | AM8: 80 | AQ8: 80 | AU8: 80 | AV8: =SUM(AV6:AV7)/3 -> 40 | AY8: 160 | AZ8: =SUM(AZ6:AZ7)/3 -> 40 | BC8: 160 | BD8: =SUM(BD6:BD7)/3 -> 80 | BG8: 160 | BH8: =SUM(BH6:BH7)/3 -> 160 | BL8: =SUMPRODUCT(--(MOD(COLUMN($O8:$AL8),4)=MOD(COLUMN($O8)+0,4)),$O8:$AL8) +SUMPRODUCT(--(MOD(COLUMN($AM8:$BJ8),4)=MOD(COLUMN($AM8)+0,4)),$AM8:$BJ8) -> 1772 | BM8: =SUMPRODUCT(--(MOD(COLUMN($O8:$AL8),4)=MOD(COLUMN($O8)+0,4)),$O8:$AL8)*$I8 +SUMPRODUCT(--(MOD(COLUMN($AM8:$BJ8),4)=MOD(COLUMN($AM8)+0,4)),$AM8:$BJ8)*$I8 -> 132900 | BN8: =SUMPRODUCT(--(MOD(COLUMN($O8:$AL8),4)=MOD(COLUMN($O8)+1,4)),$O8:$AL8) +SUMPRODUCT(--(MOD(COLUMN($AM8:$BJ8),4)=MOD(COLUMN($AM8)+1,4)),$AM8:$BJ8) -> 1320 | BO8: =SUMPRODUCT(--(MOD(COLUMN($O8:$AL8),4)=MOD(COLUMN($O8)+1,4)),$O8:$AL8)*$I8 +SUMPRODUCT(--(MOD(COLUMN($AM8:$BJ8),4)=MOD(COLUMN($AM8)+1,4)),$AM8:$BJ8)*$I8 -> 99000 | BP8: =SUMPRODUCT(--(MOD(COLUMN($O8:$AL8),4)=MOD(COLUMN($O8)+2,4)),$O8:$AL8) +SUMPRODUCT(--(MOD(COLUMN($AM8:$BJ8),4)=MOD(COLUMN($AM8)+2,4)),$AM8:$BJ8) -> 1000 | BQ8: =SUMPRODUCT(--(MOD(COLUMN($O8:$AL8),4)=MOD(COLUMN($O8)+2,4)),$O8:$AL8)*$I8 +SUMPRODUCT(--(MOD(COLUMN($AM8:$BJ8),4)=MOD(COLUMN($AM8)+2,4)),$AM8:$BJ8)*$I8 -> 75000 | BT8: 694 | BX8: 694 | CB8: 694 | CF8: 694 | CJ8: 694 | CN8: 694 | CR8: 694 | CV8: 694 | CZ8: 694 | DD8: 694 | DH8: 694 | DL8: 694 | DQ8: =SUMPRODUCT(--(MOD(COLUMN(BT8:CQ8),4)=MOD(COLUMN(BT8),4)),BT8:CQ8)+SUMPRODUCT(--(MOD(COLUMN(CR8:DO8),4)=MOD(COLUMN(CR8),4)),CR8:DO8) -> 8328 | DR8: =SUMPRODUCT(--(MOD(COLUMN(BT8:CQ8),4)=MOD(COLUMN(BT8),4)),BT8:CQ8)*#REF!+SUMPRODUCT(--(MOD(COLUMN(CR8:DO8),4)=MOD(COLUMN(CR8),4)),CR8:DO8)*#REF! -> #REF! | DU8: 1388 | DY8: 1388 | EC8: 1388 | EG8: 1388 | EK8: 1388 | EO8: 1388 | ES8: 1388 | EW8: 1388 | FA8: 1388 | FE8: 1388 | FI8: 1388 | FM8: 1388 | FR8: =SUMPRODUCT(--(MOD(COLUMN(DU8:ER8),4)=MOD(COLUMN(DU8),4)),DU8:ER8)+SUMPRODUCT(--(MOD(COLUMN(ES8:FP8),4)=MOD(COLUMN(ES8),4)),ES8:FP8) -> 16656 | FS8: =SUMPRODUCT(--(MOD(COLUMN(DU8:ER8),4)=MOD(COLUMN(DU8),4)),DU8:ER8)*#REF!+SUMPRODUCT(--(MOD(COLUMN(ES8:FP8),4)=MOD(COLUMN(ES8),4)),ES8:FP8)*#REF! -> #REF!
A9: АВТОКОМПОНЕНТ НАО | B9: Предоплата 50% | C9: ВБК Восток | D9: Прасолов, Соловьёв | E9: =IF(ISBLANK(G9),"",IF($A$6:$A$64=$A9,COUNTIF($A$6:A9,$A9),"")) -> 4 | F9: 1 | G9: 8997605104 | H9: Втулка датчика АБС | I9: =8.4/НДС_20 -> 7 | L9: =IF(K9="RUB",J9/ЮАНЬ,IF(K9="EUR",J9*ЕВРО/ЮАНЬ,"")) | N9: =IF(BP9>0,1,IF(BN9>0,2,)) -> 1 | S9: 1000 | U9: 0 | AA9: 6 | AB9: =1000 -> 1000 | AC9: 1000 | AE9: 6 | AG9: 0 | AI9: 40 | AM9: 80 | AQ9: 80 | AU9: 80 | AV9: =SUM(AV6:AV7)/3 -> 40 | AY9: 160 | AZ9: =SUM(AZ6:AZ7)/3 -> 40 | BC9: 160 | BD9: =SUM(BD6:BD7)/3 -> 80 | BG9: 160 | BH9: =SUM(BH6:BH7)/3 -> 160 | BL9: =SUMPRODUCT(--(MOD(COLUMN($O9:$AL9),4)=MOD(COLUMN($O9)+0,4)),$O9:$AL9) +SUMPRODUCT(--(MOD(COLUMN($AM9:$BJ9),4)=MOD(COLUMN($AM9)+0,4)),$AM9:$BJ9) -> 1772 | BM9: =SUMPRODUCT(--(MOD(COLUMN($O9:$AL9),4)=MOD(COLUMN($O9)+0,4)),$O9:$AL9)*$I9 +SUMPRODUCT(--(MOD(COLUMN($AM9:$BJ9),4)=MOD(COLUMN($AM9)+0,4)),$AM9:$BJ9)*$I9 -> 12404 | BN9: =SUMPRODUCT(--(MOD(COLUMN($O9:$AL9),4)=MOD(COLUMN($O9)+1,4)),$O9:$AL9) +SUMPRODUCT(--(MOD(COLUMN($AM9:$BJ9),4)=MOD(COLUMN($AM9)+1,4)),$AM9:$BJ9) -> 1320 | BO9: =SUMPRODUCT(--(MOD(COLUMN($O9:$AL9),4)=MOD(COLUMN($O9)+1,4)),$O9:$AL9)*$I9 +SUMPRODUCT(--(MOD(COLUMN($AM9:$BJ9),4)=MOD(COLUMN($AM9)+1,4)),$AM9:$BJ9)*$I9 -> 9240 | BP9: =SUMPRODUCT(--(MOD(COLUMN($O9:$AL9),4)=MOD(COLUMN($O9)+2,4)),$O9:$AL9) +SUMPRODUCT(--(MOD(COLUMN($AM9:$BJ9),4)=MOD(COLUMN($AM9)+2,4)),$AM9:$BJ9) -> 1000 | BQ9: =SUMPRODUCT(--(MOD(COLUMN($O9:$AL9),4)=MOD(COLUMN($O9)+2,4)),$O9:$AL9)*$I9 +SUMPRODUCT(--(MOD(COLUMN($AM9:$BJ9),4)=MOD(COLUMN($AM9)+2,4)),$AM9:$BJ9)*$I9 -> 7000 | BT9: 694 | BX9: 694 | CB9: 694 | CF9: 694 | CJ9: 694 | CN9: 694 | CR9: 694 | CV9: 694 | CZ9: 694 | DD9: 694 | DH9: 694 | DL9: 694 | DQ9: =SUMPRODUCT(--(MOD(COLUMN(BT9:CQ9),4)=MOD(COLUMN(BT9),4)),BT9:CQ9)+SUMPRODUCT(--(MOD(COLUMN(CR9:DO9),4)=MOD(COLUMN(CR9),4)),CR9:DO9) -> 8328 | DR9: =SUMPRODUCT(--(MOD(COLUMN(BT9:CQ9),4)=MOD(COLUMN(BT9),4)),BT9:CQ9)*#REF!+SUMPRODUCT(--(MOD(COLUMN(CR9:DO9),4)=MOD(COLUMN(CR9),4)),CR9:DO9)*#REF! -> #REF! | DU9: 1388 | DY9: 1388 | EC9: 1388 | EG9: 1388 | EK9: 1388 | EO9: 1388 | ES9: 1388 | EW9: 1388 | FA9: 1388 | FE9: 1388 | FI9: 1388 | FM9: 1388 | FR9: =SUMPRODUCT(--(MOD(COLUMN(DU9:ER9),4)=MOD(COLUMN(DU9),4)),DU9:ER9)+SUMPRODUCT(--(MOD(COLUMN(ES9:FP9),4)=MOD(COLUMN(ES9),4)),ES9:FP9) -> 16656 | FS9: =SUMPRODUCT(--(MOD(COLUMN(DU9:ER9),4)=MOD(COLUMN(DU9),4)),DU9:ER9)*#REF!+SUMPRODUCT(--(MOD(COLUMN(ES9:FP9),4)=MOD(COLUMN(ES9),4)),ES9:FP9)*#REF! -> #REF!
A10: АВТОКОМПОНЕНТ НАО | B10: Предоплата 50% | C10: ВБК Восток | D10: Прасолов, Соловьёв | E10: =IF(ISBLANK(G10),"",IF($A$6:$A$64=$A10,COUNTIF($A$6:A10,$A10),"")) -> 5 | F10: 1 | G10: 4235041001 | H10: Тормозная камера, тип 20 | I10: =163.08/НДС_20 -> 135.9 | L10: =IF(K10="RUB",J10/ЮАНЬ,IF(K10="EUR",J10*ЕВРО/ЮАНЬ,"")) | N10: =IF(BP10>0,1,IF(BN10>0,2,)) -> 2 | U10: 0 | AG10: 0 | AR10: =600 -> 600 | BL10: =SUMPRODUCT(--(MOD(COLUMN($O10:$AL10),4)=MOD(COLUMN($O10)+0,4)),$O10:$AL10) +SUMPRODUCT(--(MOD(COLUMN($AM10:$BJ10),4)=MOD(COLUMN($AM10)+0,4)),$AM10:$BJ10) -> 0 | BM10: =SUMPRODUCT(--(MOD(COLUMN($O10:$AL10),4)=MOD(COLUMN($O10)+0,4)),$O10:$AL10)*$I10 +SUMPRODUCT(--(MOD(COLUMN($AM10:$BJ10),4)=MOD(COLUMN($AM10)+0,4)),$AM10:$BJ10)*$I10 -> 0 | BN10: =SUMPRODUCT(--(MOD(COLUMN($O10:$AL10),4)=MOD(COLUMN($O10)+1,4)),$O10:$AL10) +SUMPRODUCT(--(MOD(COLUMN($AM10:$BJ10),4)=MOD(COLUMN($AM10)+1,4)),$AM10:$BJ10) -> 600 | BO10: =SUMPRODUCT(--(MOD(COLUMN($O10:$AL10),4)=MOD(COLUMN($O10)+1,4)),$O10:$AL10)*$I10 +SUMPRODUCT(--(MOD(COLUMN($AM10:$BJ10),4)=MOD(COLUMN($AM10)+1,4)),$AM10:$BJ10)*$I10 -> 81540 | BP10: =SUMPRODUCT(--(MOD(COLUMN($O10:$AL10),4)=MOD(COLUMN($O10)+2,4)),$O10:$AL10) +SUMPRODUCT(--(MOD(COLUMN($AM10:$BJ10),4)=MOD(COLUMN($AM10)+2,4)),$AM10:$BJ10) -> 0 | BQ10: =SUMPRODUCT(--(MOD(COLUMN($O10:$AL10),4)=MOD(COLUMN($O10)+2,4)),$O10:$AL10)*$I10 +SUMPRODUCT(--(MOD(COLUMN($AM10:$BJ10),4)=MOD(COLUMN($AM10)+2,4)),$AM10:$BJ10)*$I10 -> 0 | BT10: 694 | BX10: 694 | CB10: 694 | CF10: 694 | CJ10: 694 | CN10: 694 | CR10: 694 | CV10: 694 | CZ10: 694 | DD10: 694 | DH10: 694 | DL10: 694 | DQ10: =SUMPRODUCT(--(MOD(COLUMN(BT10:CQ10),4)=MOD(COLUMN(BT10),4)),BT10:CQ10)+SUMPRODUCT(--(MOD(COLUMN(CR10:DO10),4)=MOD(COLUMN(CR10),4)),CR10:DO10) -> 8328 | DR10: =SUMPRODUCT(--(MOD(COLUMN(BT10:CQ10),4)=MOD(COLUMN(BT10),4)),BT10:CQ10)*#REF!+SUMPRODUCT(--(MOD(COLUMN(CR10:DO10),4)=MOD(COLUMN(CR10),4)),CR10:DO10)*#REF! -> #REF! | DU10: 1388 | DY10: 1388 | EC10: 1388 | EG10: 1388 | EK10: 1388 | EO10: 1388 | ES10: 1388 | EW10: 1388 | FA10: 1388 | FE10: 1388 | FI10: 1388 | FM10: 1388 | FR10: =SUMPRODUCT(--(MOD(COLUMN(DU10:ER10),4)=MOD(COLUMN(DU10),4)),DU10:ER10)+SUMPRODUCT(--(MOD(COLUMN(ES10:FP10),4)=MOD(COLUMN(ES10),4)),ES10:FP10) -> 16656 | FS10: =SUMPRODUCT(--(MOD(COLUMN(DU10:ER10),4)=MOD(COLUMN(DU10),4)),DU10:ER10)*#REF!+SUMPRODUCT(--(MOD(COLUMN(ES10:FP10),4)=MOD(COLUMN(ES10),4)),ES10:FP10)*#REF! -> #REF!
A11: АВТОКОМПОНЕНТ НАО | B11: Предоплата 50% | C11: ВБК Восток | D11: Прасолов, Соловьёв | E11: =IF(ISBLANK(G11),"",IF($A$6:$A$64=$A11,COUNTIF($A$6:A11,$A11),"")) -> 6 | F11: 1 | G11: 9254800504 | H11: Энергоаккумулятор, тип 20/24 | I11: =373.98/НДС_20 -> 311.65 | L11: =IF(K11="RUB",J11/ЮАНЬ,IF(K11="EUR",J11*ЕВРО/ЮАНЬ,"")) | N11: =IF(BP11>0,1,IF(BN11>0,2,)) -> 2 | U11: 0 | AG11: 0 | AR11: =1000 -> 1000 | BL11: =SUMPRODUCT(--(MOD(COLUMN($O11:$AL11),4)=MOD(COLUMN($O11)+0,4)),$O11:$AL11) +SUMPRODUCT(--(MOD(COLUMN($AM11:$BJ11),4)=MOD(COLUMN($AM11)+0,4)),$AM11:$BJ11) -> 0 | BM11: =SUMPRODUCT(--(MOD(COLUMN($O11:$AL11),4)=MOD(COLUMN($O11)+0,4)),$O11:$AL11)*$I11 +SUMPRODUCT(--(MOD(COLUMN($AM11:$BJ11),4)=MOD(COLUMN($AM11)+0,4)),$AM11:$BJ11)*$I11 -> 0 | BN11: =SUMPRODUCT(--(MOD(COLUMN($O11:$AL11),4)=MOD(COLUMN($O11)+1,4)),$O11:$AL11) +SUMPRODUCT(--(MOD(COLUMN($AM11:$BJ11),4)=MOD(COLUMN($AM11)+1,4)),$AM11:$BJ11) -> 1000 | BO11: =SUMPRODUCT(--(MOD(COLUMN($O11:$AL11),4)=MOD(COLUMN($O11)+1,4)),$O11:$AL11)*$I11 +SUMPRODUCT(--(MOD(COLUMN($AM11:$BJ11),4)=MOD(COLUMN($AM11)+1,4)),$AM11:$BJ11)*$I11 -> 311650 | BP11: =SUMPRODUCT(--(MOD(COLUMN($O11:$AL11),4)=MOD(COLUMN($O11)+2,4)),$O11:$AL11) +SUMPRODUCT(--(MOD(COLUMN($AM11:$BJ11),4)=MOD(COLUMN($AM11)+2,4)),$AM11:$BJ11) -> 0 | BQ11: =SUMPRODUCT(--(MOD(COLUMN($O11:$AL11),4)=MOD(COLUMN($O11)+2,4)),$O11:$AL11)*$I11 +SUMPRODUCT(--(MOD(COLUMN($AM11:$BJ11),4)=MOD(COLUMN($AM11)+2,4)),$AM11:$BJ11)*$I11 -> 0 | BT11: 1388 | BX11: 1388 | CB11: 1388 | CF11: 1388 | CJ11: 1388 | CN11: 1388 | CR11: 1388 | CV11: 1388 | CZ11: 1388 | DD11: 1388 | DH11: 1388 | DL11: 1388 | DQ11: =SUMPRODUCT(--(MOD(COLUMN(BT11:CQ11),4)=MOD(COLUMN(BT11),4)),BT11:CQ11)+SUMPRODUCT(--(MOD(COLUMN(CR11:DO11),4)=MOD(COLUMN(CR11),4)),CR11:DO11) -> 16656 | DR11: =SUMPRODUCT(--(MOD(COLUMN(BT11:CQ11),4)=MOD(COLUMN(BT11),4)),BT11:CQ11)*#REF!+SUMPRODUCT(--(MOD(COLUMN(CR11:DO11),4)=MOD(COLUMN(CR11),4)),CR11:DO11)*#REF! -> #REF! | DU11: 2776 | DY11: 2776 | EC11: 2776 | EG11: 2776 | EK11: 2776 | EO11: 2776 | ES11: 2776 | EW11: 2776 | FA11: 2776 | FE11: 2776 | FI11: 2776 | FM11: 2776 | FR11: =SUMPRODUCT(--(MOD(COLUMN(DU11:ER11),4)=MOD(COLUMN(DU11),4)),DU11:ER11)+SUMPRODUCT(--(MOD(COLUMN(ES11:FP11),4)=MOD(COLUMN(ES11),4)),ES11:FP11) -> 33312 | FS11: =SUMPRODUCT(--(MOD(COLUMN(DU11:ER11),4)=MOD(COLUMN(DU11),4)),DU11:ER11)*#REF!+SUMPRODUCT(--(MOD(COLUMN(ES11:FP11),4)=MOD(COLUMN(ES11),4)),ES11:FP11)*#REF! -> #REF!
A12: АВТОКОМПОНЕНТ НАО | B12: Предоплата 50% | C12: ВБК Восток | D12: Прасолов, Соловьёв | E12: =IF(ISBLANK(G12),"",IF($A$6:$A$64=$A12,COUNTIF($A$6:A12,$A12),"")) -> 7 | F12: 1 | G12: S4240002000 | H12: Комплект удлинения | I12: =65.4/НДС_20 -> 54.5 | L12: =IF(K12="RUB",J12/ЮАНЬ,IF(K12="EUR",J12*ЕВРО/ЮАНЬ,"")) | N12: =IF(BP12>0,1,IF(BN12>0,2,)) -> 0 | U12: 0 | BL12: =SUMPRODUCT(--(MOD(COLUMN($O12:$AL12),4)=MOD(COLUMN($O12)+0,4)),$O12:$AL12) +SUMPRODUCT(--(MOD(COLUMN($AM12:$BJ12),4)=MOD(COLUMN($AM12)+0,4)),$AM12:$BJ12) -> 0 | BM12: =SUMPRODUCT(--(MOD(COLUMN($O12:$AL12),4)=MOD(COLUMN($O12)+0,4)),$O12:$AL12)*$I12 +SUMPRODUCT(--(MOD(COLUMN($AM12:$BJ12),4)=MOD(COLUMN($AM12)+0,4)),$AM12:$BJ12)*$I12 -> 0 | BN12: =SUMPRODUCT(--(MOD(COLUMN($O12:$AL12),4)=MOD(COLUMN($O12)+1,4)),$O12:$AL12) +SUMPRODUCT(--(MOD(COLUMN($AM12:$BJ12),4)=MOD(COLUMN($AM12)+1,4)),$AM12:$BJ12) -> 0 | BO12: =SUMPRODUCT(--(MOD(COLUMN($O12:$AL12),4)=MOD(COLUMN($O12)+1,4)),$O12:$AL12)*$I12 +SUMPRODUCT(--(MOD(COLUMN($AM12:$BJ12),4)=MOD(COLUMN($AM12)+1,4)),$AM12:$BJ12)*$I12 -> 0 | BP12: =SUMPRODUCT(--(MOD(COLUMN($O12:$AL12),4)=MOD(COLUMN($O12)+2,4)),$O12:$AL12) +SUMPRODUCT(--(MOD(COLUMN($AM12:$BJ12),4)=MOD(COLUMN($AM12)+2,4)),$AM12:$BJ12) -> 0 | BQ12: =SUMPRODUCT(--(MOD(COLUMN($O12:$AL12),4)=MOD(COLUMN($O12)+2,4)),$O12:$AL12)*$I12 +SUMPRODUCT(--(MOD(COLUMN($AM12:$BJ12),4)=MOD(COLUMN($AM12)+2,4)),$AM12:$BJ12)*$I12 -> 0 | DQ12: =SUMPRODUCT(--(MOD(COLUMN(BT12:CQ12),4)=MOD(COLUMN(BT12),4)),BT12:CQ12)+SUMPRODUCT(--(MOD(COLUMN(CR12:DO12),4)=MOD(COLUMN(CR12),4)),CR12:DO12) -> 0 | DR12: =SUMPRODUCT(--(MOD(COLUMN(BT12:CQ12),4)=MOD(COLUMN(BT12),4)),BT12:CQ12)*#REF!+SUMPRODUCT(--(MOD(COLUMN(CR12:DO12),4)=MOD(COLUMN(CR12),4)),CR12:DO12)*#REF! -> #REF! | FR12: =SUMPRODUCT(--(MOD(COLUMN(DU12:ER12),4)=MOD(COLUMN(DU12),4)),DU12:ER12)+SUMPRODUCT(--(MOD(COLUMN(ES12:FP12),4)=MOD(COLUMN(ES12),4)),ES12:FP12) -> 0 | FS12: =SUMPRODUCT(--(MOD(COLUMN(DU12:ER12),4)=MOD(COLUMN(DU12),4)),DU12:ER12)*#REF!+SUMPRODUCT(--(MOD(COLUMN(ES12:FP12),4)=MOD(COLUMN(ES12),4)),ES12:FP12)*#REF! -> #REF!
A13: АВТОКОМПОНЕНТ НАО | E13: =IF(ISBLANK(G13),"",IF($A$6:$A$64=$A13,COUNTIF($A$6:A13,$A13),"")) | H13: Итого | L13: =IF(K13="RUB",J13/ЮАНЬ,IF(K13="EUR",J13*ЕВРО/ЮАНЬ,"")) | N13: =IF(BP13>0,1,IF(BN13>0,2,)) -> 0 | BL13: =SUMPRODUCT(--(MOD(COLUMN($O13:$AL13),4)=MOD(COLUMN($O13)+0,4)),$O13:$AL13) +SUMPRODUCT(--(MOD(COLUMN($AM13:$BJ13),4)=MOD(COLUMN($AM13)+0,4)),$AM13:$BJ13) -> 0 | BM13: =SUMPRODUCT(--(MOD(COLUMN($O13:$AL13),4)=MOD(COLUMN($O13)+0,4)),$O13:$AL13)*$I13 +SUMPRODUCT(--(MOD(COLUMN($AM13:$BJ13),4)=MOD(COLUMN($AM13)+0,4)),$AM13:$BJ13)*$I13 -> 0 | BN13: =SUMPRODUCT(--(MOD(COLUMN($O13:$AL13),4)=MOD(COLUMN($O13)+1,4)),$O13:$AL13) +SUMPRODUCT(--(MOD(COLUMN($AM13:$BJ13),4)=MOD(COLUMN($AM13)+1,4)),$AM13:$BJ13) -> 0 | BO13: =SUMPRODUCT(--(MOD(COLUMN($O13:$AL13),4)=MOD(COLUMN($O13)+1,4)),$O13:$AL13)*$I13 +SUMPRODUCT(--(MOD(COLUMN($AM13:$BJ13),4)=MOD(COLUMN($AM13)+1,4)),$AM13:$BJ13)*$I13 -> 0 | BP13: =SUMPRODUCT(--(MOD(COLUMN($O13:$AL13),4)=MOD(COLUMN($O13)+2,4)),$O13:$AL13) +SUMPRODUCT(--(MOD(COLUMN($AM13:$BJ13),4)=MOD(COLUMN($AM13)+2,4)),$AM13:$BJ13) -> 0 | BQ13: =SUMPRODUCT(--(MOD(COLUMN($O13:$AL13),4)=MOD(COLUMN($O13)+2,4)),$O13:$AL13)*$I13 +SUMPRODUCT(--(MOD(COLUMN($AM13:$BJ13),4)=MOD(COLUMN($AM13)+2,4)),$AM13:$BJ13)*$I13 -> 0 | DQ13: =SUMPRODUCT(--(MOD(COLUMN(BT13:CQ13),4)=MOD(COLUMN(BT13),4)),BT13:CQ13)+SUMPRODUCT(--(MOD(COLUMN(CR13:DO13),4)=MOD(COLUMN(CR13),4)),CR13:DO13) -> 0 | DR13: =SUMPRODUCT(--(MOD(COLUMN(BT13:CQ13),4)=MOD(COLUMN(BT13),4)),BT13:CQ13)*#REF!+SUMPRODUCT(--(MOD(COLUMN(CR13:DO13),4)=MOD(COLUMN(CR13),4)),CR13:DO13)*#REF! -> #REF! | FR13: =SUMPRODUCT(--(MOD(COLUMN(DU13:ER13),4)=MOD(COLUMN(DU13),4)),DU13:ER13)+SUMPRODUCT(--(MOD(COLUMN(ES13:FP13),4)=MOD(COLUMN(ES13),4)),ES13:FP13) -> 0 | FS13: =SUMPRODUCT(--(MOD(COLUMN(DU13:ER13),4)=MOD(COLUMN(DU13),4)),DU13:ER13)*#REF!+SUMPRODUCT(--(MOD(COLUMN(ES13:FP13),4)=MOD(COLUMN(ES13),4)),ES13:FP13)*#REF! -> #REF!
A14: АВТОКОМПОНЕНТ НАО | E14: =IF(ISBLANK(G14),"",IF($A$6:$A$64=$A14,COUNTIF($A$6:A14,$A14),"")) | L14: =IF(K14="RUB",J14/ЮАНЬ,IF(K14="EUR",J14*ЕВРО/ЮАНЬ,"")) | N14: =IF(BP14>0,1,IF(BN14>0,2,)) -> 0 | BL14: =SUMPRODUCT(--(MOD(COLUMN($O14:$AL14),4)=MOD(COLUMN($O14)+0,4)),$O14:$AL14) +SUMPRODUCT(--(MOD(COLUMN($AM14:$BJ14),4)=MOD(COLUMN($AM14)+0,4)),$AM14:$BJ14) -> 0 | BM14: =SUMPRODUCT(--(MOD(COLUMN($O14:$AL14),4)=MOD(COLUMN($O14)+0,4)),$O14:$AL14)*$I14 +SUMPRODUCT(--(MOD(COLUMN($AM14:$BJ14),4)=MOD(COLUMN($AM14)+0,4)),$AM14:$BJ14)*$I14 -> 0 | BN14: =SUMPRODUCT(--(MOD(COLUMN($O14:$AL14),4)=MOD(COLUMN($O14)+1,4)),$O14:$AL14) +SUMPRODUCT(--(MOD(COLUMN($AM14:$BJ14),4)=MOD(COLUMN($AM14)+1,4)),$AM14:$BJ14) -> 0 | BO14: =SUMPRODUCT(--(MOD(COLUMN($O14:$AL14),4)=MOD(COLUMN($O14)+1,4)),$O14:$AL14)*$I14 +SUMPRODUCT(--(MOD(COLUMN($AM14:$BJ14),4)=MOD(COLUMN($AM14)+1,4)),$AM14:$BJ14)*$I14 -> 0 | BP14: =SUMPRODUCT(--(MOD(COLUMN($O14:$AL14),4)=MOD(COLUMN($O14)+2,4)),$O14:$AL14) +SUMPRODUCT(--(MOD(COLUMN($AM14:$BJ14),4)=MOD(COLUMN($AM14)+2,4)),$AM14:$BJ14) -> 0 | BQ14: =SUMPRODUCT(--(MOD(COLUMN($O14:$AL14),4)=MOD(COLUMN($O14)+2,4)),$O14:$AL14)*$I14 +SUMPRODUCT(--(MOD(COLUMN($AM14:$BJ14),4)=MOD(COLUMN($AM14)+2,4)),$AM14:$BJ14)*$I14 -> 0 | DQ14: =SUMPRODUCT(--(MOD(COLUMN(BT14:CQ14),4)=MOD(COLUMN(BT14),4)),BT14:CQ14)+SUMPRODUCT(--(MOD(COLUMN(CR14:DO14),4)=MOD(COLUMN(CR14),4)),CR14:DO14) -> 0 | DR14: =SUMPRODUCT(--(MOD(COLUMN(BT14:CQ14),4)=MOD(COLUMN(BT14),4)),BT14:CQ14)*#REF!+SUMPRODUCT(--(MOD(COLUMN(CR14:DO14),4)=MOD(COLUMN(CR14),4)),CR14:DO14)*#REF! -> #REF! | FR14: =SUMPRODUCT(--(MOD(COLUMN(DU14:ER14),4)=MOD(COLUMN(DU14),4)),DU14:ER14)+SUMPRODUCT(--(MOD(COLUMN(ES14:FP14),4)=MOD(COLUMN(ES14),4)),ES14:FP14) -> 0 | FS14: =SUMPRODUCT(--(MOD(COLUMN(DU14:ER14),4)=MOD(COLUMN(DU14),4)),DU14:ER14)*#REF!+SUMPRODUCT(--(MOD(COLUMN(ES14:FP14),4)=MOD(COLUMN(ES14),4)),ES14:FP14)*#REF! -> #REF!
A15: BPW (нет в системе) | B15: Договор не подписан | C15: ВБК Восток | D15: Прасолов, Соловьёв | E15: =IF(ISBLANK(G15),"",IF($A$6:$A$64=$A15,COUNTIF($A$6:A15,$A15),"")) -> 1 | F15: 1 | G15: 6402250560 | H15: 6402250560 AA Тормоз дисковый ( левый ) | I15: =2100/НДС_20 -> 1750 | L15: =IF(K15="RUB",J15/ЮАНЬ,IF(K15="EUR",J15*ЕВРО/ЮАНЬ,"")) | N15: =IF(BP15>0,1,IF(BN15>0,2,)) -> 0 | U15: 0 | BL15: =SUMPRODUCT(--(MOD(COLUMN($O15:$AL15),4)=MOD(COLUMN($O15)+0,4)),$O15:$AL15) +SUMPRODUCT(--(MOD(COLUMN($AM15:$BJ15),4)=MOD(COLUMN($AM15)+0,4)),$AM15:$BJ15) -> 0 | BM15: =SUMPRODUCT(--(MOD(COLUMN($O15:$AL15),4)=MOD(COLUMN($O15)+0,4)),$O15:$AL15)*$I15 +SUMPRODUCT(--(MOD(COLUMN($AM15:$BJ15),4)=MOD(COLUMN($AM15)+0,4)),$AM15:$BJ15)*$I15 -> 0 | BN15: =SUMPRODUCT(--(MOD(COLUMN($O15:$AL15),4)=MOD(COLUMN($O15)+1,4)),$O15:$AL15) +SUMPRODUCT(--(MOD(COLUMN($AM15:$BJ15),4)=MOD(COLUMN($AM15)+1,4)),$AM15:$BJ15) -> 0 | BO15: =SUMPRODUCT(--(MOD(COLUMN($O15:$AL15),4)=MOD(COLUMN($O15)+1,4)),$O15:$AL15)*$I15 +SUMPRODUCT(--(MOD(COLUMN($AM15:$BJ15),4)=MOD(COLUMN($AM15)+1,4)),$AM15:$BJ15)*$I15 -> 0 | BP15: =SUMPRODUCT(--(MOD(COLUMN($O15:$AL15),4)=MOD(COLUMN($O15)+2,4)),$O15:$AL15) +SUMPRODUCT(--(MOD(COLUMN($AM15:$BJ15),4)=MOD(COLUMN($AM15)+2,4)),$AM15:$BJ15) -> 0 | BQ15: =SUMPRODUCT(--(MOD(COLUMN($O15:$AL15),4)=MOD(COLUMN($O15)+2,4)),$O15:$AL15)*$I15 +SUMPRODUCT(--(MOD(COLUMN($AM15:$BJ15),4)=MOD(COLUMN($AM15)+2,4)),$AM15:$BJ15)*$I15 -> 0 | BT15: 207 | BX15: 207 | CB15: 207 | CF15: 207 | CJ15: 207 | CN15: 207 | CR15: 207 | CV15: 207 | CZ15: 207 | DD15: 207 | DH15: 207 | DL15: 207 | DQ15: =SUMPRODUCT(--(MOD(COLUMN(BT15:CQ15),4)=MOD(COLUMN(BT15),4)),BT15:CQ15)+SUMPRODUCT(--(MOD(COLUMN(CR15:DO15),4)=MOD(COLUMN(CR15),4)),CR15:DO15) -> 2484 | DR15: =SUMPRODUCT(--(MOD(COLUMN(BT15:CQ15),4)=MOD(COLUMN(BT15),4)),BT15:CQ15)*#REF!+SUMPRODUCT(--(MOD(COLUMN(CR15:DO15),4)=MOD(COLUMN(CR15),4)),CR15:DO15)*#REF! -> #REF! | DU15: 414 | DY15: 414 | EC15: 414 | EG15: 414 | EK15: 414 | EO15: 414 | ES15: 414 | EW15: 414 | FA15: 414 | FE15: 414 | FI15: 414 | FM15: 414 | FR15: =SUMPRODUCT(--(MOD(COLUMN(DU15:ER15),4)=MOD(COLUMN(DU15),4)),DU15:ER15)+SUMPRODUCT(--(MOD(COLUMN(ES15:FP15),4)=MOD(COLUMN(ES15),4)),ES15:FP15) -> 4968 | FS15: =SUMPRODUCT(--(MOD(COLUMN(DU15:ER15),4)=MOD(COLUMN(DU15),4)),DU15:ER15)*#REF!+SUMPRODUCT(--(MOD(COLUMN(ES15:FP15),4)=MOD(COLUMN(ES15),4)),ES15:FP15)*#REF! -> #REF!
A16: BPW (нет в системе) | B16: Договор не подписан | C16: ВБК Восток | D16: Прасолов, Соловьёв | E16: =IF(ISBLANK(G16),"",IF($A$6:$A$64=$A16,COUNTIF($A$6:A16,$A16),"")) -> 2 | F16: 1 | G16: 6402250570 | H16: 6402250570 AA Тормоз дисковый ( правый ) | I16: =I15 -> 1750 | L16: =IF(K16="RUB",J16/ЮАНЬ,IF(K16="EUR",J16*ЕВРО/ЮАНЬ,"")) | N16: =IF(BP16>0,1,IF(BN16>0,2,)) -> 0 | U16: 0 | BL16: =SUMPRODUCT(--(MOD(COLUMN($O16:$AL16),4)=MOD(COLUMN($O16)+0,4)),$O16:$AL16) +SUMPRODUCT(--(MOD(COLUMN($AM16:$BJ16),4)=MOD(COLUMN($AM16)+0,4)),$AM16:$BJ16) -> 0 | BM16: =SUMPRODUCT(--(MOD(COLUMN($O16:$AL16),4)=MOD(COLUMN($O16)+0,4)),$O16:$AL16)*$I16 +SUMPRODUCT(--(MOD(COLUMN($AM16:$BJ16),4)=MOD(COLUMN($AM16)+0,4)),$AM16:$BJ16)*$I16 -> 0 | BN16: =SUMPRODUCT(--(MOD(COLUMN($O16:$AL16),4)=MOD(COLUMN($O16)+1,4)),$O16:$AL16) +SUMPRODUCT(--(MOD(COLUMN($AM16:$BJ16),4)=MOD(COLUMN($AM16)+1,4)),$AM16:$BJ16) -> 0 | BO16: =SUMPRODUCT(--(MOD(COLUMN($O16:$AL16),4)=MOD(COLUMN($O16)+1,4)),$O16:$AL16)*$I16 +SUMPRODUCT(--(MOD(COLUMN($AM16:$BJ16),4)=MOD(COLUMN($AM16)+1,4)),$AM16:$BJ16)*$I16 -> 0 | BP16: =SUMPRODUCT(--(MOD(COLUMN($O16:$AL16),4)=MOD(COLUMN($O16)+2,4)),$O16:$AL16) +SUMPRODUCT(--(MOD(COLUMN($AM16:$BJ16),4)=MOD(COLUMN($AM16)+2,4)),$AM16:$BJ16) -> 0 | BQ16: =SUMPRODUCT(--(MOD(COLUMN($O16:$AL16),4)=MOD(COLUMN($O16)+2,4)),$O16:$AL16)*$I16 +SUMPRODUCT(--(MOD(COLUMN($AM16:$BJ16),4)=MOD(COLUMN($AM16)+2,4)),$AM16:$BJ16)*$I16 -> 0 | BT16: 207 | BX16: 207 | CB16: 207 | CF16: 207 | CJ16: 207 | CN16: 207 | CR16: 207 | CV16: 207 | CZ16: 207 | DD16: 207 | DH16: 207 | DL16: 207 | DQ16: =SUMPRODUCT(--(MOD(COLUMN(BT16:CQ16),4)=MOD(COLUMN(BT16),4)),BT16:CQ16)+SUMPRODUCT(--(MOD(COLUMN(CR16:DO16),4)=MOD(COLUMN(CR16),4)),CR16:DO16) -> 2484 | DR16: =SUMPRODUCT(--(MOD(COLUMN(BT16:CQ16),4)=MOD(COLUMN(BT16),4)),BT16:CQ16)*#REF!+SUMPRODUCT(--(MOD(COLUMN(CR16:DO16),4)=MOD(COLUMN(CR16),4)),CR16:DO16)*#REF! -> #REF! | DU16: 414 | DY16: 414 | EC16: 414 | EG16: 414 | EK16: 414 | EO16: 414 | ES16: 414 | EW16: 414 | FA16: 414 | FE16: 414 | FI16: 414 | FM16: 414 | FR16: =SUMPRODUCT(--(MOD(COLUMN(DU16:ER16),4)=MOD(COLUMN(DU16),4)),DU16:ER16)+SUMPRODUCT(--(MOD(COLUMN(ES16:FP16),4)=MOD(COLUMN(ES16),4)),ES16:FP16) -> 4968 | FS16: =SUMPRODUCT(--(MOD(COLUMN(DU16:ER16),4)=MOD(COLUMN(DU16),4)),DU16:ER16)*#REF!+SUMPRODUCT(--(MOD(COLUMN(ES16:FP16),4)=MOD(COLUMN(ES16),4)),ES16:FP16)*#REF! -> #REF!
A17: BPW (нет в системе) | B17: Договор не подписан | C17: ВБК Восток | D17: Прасолов, Соловьёв | E17: =IF(ISBLANK(G17),"",IF($A$6:$A$64=$A17,COUNTIF($A$6:A17,$A17),"")) -> 3 | F17: 1 | G17: 4410328080 | H17: Датчик АБС, 0,4 м | I17: =84/НДС_20 -> 70 | L17: =IF(K17="RUB",J17/ЮАНЬ,IF(K17="EUR",J17*ЕВРО/ЮАНЬ,"")) | N17: =IF(BP17>0,1,IF(BN17>0,2,)) -> 0 | U17: 0 | BL17: =SUMPRODUCT(--(MOD(COLUMN($O17:$AL17),4)=MOD(COLUMN($O17)+0,4)),$O17:$AL17) +SUMPRODUCT(--(MOD(COLUMN($AM17:$BJ17),4)=MOD(COLUMN($AM17)+0,4)),$AM17:$BJ17) -> 0 | BM17: =SUMPRODUCT(--(MOD(COLUMN($O17:$AL17),4)=MOD(COLUMN($O17)+0,4)),$O17:$AL17)*$I17 +SUMPRODUCT(--(MOD(COLUMN($AM17:$BJ17),4)=MOD(COLUMN($AM17)+0,4)),$AM17:$BJ17)*$I17 -> 0 | BN17: =SUMPRODUCT(--(MOD(COLUMN($O17:$AL17),4)=MOD(COLUMN($O17)+1,4)),$O17:$AL17) +SUMPRODUCT(--(MOD(COLUMN($AM17:$BJ17),4)=MOD(COLUMN($AM17)+1,4)),$AM17:$BJ17) -> 0 | BO17: =SUMPRODUCT(--(MOD(COLUMN($O17:$AL17),4)=MOD(COLUMN($O17)+1,4)),$O17:$AL17)*$I17 +SUMPRODUCT(--(MOD(COLUMN($AM17:$BJ17),4)=MOD(COLUMN($AM17)+1,4)),$AM17:$BJ17)*$I17 -> 0 | BP17: =SUMPRODUCT(--(MOD(COLUMN($O17:$AL17),4)=MOD(COLUMN($O17)+2,4)),$O17:$AL17) +SUMPRODUCT(--(MOD(COLUMN($AM17:$BJ17),4)=MOD(COLUMN($AM17)+2,4)),$AM17:$BJ17) -> 0 | BQ17: =SUMPRODUCT(--(MOD(COLUMN($O17:$AL17),4)=MOD(COLUMN($O17)+2,4)),$O17:$AL17)*$I17 +SUMPRODUCT(--(MOD(COLUMN($AM17:$BJ17),4)=MOD(COLUMN($AM17)+2,4)),$AM17:$BJ17)*$I17 -> 0 | BT17: 138 | BX17: 138 | CB17: 138 | CF17: 138 | CJ17: 138 | CN17: 138 | CR17: 138 | CV17: 138 | CZ17: 138 | DD17: 138 | DH17: 138 | DL17: 138 | DQ17: =SUMPRODUCT(--(MOD(COLUMN(BT17:CQ17),4)=MOD(COLUMN(BT17),4)),BT17:CQ17)+SUMPRODUCT(--(MOD(COLUMN(CR17:DO17),4)=MOD(COLUMN(CR17),4)),CR17:DO17) -> 1656 | DR17: =SUMPRODUCT(--(MOD(COLUMN(BT17:CQ17),4)=MOD(COLUMN(BT17),4)),BT17:CQ17)*#REF!+SUMPRODUCT(--(MOD(COLUMN(CR17:DO17),4)=MOD(COLUMN(CR17),4)),CR17:DO17)*#REF! -> #REF! | DU17: 276 | DY17: 276 | EC17: 276 | EG17: 276 | EK17: 276 | EO17: 276 | ES17: 276 | EW17: 276 | FA17: 276 | FE17: 276 | FI17: 276 | FM17: 276 | FR17: =SUMPRODUCT(--(MOD(COLUMN(DU17:ER17),4)=MOD(COLUMN(DU17),4)),DU17:ER17)+SUMPRODUCT(--(MOD(COLUMN(ES17:FP17),4)=MOD(COLUMN(ES17),4)),ES17:FP17) -> 3312 | FS17: =SUMPRODUCT(--(MOD(COLUMN(DU17:ER17),4)=MOD(COLUMN(DU17),4)),DU17:ER17)*#REF!+SUMPRODUCT(--(MOD(COLUMN(ES17:FP17),4)=MOD(COLUMN(ES17),4)),ES17:FP17)*#REF! -> #REF!
A18: BPW (нет в системе) | B18: Договор не подписан | C18: ВБК Восток | D18: Прасолов, Соловьёв | E18: =IF(ISBLANK(G18),"",IF($A$6:$A$64=$A18,COUNTIF($A$6:A18,$A18),"")) -> 4 | F18: 1 | G18: 8997598154 | H18: Втулка датчика АБС | I18: =8.4/НДС_20 -> 7 | L18: =IF(K18="RUB",J18/ЮАНЬ,IF(K18="EUR",J18*ЕВРО/ЮАНЬ,"")) | N18: =IF(BP18>0,1,IF(BN18>0,2,)) -> 0 | U18: 0 | BL18: =SUMPRODUCT(--(MOD(COLUMN($O18:$AL18),4)=MOD(COLUMN($O18)+0,4)),$O18:$AL18) +SUMPRODUCT(--(MOD(COLUMN($AM18:$BJ18),4)=MOD(COLUMN($AM18)+0,4)),$AM18:$BJ18) -> 0 | BM18: =SUMPRODUCT(--(MOD(COLUMN($O18:$AL18),4)=MOD(COLUMN($O18)+0,4)),$O18:$AL18)*$I18 +SUMPRODUCT(--(MOD(COLUMN($AM18:$BJ18),4)=MOD(COLUMN($AM18)+0,4)),$AM18:$BJ18)*$I18 -> 0 | BN18: =SUMPRODUCT(--(MOD(COLUMN($O18:$AL18),4)=MOD(COLUMN($O18)+1,4)),$O18:$AL18) +SUMPRODUCT(--(MOD(COLUMN($AM18:$BJ18),4)=MOD(COLUMN($AM18)+1,4)),$AM18:$BJ18) -> 0 | BO18: =SUMPRODUCT(--(MOD(COLUMN($O18:$AL18),4)=MOD(COLUMN($O18)+1,4)),$O18:$AL18)*$I18 +SUMPRODUCT(--(MOD(COLUMN($AM18:$BJ18),4)=MOD(COLUMN($AM18)+1,4)),$AM18:$BJ18)*$I18 -> 0 | BP18: =SUMPRODUCT(--(MOD(COLUMN($O18:$AL18),4)=MOD(COLUMN($O18)+2,4)),$O18:$AL18) +SUMPRODUCT(--(MOD(COLUMN($AM18:$BJ18),4)=MOD(COLUMN($AM18)+2,4)),$AM18:$BJ18) -> 0 | BQ18: =SUMPRODUCT(--(MOD(COLUMN($O18:$AL18),4)=MOD(COLUMN($O18)+2,4)),$O18:$AL18)*$I18 +SUMPRODUCT(--(MOD(COLUMN($AM18:$BJ18),4)=MOD(COLUMN($AM18)+2,4)),$AM18:$BJ18)*$I18 -> 0 | BT18: 138 | BX18: 138 | CB18: 138 | CF18: 138 | CJ18: 138 | CN18: 138 | CR18: 138 | CV18: 138 | CZ18: 138 | DD18: 138 | DH18: 138 | DL18: 138 | DQ18: =SUMPRODUCT(--(MOD(COLUMN(BT18:CQ18),4)=MOD(COLUMN(BT18),4)),BT18:CQ18)+SUMPRODUCT(--(MOD(COLUMN(CR18:DO18),4)=MOD(COLUMN(CR18),4)),CR18:DO18) -> 1656 | DR18: =SUMPRODUCT(--(MOD(COLUMN(BT18:CQ18),4)=MOD(COLUMN(BT18),4)),BT18:CQ18)*#REF!+SUMPRODUCT(--(MOD(COLUMN(CR18:DO18),4)=MOD(COLUMN(CR18),4)),CR18:DO18)*#REF! -> #REF! | DU18: 276 | DY18: 276 | EC18: 276 | EG18: 276 | EK18: 276 | EO18: 276 | ES18: 276 | EW18: 276 | FA18: 276 | FE18: 276 | FI18: 276 | FM18: 276 | FR18: =SUMPRODUCT(--(MOD(COLUMN(DU18:ER18),4)=MOD(COLUMN(DU18),4)),DU18:ER18)+SUMPRODUCT(--(MOD(COLUMN(ES18:FP18),4)=MOD(COLUMN(ES18),4)),ES18:FP18) -> 3312 | FS18: =SUMPRODUCT(--(MOD(COLUMN(DU18:ER18),4)=MOD(COLUMN(DU18),4)),DU18:ER18)*#REF!+SUMPRODUCT(--(MOD(COLUMN(ES18:FP18),4)=MOD(COLUMN(ES18),4)),ES18:FP18)*#REF! -> #REF!
A19: BPW (нет в системе) | B19: Договор не подписан | C19: ВБК Восток | D19: Прасолов, Соловьёв | E19: =IF(ISBLANK(G19),"",IF($A$6:$A$64=$A19,COUNTIF($A$6:A19,$A19),"")) -> 5 | F19: 1 | G19: 4235041001 | H19: Тормозная камера, тип 20 | I19: =163.08/НДС_20 -> 135.9 | L19: =IF(K19="RUB",J19/ЮАНЬ,IF(K19="EUR",J19*ЕВРО/ЮАНЬ,"")) | N19: =IF(BP19>0,1,IF(BN19>0,2,)) -> 0 | U19: 0 | BL19: =SUMPRODUCT(--(MOD(COLUMN($O19:$AL19),4)=MOD(COLUMN($O19)+0,4)),$O19:$AL19) +SUMPRODUCT(--(MOD(COLUMN($AM19:$BJ19),4)=MOD(COLUMN($AM19)+0,4)),$AM19:$BJ19) -> 0 | BM19: =SUMPRODUCT(--(MOD(COLUMN($O19:$AL19),4)=MOD(COLUMN($O19)+0,4)),$O19:$AL19)*$I19 +SUMPRODUCT(--(MOD(COLUMN($AM19:$BJ19),4)=MOD(COLUMN($AM19)+0,4)),$AM19:$BJ19)*$I19 -> 0 | BN19: =SUMPRODUCT(--(MOD(COLUMN($O19:$AL19),4)=MOD(COLUMN($O19)+1,4)),$O19:$AL19) +SUMPRODUCT(--(MOD(COLUMN($AM19:$BJ19),4)=MOD(COLUMN($AM19)+1,4)),$AM19:$BJ19) -> 0 | BO19: =SUMPRODUCT(--(MOD(COLUMN($O19:$AL19),4)=MOD(COLUMN($O19)+1,4)),$O19:$AL19)*$I19 +SUMPRODUCT(--(MOD(COLUMN($AM19:$BJ19),4)=MOD(COLUMN($AM19)+1,4)),$AM19:$BJ19)*$I19 -> 0 | BP19: =SUMPRODUCT(--(MOD(COLUMN($O19:$AL19),4)=MOD(COLUMN($O19)+2,4)),$O19:$AL19) +SUMPRODUCT(--(MOD(COLUMN($AM19:$BJ19),4)=MOD(COLUMN($AM19)+2,4)),$AM19:$BJ19) -> 0 | BQ19: =SUMPRODUCT(--(MOD(COLUMN($O19:$AL19),4)=MOD(COLUMN($O19)+2,4)),$O19:$AL19)*$I19 +SUMPRODUCT(--(MOD(COLUMN($AM19:$BJ19),4)=MOD(COLUMN($AM19)+2,4)),$AM19:$BJ19)*$I19 -> 0 | BT19: 138 | BX19: 138 | CB19: 138 | CF19: 138 | CJ19: 138 | CN19: 138 | CR19: 138 | CV19: 138 | CZ19: 138 | DD19: 138 | DH19: 138 | DL19: 138 | DQ19: =SUMPRODUCT(--(MOD(COLUMN(BT19:CQ19),4)=MOD(COLUMN(BT19),4)),BT19:CQ19)+SUMPRODUCT(--(MOD(COLUMN(CR19:DO19),4)=MOD(COLUMN(CR19),4)),CR19:DO19) -> 1656 | DR19: =SUMPRODUCT(--(MOD(COLUMN(BT19:CQ19),4)=MOD(COLUMN(BT19),4)),BT19:CQ19)*#REF!+SUMPRODUCT(--(MOD(COLUMN(CR19:DO19),4)=MOD(COLUMN(CR19),4)),CR19:DO19)*#REF! -> #REF! | DU19: 276 | DY19: 276 | EC19: 276 | EG19: 276 | EK19: 276 | EO19: 276 | ES19: 276 | EW19: 276 | FA19: 276 | FE19: 276 | FI19: 276 | FM19: 276 | FR19: =SUMPRODUCT(--(MOD(COLUMN(DU19:ER19),4)=MOD(COLUMN(DU19),4)),DU19:ER19)+SUMPRODUCT(--(MOD(COLUMN(ES19:FP19),4)=MOD(COLUMN(ES19),4)),ES19:FP19) -> 3312 | FS19: =SUMPRODUCT(--(MOD(COLUMN(DU19:ER19),4)=MOD(COLUMN(DU19),4)),DU19:ER19)*#REF!+SUMPRODUCT(--(MOD(COLUMN(ES19:FP19),4)=MOD(COLUMN(ES19),4)),ES19:FP19)*#REF! -> #REF!
A20: BPW (нет в системе) | B20: Договор не подписан | C20: ВБК Восток | D20: Прасолов, Соловьёв | E20: =IF(ISBLANK(G20),"",IF($A$6:$A$64=$A20,COUNTIF($A$6:A20,$A20),"")) -> 6 | F20: 1 | G20: 9254800504 | H20: Энергоаккумулятор, тип 20/24 | I20: =373.98/НДС_20 -> 311.65 | L20: =IF(K20="RUB",J20/ЮАНЬ,IF(K20="EUR",J20*ЕВРО/ЮАНЬ,"")) | N20: =IF(BP20>0,1,IF(BN20>0,2,)) -> 0 | U20: 0 | BL20: =SUMPRODUCT(--(MOD(COLUMN($O20:$AL20),4)=MOD(COLUMN($O20)+0,4)),$O20:$AL20) +SUMPRODUCT(--(MOD(COLUMN($AM20:$BJ20),4)=MOD(COLUMN($AM20)+0,4)),$AM20:$BJ20) -> 0 | BM20: =SUMPRODUCT(--(MOD(COLUMN($O20:$AL20),4)=MOD(COLUMN($O20)+0,4)),$O20:$AL20)*$I20 +SUMPRODUCT(--(MOD(COLUMN($AM20:$BJ20),4)=MOD(COLUMN($AM20)+0,4)),$AM20:$BJ20)*$I20 -> 0 | BN20: =SUMPRODUCT(--(MOD(COLUMN($O20:$AL20),4)=MOD(COLUMN($O20)+1,4)),$O20:$AL20) +SUMPRODUCT(--(MOD(COLUMN($AM20:$BJ20),4)=MOD(COLUMN($AM20)+1,4)),$AM20:$BJ20) -> 0 | BO20: =SUMPRODUCT(--(MOD(COLUMN($O20:$AL20),4)=MOD(COLUMN($O20)+1,4)),$O20:$AL20)*$I20 +SUMPRODUCT(--(MOD(COLUMN($AM20:$BJ20),4)=MOD(COLUMN($AM20)+1,4)),$AM20:$BJ20)*$I20 -> 0 | BP20: =SUMPRODUCT(--(MOD(COLUMN($O20:$AL20),4)=MOD(COLUMN($O20)+2,4)),$O20:$AL20) +SUMPRODUCT(--(MOD(COLUMN($AM20:$BJ20),4)=MOD(COLUMN($AM20)+2,4)),$AM20:$BJ20) -> 0 | BQ20: =SUMPRODUCT(--(MOD(COLUMN($O20:$AL20),4)=MOD(COLUMN($O20)+2,4)),$O20:$AL20)*$I20 +SUMPRODUCT(--(MOD(COLUMN($AM20:$BJ20),4)=MOD(COLUMN($AM20)+2,4)),$AM20:$BJ20)*$I20 -> 0 | BT20: 276 | BX20: 276 | CB20: 276 | CF20: 276 | CJ20: 276 | CN20: 276 | CR20: 276 | CV20: 276 | CZ20: 276 | DD20: 276 | DH20: 276 | DL20: 276 | DQ20: =SUMPRODUCT(--(MOD(COLUMN(BT20:CQ20),4)=MOD(COLUMN(BT20),4)),BT20:CQ20)+SUMPRODUCT(--(MOD(COLUMN(CR20:DO20),4)=MOD(COLUMN(CR20),4)),CR20:DO20) -> 3312 | DR20: =SUMPRODUCT(--(MOD(COLUMN(BT20:CQ20),4)=MOD(COLUMN(BT20),4)),BT20:CQ20)*#REF!+SUMPRODUCT(--(MOD(COLUMN(CR20:DO20),4)=MOD(COLUMN(CR20),4)),CR20:DO20)*#REF! -> #REF! | DU20: 552 | DY20: 552 | EC20: 552 | EG20: 552 | EK20: 552 | EO20: 552 | ES20: 552 | EW20: 552 | FA20: 552 | FE20: 552 | FI20: 552 | FM20: 552 | FR20: =SUMPRODUCT(--(MOD(COLUMN(DU20:ER20),4)=MOD(COLUMN(DU20),4)),DU20:ER20)+SUMPRODUCT(--(MOD(COLUMN(ES20:FP20),4)=MOD(COLUMN(ES20),4)),ES20:FP20) -> 6624 | FS20: =SUMPRODUCT(--(MOD(COLUMN(DU20:ER20),4)=MOD(COLUMN(DU20),4)),DU20:ER20)*#REF!+SUMPRODUCT(--(MOD(COLUMN(ES20:FP20),4)=MOD(COLUMN(ES20),4)),ES20:FP20)*#REF! -> #REF!
A21: BPW (нет в системе) | E21: =IF(ISBLANK(G21),"",IF($A$6:$A$64=$A21,COUNTIF($A$6:A21,$A21),"")) | H21: Итого | L21: =IF(K21="RUB",J21/ЮАНЬ,IF(K21="EUR",J21*ЕВРО/ЮАНЬ,"")) | N21: =IF(BP21>0,1,IF(BN21>0,2,)) -> 0 | BL21: =SUMPRODUCT(--(MOD(COLUMN($O21:$AL21),4)=MOD(COLUMN($O21)+0,4)),$O21:$AL21) +SUMPRODUCT(--(MOD(COLUMN($AM21:$BJ21),4)=MOD(COLUMN($AM21)+0,4)),$AM21:$BJ21) -> 0 | BM21: =SUMPRODUCT(--(MOD(COLUMN($O21:$AL21),4)=MOD(COLUMN($O21)+0,4)),$O21:$AL21)*$I21 +SUMPRODUCT(--(MOD(COLUMN($AM21:$BJ21),4)=MOD(COLUMN($AM21)+0,4)),$AM21:$BJ21)*$I21 -> 0 | BN21: =SUMPRODUCT(--(MOD(COLUMN($O21:$AL21),4)=MOD(COLUMN($O21)+1,4)),$O21:$AL21) +SUMPRODUCT(--(MOD(COLUMN($AM21:$BJ21),4)=MOD(COLUMN($AM21)+1,4)),$AM21:$BJ21) -> 0 | BO21: =SUMPRODUCT(--(MOD(COLUMN($O21:$AL21),4)=MOD(COLUMN($O21)+1,4)),$O21:$AL21)*$I21 +SUMPRODUCT(--(MOD(COLUMN($AM21:$BJ21),4)=MOD(COLUMN($AM21)+1,4)),$AM21:$BJ21)*$I21 -> 0 | BP21: =SUMPRODUCT(--(MOD(COLUMN($O21:$AL21),4)=MOD(COLUMN($O21)+2,4)),$O21:$AL21) +SUMPRODUCT(--(MOD(COLUMN($AM21:$BJ21),4)=MOD(COLUMN($AM21)+2,4)),$AM21:$BJ21) -> 0 | BQ21: =SUMPRODUCT(--(MOD(COLUMN($O21:$AL21),4)=MOD(COLUMN($O21)+2,4)),$O21:$AL21)*$I21 +SUMPRODUCT(--(MOD(COLUMN($AM21:$BJ21),4)=MOD(COLUMN($AM21)+2,4)),$AM21:$BJ21)*$I21 -> 0 | DQ21: =SUMPRODUCT(--(MOD(COLUMN(BT21:CQ21),4)=MOD(COLUMN(BT21),4)),BT21:CQ21)+SUMPRODUCT(--(MOD(COLUMN(CR21:DO21),4)=MOD(COLUMN(CR21),4)),CR21:DO21) -> 0 | DR21: =SUMPRODUCT(--(MOD(COLUMN(BT21:CQ21),4)=MOD(COLUMN(BT21),4)),BT21:CQ21)*#REF!+SUMPRODUCT(--(MOD(COLUMN(CR21:DO21),4)=MOD(COLUMN(CR21),4)),CR21:DO21)*#REF! -> #REF! | FR21: =SUMPRODUCT(--(MOD(COLUMN(DU21:ER21),4)=MOD(COLUMN(DU21),4)),DU21:ER21)+SUMPRODUCT(--(MOD(COLUMN(ES21:FP21),4)=MOD(COLUMN(ES21),4)),ES21:FP21) -> 0 | FS21: =SUMPRODUCT(--(MOD(COLUMN(DU21:ER21),4)=MOD(COLUMN(DU21),4)),DU21:ER21)*#REF!+SUMPRODUCT(--(MOD(COLUMN(ES21:FP21),4)=MOD(COLUMN(ES21),4)),ES21:FP21)*#REF! -> #REF!
A22: BPW (нет в системе) | E22: =IF(ISBLANK(G22),"",IF($A$6:$A$64=$A22,COUNTIF($A$6:A22,$A22),"")) | L22: =IF(K22="RUB",J22/ЮАНЬ,IF(K22="EUR",J22*ЕВРО/ЮАНЬ,"")) | N22: =IF(BP22>0,1,IF(BN22>0,2,)) -> 0 | BL22: =SUMPRODUCT(--(MOD(COLUMN($O22:$AL22),4)=MOD(COLUMN($O22)+0,4)),$O22:$AL22) +SUMPRODUCT(--(MOD(COLUMN($AM22:$BJ22),4)=MOD(COLUMN($AM22)+0,4)),$AM22:$BJ22) -> 0 | BM22: =SUMPRODUCT(--(MOD(COLUMN($O22:$AL22),4)=MOD(COLUMN($O22)+0,4)),$O22:$AL22)*$I22 +SUMPRODUCT(--(MOD(COLUMN($AM22:$BJ22),4)=MOD(COLUMN($AM22)+0,4)),$AM22:$BJ22)*$I22 -> 0 | BN22: =SUMPRODUCT(--(MOD(COLUMN($O22:$AL22),4)=MOD(COLUMN($O22)+1,4)),$O22:$AL22) +SUMPRODUCT(--(MOD(COLUMN($AM22:$BJ22),4)=MOD(COLUMN($AM22)+1,4)),$AM22:$BJ22) -> 0 | BO22: =SUMPRODUCT(--(MOD(COLUMN($O22:$AL22),4)=MOD(COLUMN($O22)+1,4)),$O22:$AL22)*$I22 +SUMPRODUCT(--(MOD(COLUMN($AM22:$BJ22),4)=MOD(COLUMN($AM22)+1,4)),$AM22:$BJ22)*$I22 -> 0 | BP22: =SUMPRODUCT(--(MOD(COLUMN($O22:$AL22),4)=MOD(COLUMN($O22)+2,4)),$O22:$AL22) +SUMPRODUCT(--(MOD(COLUMN($AM22:$BJ22),4)=MOD(COLUMN($AM22)+2,4)),$AM22:$BJ22) -> 0 | BQ22: =SUMPRODUCT(--(MOD(COLUMN($O22:$AL22),4)=MOD(COLUMN($O22)+2,4)),$O22:$AL22)*$I22 +SUMPRODUCT(--(MOD(COLUMN($AM22:$BJ22),4)=MOD(COLUMN($AM22)+2,4)),$AM22:$BJ22)*$I22 -> 0 | DQ22: =SUMPRODUCT(--(MOD(COLUMN(BT22:CQ22),4)=MOD(COLUMN(BT22),4)),BT22:CQ22)+SUMPRODUCT(--(MOD(COLUMN(CR22:DO22),4)=MOD(COLUMN(CR22),4)),CR22:DO22) -> 0 | DR22: =SUMPRODUCT(--(MOD(COLUMN(BT22:CQ22),4)=MOD(COLUMN(BT22),4)),BT22:CQ22)*#REF!+SUMPRODUCT(--(MOD(COLUMN(CR22:DO22),4)=MOD(COLUMN(CR22),4)),CR22:DO22)*#REF! -> #REF! | FR22: =SUMPRODUCT(--(MOD(COLUMN(DU22:ER22),4)=MOD(COLUMN(DU22),4)),DU22:ER22)+SUMPRODUCT(--(MOD(COLUMN(ES22:FP22),4)=MOD(COLUMN(ES22),4)),ES22:FP22) -> 0 | FS22: =SUMPRODUCT(--(MOD(COLUMN(DU22:ER22),4)=MOD(COLUMN(DU22),4)),DU22:ER22)*#REF!+SUMPRODUCT(--(MOD(COLUMN(ES22:FP22),4)=MOD(COLUMN(ES22),4)),ES22:FP22)*#REF! -> #REF!
A23: HJBridge (нет в системе) | B23: Договор не подписан | C23: ВБК Восток | D23: Прасолов, Соловьёв | E23: =IF(ISBLANK(G23),"",IF($A$6:$A$64=$A23,COUNTIF($A$6:A23,$A23),"")) -> 1 | F23: 1 | G23: 6402250340 | H23: Дисковый тормозной механизм (левый) | I23: =2160/НДС_20 -> 1800 | L23: =IF(K23="RUB",J23/ЮАНЬ,IF(K23="EUR",J23*ЕВРО/ЮАНЬ,"")) | N23: =IF(BP23>0,1,IF(BN23>0,2,)) -> 0 | U23: 0 | BL23: =SUMPRODUCT(--(MOD(COLUMN($O23:$AL23),4)=MOD(COLUMN($O23)+0,4)),$O23:$AL23) +SUMPRODUCT(--(MOD(COLUMN($AM23:$BJ23),4)=MOD(COLUMN($AM23)+0,4)),$AM23:$BJ23) -> 0 | BM23: =SUMPRODUCT(--(MOD(COLUMN($O23:$AL23),4)=MOD(COLUMN($O23)+0,4)),$O23:$AL23)*$I23 +SUMPRODUCT(--(MOD(COLUMN($AM23:$BJ23),4)=MOD(COLUMN($AM23)+0,4)),$AM23:$BJ23)*$I23 -> 0 | BN23: =SUMPRODUCT(--(MOD(COLUMN($O23:$AL23),4)=MOD(COLUMN($O23)+1,4)),$O23:$AL23) +SUMPRODUCT(--(MOD(COLUMN($AM23:$BJ23),4)=MOD(COLUMN($AM23)+1,4)),$AM23:$BJ23) -> 0 | BO23: =SUMPRODUCT(--(MOD(COLUMN($O23:$AL23),4)=MOD(COLUMN($O23)+1,4)),$O23:$AL23)*$I23 +SUMPRODUCT(--(MOD(COLUMN($AM23:$BJ23),4)=MOD(COLUMN($AM23)+1,4)),$AM23:$BJ23)*$I23 -> 0 | BP23: =SUMPRODUCT(--(MOD(COLUMN($O23:$AL23),4)=MOD(COLUMN($O23)+2,4)),$O23:$AL23) +SUMPRODUCT(--(MOD(COLUMN($AM23:$BJ23),4)=MOD(COLUMN($AM23)+2,4)),$AM23:$BJ23) -> 0 | BQ23: =SUMPRODUCT(--(MOD(COLUMN($O23:$AL23),4)=MOD(COLUMN($O23)+2,4)),$O23:$AL23)*$I23 +SUMPRODUCT(--(MOD(COLUMN($AM23:$BJ23),4)=MOD(COLUMN($AM23)+2,4)),$AM23:$BJ23)*$I23 -> 0 | BT23: 621 | BX23: 621 | CB23: 621 | CF23: 621 | CJ23: 621 | CN23: 621 | CR23: 621 | CV23: 621 | CZ23: 621 | DD23: 621 | DH23: 621 | DL23: 621 | DQ23: =SUMPRODUCT(--(MOD(COLUMN(BT23:CQ23),4)=MOD(COLUMN(BT23),4)),BT23:CQ23)+SUMPRODUCT(--(MOD(COLUMN(CR23:DO23),4)=MOD(COLUMN(CR23),4)),CR23:DO23) -> 7452 | DR23: =SUMPRODUCT(--(MOD(COLUMN(BT23:CQ23),4)=MOD(COLUMN(BT23),4)),BT23:CQ23)*#REF!+SUMPRODUCT(--(MOD(COLUMN(CR23:DO23),4)=MOD(COLUMN(CR23),4)),CR23:DO23)*#REF! -> #REF! | DU23: 828 | DY23: 828 | EC23: 828 | EG23: 828 | EK23: 828 | EO23: 828 | ES23: 828 | EW23: 828 | FA23: 828 | FE23: 828 | FI23: 828 | FM23: 828 | FR23: =SUMPRODUCT(--(MOD(COLUMN(DU23:ER23),4)=MOD(COLUMN(DU23),4)),DU23:ER23)+SUMPRODUCT(--(MOD(COLUMN(ES23:FP23),4)=MOD(COLUMN(ES23),4)),ES23:FP23) -> 9936 | FS23: =SUMPRODUCT(--(MOD(COLUMN(DU23:ER23),4)=MOD(COLUMN(DU23),4)),DU23:ER23)*#REF!+SUMPRODUCT(--(MOD(COLUMN(ES23:FP23),4)=MOD(COLUMN(ES23),4)),ES23:FP23)*#REF! -> #REF!
A24: HJBridge (нет в системе) | B24: Договор не подписан | C24: ВБК Восток | D24: Прасолов, Соловьёв | E24: =IF(ISBLANK(G24),"",IF($A$6:$A$64=$A24,COUNTIF($A$6:A24,$A24),"")) -> 2 | F24: 1 | G24: 6402250350 | H24: Дисковый тормозной механизм (правый) | I24: =I23 -> 1800 | L24: =IF(K24="RUB",J24/ЮАНЬ,IF(K24="EUR",J24*ЕВРО/ЮАНЬ,"")) | N24: =IF(BP24>0,1,IF(BN24>0,2,)) -> 0 | U24: 0 | BL24: =SUMPRODUCT(--(MOD(COLUMN($O24:$AL24),4)=MOD(COLUMN($O24)+0,4)),$O24:$AL24) +SUMPRODUCT(--(MOD(COLUMN($AM24:$BJ24),4)=MOD(COLUMN($AM24)+0,4)),$AM24:$BJ24) -> 0 | BM24: =SUMPRODUCT(--(MOD(COLUMN($O24:$AL24),4)=MOD(COLUMN($O24)+0,4)),$O24:$AL24)*$I24 +SUMPRODUCT(--(MOD(COLUMN($AM24:$BJ24),4)=MOD(COLUMN($AM24)+0,4)),$AM24:$BJ24)*$I24 -> 0 | BN24: =SUMPRODUCT(--(MOD(COLUMN($O24:$AL24),4)=MOD(COLUMN($O24)+1,4)),$O24:$AL24) +SUMPRODUCT(--(MOD(COLUMN($AM24:$BJ24),4)=MOD(COLUMN($AM24)+1,4)),$AM24:$BJ24) -> 0 | BO24: =SUMPRODUCT(--(MOD(COLUMN($O24:$AL24),4)=MOD(COLUMN($O24)+1,4)),$O24:$AL24)*$I24 +SUMPRODUCT(--(MOD(COLUMN($AM24:$BJ24),4)=MOD(COLUMN($AM24)+1,4)),$AM24:$BJ24)*$I24 -> 0 | BP24: =SUMPRODUCT(--(MOD(COLUMN($O24:$AL24),4)=MOD(COLUMN($O24)+2,4)),$O24:$AL24) +SUMPRODUCT(--(MOD(COLUMN($AM24:$BJ24),4)=MOD(COLUMN($AM24)+2,4)),$AM24:$BJ24) -> 0 | BQ24: =SUMPRODUCT(--(MOD(COLUMN($O24:$AL24),4)=MOD(COLUMN($O24)+2,4)),$O24:$AL24)*$I24 +SUMPRODUCT(--(MOD(COLUMN($AM24:$BJ24),4)=MOD(COLUMN($AM24)+2,4)),$AM24:$BJ24)*$I24 -> 0 | BT24: 621 | BX24: 621 | CB24: 621 | CF24: 621 | CJ24: 621 | CN24: 621 | CR24: 621 | CV24: 621 | CZ24: 621 | DD24: 621 | DH24: 621 | DL24: 621 | DQ24: =SUMPRODUCT(--(MOD(COLUMN(BT24:CQ24),4)=MOD(COLUMN(BT24),4)),BT24:CQ24)+SUMPRODUCT(--(MOD(COLUMN(CR24:DO24),4)=MOD(COLUMN(CR24),4)),CR24:DO24) -> 7452 | DR24: =SUMPRODUCT(--(MOD(COLUMN(BT24:CQ24),4)=MOD(COLUMN(BT24),4)),BT24:CQ24)*#REF!+SUMPRODUCT(--(MOD(COLUMN(CR24:DO24),4)=MOD(COLUMN(CR24),4)),CR24:DO24)*#REF! -> #REF! | DU24: 828 | DY24: 828 | EC24: 828 | EG24: 828 | EK24: 828 | EO24: 828 | ES24: 828 | EW24: 828 | FA24: 828 | FE24: 828 | FI24: 828 | FM24: 828 | FR24: =SUMPRODUCT(--(MOD(COLUMN(DU24:ER24),4)=MOD(COLUMN(DU24),4)),DU24:ER24)+SUMPRODUCT(--(MOD(COLUMN(ES24:FP24),4)=MOD(COLUMN(ES24),4)),ES24:FP24) -> 9936 | FS24: =SUMPRODUCT(--(MOD(COLUMN(DU24:ER24),4)=MOD(COLUMN(DU24),4)),DU24:ER24)*#REF!+SUMPRODUCT(--(MOD(COLUMN(ES24:FP24),4)=MOD(COLUMN(ES24),4)),ES24:FP24)*#REF! -> #REF!
A25: HJBridge (нет в системе) | B25: Договор не подписан | C25: ВБК Восток | D25: Прасолов, Соловьёв | E25: =IF(ISBLANK(G25),"",IF($A$6:$A$64=$A25,COUNTIF($A$6:A25,$A25),"")) -> 3 | F25: 1 | G25: 4410328080 | H25: Датчик АБС, 0,4 м | I25: =84/НДС_20 -> 70 | L25: =IF(K25="RUB",J25/ЮАНЬ,IF(K25="EUR",J25*ЕВРО/ЮАНЬ,"")) | N25: =IF(BP25>0,1,IF(BN25>0,2,)) -> 0 | U25: 0 | BL25: =SUMPRODUCT(--(MOD(COLUMN($O25:$AL25),4)=MOD(COLUMN($O25)+0,4)),$O25:$AL25) +SUMPRODUCT(--(MOD(COLUMN($AM25:$BJ25),4)=MOD(COLUMN($AM25)+0,4)),$AM25:$BJ25) -> 0 | BM25: =SUMPRODUCT(--(MOD(COLUMN($O25:$AL25),4)=MOD(COLUMN($O25)+0,4)),$O25:$AL25)*$I25 +SUMPRODUCT(--(MOD(COLUMN($AM25:$BJ25),4)=MOD(COLUMN($AM25)+0,4)),$AM25:$BJ25)*$I25 -> 0 | BN25: =SUMPRODUCT(--(MOD(COLUMN($O25:$AL25),4)=MOD(COLUMN($O25)+1,4)),$O25:$AL25) +SUMPRODUCT(--(MOD(COLUMN($AM25:$BJ25),4)=MOD(COLUMN($AM25)+1,4)),$AM25:$BJ25) -> 0 | BO25: =SUMPRODUCT(--(MOD(COLUMN($O25:$AL25),4)=MOD(COLUMN($O25)+1,4)),$O25:$AL25)*$I25 +SUMPRODUCT(--(MOD(COLUMN($AM25:$BJ25),4)=MOD(COLUMN($AM25)+1,4)),$AM25:$BJ25)*$I25 -> 0 | BP25: =SUMPRODUCT(--(MOD(COLUMN($O25:$AL25),4)=MOD(COLUMN($O25)+2,4)),$O25:$AL25) +SUMPRODUCT(--(MOD(COLUMN($AM25:$BJ25),4)=MOD(COLUMN($AM25)+2,4)),$AM25:$BJ25) -> 0 | BQ25: =SUMPRODUCT(--(MOD(COLUMN($O25:$AL25),4)=MOD(COLUMN($O25)+2,4)),$O25:$AL25)*$I25 +SUMPRODUCT(--(MOD(COLUMN($AM25:$BJ25),4)=MOD(COLUMN($AM25)+2,4)),$AM25:$BJ25)*$I25 -> 0 | BT25: 414 | BX25: 414 | CB25: 414 | CF25: 414 | CJ25: 414 | CN25: 414 | CR25: 414 | CV25: 414 | CZ25: 414 | DD25: 414 | DH25: 414 | DL25: 414 | DQ25: =SUMPRODUCT(--(MOD(COLUMN(BT25:CQ25),4)=MOD(COLUMN(BT25),4)),BT25:CQ25)+SUMPRODUCT(--(MOD(COLUMN(CR25:DO25),4)=MOD(COLUMN(CR25),4)),CR25:DO25) -> 4968 | DR25: =SUMPRODUCT(--(MOD(COLUMN(BT25:CQ25),4)=MOD(COLUMN(BT25),4)),BT25:CQ25)*#REF!+SUMPRODUCT(--(MOD(COLUMN(CR25:DO25),4)=MOD(COLUMN(CR25),4)),CR25:DO25)*#REF! -> #REF! | DU25: 552 | DY25: 552 | EC25: 552 | EG25: 552 | EK25: 552 | EO25: 552 | ES25: 552 | EW25: 552 | FA25: 552 | FE25: 552 | FI25: 552 | FM25: 552 | FR25: =SUMPRODUCT(--(MOD(COLUMN(DU25:ER25),4)=MOD(COLUMN(DU25),4)),DU25:ER25)+SUMPRODUCT(--(MOD(COLUMN(ES25:FP25),4)=MOD(COLUMN(ES25),4)),ES25:FP25) -> 6624 | FS25: =SUMPRODUCT(--(MOD(COLUMN(DU25:ER25),4)=MOD(COLUMN(DU25),4)),DU25:ER25)*#REF!+SUMPRODUCT(--(MOD(COLUMN(ES25:FP25),4)=MOD(COLUMN(ES25),4)),ES25:FP25)*#REF! -> #REF!
A26: HJBridge (нет в системе) | B26: Договор не подписан | C26: ВБК Восток | D26: Прасолов, Соловьёв | E26: =IF(ISBLANK(G26),"",IF($A$6:$A$64=$A26,COUNTIF($A$6:A26,$A26),"")) -> 4 | F26: 1 | G26: 8997598154 | H26: Втулка датчика АБС | I26: =8.4/НДС_20 -> 7 | L26: =IF(K26="RUB",J26/ЮАНЬ,IF(K26="EUR",J26*ЕВРО/ЮАНЬ,"")) | N26: =IF(BP26>0,1,IF(BN26>0,2,)) -> 0 | U26: 0 | BL26: =SUMPRODUCT(--(MOD(COLUMN($O26:$AL26),4)=MOD(COLUMN($O26)+0,4)),$O26:$AL26) +SUMPRODUCT(--(MOD(COLUMN($AM26:$BJ26),4)=MOD(COLUMN($AM26)+0,4)),$AM26:$BJ26) -> 0 | BM26: =SUMPRODUCT(--(MOD(COLUMN($O26:$AL26),4)=MOD(COLUMN($O26)+0,4)),$O26:$AL26)*$I26 +SUMPRODUCT(--(MOD(COLUMN($AM26:$BJ26),4)=MOD(COLUMN($AM26)+0,4)),$AM26:$BJ26)*$I26 -> 0 | BN26: =SUMPRODUCT(--(MOD(COLUMN($O26:$AL26),4)=MOD(COLUMN($O26)+1,4)),$O26:$AL26) +SUMPRODUCT(--(MOD(COLUMN($AM26:$BJ26),4)=MOD(COLUMN($AM26)+1,4)),$AM26:$BJ26) -> 0 | BO26: =SUMPRODUCT(--(MOD(COLUMN($O26:$AL26),4)=MOD(COLUMN($O26)+1,4)),$O26:$AL26)*$I26 +SUMPRODUCT(--(MOD(COLUMN($AM26:$BJ26),4)=MOD(COLUMN($AM26)+1,4)),$AM26:$BJ26)*$I26 -> 0 | BP26: =SUMPRODUCT(--(MOD(COLUMN($O26:$AL26),4)=MOD(COLUMN($O26)+2,4)),$O26:$AL26) +SUMPRODUCT(--(MOD(COLUMN($AM26:$BJ26),4)=MOD(COLUMN($AM26)+2,4)),$AM26:$BJ26) -> 0 | BQ26: =SUMPRODUCT(--(MOD(COLUMN($O26:$AL26),4)=MOD(COLUMN($O26)+2,4)),$O26:$AL26)*$I26 +SUMPRODUCT(--(MOD(COLUMN($AM26:$BJ26),4)=MOD(COLUMN($AM26)+2,4)),$AM26:$BJ26)*$I26 -> 0 | BT26: 414 | BX26: 414 | CB26: 414 | CF26: 414 | CJ26: 414 | CN26: 414 | CR26: 414 | CV26: 414 | CZ26: 414 | DD26: 414 | DH26: 414 | DL26: 414 | DQ26: =SUMPRODUCT(--(MOD(COLUMN(BT26:CQ26),4)=MOD(COLUMN(BT26),4)),BT26:CQ26)+SUMPRODUCT(--(MOD(COLUMN(CR26:DO26),4)=MOD(COLUMN(CR26),4)),CR26:DO26) -> 4968 | DR26: =SUMPRODUCT(--(MOD(COLUMN(BT26:CQ26),4)=MOD(COLUMN(BT26),4)),BT26:CQ26)*#REF!+SUMPRODUCT(--(MOD(COLUMN(CR26:DO26),4)=MOD(COLUMN(CR26),4)),CR26:DO26)*#REF! -> #REF! | DU26: 552 | DY26: 552 | EC26: 552 | EG26: 552 | EK26: 552 | EO26: 552 | ES26: 552 | EW26: 552 | FA26: 552 | FE26: 552 | FI26: 552 | FM26: 552 | FR26: =SUMPRODUCT(--(MOD(COLUMN(DU26:ER26),4)=MOD(COLUMN(DU26),4)),DU26:ER26)+SUMPRODUCT(--(MOD(COLUMN(ES26:FP26),4)=MOD(COLUMN(ES26),4)),ES26:FP26) -> 6624 | FS26: =SUMPRODUCT(--(MOD(COLUMN(DU26:ER26),4)=MOD(COLUMN(DU26),4)),DU26:ER26)*#REF!+SUMPRODUCT(--(MOD(COLUMN(ES26:FP26),4)=MOD(COLUMN(ES26),4)),ES26:FP26)*#REF! -> #REF!
A27: HJBridge (нет в системе) | B27: Договор не подписан | C27: ВБК Восток | D27: Прасолов, Соловьёв | E27: =IF(ISBLANK(G27),"",IF($A$6:$A$64=$A27,COUNTIF($A$6:A27,$A27),"")) -> 5 | F27: 1 | G27: 4235050030 | H27: Тормозная камера, тип 20 | I27: =163.08/НДС_20 -> 135.9 | L27: =IF(K27="RUB",J27/ЮАНЬ,IF(K27="EUR",J27*ЕВРО/ЮАНЬ,"")) | N27: =IF(BP27>0,1,IF(BN27>0,2,)) -> 0 | U27: 0 | BL27: =SUMPRODUCT(--(MOD(COLUMN($O27:$AL27),4)=MOD(COLUMN($O27)+0,4)),$O27:$AL27) +SUMPRODUCT(--(MOD(COLUMN($AM27:$BJ27),4)=MOD(COLUMN($AM27)+0,4)),$AM27:$BJ27) -> 0 | BM27: =SUMPRODUCT(--(MOD(COLUMN($O27:$AL27),4)=MOD(COLUMN($O27)+0,4)),$O27:$AL27)*$I27 +SUMPRODUCT(--(MOD(COLUMN($AM27:$BJ27),4)=MOD(COLUMN($AM27)+0,4)),$AM27:$BJ27)*$I27 -> 0 | BN27: =SUMPRODUCT(--(MOD(COLUMN($O27:$AL27),4)=MOD(COLUMN($O27)+1,4)),$O27:$AL27) +SUMPRODUCT(--(MOD(COLUMN($AM27:$BJ27),4)=MOD(COLUMN($AM27)+1,4)),$AM27:$BJ27) -> 0 | BO27: =SUMPRODUCT(--(MOD(COLUMN($O27:$AL27),4)=MOD(COLUMN($O27)+1,4)),$O27:$AL27)*$I27 +SUMPRODUCT(--(MOD(COLUMN($AM27:$BJ27),4)=MOD(COLUMN($AM27)+1,4)),$AM27:$BJ27)*$I27 -> 0 | BP27: =SUMPRODUCT(--(MOD(COLUMN($O27:$AL27),4)=MOD(COLUMN($O27)+2,4)),$O27:$AL27) +SUMPRODUCT(--(MOD(COLUMN($AM27:$BJ27),4)=MOD(COLUMN($AM27)+2,4)),$AM27:$BJ27) -> 0 | BQ27: =SUMPRODUCT(--(MOD(COLUMN($O27:$AL27),4)=MOD(COLUMN($O27)+2,4)),$O27:$AL27)*$I27 +SUMPRODUCT(--(MOD(COLUMN($AM27:$BJ27),4)=MOD(COLUMN($AM27)+2,4)),$AM27:$BJ27)*$I27 -> 0 | DQ27: =SUMPRODUCT(--(MOD(COLUMN(BT27:CQ27),4)=MOD(COLUMN(BT27),4)),BT27:CQ27)+SUMPRODUCT(--(MOD(COLUMN(CR27:DO27),4)=MOD(COLUMN(CR27),4)),CR27:DO27) -> 0 | DR27: =SUMPRODUCT(--(MOD(COLUMN(BT27:CQ27),4)=MOD(COLUMN(BT27),4)),BT27:CQ27)*#REF!+SUMPRODUCT(--(MOD(COLUMN(CR27:DO27),4)=MOD(COLUMN(CR27),4)),CR27:DO27)*#REF! -> #REF! | FR27: =SUMPRODUCT(--(MOD(COLUMN(DU27:ER27),4)=MOD(COLUMN(DU27),4)),DU27:ER27)+SUMPRODUCT(--(MOD(COLUMN(ES27:FP27),4)=MOD(COLUMN(ES27),4)),ES27:FP27) -> 0 | FS27: =SUMPRODUCT(--(MOD(COLUMN(DU27:ER27),4)=MOD(COLUMN(DU27),4)),DU27:ER27)*#REF!+SUMPRODUCT(--(MOD(COLUMN(ES27:FP27),4)=MOD(COLUMN(ES27),4)),ES27:FP27)*#REF! -> #REF!
A28: HJBridge (нет в системе) | B28: Договор не подписан | C28: ВБК Восток | D28: Прасолов, Соловьёв | E28: =IF(ISBLANK(G28),"",IF($A$6:$A$64=$A28,COUNTIF($A$6:A28,$A28),"")) -> 6 | F28: 1 | G28: 9254800506 | H28: Энергоаккумулятор, тип 20/24 | I28: =373.98/НДС_20 -> 311.65 | L28: =IF(K28="RUB",J28/ЮАНЬ,IF(K28="EUR",J28*ЕВРО/ЮАНЬ,"")) | N28: =IF(BP28>0,1,IF(BN28>0,2,)) -> 0 | U28: 0 | BL28: =SUMPRODUCT(--(MOD(COLUMN($O28:$AL28),4)=MOD(COLUMN($O28)+0,4)),$O28:$AL28) +SUMPRODUCT(--(MOD(COLUMN($AM28:$BJ28),4)=MOD(COLUMN($AM28)+0,4)),$AM28:$BJ28) -> 0 | BM28: =SUMPRODUCT(--(MOD(COLUMN($O28:$AL28),4)=MOD(COLUMN($O28)+0,4)),$O28:$AL28)*$I28 +SUMPRODUCT(--(MOD(COLUMN($AM28:$BJ28),4)=MOD(COLUMN($AM28)+0,4)),$AM28:$BJ28)*$I28 -> 0 | BN28: =SUMPRODUCT(--(MOD(COLUMN($O28:$AL28),4)=MOD(COLUMN($O28)+1,4)),$O28:$AL28) +SUMPRODUCT(--(MOD(COLUMN($AM28:$BJ28),4)=MOD(COLUMN($AM28)+1,4)),$AM28:$BJ28) -> 0 | BO28: =SUMPRODUCT(--(MOD(COLUMN($O28:$AL28),4)=MOD(COLUMN($O28)+1,4)),$O28:$AL28)*$I28 +SUMPRODUCT(--(MOD(COLUMN($AM28:$BJ28),4)=MOD(COLUMN($AM28)+1,4)),$AM28:$BJ28)*$I28 -> 0 | BP28: =SUMPRODUCT(--(MOD(COLUMN($O28:$AL28),4)=MOD(COLUMN($O28)+2,4)),$O28:$AL28) +SUMPRODUCT(--(MOD(COLUMN($AM28:$BJ28),4)=MOD(COLUMN($AM28)+2,4)),$AM28:$BJ28) -> 0 | BQ28: =SUMPRODUCT(--(MOD(COLUMN($O28:$AL28),4)=MOD(COLUMN($O28)+2,4)),$O28:$AL28)*$I28 +SUMPRODUCT(--(MOD(COLUMN($AM28:$BJ28),4)=MOD(COLUMN($AM28)+2,4)),$AM28:$BJ28)*$I28 -> 0 | DQ28: =SUMPRODUCT(--(MOD(COLUMN(BT28:CQ28),4)=MOD(COLUMN(BT28),4)),BT28:CQ28)+SUMPRODUCT(--(MOD(COLUMN(CR28:DO28),4)=MOD(COLUMN(CR28),4)),CR28:DO28) -> 0 | DR28: =SUMPRODUCT(--(MOD(COLUMN(BT28:CQ28),4)=MOD(COLUMN(BT28),4)),BT28:CQ28)*#REF!+SUMPRODUCT(--(MOD(COLUMN(CR28:DO28),4)=MOD(COLUMN(CR28),4)),CR28:DO28)*#REF! -> #REF! | FR28: =SUMPRODUCT(--(MOD(COLUMN(DU28:ER28),4)=MOD(COLUMN(DU28),4)),DU28:ER28)+SUMPRODUCT(--(MOD(COLUMN(ES28:FP28),4)=MOD(COLUMN(ES28),4)),ES28:FP28) -> 0 | FS28: =SUMPRODUCT(--(MOD(COLUMN(DU28:ER28),4)=MOD(COLUMN(DU28),4)),DU28:ER28)*#REF!+SUMPRODUCT(--(MOD(COLUMN(ES28:FP28),4)=MOD(COLUMN(ES28),4)),ES28:FP28)*#REF! -> #REF!
A29: HJBridge (нет в системе) | B29: Договор не подписан | C29: ВБК Восток | D29: Прасолов, Соловьёв | E29: =IF(ISBLANK(G29),"",IF($A$6:$A$64=$A29,COUNTIF($A$6:A29,$A29),"")) -> 7 | F29: 1 | G29: 4235041050 | H29: Тормозная камера, тип 16 | I29: =156/НДС_20 -> 130 | L29: =IF(K29="RUB",J29/ЮАНЬ,IF(K29="EUR",J29*ЕВРО/ЮАНЬ,"")) | N29: =IF(BP29>0,1,IF(BN29>0,2,)) -> 0 | U29: 0 | BL29: =SUMPRODUCT(--(MOD(COLUMN($O29:$AL29),4)=MOD(COLUMN($O29)+0,4)),$O29:$AL29) +SUMPRODUCT(--(MOD(COLUMN($AM29:$BJ29),4)=MOD(COLUMN($AM29)+0,4)),$AM29:$BJ29) -> 0 | BM29: =SUMPRODUCT(--(MOD(COLUMN($O29:$AL29),4)=MOD(COLUMN($O29)+0,4)),$O29:$AL29)*$I29 +SUMPRODUCT(--(MOD(COLUMN($AM29:$BJ29),4)=MOD(COLUMN($AM29)+0,4)),$AM29:$BJ29)*$I29 -> 0 | BN29: =SUMPRODUCT(--(MOD(COLUMN($O29:$AL29),4)=MOD(COLUMN($O29)+1,4)),$O29:$AL29) +SUMPRODUCT(--(MOD(COLUMN($AM29:$BJ29),4)=MOD(COLUMN($AM29)+1,4)),$AM29:$BJ29) -> 0 | BO29: =SUMPRODUCT(--(MOD(COLUMN($O29:$AL29),4)=MOD(COLUMN($O29)+1,4)),$O29:$AL29)*$I29 +SUMPRODUCT(--(MOD(COLUMN($AM29:$BJ29),4)=MOD(COLUMN($AM29)+1,4)),$AM29:$BJ29)*$I29 -> 0 | BP29: =SUMPRODUCT(--(MOD(COLUMN($O29:$AL29),4)=MOD(COLUMN($O29)+2,4)),$O29:$AL29) +SUMPRODUCT(--(MOD(COLUMN($AM29:$BJ29),4)=MOD(COLUMN($AM29)+2,4)),$AM29:$BJ29) -> 0 | BQ29: =SUMPRODUCT(--(MOD(COLUMN($O29:$AL29),4)=MOD(COLUMN($O29)+2,4)),$O29:$AL29)*$I29 +SUMPRODUCT(--(MOD(COLUMN($AM29:$BJ29),4)=MOD(COLUMN($AM29)+2,4)),$AM29:$BJ29)*$I29 -> 0 | DQ29: =SUMPRODUCT(--(MOD(COLUMN(BT29:CQ29),4)=MOD(COLUMN(BT29),4)),BT29:CQ29)+SUMPRODUCT(--(MOD(COLUMN(CR29:DO29),4)=MOD(COLUMN(CR29),4)),CR29:DO29) -> 0 | DR29: =SUMPRODUCT(--(MOD(COLUMN(BT29:CQ29),4)=MOD(COLUMN(BT29),4)),BT29:CQ29)*#REF!+SUMPRODUCT(--(MOD(COLUMN(CR29:DO29),4)=MOD(COLUMN(CR29),4)),CR29:DO29)*#REF! -> #REF! | FR29: =SUMPRODUCT(--(MOD(COLUMN(DU29:ER29),4)=MOD(COLUMN(DU29),4)),DU29:ER29)+SUMPRODUCT(--(MOD(COLUMN(ES29:FP29),4)=MOD(COLUMN(ES29),4)),ES29:FP29) -> 0 | FS29: =SUMPRODUCT(--(MOD(COLUMN(DU29:ER29),4)=MOD(COLUMN(DU29),4)),DU29:ER29)*#REF!+SUMPRODUCT(--(MOD(COLUMN(ES29:FP29),4)=MOD(COLUMN(ES29),4)),ES29:FP29)*#REF! -> #REF!
A30: HJBridge (нет в системе) | B30: Договор не подписан | C30: ВБК Восток | D30: Прасолов, Соловьёв | E30: =IF(ISBLANK(G30),"",IF($A$6:$A$64=$A30,COUNTIF($A$6:A30,$A30),"")) -> 8 | F30: 1 | G30: 9254849611 | H30: Энергоаккумулятор, тип 16/24 | I30: =360/НДС_20 -> 300 | L30: =IF(K30="RUB",J30/ЮАНЬ,IF(K30="EUR",J30*ЕВРО/ЮАНЬ,"")) | N30: =IF(BP30>0,1,IF(BN30>0,2,)) -> 0 | U30: 0 | BL30: =SUMPRODUCT(--(MOD(COLUMN($O30:$AL30),4)=MOD(COLUMN($O30)+0,4)),$O30:$AL30) +SUMPRODUCT(--(MOD(COLUMN($AM30:$BJ30),4)=MOD(COLUMN($AM30)+0,4)),$AM30:$BJ30) -> 0 | BM30: =SUMPRODUCT(--(MOD(COLUMN($O30:$AL30),4)=MOD(COLUMN($O30)+0,4)),$O30:$AL30)*$I30 +SUMPRODUCT(--(MOD(COLUMN($AM30:$BJ30),4)=MOD(COLUMN($AM30)+0,4)),$AM30:$BJ30)*$I30 -> 0 | BN30: =SUMPRODUCT(--(MOD(COLUMN($O30:$AL30),4)=MOD(COLUMN($O30)+1,4)),$O30:$AL30) +SUMPRODUCT(--(MOD(COLUMN($AM30:$BJ30),4)=MOD(COLUMN($AM30)+1,4)),$AM30:$BJ30) -> 0 | BO30: =SUMPRODUCT(--(MOD(COLUMN($O30:$AL30),4)=MOD(COLUMN($O30)+1,4)),$O30:$AL30)*$I30 +SUMPRODUCT(--(MOD(COLUMN($AM30:$BJ30),4)=MOD(COLUMN($AM30)+1,4)),$AM30:$BJ30)*$I30 -> 0 | BP30: =SUMPRODUCT(--(MOD(COLUMN($O30:$AL30),4)=MOD(COLUMN($O30)+2,4)),$O30:$AL30) +SUMPRODUCT(--(MOD(COLUMN($AM30:$BJ30),4)=MOD(COLUMN($AM30)+2,4)),$AM30:$BJ30) -> 0 | BQ30: =SUMPRODUCT(--(MOD(COLUMN($O30:$AL30),4)=MOD(COLUMN($O30)+2,4)),$O30:$AL30)*$I30 +SUMPRODUCT(--(MOD(COLUMN($AM30:$BJ30),4)=MOD(COLUMN($AM30)+2,4)),$AM30:$BJ30)*$I30 -> 0 | DQ30: =SUMPRODUCT(--(MOD(COLUMN(BT30:CQ30),4)=MOD(COLUMN(BT30),4)),BT30:CQ30)+SUMPRODUCT(--(MOD(COLUMN(CR30:DO30),4)=MOD(COLUMN(CR30),4)),CR30:DO30) -> 0 | DR30: =SUMPRODUCT(--(MOD(COLUMN(BT30:CQ30),4)=MOD(COLUMN(BT30),4)),BT30:CQ30)*#REF!+SUMPRODUCT(--(MOD(COLUMN(CR30:DO30),4)=MOD(COLUMN(CR30),4)),CR30:DO30)*#REF! -> #REF! | FR30: =SUMPRODUCT(--(MOD(COLUMN(DU30:ER30),4)=MOD(COLUMN(DU30),4)),DU30:ER30)+SUMPRODUCT(--(MOD(COLUMN(ES30:FP30),4)=MOD(COLUMN(ES30),4)),ES30:FP30) -> 0 | FS30: =SUMPRODUCT(--(MOD(COLUMN(DU30:ER30),4)=MOD(COLUMN(DU30),4)),DU30:ER30)*#REF!+SUMPRODUCT(--(MOD(COLUMN(ES30:FP30),4)=MOD(COLUMN(ES30),4)),ES30:FP30)*#REF! -> #REF!
A31: HJBridge (нет в системе) | B31: Договор не подписан | C31: ВБК Восток | D31: Прасолов, Соловьёв | E31: =IF(ISBLANK(G31),"",IF($A$6:$A$64=$A31,COUNTIF($A$6:A31,$A31),"")) -> 9 | F31: 1 | G31: 9254800620 | H31: Энергоаккумулятор, тип 16/24 | I31: =360/НДС_20 -> 300 | L31: =IF(K31="RUB",J31/ЮАНЬ,IF(K31="EUR",J31*ЕВРО/ЮАНЬ,"")) | N31: =IF(BP31>0,1,IF(BN31>0,2,)) -> 0 | U31: 0 | BL31: =SUMPRODUCT(--(MOD(COLUMN($O31:$AL31),4)=MOD(COLUMN($O31)+0,4)),$O31:$AL31) +SUMPRODUCT(--(MOD(COLUMN($AM31:$BJ31),4)=MOD(COLUMN($AM31)+0,4)),$AM31:$BJ31) -> 0 | BM31: =SUMPRODUCT(--(MOD(COLUMN($O31:$AL31),4)=MOD(COLUMN($O31)+0,4)),$O31:$AL31)*$I31 +SUMPRODUCT(--(MOD(COLUMN($AM31:$BJ31),4)=MOD(COLUMN($AM31)+0,4)),$AM31:$BJ31)*$I31 -> 0 | BN31: =SUMPRODUCT(--(MOD(COLUMN($O31:$AL31),4)=MOD(COLUMN($O31)+1,4)),$O31:$AL31) +SUMPRODUCT(--(MOD(COLUMN($AM31:$BJ31),4)=MOD(COLUMN($AM31)+1,4)),$AM31:$BJ31) -> 0 | BO31: =SUMPRODUCT(--(MOD(COLUMN($O31:$AL31),4)=MOD(COLUMN($O31)+1,4)),$O31:$AL31)*$I31 +SUMPRODUCT(--(MOD(COLUMN($AM31:$BJ31),4)=MOD(COLUMN($AM31)+1,4)),$AM31:$BJ31)*$I31 -> 0 | BP31: =SUMPRODUCT(--(MOD(COLUMN($O31:$AL31),4)=MOD(COLUMN($O31)+2,4)),$O31:$AL31) +SUMPRODUCT(--(MOD(COLUMN($AM31:$BJ31),4)=MOD(COLUMN($AM31)+2,4)),$AM31:$BJ31) -> 0 | BQ31: =SUMPRODUCT(--(MOD(COLUMN($O31:$AL31),4)=MOD(COLUMN($O31)+2,4)),$O31:$AL31)*$I31 +SUMPRODUCT(--(MOD(COLUMN($AM31:$BJ31),4)=MOD(COLUMN($AM31)+2,4)),$AM31:$BJ31)*$I31 -> 0 | DQ31: =SUMPRODUCT(--(MOD(COLUMN(BT31:CQ31),4)=MOD(COLUMN(BT31),4)),BT31:CQ31)+SUMPRODUCT(--(MOD(COLUMN(CR31:DO31),4)=MOD(COLUMN(CR31),4)),CR31:DO31) -> 0 | DR31: =SUMPRODUCT(--(MOD(COLUMN(BT31:CQ31),4)=MOD(COLUMN(BT31),4)),BT31:CQ31)*#REF!+SUMPRODUCT(--(MOD(COLUMN(CR31:DO31),4)=MOD(COLUMN(CR31),4)),CR31:DO31)*#REF! -> #REF! | FR31: =SUMPRODUCT(--(MOD(COLUMN(DU31:ER31),4)=MOD(COLUMN(DU31),4)),DU31:ER31)+SUMPRODUCT(--(MOD(COLUMN(ES31:FP31),4)=MOD(COLUMN(ES31),4)),ES31:FP31) -> 0 | FS31: =SUMPRODUCT(--(MOD(COLUMN(DU31:ER31),4)=MOD(COLUMN(DU31),4)),DU31:ER31)*#REF!+SUMPRODUCT(--(MOD(COLUMN(ES31:FP31),4)=MOD(COLUMN(ES31),4)),ES31:FP31)*#REF! -> #REF!
A32: HJBridge (нет в системе) | B32: Договор не подписан | C32: ВБК Восток | D32: Прасолов, Соловьёв | E32: =IF(ISBLANK(G32),"",IF($A$6:$A$64=$A32,COUNTIF($A$6:A32,$A32),"")) -> 10 | F32: 1 | G32: 4235041060 | H32: Тормозная камера, тип 44 | I32: =600/НДС_20 -> 500 | L32: =IF(K32="RUB",J32/ЮАНЬ,IF(K32="EUR",J32*ЕВРО/ЮАНЬ,"")) | N32: =IF(BP32>0,1,IF(BN32>0,2,)) -> 0 | U32: 0 | BL32: =SUMPRODUCT(--(MOD(COLUMN($O32:$AL32),4)=MOD(COLUMN($O32)+0,4)),$O32:$AL32) +SUMPRODUCT(--(MOD(COLUMN($AM32:$BJ32),4)=MOD(COLUMN($AM32)+0,4)),$AM32:$BJ32) -> 0 | BM32: =SUMPRODUCT(--(MOD(COLUMN($O32:$AL32),4)=MOD(COLUMN($O32)+0,4)),$O32:$AL32)*$I32 +SUMPRODUCT(--(MOD(COLUMN($AM32:$BJ32),4)=MOD(COLUMN($AM32)+0,4)),$AM32:$BJ32)*$I32 -> 0 | BN32: =SUMPRODUCT(--(MOD(COLUMN($O32:$AL32),4)=MOD(COLUMN($O32)+1,4)),$O32:$AL32) +SUMPRODUCT(--(MOD(COLUMN($AM32:$BJ32),4)=MOD(COLUMN($AM32)+1,4)),$AM32:$BJ32) -> 0 | BO32: =SUMPRODUCT(--(MOD(COLUMN($O32:$AL32),4)=MOD(COLUMN($O32)+1,4)),$O32:$AL32)*$I32 +SUMPRODUCT(--(MOD(COLUMN($AM32:$BJ32),4)=MOD(COLUMN($AM32)+1,4)),$AM32:$BJ32)*$I32 -> 0 | BP32: =SUMPRODUCT(--(MOD(COLUMN($O32:$AL32),4)=MOD(COLUMN($O32)+2,4)),$O32:$AL32) +SUMPRODUCT(--(MOD(COLUMN($AM32:$BJ32),4)=MOD(COLUMN($AM32)+2,4)),$AM32:$BJ32) -> 0 | BQ32: =SUMPRODUCT(--(MOD(COLUMN($O32:$AL32),4)=MOD(COLUMN($O32)+2,4)),$O32:$AL32)*$I32 +SUMPRODUCT(--(MOD(COLUMN($AM32:$BJ32),4)=MOD(COLUMN($AM32)+2,4)),$AM32:$BJ32)*$I32 -> 0 | DQ32: =SUMPRODUCT(--(MOD(COLUMN(BT32:CQ32),4)=MOD(COLUMN(BT32),4)),BT32:CQ32)+SUMPRODUCT(--(MOD(COLUMN(CR32:DO32),4)=MOD(COLUMN(CR32),4)),CR32:DO32) -> 0 | DR32: =SUMPRODUCT(--(MOD(COLUMN(BT32:CQ32),4)=MOD(COLUMN(BT32),4)),BT32:CQ32)*#REF!+SUMPRODUCT(--(MOD(COLUMN(CR32:DO32),4)=MOD(COLUMN(CR32),4)),CR32:DO32)*#REF! -> #REF! | FR32: =SUMPRODUCT(--(MOD(COLUMN(DU32:ER32),4)=MOD(COLUMN(DU32),4)),DU32:ER32)+SUMPRODUCT(--(MOD(COLUMN(ES32:FP32),4)=MOD(COLUMN(ES32),4)),ES32:FP32) -> 0 | FS32: =SUMPRODUCT(--(MOD(COLUMN(DU32:ER32),4)=MOD(COLUMN(DU32),4)),DU32:ER32)*#REF!+SUMPRODUCT(--(MOD(COLUMN(ES32:FP32),4)=MOD(COLUMN(ES32),4)),ES32:FP32)*#REF! -> #REF!
A33: HJBridge (нет в системе) | E33: =IF(ISBLANK(G33),"",IF($A$6:$A$64=$A33,COUNTIF($A$6:A33,$A33),"")) | H33: Итого | L33: =IF(K33="RUB",J33/ЮАНЬ,IF(K33="EUR",J33*ЕВРО/ЮАНЬ,"")) | N33: =IF(BP33>0,1,IF(BN33>0,2,)) -> 0 | BL33: =SUMPRODUCT(--(MOD(COLUMN($O33:$AL33),4)=MOD(COLUMN($O33)+0,4)),$O33:$AL33) +SUMPRODUCT(--(MOD(COLUMN($AM33:$BJ33),4)=MOD(COLUMN($AM33)+0,4)),$AM33:$BJ33) -> 0 | BM33: =SUMPRODUCT(--(MOD(COLUMN($O33:$AL33),4)=MOD(COLUMN($O33)+0,4)),$O33:$AL33)*$I33 +SUMPRODUCT(--(MOD(COLUMN($AM33:$BJ33),4)=MOD(COLUMN($AM33)+0,4)),$AM33:$BJ33)*$I33 -> 0 | BN33: =SUMPRODUCT(--(MOD(COLUMN($O33:$AL33),4)=MOD(COLUMN($O33)+1,4)),$O33:$AL33) +SUMPRODUCT(--(MOD(COLUMN($AM33:$BJ33),4)=MOD(COLUMN($AM33)+1,4)),$AM33:$BJ33) -> 0 | BO33: =SUMPRODUCT(--(MOD(COLUMN($O33:$AL33),4)=MOD(COLUMN($O33)+1,4)),$O33:$AL33)*$I33 +SUMPRODUCT(--(MOD(COLUMN($AM33:$BJ33),4)=MOD(COLUMN($AM33)+1,4)),$AM33:$BJ33)*$I33 -> 0 | BP33: =SUMPRODUCT(--(MOD(COLUMN($O33:$AL33),4)=MOD(COLUMN($O33)+2,4)),$O33:$AL33) +SUMPRODUCT(--(MOD(COLUMN($AM33:$BJ33),4)=MOD(COLUMN($AM33)+2,4)),$AM33:$BJ33) -> 0 | BQ33: =SUMPRODUCT(--(MOD(COLUMN($O33:$AL33),4)=MOD(COLUMN($O33)+2,4)),$O33:$AL33)*$I33 +SUMPRODUCT(--(MOD(COLUMN($AM33:$BJ33),4)=MOD(COLUMN($AM33)+2,4)),$AM33:$BJ33)*$I33 -> 0 | DQ33: =SUMPRODUCT(--(MOD(COLUMN(BT33:CQ33),4)=MOD(COLUMN(BT33),4)),BT33:CQ33)+SUMPRODUCT(--(MOD(COLUMN(CR33:DO33),4)=MOD(COLUMN(CR33),4)),CR33:DO33) -> 0 | DR33: =SUMPRODUCT(--(MOD(COLUMN(BT33:CQ33),4)=MOD(COLUMN(BT33),4)),BT33:CQ33)*#REF!+SUMPRODUCT(--(MOD(COLUMN(CR33:DO33),4)=MOD(COLUMN(CR33),4)),CR33:DO33)*#REF! -> #REF! | FR33: =SUMPRODUCT(--(MOD(COLUMN(DU33:ER33),4)=MOD(COLUMN(DU33),4)),DU33:ER33)+SUMPRODUCT(--(MOD(COLUMN(ES33:FP33),4)=MOD(COLUMN(ES33),4)),ES33:FP33) -> 0 | FS33: =SUMPRODUCT(--(MOD(COLUMN(DU33:ER33),4)=MOD(COLUMN(DU33),4)),DU33:ER33)*#REF!+SUMPRODUCT(--(MOD(COLUMN(ES33:FP33),4)=MOD(COLUMN(ES33),4)),ES33:FP33)*#REF! -> #REF!
A34: HJBridge (нет в системе) | E34: =IF(ISBLANK(G34),"",IF($A$6:$A$64=$A34,COUNTIF($A$6:A34,$A34),"")) | L34: =IF(K34="RUB",J34/ЮАНЬ,IF(K34="EUR",J34*ЕВРО/ЮАНЬ,"")) | N34: =IF(BP34>0,1,IF(BN34>0,2,)) -> 0 | BL34: =SUMPRODUCT(--(MOD(COLUMN($O34:$AL34),4)=MOD(COLUMN($O34)+0,4)),$O34:$AL34) +SUMPRODUCT(--(MOD(COLUMN($AM34:$BJ34),4)=MOD(COLUMN($AM34)+0,4)),$AM34:$BJ34) -> 0 | BM34: =SUMPRODUCT(--(MOD(COLUMN($O34:$AL34),4)=MOD(COLUMN($O34)+0,4)),$O34:$AL34)*$I34 +SUMPRODUCT(--(MOD(COLUMN($AM34:$BJ34),4)=MOD(COLUMN($AM34)+0,4)),$AM34:$BJ34)*$I34 -> 0 | BN34: =SUMPRODUCT(--(MOD(COLUMN($O34:$AL34),4)=MOD(COLUMN($O34)+1,4)),$O34:$AL34) +SUMPRODUCT(--(MOD(COLUMN($AM34:$BJ34),4)=MOD(COLUMN($AM34)+1,4)),$AM34:$BJ34) -> 0 | BO34: =SUMPRODUCT(--(MOD(COLUMN($O34:$AL34),4)=MOD(COLUMN($O34)+1,4)),$O34:$AL34)*$I34 +SUMPRODUCT(--(MOD(COLUMN($AM34:$BJ34),4)=MOD(COLUMN($AM34)+1,4)),$AM34:$BJ34)*$I34 -> 0 | BP34: =SUMPRODUCT(--(MOD(COLUMN($O34:$AL34),4)=MOD(COLUMN($O34)+2,4)),$O34:$AL34) +SUMPRODUCT(--(MOD(COLUMN($AM34:$BJ34),4)=MOD(COLUMN($AM34)+2,4)),$AM34:$BJ34) -> 0 | BQ34: =SUMPRODUCT(--(MOD(COLUMN($O34:$AL34),4)=MOD(COLUMN($O34)+2,4)),$O34:$AL34)*$I34 +SUMPRODUCT(--(MOD(COLUMN($AM34:$BJ34),4)=MOD(COLUMN($AM34)+2,4)),$AM34:$BJ34)*$I34 -> 0 | DQ34: =SUMPRODUCT(--(MOD(COLUMN(BT34:CQ34),4)=MOD(COLUMN(BT34),4)),BT34:CQ34)+SUMPRODUCT(--(MOD(COLUMN(CR34:DO34),4)=MOD(COLUMN(CR34),4)),CR34:DO34) -> 0 | DR34: =SUMPRODUCT(--(MOD(COLUMN(BT34:CQ34),4)=MOD(COLUMN(BT34),4)),BT34:CQ34)*#REF!+SUMPRODUCT(--(MOD(COLUMN(CR34:DO34),4)=MOD(COLUMN(CR34),4)),CR34:DO34)*#REF! -> #REF! | FR34: =SUMPRODUCT(--(MOD(COLUMN(DU34:ER34),4)=MOD(COLUMN(DU34),4)),DU34:ER34)+SUMPRODUCT(--(MOD(COLUMN(ES34:FP34),4)=MOD(COLUMN(ES34),4)),ES34:FP34) -> 0 | FS34: =SUMPRODUCT(--(MOD(COLUMN(DU34:ER34),4)=MOD(COLUMN(DU34),4)),DU34:ER34)*#REF!+SUMPRODUCT(--(MOD(COLUMN(ES34:FP34),4)=MOD(COLUMN(ES34),4)),ES34:FP34)*#REF! -> #REF!
A35: НПО РОСТАР ООО | B35: Отсрочка 10 дней | C35: ВБК Восток | D35: Прасолов, Соловьёв | E35: =IF(ISBLANK(G35),"",IF($A$6:$A$64=$A35,COUNTIF($A$6:A35,$A35),"")) -> 1 | F35: 1 | G35: 6402250560 | H35: 6402250560 AC Тормоз дисковый ( левый ) | I35: =2048 -> 2048 | L35: =IF(K35="RUB",J35/ЮАНЬ,IF(K35="EUR",J35*ЕВРО/ЮАНЬ,"")) | N35: =IF(BP35>0,1,IF(BN35>0,2,)) -> 0 | U35: 0 | AC35: 0 | BL35: =SUMPRODUCT(--(MOD(COLUMN($O35:$AL35),4)=MOD(COLUMN($O35)+0,4)),$O35:$AL35) +SUMPRODUCT(--(MOD(COLUMN($AM35:$BJ35),4)=MOD(COLUMN($AM35)+0,4)),$AM35:$BJ35) -> 0 | BM35: =SUMPRODUCT(--(MOD(COLUMN($O35:$AL35),4)=MOD(COLUMN($O35)+0,4)),$O35:$AL35)*$I35 +SUMPRODUCT(--(MOD(COLUMN($AM35:$BJ35),4)=MOD(COLUMN($AM35)+0,4)),$AM35:$BJ35)*$I35 -> 0 | BN35: =SUMPRODUCT(--(MOD(COLUMN($O35:$AL35),4)=MOD(COLUMN($O35)+1,4)),$O35:$AL35) +SUMPRODUCT(--(MOD(COLUMN($AM35:$BJ35),4)=MOD(COLUMN($AM35)+1,4)),$AM35:$BJ35) -> 0 | BO35: =SUMPRODUCT(--(MOD(COLUMN($O35:$AL35),4)=MOD(COLUMN($O35)+1,4)),$O35:$AL35)*$I35 +SUMPRODUCT(--(MOD(COLUMN($AM35:$BJ35),4)=MOD(COLUMN($AM35)+1,4)),$AM35:$BJ35)*$I35 -> 0 | BP35: =SUMPRODUCT(--(MOD(COLUMN($O35:$AL35),4)=MOD(COLUMN($O35)+2,4)),$O35:$AL35) +SUMPRODUCT(--(MOD(COLUMN($AM35:$BJ35),4)=MOD(COLUMN($AM35)+2,4)),$AM35:$BJ35) -> 0 | BQ35: =SUMPRODUCT(--(MOD(COLUMN($O35:$AL35),4)=MOD(COLUMN($O35)+2,4)),$O35:$AL35)*$I35 +SUMPRODUCT(--(MOD(COLUMN($AM35:$BJ35),4)=MOD(COLUMN($AM35)+2,4)),$AM35:$BJ35)*$I35 -> 0 | DQ35: =SUMPRODUCT(--(MOD(COLUMN(BT35:CQ35),4)=MOD(COLUMN(BT35),4)),BT35:CQ35)+SUMPRODUCT(--(MOD(COLUMN(CR35:DO35),4)=MOD(COLUMN(CR35),4)),CR35:DO35) -> 0 | DR35: =SUMPRODUCT(--(MOD(COLUMN(BT35:CQ35),4)=MOD(COLUMN(BT35),4)),BT35:CQ35)*#REF!+SUMPRODUCT(--(MOD(COLUMN(CR35:DO35),4)=MOD(COLUMN(CR35),4)),CR35:DO35)*#REF! -> #REF! | FR35: =SUMPRODUCT(--(MOD(COLUMN(DU35:ER35),4)=MOD(COLUMN(DU35),4)),DU35:ER35)+SUMPRODUCT(--(MOD(COLUMN(ES35:FP35),4)=MOD(COLUMN(ES35),4)),ES35:FP35) -> 0 | FS35: =SUMPRODUCT(--(MOD(COLUMN(DU35:ER35),4)=MOD(COLUMN(DU35),4)),DU35:ER35)*#REF!+SUMPRODUCT(--(MOD(COLUMN(ES35:FP35),4)=MOD(COLUMN(ES35),4)),ES35:FP35)*#REF! -> #REF!
A36: НПО РОСТАР ООО | B36: Отсрочка 10 дней | C36: ВБК Восток | D36: Прасолов, Соловьёв | E36: =IF(ISBLANK(G36),"",IF($A$6:$A$64=$A36,COUNTIF($A$6:A36,$A36),"")) -> 2 | F36: 1 | G36: 6402250570 | H36: 6402250570 AC Тормоз дисковый ( правый ) | I36: =I35 -> 2048 | L36: =IF(K36="RUB",J36/ЮАНЬ,IF(K36="EUR",J36*ЕВРО/ЮАНЬ,"")) | N36: =IF(BP36>0,1,IF(BN36>0,2,)) -> 0 | U36: 0 | BL36: =SUMPRODUCT(--(MOD(COLUMN($O36:$AL36),4)=MOD(COLUMN($O36)+0,4)),$O36:$AL36) +SUMPRODUCT(--(MOD(COLUMN($AM36:$BJ36),4)=MOD(COLUMN($AM36)+0,4)),$AM36:$BJ36) -> 0 | BM36: =SUMPRODUCT(--(MOD(COLUMN($O36:$AL36),4)=MOD(COLUMN($O36)+0,4)),$O36:$AL36)*$I36 +SUMPRODUCT(--(MOD(COLUMN($AM36:$BJ36),4)=MOD(COLUMN($AM36)+0,4)),$AM36:$BJ36)*$I36 -> 0 | BN36: =SUMPRODUCT(--(MOD(COLUMN($O36:$AL36),4)=MOD(COLUMN($O36)+1,4)),$O36:$AL36) +SUMPRODUCT(--(MOD(COLUMN($AM36:$BJ36),4)=MOD(COLUMN($AM36)+1,4)),$AM36:$BJ36) -> 0 | BO36: =SUMPRODUCT(--(MOD(COLUMN($O36:$AL36),4)=MOD(COLUMN($O36)+1,4)),$O36:$AL36)*$I36 +SUMPRODUCT(--(MOD(COLUMN($AM36:$BJ36),4)=MOD(COLUMN($AM36)+1,4)),$AM36:$BJ36)*$I36 -> 0 | BP36: =SUMPRODUCT(--(MOD(COLUMN($O36:$AL36),4)=MOD(COLUMN($O36)+2,4)),$O36:$AL36) +SUMPRODUCT(--(MOD(COLUMN($AM36:$BJ36),4)=MOD(COLUMN($AM36)+2,4)),$AM36:$BJ36) -> 0 | BQ36: =SUMPRODUCT(--(MOD(COLUMN($O36:$AL36),4)=MOD(COLUMN($O36)+2,4)),$O36:$AL36)*$I36 +SUMPRODUCT(--(MOD(COLUMN($AM36:$BJ36),4)=MOD(COLUMN($AM36)+2,4)),$AM36:$BJ36)*$I36 -> 0 | DQ36: =SUMPRODUCT(--(MOD(COLUMN(BT36:CQ36),4)=MOD(COLUMN(BT36),4)),BT36:CQ36)+SUMPRODUCT(--(MOD(COLUMN(CR36:DO36),4)=MOD(COLUMN(CR36),4)),CR36:DO36) -> 0 | DR36: =SUMPRODUCT(--(MOD(COLUMN(BT36:CQ36),4)=MOD(COLUMN(BT36),4)),BT36:CQ36)*#REF!+SUMPRODUCT(--(MOD(COLUMN(CR36:DO36),4)=MOD(COLUMN(CR36),4)),CR36:DO36)*#REF! -> #REF! | FR36: =SUMPRODUCT(--(MOD(COLUMN(DU36:ER36),4)=MOD(COLUMN(DU36),4)),DU36:ER36)+SUMPRODUCT(--(MOD(COLUMN(ES36:FP36),4)=MOD(COLUMN(ES36),4)),ES36:FP36) -> 0 | FS36: =SUMPRODUCT(--(MOD(COLUMN(DU36:ER36),4)=MOD(COLUMN(DU36),4)),DU36:ER36)*#REF!+SUMPRODUCT(--(MOD(COLUMN(ES36:FP36),4)=MOD(COLUMN(ES36),4)),ES36:FP36)*#REF! -> #REF!
A37: НПО РОСТАР ООО | B37: Отсрочка 10 дней | C37: ВБК Восток | D37: Прасолов, Соловьёв | E37: =IF(ISBLANK(G37),"",IF($A$6:$A$64=$A37,COUNTIF($A$6:A37,$A37),"")) -> 3 | F37: 1 | G37: 4410328080 | H37: Датчик АБС, 0,4 м | I37: =84/НДС_20 -> 70 | L37: =IF(K37="RUB",J37/ЮАНЬ,IF(K37="EUR",J37*ЕВРО/ЮАНЬ,"")) | N37: =IF(BP37>0,1,IF(BN37>0,2,)) -> 0 | U37: 0 | BL37: =SUMPRODUCT(--(MOD(COLUMN($O37:$AL37),4)=MOD(COLUMN($O37)+0,4)),$O37:$AL37) +SUMPRODUCT(--(MOD(COLUMN($AM37:$BJ37),4)=MOD(COLUMN($AM37)+0,4)),$AM37:$BJ37) -> 0 | BM37: =SUMPRODUCT(--(MOD(COLUMN($O37:$AL37),4)=MOD(COLUMN($O37)+0,4)),$O37:$AL37)*$I37 +SUMPRODUCT(--(MOD(COLUMN($AM37:$BJ37),4)=MOD(COLUMN($AM37)+0,4)),$AM37:$BJ37)*$I37 -> 0 | BN37: =SUMPRODUCT(--(MOD(COLUMN($O37:$AL37),4)=MOD(COLUMN($O37)+1,4)),$O37:$AL37) +SUMPRODUCT(--(MOD(COLUMN($AM37:$BJ37),4)=MOD(COLUMN($AM37)+1,4)),$AM37:$BJ37) -> 0 | BO37: =SUMPRODUCT(--(MOD(COLUMN($O37:$AL37),4)=MOD(COLUMN($O37)+1,4)),$O37:$AL37)*$I37 +SUMPRODUCT(--(MOD(COLUMN($AM37:$BJ37),4)=MOD(COLUMN($AM37)+1,4)),$AM37:$BJ37)*$I37 -> 0 | BP37: =SUMPRODUCT(--(MOD(COLUMN($O37:$AL37),4)=MOD(COLUMN($O37)+2,4)),$O37:$AL37) +SUMPRODUCT(--(MOD(COLUMN($AM37:$BJ37),4)=MOD(COLUMN($AM37)+2,4)),$AM37:$BJ37) -> 0 | BQ37: =SUMPRODUCT(--(MOD(COLUMN($O37:$AL37),4)=MOD(COLUMN($O37)+2,4)),$O37:$AL37)*$I37 +SUMPRODUCT(--(MOD(COLUMN($AM37:$BJ37),4)=MOD(COLUMN($AM37)+2,4)),$AM37:$BJ37)*$I37 -> 0 | DQ37: =SUMPRODUCT(--(MOD(COLUMN(BT37:CQ37),4)=MOD(COLUMN(BT37),4)),BT37:CQ37)+SUMPRODUCT(--(MOD(COLUMN(CR37:DO37),4)=MOD(COLUMN(CR37),4)),CR37:DO37) -> 0 | DR37: =SUMPRODUCT(--(MOD(COLUMN(BT37:CQ37),4)=MOD(COLUMN(BT37),4)),BT37:CQ37)*#REF!+SUMPRODUCT(--(MOD(COLUMN(CR37:DO37),4)=MOD(COLUMN(CR37),4)),CR37:DO37)*#REF! -> #REF! | FR37: =SUMPRODUCT(--(MOD(COLUMN(DU37:ER37),4)=MOD(COLUMN(DU37),4)),DU37:ER37)+SUMPRODUCT(--(MOD(COLUMN(ES37:FP37),4)=MOD(COLUMN(ES37),4)),ES37:FP37) -> 0 | FS37: =SUMPRODUCT(--(MOD(COLUMN(DU37:ER37),4)=MOD(COLUMN(DU37),4)),DU37:ER37)*#REF!+SUMPRODUCT(--(MOD(COLUMN(ES37:FP37),4)=MOD(COLUMN(ES37),4)),ES37:FP37)*#REF! -> #REF!
A38: НПО РОСТАР ООО | B38: Отсрочка 10 дней | C38: ВБК Восток | D38: Прасолов, Соловьёв | E38: =IF(ISBLANK(G38),"",IF($A$6:$A$64=$A38,COUNTIF($A$6:A38,$A38),"")) -> 4 | F38: 1 | G38: 8997598154 | H38: Втулка датчика АБС | I38: 6.44 | L38: =IF(K38="RUB",J38/ЮАНЬ,IF(K38="EUR",J38*ЕВРО/ЮАНЬ,"")) | N38: =IF(BP38>0,1,IF(BN38>0,2,)) -> 0 | U38: 0 | BL38: =SUMPRODUCT(--(MOD(COLUMN($O38:$AL38),4)=MOD(COLUMN($O38)+0,4)),$O38:$AL38) +SUMPRODUCT(--(MOD(COLUMN($AM38:$BJ38),4)=MOD(COLUMN($AM38)+0,4)),$AM38:$BJ38) -> 0 | BM38: =SUMPRODUCT(--(MOD(COLUMN($O38:$AL38),4)=MOD(COLUMN($O38)+0,4)),$O38:$AL38)*$I38 +SUMPRODUCT(--(MOD(COLUMN($AM38:$BJ38),4)=MOD(COLUMN($AM38)+0,4)),$AM38:$BJ38)*$I38 -> 0 | BN38: =SUMPRODUCT(--(MOD(COLUMN($O38:$AL38),4)=MOD(COLUMN($O38)+1,4)),$O38:$AL38) +SUMPRODUCT(--(MOD(COLUMN($AM38:$BJ38),4)=MOD(COLUMN($AM38)+1,4)),$AM38:$BJ38) -> 0 | BO38: =SUMPRODUCT(--(MOD(COLUMN($O38:$AL38),4)=MOD(COLUMN($O38)+1,4)),$O38:$AL38)*$I38 +SUMPRODUCT(--(MOD(COLUMN($AM38:$BJ38),4)=MOD(COLUMN($AM38)+1,4)),$AM38:$BJ38)*$I38 -> 0 | BP38: =SUMPRODUCT(--(MOD(COLUMN($O38:$AL38),4)=MOD(COLUMN($O38)+2,4)),$O38:$AL38) +SUMPRODUCT(--(MOD(COLUMN($AM38:$BJ38),4)=MOD(COLUMN($AM38)+2,4)),$AM38:$BJ38) -> 0 | BQ38: =SUMPRODUCT(--(MOD(COLUMN($O38:$AL38),4)=MOD(COLUMN($O38)+2,4)),$O38:$AL38)*$I38 +SUMPRODUCT(--(MOD(COLUMN($AM38:$BJ38),4)=MOD(COLUMN($AM38)+2,4)),$AM38:$BJ38)*$I38 -> 0 | DQ38: =SUMPRODUCT(--(MOD(COLUMN(BT38:CQ38),4)=MOD(COLUMN(BT38),4)),BT38:CQ38)+SUMPRODUCT(--(MOD(COLUMN(CR38:DO38),4)=MOD(COLUMN(CR38),4)),CR38:DO38) -> 0 | DR38: =SUMPRODUCT(--(MOD(COLUMN(BT38:CQ38),4)=MOD(COLUMN(BT38),4)),BT38:CQ38)*#REF!+SUMPRODUCT(--(MOD(COLUMN(CR38:DO38),4)=MOD(COLUMN(CR38),4)),CR38:DO38)*#REF! -> #REF! | FR38: =SUMPRODUCT(--(MOD(COLUMN(DU38:ER38),4)=MOD(COLUMN(DU38),4)),DU38:ER38)+SUMPRODUCT(--(MOD(COLUMN(ES38:FP38),4)=MOD(COLUMN(ES38),4)),ES38:FP38) -> 0 | FS38: =SUMPRODUCT(--(MOD(COLUMN(DU38:ER38),4)=MOD(COLUMN(DU38),4)),DU38:ER38)*#REF!+SUMPRODUCT(--(MOD(COLUMN(ES38:FP38),4)=MOD(COLUMN(ES38),4)),ES38:FP38)*#REF! -> #REF!
A39: НПО РОСТАР ООО | B39: Отсрочка 10 дней | C39: ВБК Восток | D39: Прасолов, Соловьёв | E39: =IF(ISBLANK(G39),"",IF($A$6:$A$64=$A39,COUNTIF($A$6:A39,$A39),"")) -> 5 | F39: 1 | G39: 4235041001 | H39: Тормозная камера, тип 20 | I39: =163.08/НДС_20 -> 135.9 | L39: =IF(K39="RUB",J39/ЮАНЬ,IF(K39="EUR",J39*ЕВРО/ЮАНЬ,"")) | N39: =IF(BP39>0,1,IF(BN39>0,2,)) -> 0 | U39: 0 | BL39: =SUMPRODUCT(--(MOD(COLUMN($O39:$AL39),4)=MOD(COLUMN($O39)+0,4)),$O39:$AL39) +SUMPRODUCT(--(MOD(COLUMN($AM39:$BJ39),4)=MOD(COLUMN($AM39)+0,4)),$AM39:$BJ39) -> 0 | BM39: =SUMPRODUCT(--(MOD(COLUMN($O39:$AL39),4)=MOD(COLUMN($O39)+0,4)),$O39:$AL39)*$I39 +SUMPRODUCT(--(MOD(COLUMN($AM39:$BJ39),4)=MOD(COLUMN($AM39)+0,4)),$AM39:$BJ39)*$I39 -> 0 | BN39: =SUMPRODUCT(--(MOD(COLUMN($O39:$AL39),4)=MOD(COLUMN($O39)+1,4)),$O39:$AL39) +SUMPRODUCT(--(MOD(COLUMN($AM39:$BJ39),4)=MOD(COLUMN($AM39)+1,4)),$AM39:$BJ39) -> 0 | BO39: =SUMPRODUCT(--(MOD(COLUMN($O39:$AL39),4)=MOD(COLUMN($O39)+1,4)),$O39:$AL39)*$I39 +SUMPRODUCT(--(MOD(COLUMN($AM39:$BJ39),4)=MOD(COLUMN($AM39)+1,4)),$AM39:$BJ39)*$I39 -> 0 | BP39: =SUMPRODUCT(--(MOD(COLUMN($O39:$AL39),4)=MOD(COLUMN($O39)+2,4)),$O39:$AL39) +SUMPRODUCT(--(MOD(COLUMN($AM39:$BJ39),4)=MOD(COLUMN($AM39)+2,4)),$AM39:$BJ39) -> 0 | BQ39: =SUMPRODUCT(--(MOD(COLUMN($O39:$AL39),4)=MOD(COLUMN($O39)+2,4)),$O39:$AL39)*$I39 +SUMPRODUCT(--(MOD(COLUMN($AM39:$BJ39),4)=MOD(COLUMN($AM39)+2,4)),$AM39:$BJ39)*$I39 -> 0 | DQ39: =SUMPRODUCT(--(MOD(COLUMN(BT39:CQ39),4)=MOD(COLUMN(BT39),4)),BT39:CQ39)+SUMPRODUCT(--(MOD(COLUMN(CR39:DO39),4)=MOD(COLUMN(CR39),4)),CR39:DO39) -> 0 | DR39: =SUMPRODUCT(--(MOD(COLUMN(BT39:CQ39),4)=MOD(COLUMN(BT39),4)),BT39:CQ39)*#REF!+SUMPRODUCT(--(MOD(COLUMN(CR39:DO39),4)=MOD(COLUMN(CR39),4)),CR39:DO39)*#REF! -> #REF! | FR39: =SUMPRODUCT(--(MOD(COLUMN(DU39:ER39),4)=MOD(COLUMN(DU39),4)),DU39:ER39)+SUMPRODUCT(--(MOD(COLUMN(ES39:FP39),4)=MOD(COLUMN(ES39),4)),ES39:FP39) -> 0 | FS39: =SUMPRODUCT(--(MOD(COLUMN(DU39:ER39),4)=MOD(COLUMN(DU39),4)),DU39:ER39)*#REF!+SUMPRODUCT(--(MOD(COLUMN(ES39:FP39),4)=MOD(COLUMN(ES39),4)),ES39:FP39)*#REF! -> #REF!
A40: НПО РОСТАР ООО | B40: Отсрочка 10 дней | C40: ВБК Восток | D40: Прасолов, Соловьёв | E40: =IF(ISBLANK(G40),"",IF($A$6:$A$64=$A40,COUNTIF($A$6:A40,$A40),"")) -> 6 | F40: 1 | G40: 9254800504 | H40: Энергоаккумулятор, тип 20/24 | I40: =373.98/НДС_20 -> 311.65 | L40: =IF(K40="RUB",J40/ЮАНЬ,IF(K40="EUR",J40*ЕВРО/ЮАНЬ,"")) | N40: =IF(BP40>0,1,IF(BN40>0,2,)) -> 0 | U40: 0 | BL40: =SUMPRODUCT(--(MOD(COLUMN($O40:$AL40),4)=MOD(COLUMN($O40)+0,4)),$O40:$AL40) +SUMPRODUCT(--(MOD(COLUMN($AM40:$BJ40),4)=MOD(COLUMN($AM40)+0,4)),$AM40:$BJ40) -> 0 | BM40: =SUMPRODUCT(--(MOD(COLUMN($O40:$AL40),4)=MOD(COLUMN($O40)+0,4)),$O40:$AL40)*$I40 +SUMPRODUCT(--(MOD(COLUMN($AM40:$BJ40),4)=MOD(COLUMN($AM40)+0,4)),$AM40:$BJ40)*$I40 -> 0 | BN40: =SUMPRODUCT(--(MOD(COLUMN($O40:$AL40),4)=MOD(COLUMN($O40)+1,4)),$O40:$AL40) +SUMPRODUCT(--(MOD(COLUMN($AM40:$BJ40),4)=MOD(COLUMN($AM40)+1,4)),$AM40:$BJ40) -> 0 | BO40: =SUMPRODUCT(--(MOD(COLUMN($O40:$AL40),4)=MOD(COLUMN($O40)+1,4)),$O40:$AL40)*$I40 +SUMPRODUCT(--(MOD(COLUMN($AM40:$BJ40),4)=MOD(COLUMN($AM40)+1,4)),$AM40:$BJ40)*$I40 -> 0 | BP40: =SUMPRODUCT(--(MOD(COLUMN($O40:$AL40),4)=MOD(COLUMN($O40)+2,4)),$O40:$AL40) +SUMPRODUCT(--(MOD(COLUMN($AM40:$BJ40),4)=MOD(COLUMN($AM40)+2,4)),$AM40:$BJ40) -> 0 | BQ40: =SUMPRODUCT(--(MOD(COLUMN($O40:$AL40),4)=MOD(COLUMN($O40)+2,4)),$O40:$AL40)*$I40 +SUMPRODUCT(--(MOD(COLUMN($AM40:$BJ40),4)=MOD(COLUMN($AM40)+2,4)),$AM40:$BJ40)*$I40 -> 0 | DQ40: =SUMPRODUCT(--(MOD(COLUMN(BT40:CQ40),4)=MOD(COLUMN(BT40),4)),BT40:CQ40)+SUMPRODUCT(--(MOD(COLUMN(CR40:DO40),4)=MOD(COLUMN(CR40),4)),CR40:DO40) -> 0 | DR40: =SUMPRODUCT(--(MOD(COLUMN(BT40:CQ40),4)=MOD(COLUMN(BT40),4)),BT40:CQ40)*#REF!+SUMPRODUCT(--(MOD(COLUMN(CR40:DO40),4)=MOD(COLUMN(CR40),4)),CR40:DO40)*#REF! -> #REF! | FR40: =SUMPRODUCT(--(MOD(COLUMN(DU40:ER40),4)=MOD(COLUMN(DU40),4)),DU40:ER40)+SUMPRODUCT(--(MOD(COLUMN(ES40:FP40),4)=MOD(COLUMN(ES40),4)),ES40:FP40) -> 0 | FS40: =SUMPRODUCT(--(MOD(COLUMN(DU40:ER40),4)=MOD(COLUMN(DU40),4)),DU40:ER40)*#REF!+SUMPRODUCT(--(MOD(COLUMN(ES40:FP40),4)=MOD(COLUMN(ES40),4)),ES40:FP40)*#REF! -> #REF!
A41: НПО РОСТАР ООО | E41: =IF(ISBLANK(G41),"",IF($A$6:$A$64=$A41,COUNTIF($A$6:A41,$A41),"")) | H41: Итого | L41: =IF(K41="RUB",J41/ЮАНЬ,IF(K41="EUR",J41*ЕВРО/ЮАНЬ,"")) | N41: =IF(BP41>0,1,IF(BN41>0,2,)) -> 0 | BL41: =SUMPRODUCT(--(MOD(COLUMN($O41:$AL41),4)=MOD(COLUMN($O41)+0,4)),$O41:$AL41) +SUMPRODUCT(--(MOD(COLUMN($AM41:$BJ41),4)=MOD(COLUMN($AM41)+0,4)),$AM41:$BJ41) -> 0 | BM41: =SUMPRODUCT(--(MOD(COLUMN($O41:$AL41),4)=MOD(COLUMN($O41)+0,4)),$O41:$AL41)*$I41 +SUMPRODUCT(--(MOD(COLUMN($AM41:$BJ41),4)=MOD(COLUMN($AM41)+0,4)),$AM41:$BJ41)*$I41 -> 0 | BN41: =SUMPRODUCT(--(MOD(COLUMN($O41:$AL41),4)=MOD(COLUMN($O41)+1,4)),$O41:$AL41) +SUMPRODUCT(--(MOD(COLUMN($AM41:$BJ41),4)=MOD(COLUMN($AM41)+1,4)),$AM41:$BJ41) -> 0 | BO41: =SUMPRODUCT(--(MOD(COLUMN($O41:$AL41),4)=MOD(COLUMN($O41)+1,4)),$O41:$AL41)*$I41 +SUMPRODUCT(--(MOD(COLUMN($AM41:$BJ41),4)=MOD(COLUMN($AM41)+1,4)),$AM41:$BJ41)*$I41 -> 0 | BP41: =SUMPRODUCT(--(MOD(COLUMN($O41:$AL41),4)=MOD(COLUMN($O41)+2,4)),$O41:$AL41) +SUMPRODUCT(--(MOD(COLUMN($AM41:$BJ41),4)=MOD(COLUMN($AM41)+2,4)),$AM41:$BJ41) -> 0 | BQ41: =SUMPRODUCT(--(MOD(COLUMN($O41:$AL41),4)=MOD(COLUMN($O41)+2,4)),$O41:$AL41)*$I41 +SUMPRODUCT(--(MOD(COLUMN($AM41:$BJ41),4)=MOD(COLUMN($AM41)+2,4)),$AM41:$BJ41)*$I41 -> 0 | DQ41: =SUMPRODUCT(--(MOD(COLUMN(BT41:CQ41),4)=MOD(COLUMN(BT41),4)),BT41:CQ41)+SUMPRODUCT(--(MOD(COLUMN(CR41:DO41),4)=MOD(COLUMN(CR41),4)),CR41:DO41) -> 0 | DR41: =SUMPRODUCT(--(MOD(COLUMN(BT41:CQ41),4)=MOD(COLUMN(BT41),4)),BT41:CQ41)*#REF!+SUMPRODUCT(--(MOD(COLUMN(CR41:DO41),4)=MOD(COLUMN(CR41),4)),CR41:DO41)*#REF! -> #REF! | FR41: =SUMPRODUCT(--(MOD(COLUMN(DU41:ER41),4)=MOD(COLUMN(DU41),4)),DU41:ER41)+SUMPRODUCT(--(MOD(COLUMN(ES41:FP41),4)=MOD(COLUMN(ES41),4)),ES41:FP41) -> 0 | FS41: =SUMPRODUCT(--(MOD(COLUMN(DU41:ER41),4)=MOD(COLUMN(DU41),4)),DU41:ER41)*#REF!+SUMPRODUCT(--(MOD(COLUMN(ES41:FP41),4)=MOD(COLUMN(ES41),4)),ES41:FP41)*#REF! -> #REF!
A42: НПО РОСТАР ООО | E42: =IF(ISBLANK(G42),"",IF($A$6:$A$64=$A42,COUNTIF($A$6:A42,$A42),"")) | L42: =IF(K42="RUB",J42/ЮАНЬ,IF(K42="EUR",J42*ЕВРО/ЮАНЬ,"")) | N42: =IF(BP42>0,1,IF(BN42>0,2,)) -> 0 | BL42: =SUMPRODUCT(--(MOD(COLUMN($O42:$AL42),4)=MOD(COLUMN($O42)+0,4)),$O42:$AL42) +SUMPRODUCT(--(MOD(COLUMN($AM42:$BJ42),4)=MOD(COLUMN($AM42)+0,4)),$AM42:$BJ42) -> 0 | BM42: =SUMPRODUCT(--(MOD(COLUMN($O42:$AL42),4)=MOD(COLUMN($O42)+0,4)),$O42:$AL42)*$I42 +SUMPRODUCT(--(MOD(COLUMN($AM42:$BJ42),4)=MOD(COLUMN($AM42)+0,4)),$AM42:$BJ42)*$I42 -> 0 | BN42: =SUMPRODUCT(--(MOD(COLUMN($O42:$AL42),4)=MOD(COLUMN($O42)+1,4)),$O42:$AL42) +SUMPRODUCT(--(MOD(COLUMN($AM42:$BJ42),4)=MOD(COLUMN($AM42)+1,4)),$AM42:$BJ42) -> 0 | BO42: =SUMPRODUCT(--(MOD(COLUMN($O42:$AL42),4)=MOD(COLUMN($O42)+1,4)),$O42:$AL42)*$I42 +SUMPRODUCT(--(MOD(COLUMN($AM42:$BJ42),4)=MOD(COLUMN($AM42)+1,4)),$AM42:$BJ42)*$I42 -> 0 | BP42: =SUMPRODUCT(--(MOD(COLUMN($O42:$AL42),4)=MOD(COLUMN($O42)+2,4)),$O42:$AL42) +SUMPRODUCT(--(MOD(COLUMN($AM42:$BJ42),4)=MOD(COLUMN($AM42)+2,4)),$AM42:$BJ42) -> 0 | BQ42: =SUMPRODUCT(--(MOD(COLUMN($O42:$AL42),4)=MOD(COLUMN($O42)+2,4)),$O42:$AL42)*$I42 +SUMPRODUCT(--(MOD(COLUMN($AM42:$BJ42),4)=MOD(COLUMN($AM42)+2,4)),$AM42:$BJ42)*$I42 -> 0 | DQ42: =SUMPRODUCT(--(MOD(COLUMN(BT42:CQ42),4)=MOD(COLUMN(BT42),4)),BT42:CQ42)+SUMPRODUCT(--(MOD(COLUMN(CR42:DO42),4)=MOD(COLUMN(CR42),4)),CR42:DO42) -> 0 | DR42: =SUMPRODUCT(--(MOD(COLUMN(BT42:CQ42),4)=MOD(COLUMN(BT42),4)),BT42:CQ42)*#REF!+SUMPRODUCT(--(MOD(COLUMN(CR42:DO42),4)=MOD(COLUMN(CR42),4)),CR42:DO42)*#REF! -> #REF! | FR42: =SUMPRODUCT(--(MOD(COLUMN(DU42:ER42),4)=MOD(COLUMN(DU42),4)),DU42:ER42)+SUMPRODUCT(--(MOD(COLUMN(ES42:FP42),4)=MOD(COLUMN(ES42),4)),ES42:FP42) -> 0 | FS42: =SUMPRODUCT(--(MOD(COLUMN(DU42:ER42),4)=MOD(COLUMN(DU42),4)),DU42:ER42)*#REF!+SUMPRODUCT(--(MOD(COLUMN(ES42:FP42),4)=MOD(COLUMN(ES42),4)),ES42:FP42)*#REF! -> #REF!
A43: ПЛАНТ ООО | B43: Предоплата 50% | C43: ВБК Восток | D43: Прасолов, Соловьёв | E43: =IF(ISBLANK(G43),"",IF($A$6:$A$64=$A43,COUNTIF($A$6:A43,$A43),"")) -> 1 | F43: 1 | G43: 6402250560 | H43: 6402250560 AC Тормоз дисковый ( левый ) | I43: 2068 | L43: =IF(K43="RUB",J43/ЮАНЬ,IF(K43="EUR",J43*ЕВРО/ЮАНЬ,"")) | N43: =IF(BP43>0,1,IF(BN43>0,2,)) -> 1 | U43: 0 | X43: =24+27 -> 51 | Y43: 51 | AB43: =(15+30+29) -> 74 | AC43: 74 | AF43: =20 -> 20 | AG43: 20 | AJ43: =(146-(27+15+30+29+20)) -> 25 | AN43: 50 | BL43: =SUMPRODUCT(--(MOD(COLUMN($O43:$AL43),4)=MOD(COLUMN($O43)+0,4)),$O43:$AL43) +SUMPRODUCT(--(MOD(COLUMN($AM43:$BJ43),4)=MOD(COLUMN($AM43)+0,4)),$AM43:$BJ43) -> 0 | BM43: =SUMPRODUCT(--(MOD(COLUMN($O43:$AL43),4)=MOD(COLUMN($O43)+0,4)),$O43:$AL43)*$I43 +SUMPRODUCT(--(MOD(COLUMN($AM43:$BJ43),4)=MOD(COLUMN($AM43)+0,4)),$AM43:$BJ43)*$I43 -> 0 | BN43: =SUMPRODUCT(--(MOD(COLUMN($O43:$AL43),4)=MOD(COLUMN($O43)+1,4)),$O43:$AL43) +SUMPRODUCT(--(MOD(COLUMN($AM43:$BJ43),4)=MOD(COLUMN($AM43)+1,4)),$AM43:$BJ43) -> 220 | BO43: =SUMPRODUCT(--(MOD(COLUMN($O43:$AL43),4)=MOD(COLUMN($O43)+1,4)),$O43:$AL43)*$I43 +SUMPRODUCT(--(MOD(COLUMN($AM43:$BJ43),4)=MOD(COLUMN($AM43)+1,4)),$AM43:$BJ43)*$I43 -> 454960 | BP43: =SUMPRODUCT(--(MOD(COLUMN($O43:$AL43),4)=MOD(COLUMN($O43)+2,4)),$O43:$AL43) +SUMPRODUCT(--(MOD(COLUMN($AM43:$BJ43),4)=MOD(COLUMN($AM43)+2,4)),$AM43:$BJ43) -> 145 | BQ43: =SUMPRODUCT(--(MOD(COLUMN($O43:$AL43),4)=MOD(COLUMN($O43)+2,4)),$O43:$AL43)*$I43 +SUMPRODUCT(--(MOD(COLUMN($AM43:$BJ43),4)=MOD(COLUMN($AM43)+2,4)),$AM43:$BJ43)*$I43 -> 299860
A44: ПЛАНТ ООО | B44: Предоплата 50% | C44: ВБК Восток | D44: Прасолов, Соловьёв | E44: =IF(ISBLANK(G44),"",IF($A$6:$A$64=$A44,COUNTIF($A$6:A44,$A44),"")) -> 2 | F44: 1 | G44: 6402250570 | H44: 6402250570 AC Тормоз дисковый ( правый ) | I44: =I43 -> 2068 | L44: =IF(K44="RUB",J44/ЮАНЬ,IF(K44="EUR",J44*ЕВРО/ЮАНЬ,"")) | N44: =IF(BP44>0,1,IF(BN44>0,2,)) -> 1 | U44: 0 | X44: =X43 -> 51 | Y44: 51 | AB44: =AB43 -> 74 | AC44: 74 | AF44: =AF43 -> 20 | AG44: 20 | AJ44: =AJ43 -> 25 | AN44: =AN43 -> 50 | BL44: =SUMPRODUCT(--(MOD(COLUMN($O44:$AL44),4)=MOD(COLUMN($O44)+0,4)),$O44:$AL44) +SUMPRODUCT(--(MOD(COLUMN($AM44:$BJ44),4)=MOD(COLUMN($AM44)+0,4)),$AM44:$BJ44) -> 0 | BM44: =SUMPRODUCT(--(MOD(COLUMN($O44:$AL44),4)=MOD(COLUMN($O44)+0,4)),$O44:$AL44)*$I44 +SUMPRODUCT(--(MOD(COLUMN($AM44:$BJ44),4)=MOD(COLUMN($AM44)+0,4)),$AM44:$BJ44)*$I44 -> 0 | BN44: =SUMPRODUCT(--(MOD(COLUMN($O44:$AL44),4)=MOD(COLUMN($O44)+1,4)),$O44:$AL44) +SUMPRODUCT(--(MOD(COLUMN($AM44:$BJ44),4)=MOD(COLUMN($AM44)+1,4)),$AM44:$BJ44) -> 220 | BO44: =SUMPRODUCT(--(MOD(COLUMN($O44:$AL44),4)=MOD(COLUMN($O44)+1,4)),$O44:$AL44)*$I44 +SUMPRODUCT(--(MOD(COLUMN($AM44:$BJ44),4)=MOD(COLUMN($AM44)+1,4)),$AM44:$BJ44)*$I44 -> 454960 | BP44: =SUMPRODUCT(--(MOD(COLUMN($O44:$AL44),4)=MOD(COLUMN($O44)+2,4)),$O44:$AL44) +SUMPRODUCT(--(MOD(COLUMN($AM44:$BJ44),4)=MOD(COLUMN($AM44)+2,4)),$AM44:$BJ44) -> 145 | BQ44: =SUMPRODUCT(--(MOD(COLUMN($O44:$AL44),4)=MOD(COLUMN($O44)+2,4)),$O44:$AL44)*$I44 +SUMPRODUCT(--(MOD(COLUMN($AM44:$BJ44),4)=MOD(COLUMN($AM44)+2,4)),$AM44:$BJ44)*$I44 -> 299860
A45: ПЛАНТ ООО | B45: Предоплата 50% | C45: ВБК Восток | D45: Прасолов, Соловьёв | E45: =IF(ISBLANK(G45),"",IF($A$6:$A$64=$A45,COUNTIF($A$6:A45,$A45),"")) -> 3 | F45: 1 | G45: 4410328080 | H45: Датчик АБС, 0,4 м | I45: =84/НДС_20 -> 70 | L45: =IF(K45="RUB",J45/ЮАНЬ,IF(K45="EUR",J45*ЕВРО/ЮАНЬ,"")) | N45: =IF(BP45>0,1,IF(BN45>0,2,)) -> 0 | U45: 0 | BL45: =SUMPRODUCT(--(MOD(COLUMN($O45:$AL45),4)=MOD(COLUMN($O45)+0,4)),$O45:$AL45) +SUMPRODUCT(--(MOD(COLUMN($AM45:$BJ45),4)=MOD(COLUMN($AM45)+0,4)),$AM45:$BJ45) -> 0 | BM45: =SUMPRODUCT(--(MOD(COLUMN($O45:$AL45),4)=MOD(COLUMN($O45)+0,4)),$O45:$AL45)*$I45 +SUMPRODUCT(--(MOD(COLUMN($AM45:$BJ45),4)=MOD(COLUMN($AM45)+0,4)),$AM45:$BJ45)*$I45 -> 0 | BN45: =SUMPRODUCT(--(MOD(COLUMN($O45:$AL45),4)=MOD(COLUMN($O45)+1,4)),$O45:$AL45) +SUMPRODUCT(--(MOD(COLUMN($AM45:$BJ45),4)=MOD(COLUMN($AM45)+1,4)),$AM45:$BJ45) -> 0 | BO45: =SUMPRODUCT(--(MOD(COLUMN($O45:$AL45),4)=MOD(COLUMN($O45)+1,4)),$O45:$AL45)*$I45 +SUMPRODUCT(--(MOD(COLUMN($AM45:$BJ45),4)=MOD(COLUMN($AM45)+1,4)),$AM45:$BJ45)*$I45 -> 0 | BP45: =SUMPRODUCT(--(MOD(COLUMN($O45:$AL45),4)=MOD(COLUMN($O45)+2,4)),$O45:$AL45) +SUMPRODUCT(--(MOD(COLUMN($AM45:$BJ45),4)=MOD(COLUMN($AM45)+2,4)),$AM45:$BJ45) -> 0 | BQ45: =SUMPRODUCT(--(MOD(COLUMN($O45:$AL45),4)=MOD(COLUMN($O45)+2,4)),$O45:$AL45)*$I45 +SUMPRODUCT(--(MOD(COLUMN($AM45:$BJ45),4)=MOD(COLUMN($AM45)+2,4)),$AM45:$BJ45)*$I45 -> 0
A46: ПЛАНТ ООО | B46: Предоплата 50% | C46: ВБК Восток | D46: Прасолов, Соловьёв | E46: =IF(ISBLANK(G46),"",IF($A$6:$A$64=$A46,COUNTIF($A$6:A46,$A46),"")) -> 4 | F46: 1 | G46: 8997598154 | H46: Втулка датчика АБС | I46: =8.4/НДС_20 -> 7 | L46: =IF(K46="RUB",J46/ЮАНЬ,IF(K46="EUR",J46*ЕВРО/ЮАНЬ,"")) | N46: =IF(BP46>0,1,IF(BN46>0,2,)) -> 0 | U46: 0 | BL46: =SUMPRODUCT(--(MOD(COLUMN($O46:$AL46),4)=MOD(COLUMN($O46)+0,4)),$O46:$AL46) +SUMPRODUCT(--(MOD(COLUMN($AM46:$BJ46),4)=MOD(COLUMN($AM46)+0,4)),$AM46:$BJ46) -> 0 | BM46: =SUMPRODUCT(--(MOD(COLUMN($O46:$AL46),4)=MOD(COLUMN($O46)+0,4)),$O46:$AL46)*$I46 +SUMPRODUCT(--(MOD(COLUMN($AM46:$BJ46),4)=MOD(COLUMN($AM46)+0,4)),$AM46:$BJ46)*$I46 -> 0 | BN46: =SUMPRODUCT(--(MOD(COLUMN($O46:$AL46),4)=MOD(COLUMN($O46)+1,4)),$O46:$AL46) +SUMPRODUCT(--(MOD(COLUMN($AM46:$BJ46),4)=MOD(COLUMN($AM46)+1,4)),$AM46:$BJ46) -> 0 | BO46: =SUMPRODUCT(--(MOD(COLUMN($O46:$AL46),4)=MOD(COLUMN($O46)+1,4)),$O46:$AL46)*$I46 +SUMPRODUCT(--(MOD(COLUMN($AM46:$BJ46),4)=MOD(COLUMN($AM46)+1,4)),$AM46:$BJ46)*$I46 -> 0 | BP46: =SUMPRODUCT(--(MOD(COLUMN($O46:$AL46),4)=MOD(COLUMN($O46)+2,4)),$O46:$AL46) +SUMPRODUCT(--(MOD(COLUMN($AM46:$BJ46),4)=MOD(COLUMN($AM46)+2,4)),$AM46:$BJ46) -> 0 | BQ46: =SUMPRODUCT(--(MOD(COLUMN($O46:$AL46),4)=MOD(COLUMN($O46)+2,4)),$O46:$AL46)*$I46 +SUMPRODUCT(--(MOD(COLUMN($AM46:$BJ46),4)=MOD(COLUMN($AM46)+2,4)),$AM46:$BJ46)*$I46 -> 0
A47: ПЛАНТ ООО | B47: Предоплата 50% | C47: ВБК Восток | D47: Прасолов, Соловьёв | E47: =IF(ISBLANK(G47),"",IF($A$6:$A$64=$A47,COUNTIF($A$6:A47,$A47),"")) -> 5 | F47: 1 | G47: 4235041001 | H47: Тормозная камера, тип 20 | I47: =163.08/НДС_20 -> 135.9 | L47: =IF(K47="RUB",J47/ЮАНЬ,IF(K47="EUR",J47*ЕВРО/ЮАНЬ,"")) | N47: =IF(BP47>0,1,IF(BN47>0,2,)) -> 0 | U47: 0 | BL47: =SUMPRODUCT(--(MOD(COLUMN($O47:$AL47),4)=MOD(COLUMN($O47)+0,4)),$O47:$AL47) +SUMPRODUCT(--(MOD(COLUMN($AM47:$BJ47),4)=MOD(COLUMN($AM47)+0,4)),$AM47:$BJ47) -> 0 | BM47: =SUMPRODUCT(--(MOD(COLUMN($O47:$AL47),4)=MOD(COLUMN($O47)+0,4)),$O47:$AL47)*$I47 +SUMPRODUCT(--(MOD(COLUMN($AM47:$BJ47),4)=MOD(COLUMN($AM47)+0,4)),$AM47:$BJ47)*$I47 -> 0 | BN47: =SUMPRODUCT(--(MOD(COLUMN($O47:$AL47),4)=MOD(COLUMN($O47)+1,4)),$O47:$AL47) +SUMPRODUCT(--(MOD(COLUMN($AM47:$BJ47),4)=MOD(COLUMN($AM47)+1,4)),$AM47:$BJ47) -> 0 | BO47: =SUMPRODUCT(--(MOD(COLUMN($O47:$AL47),4)=MOD(COLUMN($O47)+1,4)),$O47:$AL47)*$I47 +SUMPRODUCT(--(MOD(COLUMN($AM47:$BJ47),4)=MOD(COLUMN($AM47)+1,4)),$AM47:$BJ47)*$I47 -> 0 | BP47: =SUMPRODUCT(--(MOD(COLUMN($O47:$AL47),4)=MOD(COLUMN($O47)+2,4)),$O47:$AL47) +SUMPRODUCT(--(MOD(COLUMN($AM47:$BJ47),4)=MOD(COLUMN($AM47)+2,4)),$AM47:$BJ47) -> 0 | BQ47: =SUMPRODUCT(--(MOD(COLUMN($O47:$AL47),4)=MOD(COLUMN($O47)+2,4)),$O47:$AL47)*$I47 +SUMPRODUCT(--(MOD(COLUMN($AM47:$BJ47),4)=MOD(COLUMN($AM47)+2,4)),$AM47:$BJ47)*$I47 -> 0
A48: ПЛАНТ ООО | B48: Предоплата 50% | C48: ВБК Восток | D48: Прасолов, Соловьёв | E48: =IF(ISBLANK(G48),"",IF($A$6:$A$64=$A48,COUNTIF($A$6:A48,$A48),"")) -> 6 | F48: 1 | G48: 9254800504 | H48: Энергоаккумулятор, тип 20/24 | I48: =373.98/НДС_20 -> 311.65 | L48: =IF(K48="RUB",J48/ЮАНЬ,IF(K48="EUR",J48*ЕВРО/ЮАНЬ,"")) | N48: =IF(BP48>0,1,IF(BN48>0,2,)) -> 0 | U48: 0 | BL48: =SUMPRODUCT(--(MOD(COLUMN($O48:$AL48),4)=MOD(COLUMN($O48)+0,4)),$O48:$AL48) +SUMPRODUCT(--(MOD(COLUMN($AM48:$BJ48),4)=MOD(COLUMN($AM48)+0,4)),$AM48:$BJ48) -> 0 | BM48: =SUMPRODUCT(--(MOD(COLUMN($O48:$AL48),4)=MOD(COLUMN($O48)+0,4)),$O48:$AL48)*$I48 +SUMPRODUCT(--(MOD(COLUMN($AM48:$BJ48),4)=MOD(COLUMN($AM48)+0,4)),$AM48:$BJ48)*$I48 -> 0 | BN48: =SUMPRODUCT(--(MOD(COLUMN($O48:$AL48),4)=MOD(COLUMN($O48)+1,4)),$O48:$AL48) +SUMPRODUCT(--(MOD(COLUMN($AM48:$BJ48),4)=MOD(COLUMN($AM48)+1,4)),$AM48:$BJ48) -> 0 | BO48: =SUMPRODUCT(--(MOD(COLUMN($O48:$AL48),4)=MOD(COLUMN($O48)+1,4)),$O48:$AL48)*$I48 +SUMPRODUCT(--(MOD(COLUMN($AM48:$BJ48),4)=MOD(COLUMN($AM48)+1,4)),$AM48:$BJ48)*$I48 -> 0 | BP48: =SUMPRODUCT(--(MOD(COLUMN($O48:$AL48),4)=MOD(COLUMN($O48)+2,4)),$O48:$AL48) +SUMPRODUCT(--(MOD(COLUMN($AM48:$BJ48),4)=MOD(COLUMN($AM48)+2,4)),$AM48:$BJ48) -> 0 | BQ48: =SUMPRODUCT(--(MOD(COLUMN($O48:$AL48),4)=MOD(COLUMN($O48)+2,4)),$O48:$AL48)*$I48 +SUMPRODUCT(--(MOD(COLUMN($AM48:$BJ48),4)=MOD(COLUMN($AM48)+2,4)),$AM48:$BJ48)*$I48 -> 0
A49: ПЛАНТ ООО | E49: =IF(ISBLANK(G49),"",IF($A$6:$A$64=$A49,COUNTIF($A$6:A49,$A49),"")) | H49: Итого | L49: =IF(K49="RUB",J49/ЮАНЬ,IF(K49="EUR",J49*ЕВРО/ЮАНЬ,"")) | N49: =IF(BP49>0,1,IF(BN49>0,2,)) -> 0 | BL49: =SUMPRODUCT(--(MOD(COLUMN($O49:$AL49),4)=MOD(COLUMN($O49)+0,4)),$O49:$AL49) +SUMPRODUCT(--(MOD(COLUMN($AM49:$BJ49),4)=MOD(COLUMN($AM49)+0,4)),$AM49:$BJ49) -> 0 | BM49: =SUMPRODUCT(--(MOD(COLUMN($O49:$AL49),4)=MOD(COLUMN($O49)+0,4)),$O49:$AL49)*$I49 +SUMPRODUCT(--(MOD(COLUMN($AM49:$BJ49),4)=MOD(COLUMN($AM49)+0,4)),$AM49:$BJ49)*$I49 -> 0 | BN49: =SUMPRODUCT(--(MOD(COLUMN($O49:$AL49),4)=MOD(COLUMN($O49)+1,4)),$O49:$AL49) +SUMPRODUCT(--(MOD(COLUMN($AM49:$BJ49),4)=MOD(COLUMN($AM49)+1,4)),$AM49:$BJ49) -> 0 | BO49: =SUMPRODUCT(--(MOD(COLUMN($O49:$AL49),4)=MOD(COLUMN($O49)+1,4)),$O49:$AL49)*$I49 +SUMPRODUCT(--(MOD(COLUMN($AM49:$BJ49),4)=MOD(COLUMN($AM49)+1,4)),$AM49:$BJ49)*$I49 -> 0 | BP49: =SUMPRODUCT(--(MOD(COLUMN($O49:$AL49),4)=MOD(COLUMN($O49)+2,4)),$O49:$AL49) +SUMPRODUCT(--(MOD(COLUMN($AM49:$BJ49),4)=MOD(COLUMN($AM49)+2,4)),$AM49:$BJ49) -> 0 | BQ49: =SUMPRODUCT(--(MOD(COLUMN($O49:$AL49),4)=MOD(COLUMN($O49)+2,4)),$O49:$AL49)*$I49 +SUMPRODUCT(--(MOD(COLUMN($AM49:$BJ49),4)=MOD(COLUMN($AM49)+2,4)),$AM49:$BJ49)*$I49 -> 0
A50: ПЛАНТ ООО | E50: =IF(ISBLANK(G50),"",IF($A$6:$A$64=$A50,COUNTIF($A$6:A50,$A50),"")) | N50: =IF(BP50>0,1,IF(BN50>0,2,)) -> 0 | BL50: =SUMPRODUCT(--(MOD(COLUMN($O50:$AL50),4)=MOD(COLUMN($O50)+0,4)),$O50:$AL50) +SUMPRODUCT(--(MOD(COLUMN($AM50:$BJ50),4)=MOD(COLUMN($AM50)+0,4)),$AM50:$BJ50) -> 0 | BM50: =SUMPRODUCT(--(MOD(COLUMN($O50:$AL50),4)=MOD(COLUMN($O50)+0,4)),$O50:$AL50)*$I50 +SUMPRODUCT(--(MOD(COLUMN($AM50:$BJ50),4)=MOD(COLUMN($AM50)+0,4)),$AM50:$BJ50)*$I50 -> 0 | BN50: =SUMPRODUCT(--(MOD(COLUMN($O50:$AL50),4)=MOD(COLUMN($O50)+1,4)),$O50:$AL50) +SUMPRODUCT(--(MOD(COLUMN($AM50:$BJ50),4)=MOD(COLUMN($AM50)+1,4)),$AM50:$BJ50) -> 0 | BO50: =SUMPRODUCT(--(MOD(COLUMN($O50:$AL50),4)=MOD(COLUMN($O50)+1,4)),$O50:$AL50)*$I50 +SUMPRODUCT(--(MOD(COLUMN($AM50:$BJ50),4)=MOD(COLUMN($AM50)+1,4)),$AM50:$BJ50)*$I50 -> 0 | BP50: =SUMPRODUCT(--(MOD(COLUMN($O50:$AL50),4)=MOD(COLUMN($O50)+2,4)),$O50:$AL50) +SUMPRODUCT(--(MOD(COLUMN($AM50:$BJ50),4)=MOD(COLUMN($AM50)+2,4)),$AM50:$BJ50) -> 0 | BQ50: =SUMPRODUCT(--(MOD(COLUMN($O50:$AL50),4)=MOD(COLUMN($O50)+2,4)),$O50:$AL50)*$I50 +SUMPRODUCT(--(MOD(COLUMN($AM50:$BJ50),4)=MOD(COLUMN($AM50)+2,4)),$AM50:$BJ50)*$I50 -> 0
A51: АВГ АВТОКОМПОНЕНТЫ ООО | B51: Отсрочка 30 дней | C51: ВБК Восток | D51: Прасолов, Соловьёв | E51: =IF(ISBLANK(G51),"",IF($A$6:$A$64=$A51,COUNTIF($A$6:A51,$A51),"")) -> 1 | F51: 1 | G51: 6402250560 | H51: 6402250560 AA Тормоз дисковый ( левый ) | I51: =2100/НДС_20 -> 1750 | L51: =IF(K51="RUB",J51/ЮАНЬ,IF(K51="EUR",J51*ЕВРО/ЮАНЬ,"")) | N51: =IF(BP51>0,1,IF(BN51>0,2,)) -> 0 | U51: 0 | AC51: 0 | BL51: =SUMPRODUCT(--(MOD(COLUMN($O51:$AL51),4)=MOD(COLUMN($O51)+0,4)),$O51:$AL51) +SUMPRODUCT(--(MOD(COLUMN($AM51:$BJ51),4)=MOD(COLUMN($AM51)+0,4)),$AM51:$BJ51) -> 0 | BM51: =SUMPRODUCT(--(MOD(COLUMN($O51:$AL51),4)=MOD(COLUMN($O51)+0,4)),$O51:$AL51)*$I51 +SUMPRODUCT(--(MOD(COLUMN($AM51:$BJ51),4)=MOD(COLUMN($AM51)+0,4)),$AM51:$BJ51)*$I51 -> 0 | BN51: =SUMPRODUCT(--(MOD(COLUMN($O51:$AL51),4)=MOD(COLUMN($O51)+1,4)),$O51:$AL51) +SUMPRODUCT(--(MOD(COLUMN($AM51:$BJ51),4)=MOD(COLUMN($AM51)+1,4)),$AM51:$BJ51) -> 0 | BO51: =SUMPRODUCT(--(MOD(COLUMN($O51:$AL51),4)=MOD(COLUMN($O51)+1,4)),$O51:$AL51)*$I51 +SUMPRODUCT(--(MOD(COLUMN($AM51:$BJ51),4)=MOD(COLUMN($AM51)+1,4)),$AM51:$BJ51)*$I51 -> 0 | BP51: =SUMPRODUCT(--(MOD(COLUMN($O51:$AL51),4)=MOD(COLUMN($O51)+2,4)),$O51:$AL51) +SUMPRODUCT(--(MOD(COLUMN($AM51:$BJ51),4)=MOD(COLUMN($AM51)+2,4)),$AM51:$BJ51) -> 0 | BQ51: =SUMPRODUCT(--(MOD(COLUMN($O51:$AL51),4)=MOD(COLUMN($O51)+2,4)),$O51:$AL51)*$I51 +SUMPRODUCT(--(MOD(COLUMN($AM51:$BJ51),4)=MOD(COLUMN($AM51)+2,4)),$AM51:$BJ51)*$I51 -> 0 | DQ51: =SUMPRODUCT(--(MOD(COLUMN(BT51:CQ51),4)=MOD(COLUMN(BT51),4)),BT51:CQ51)+SUMPRODUCT(--(MOD(COLUMN(CR51:DO51),4)=MOD(COLUMN(CR51),4)),CR51:DO51) -> 0 | DR51: =SUMPRODUCT(--(MOD(COLUMN(BT51:CQ51),4)=MOD(COLUMN(BT51),4)),BT51:CQ51)*#REF!+SUMPRODUCT(--(MOD(COLUMN(CR51:DO51),4)=MOD(COLUMN(CR51),4)),CR51:DO51)*#REF! -> #REF! | FR51: =SUMPRODUCT(--(MOD(COLUMN(DU51:ER51),4)=MOD(COLUMN(DU51),4)),DU51:ER51)+SUMPRODUCT(--(MOD(COLUMN(ES51:FP51),4)=MOD(COLUMN(ES51),4)),ES51:FP51) -> 0 | FS51: =SUMPRODUCT(--(MOD(COLUMN(DU51:ER51),4)=MOD(COLUMN(DU51),4)),DU51:ER51)*#REF!+SUMPRODUCT(--(MOD(COLUMN(ES51:FP51),4)=MOD(COLUMN(ES51),4)),ES51:FP51)*#REF! -> #REF!
A52: АВГ АВТОКОМПОНЕНТЫ ООО | B52: Отсрочка 30 дней | C52: ВБК Восток | D52: Прасолов, Соловьёв | E52: =IF(ISBLANK(G52),"",IF($A$6:$A$64=$A52,COUNTIF($A$6:A52,$A52),"")) -> 2 | F52: 1 | G52: 6402250570 | H52: 6402250570 AA Тормоз дисковый ( правый ) | I52: =I51 -> 1750 | L52: =IF(K52="RUB",J52/ЮАНЬ,IF(K52="EUR",J52*ЕВРО/ЮАНЬ,"")) | N52: =IF(BP52>0,1,IF(BN52>0,2,)) -> 0 | U52: 0 | BL52: =SUMPRODUCT(--(MOD(COLUMN($O52:$AL52),4)=MOD(COLUMN($O52)+0,4)),$O52:$AL52) +SUMPRODUCT(--(MOD(COLUMN($AM52:$BJ52),4)=MOD(COLUMN($AM52)+0,4)),$AM52:$BJ52) -> 0 | BM52: =SUMPRODUCT(--(MOD(COLUMN($O52:$AL52),4)=MOD(COLUMN($O52)+0,4)),$O52:$AL52)*$I52 +SUMPRODUCT(--(MOD(COLUMN($AM52:$BJ52),4)=MOD(COLUMN($AM52)+0,4)),$AM52:$BJ52)*$I52 -> 0 | BN52: =SUMPRODUCT(--(MOD(COLUMN($O52:$AL52),4)=MOD(COLUMN($O52)+1,4)),$O52:$AL52) +SUMPRODUCT(--(MOD(COLUMN($AM52:$BJ52),4)=MOD(COLUMN($AM52)+1,4)),$AM52:$BJ52) -> 0 | BO52: =SUMPRODUCT(--(MOD(COLUMN($O52:$AL52),4)=MOD(COLUMN($O52)+1,4)),$O52:$AL52)*$I52 +SUMPRODUCT(--(MOD(COLUMN($AM52:$BJ52),4)=MOD(COLUMN($AM52)+1,4)),$AM52:$BJ52)*$I52 -> 0 | BP52: =SUMPRODUCT(--(MOD(COLUMN($O52:$AL52),4)=MOD(COLUMN($O52)+2,4)),$O52:$AL52) +SUMPRODUCT(--(MOD(COLUMN($AM52:$BJ52),4)=MOD(COLUMN($AM52)+2,4)),$AM52:$BJ52) -> 0 | BQ52: =SUMPRODUCT(--(MOD(COLUMN($O52:$AL52),4)=MOD(COLUMN($O52)+2,4)),$O52:$AL52)*$I52 +SUMPRODUCT(--(MOD(COLUMN($AM52:$BJ52),4)=MOD(COLUMN($AM52)+2,4)),$AM52:$BJ52)*$I52 -> 0 | DQ52: =SUMPRODUCT(--(MOD(COLUMN(BT52:CQ52),4)=MOD(COLUMN(BT52),4)),BT52:CQ52)+SUMPRODUCT(--(MOD(COLUMN(CR52:DO52),4)=MOD(COLUMN(CR52),4)),CR52:DO52) -> 0 | DR52: =SUMPRODUCT(--(MOD(COLUMN(BT52:CQ52),4)=MOD(COLUMN(BT52),4)),BT52:CQ52)*#REF!+SUMPRODUCT(--(MOD(COLUMN(CR52:DO52),4)=MOD(COLUMN(CR52),4)),CR52:DO52)*#REF! -> #REF! | FR52: =SUMPRODUCT(--(MOD(COLUMN(DU52:ER52),4)=MOD(COLUMN(DU52),4)),DU52:ER52)+SUMPRODUCT(--(MOD(COLUMN(ES52:FP52),4)=MOD(COLUMN(ES52),4)),ES52:FP52) -> 0 | FS52: =SUMPRODUCT(--(MOD(COLUMN(DU52:ER52),4)=MOD(COLUMN(DU52),4)),DU52:ER52)*#REF!+SUMPRODUCT(--(MOD(COLUMN(ES52:FP52),4)=MOD(COLUMN(ES52),4)),ES52:FP52)*#REF! -> #REF!
A53: АВГ АВТОКОМПОНЕНТЫ ООО | B53: Отсрочка 30 дней | C53: ВБК Восток | D53: Прасолов, Соловьёв | E53: =IF(ISBLANK(G53),"",IF($A$6:$A$64=$A53,COUNTIF($A$6:A53,$A53),"")) -> 3 | F53: 1 | G53: 6402250560 | H53: 6402250560 AC Тормоз дисковый ( левый ) | I53: 2030 | L53: =IF(K53="RUB",J53/ЮАНЬ,IF(K53="EUR",J53*ЕВРО/ЮАНЬ,"")) | N53: =IF(BP53>0,1,IF(BN53>0,2,)) -> 1 | O53: 12 | S53: 12 | U53: 0 | W53: 12 | AA53: 42 | AE53: 42 | AF53: =8 -> 8 | AG53: 8 | AI53: 42 | AJ53: =(50-8) -> 42 | AM53: 84 | AN53: 12 | AQ53: 84 | AR53: 30 | AU53: 84 | AV53: 42 | AY53: 84 | AZ53: 84 | BC53: 84 | BD53: 84 | BG53: 84 | BH53: 84 | BL53: =SUMPRODUCT(--(MOD(COLUMN($O53:$AL53),4)=MOD(COLUMN($O53)+0,4)),$O53:$AL53) +SUMPRODUCT(--(MOD(COLUMN($AM53:$BJ53),4)=MOD(COLUMN($AM53)+0,4)),$AM53:$BJ53) -> 666 | BM53: =SUMPRODUCT(--(MOD(COLUMN($O53:$AL53),4)=MOD(COLUMN($O53)+0,4)),$O53:$AL53)*$I53 +SUMPRODUCT(--(MOD(COLUMN($AM53:$BJ53),4)=MOD(COLUMN($AM53)+0,4)),$AM53:$BJ53)*$I53 -> 1351980 | BN53: =SUMPRODUCT(--(MOD(COLUMN($O53:$AL53),4)=MOD(COLUMN($O53)+1,4)),$O53:$AL53) +SUMPRODUCT(--(MOD(COLUMN($AM53:$BJ53),4)=MOD(COLUMN($AM53)+1,4)),$AM53:$BJ53) -> 386 | BO53: =SUMPRODUCT(--(MOD(COLUMN($O53:$AL53),4)=MOD(COLUMN($O53)+1,4)),$O53:$AL53)*$I53 +SUMPRODUCT(--(MOD(COLUMN($AM53:$BJ53),4)=MOD(COLUMN($AM53)+1,4)),$AM53:$BJ53)*$I53 -> 783580 | BP53: =SUMPRODUCT(--(MOD(COLUMN($O53:$AL53),4)=MOD(COLUMN($O53)+2,4)),$O53:$AL53) +SUMPRODUCT(--(MOD(COLUMN($AM53:$BJ53),4)=MOD(COLUMN($AM53)+2,4)),$AM53:$BJ53) -> 8 | BQ53: =SUMPRODUCT(--(MOD(COLUMN($O53:$AL53),4)=MOD(COLUMN($O53)+2,4)),$O53:$AL53)*$I53 +SUMPRODUCT(--(MOD(COLUMN($AM53:$BJ53),4)=MOD(COLUMN($AM53)+2,4)),$AM53:$BJ53)*$I53 -> 16240 | BT53: 207 | BX53: 207 | CB53: 207 | CF53: 207 | CJ53: 207 | CN53: 207 | CR53: 207 | CV53: 207 | CZ53: 207 | DD53: 207 | DH53: 207 | DL53: 207 | DQ53: =SUMPRODUCT(--(MOD(COLUMN(BT53:CQ53),4)=MOD(COLUMN(BT53),4)),BT53:CQ53)+SUMPRODUCT(--(MOD(COLUMN(CR53:DO53),4)=MOD(COLUMN(CR53),4)),CR53:DO53) -> 2484 | DR53: =SUMPRODUCT(--(MOD(COLUMN(BT53:CQ53),4)=MOD(COLUMN(BT53),4)),BT53:CQ53)*#REF!+SUMPRODUCT(--(MOD(COLUMN(CR53:DO53),4)=MOD(COLUMN(CR53),4)),CR53:DO53)*#REF! -> #REF! | DU53: 414 | DY53: 414 | EC53: 414 | EG53: 414 | EK53: 414 | EO53: 414 | ES53: 414 | EW53: 414 | FA53: 414 | FE53: 414 | FI53: 414 | FM53: 414 | FR53: =SUMPRODUCT(--(MOD(COLUMN(DU53:ER53),4)=MOD(COLUMN(DU53),4)),DU53:ER53)+SUMPRODUCT(--(MOD(COLUMN(ES53:FP53),4)=MOD(COLUMN(ES53),4)),ES53:FP53) -> 4968 | FS53: =SUMPRODUCT(--(MOD(COLUMN(DU53:ER53),4)=MOD(COLUMN(DU53),4)),DU53:ER53)*#REF!+SUMPRODUCT(--(MOD(COLUMN(ES53:FP53),4)=MOD(COLUMN(ES53),4)),ES53:FP53)*#REF! -> #REF!
A54: АВГ АВТОКОМПОНЕНТЫ ООО | B54: Отсрочка 30 дней | C54: ВБК Восток | D54: Прасолов, Соловьёв | E54: =IF(ISBLANK(G54),"",IF($A$6:$A$64=$A54,COUNTIF($A$6:A54,$A54),"")) -> 4 | F54: 1 | G54: 6402250570 | H54: 6402250570 AC Тормоз дисковый ( правый ) | I54: =I53 -> 2030 | L54: =IF(K54="RUB",J54/ЮАНЬ,IF(K54="EUR",J54*ЕВРО/ЮАНЬ,"")) | N54: =IF(BP54>0,1,IF(BN54>0,2,)) -> 1 | O54: 12 | S54: 12 | U54: 0 | W54: 12 | AA54: 42 | AE54: 42 | AF54: =AF53 -> 8 | AG54: 8 | AI54: 42 | AJ54: =AJ53 -> 42 | AM54: 84 | AN54: =AN53 -> 12 | AQ54: 84 | AR54: =AR53 -> 30 | AU54: 84 | AV54: =AV53 -> 42 | AY54: 84 | AZ54: =AZ53 -> 84 | BC54: 84 | BD54: =BD53 -> 84 | BG54: 84 | BH54: =BH53 -> 84 | BL54: =SUMPRODUCT(--(MOD(COLUMN($O54:$AL54),4)=MOD(COLUMN($O54)+0,4)),$O54:$AL54) +SUMPRODUCT(--(MOD(COLUMN($AM54:$BJ54),4)=MOD(COLUMN($AM54)+0,4)),$AM54:$BJ54) -> 666 | BM54: =SUMPRODUCT(--(MOD(COLUMN($O54:$AL54),4)=MOD(COLUMN($O54)+0,4)),$O54:$AL54)*$I54 +SUMPRODUCT(--(MOD(COLUMN($AM54:$BJ54),4)=MOD(COLUMN($AM54)+0,4)),$AM54:$BJ54)*$I54 -> 1351980 | BN54: =SUMPRODUCT(--(MOD(COLUMN($O54:$AL54),4)=MOD(COLUMN($O54)+1,4)),$O54:$AL54) +SUMPRODUCT(--(MOD(COLUMN($AM54:$BJ54),4)=MOD(COLUMN($AM54)+1,4)),$AM54:$BJ54) -> 386 | BO54: =SUMPRODUCT(--(MOD(COLUMN($O54:$AL54),4)=MOD(COLUMN($O54)+1,4)),$O54:$AL54)*$I54 +SUMPRODUCT(--(MOD(COLUMN($AM54:$BJ54),4)=MOD(COLUMN($AM54)+1,4)),$AM54:$BJ54)*$I54 -> 783580 | BP54: =SUMPRODUCT(--(MOD(COLUMN($O54:$AL54),4)=MOD(COLUMN($O54)+2,4)),$O54:$AL54) +SUMPRODUCT(--(MOD(COLUMN($AM54:$BJ54),4)=MOD(COLUMN($AM54)+2,4)),$AM54:$BJ54) -> 8 | BQ54: =SUMPRODUCT(--(MOD(COLUMN($O54:$AL54),4)=MOD(COLUMN($O54)+2,4)),$O54:$AL54)*$I54 +SUMPRODUCT(--(MOD(COLUMN($AM54:$BJ54),4)=MOD(COLUMN($AM54)+2,4)),$AM54:$BJ54)*$I54 -> 16240 | BT54: 207 | BX54: 207 | CB54: 207 | CF54: 207 | CJ54: 207 | CN54: 207 | CR54: 207 | CV54: 207 | CZ54: 207 | DD54: 207 | DH54: 207 | DL54: 207 | DQ54: =SUMPRODUCT(--(MOD(COLUMN(BT54:CQ54),4)=MOD(COLUMN(BT54),4)),BT54:CQ54)+SUMPRODUCT(--(MOD(COLUMN(CR54:DO54),4)=MOD(COLUMN(CR54),4)),CR54:DO54) -> 2484 | DR54: =SUMPRODUCT(--(MOD(COLUMN(BT54:CQ54),4)=MOD(COLUMN(BT54),4)),BT54:CQ54)*#REF!+SUMPRODUCT(--(MOD(COLUMN(CR54:DO54),4)=MOD(COLUMN(CR54),4)),CR54:DO54)*#REF! -> #REF! | DU54: 414 | DY54: 414 | EC54: 414 | EG54: 414 | EK54: 414 | EO54: 414 | ES54: 414 | EW54: 414 | FA54: 414 | FE54: 414 | FI54: 414 | FM54: 414 | FR54: =SUMPRODUCT(--(MOD(COLUMN(DU54:ER54),4)=MOD(COLUMN(DU54),4)),DU54:ER54)+SUMPRODUCT(--(MOD(COLUMN(ES54:FP54),4)=MOD(COLUMN(ES54),4)),ES54:FP54) -> 4968 | FS54: =SUMPRODUCT(--(MOD(COLUMN(DU54:ER54),4)=MOD(COLUMN(DU54),4)),DU54:ER54)*#REF!+SUMPRODUCT(--(MOD(COLUMN(ES54:FP54),4)=MOD(COLUMN(ES54),4)),ES54:FP54)*#REF! -> #REF!
A55: АВГ АВТОКОМПОНЕНТЫ ООО | B55: Отсрочка 30 дней | C55: ВБК Восток | D55: Прасолов, Соловьёв | E55: =IF(ISBLANK(G55),"",IF($A$6:$A$64=$A55,COUNTIF($A$6:A55,$A55),"")) -> 5 | F55: 1 | G55: 4410328080 | H55: Датчик АБС, 0,4 м | I55: =84/НДС_20 -> 70 | L55: =IF(K55="RUB",J55/ЮАНЬ,IF(K55="EUR",J55*ЕВРО/ЮАНЬ,"")) | N55: =IF(BP55>0,1,IF(BN55>0,2,)) -> 2 | O55: 8 | S55: 8 | U55: 0 | W55: 8 | AA55: 28 | AE55: 28 | AI55: 28 | AM55: 56 | AQ55: 56 | AU55: 56 | AV55: =SUM(AV53:AV54)/3 -> 28 | AY55: 56 | AZ55: =SUM(AZ53:AZ54)/3 -> 56 | BC55: 56 | BD55: =SUM(BD53:BD54)/3 -> 56 | BG55: 56 | BH55: =SUM(BH53:BH54)/3 -> 56 | BL55: =SUMPRODUCT(--(MOD(COLUMN($O55:$AL55),4)=MOD(COLUMN($O55)+0,4)),$O55:$AL55) +SUMPRODUCT(--(MOD(COLUMN($AM55:$BJ55),4)=MOD(COLUMN($AM55)+0,4)),$AM55:$BJ55) -> 444 | BM55: =SUMPRODUCT(--(MOD(COLUMN($O55:$AL55),4)=MOD(COLUMN($O55)+0,4)),$O55:$AL55)*$I55 +SUMPRODUCT(--(MOD(COLUMN($AM55:$BJ55),4)=MOD(COLUMN($AM55)+0,4)),$AM55:$BJ55)*$I55 -> 31080 | BN55: =SUMPRODUCT(--(MOD(COLUMN($O55:$AL55),4)=MOD(COLUMN($O55)+1,4)),$O55:$AL55) +SUMPRODUCT(--(MOD(COLUMN($AM55:$BJ55),4)=MOD(COLUMN($AM55)+1,4)),$AM55:$BJ55) -> 196 | BO55: =SUMPRODUCT(--(MOD(COLUMN($O55:$AL55),4)=MOD(COLUMN($O55)+1,4)),$O55:$AL55)*$I55 +SUMPRODUCT(--(MOD(COLUMN($AM55:$BJ55),4)=MOD(COLUMN($AM55)+1,4)),$AM55:$BJ55)*$I55 -> 13720 | BP55: =SUMPRODUCT(--(MOD(COLUMN($O55:$AL55),4)=MOD(COLUMN($O55)+2,4)),$O55:$AL55) +SUMPRODUCT(--(MOD(COLUMN($AM55:$BJ55),4)=MOD(COLUMN($AM55)+2,4)),$AM55:$BJ55) -> 0 | BQ55: =SUMPRODUCT(--(MOD(COLUMN($O55:$AL55),4)=MOD(COLUMN($O55)+2,4)),$O55:$AL55)*$I55 +SUMPRODUCT(--(MOD(COLUMN($AM55:$BJ55),4)=MOD(COLUMN($AM55)+2,4)),$AM55:$BJ55)*$I55 -> 0 | BT55: 138 | BX55: 138 | CB55: 138 | CF55: 138 | CJ55: 138 | CN55: 138 | CR55: 138 | CV55: 138 | CZ55: 138 | DD55: 138 | DH55: 138 | DL55: 138 | DQ55: =SUMPRODUCT(--(MOD(COLUMN(BT55:CQ55),4)=MOD(COLUMN(BT55),4)),BT55:CQ55)+SUMPRODUCT(--(MOD(COLUMN(CR55:DO55),4)=MOD(COLUMN(CR55),4)),CR55:DO55) -> 1656 | DR55: =SUMPRODUCT(--(MOD(COLUMN(BT55:CQ55),4)=MOD(COLUMN(BT55),4)),BT55:CQ55)*#REF!+SUMPRODUCT(--(MOD(COLUMN(CR55:DO55),4)=MOD(COLUMN(CR55),4)),CR55:DO55)*#REF! -> #REF! | DU55: 276 | DY55: 276 | EC55: 276 | EG55: 276 | EK55: 276 | EO55: 276 | ES55: 276 | EW55: 276 | FA55: 276 | FE55: 276 | FI55: 276 | FM55: 276 | FR55: =SUMPRODUCT(--(MOD(COLUMN(DU55:ER55),4)=MOD(COLUMN(DU55),4)),DU55:ER55)+SUMPRODUCT(--(MOD(COLUMN(ES55:FP55),4)=MOD(COLUMN(ES55),4)),ES55:FP55) -> 3312 | FS55: =SUMPRODUCT(--(MOD(COLUMN(DU55:ER55),4)=MOD(COLUMN(DU55),4)),DU55:ER55)*#REF!+SUMPRODUCT(--(MOD(COLUMN(ES55:FP55),4)=MOD(COLUMN(ES55),4)),ES55:FP55)*#REF! -> #REF!
A56: АВГ АВТОКОМПОНЕНТЫ ООО | B56: Отсрочка 30 дней | C56: ВБК Восток | D56: Прасолов, Соловьёв | E56: =IF(ISBLANK(G56),"",IF($A$6:$A$64=$A56,COUNTIF($A$6:A56,$A56),"")) -> 6 | F56: 1 | G56: 8997598154 | H56: Втулка датчика АБС | I56: =8.4/НДС_20 -> 7 | L56: =IF(K56="RUB",J56/ЮАНЬ,IF(K56="EUR",J56*ЕВРО/ЮАНЬ,"")) | N56: =IF(BP56>0,1,IF(BN56>0,2,)) -> 2 | O56: 8 | S56: 8 | U56: 0 | W56: 8 | AA56: 28 | AE56: 28 | AI56: 28 | AM56: 56 | AQ56: 56 | AU56: 56 | AV56: =SUM(AV53:AV54)/3 -> 28 | AY56: 56 | AZ56: =SUM(AZ53:AZ54)/3 -> 56 | BC56: 56 | BD56: =SUM(BD53:BD54)/3 -> 56 | BG56: 56 | BH56: =SUM(BH53:BH54)/3 -> 56 | BL56: =SUMPRODUCT(--(MOD(COLUMN($O56:$AL56),4)=MOD(COLUMN($O56)+0,4)),$O56:$AL56) +SUMPRODUCT(--(MOD(COLUMN($AM56:$BJ56),4)=MOD(COLUMN($AM56)+0,4)),$AM56:$BJ56) -> 444 | BM56: =SUMPRODUCT(--(MOD(COLUMN($O56:$AL56),4)=MOD(COLUMN($O56)+0,4)),$O56:$AL56)*$I56 +SUMPRODUCT(--(MOD(COLUMN($AM56:$BJ56),4)=MOD(COLUMN($AM56)+0,4)),$AM56:$BJ56)*$I56 -> 3108 | BN56: =SUMPRODUCT(--(MOD(COLUMN($O56:$AL56),4)=MOD(COLUMN($O56)+1,4)),$O56:$AL56) +SUMPRODUCT(--(MOD(COLUMN($AM56:$BJ56),4)=MOD(COLUMN($AM56)+1,4)),$AM56:$BJ56) -> 196 | BO56: =SUMPRODUCT(--(MOD(COLUMN($O56:$AL56),4)=MOD(COLUMN($O56)+1,4)),$O56:$AL56)*$I56 +SUMPRODUCT(--(MOD(COLUMN($AM56:$BJ56),4)=MOD(COLUMN($AM56)+1,4)),$AM56:$BJ56)*$I56 -> 1372 | BP56: =SUMPRODUCT(--(MOD(COLUMN($O56:$AL56),4)=MOD(COLUMN($O56)+2,4)),$O56:$AL56) +SUMPRODUCT(--(MOD(COLUMN($AM56:$BJ56),4)=MOD(COLUMN($AM56)+2,4)),$AM56:$BJ56) -> 0 | BQ56: =SUMPRODUCT(--(MOD(COLUMN($O56:$AL56),4)=MOD(COLUMN($O56)+2,4)),$O56:$AL56)*$I56 +SUMPRODUCT(--(MOD(COLUMN($AM56:$BJ56),4)=MOD(COLUMN($AM56)+2,4)),$AM56:$BJ56)*$I56 -> 0 | BT56: 138 | BX56: 138 | CB56: 138 | CF56: 138 | CJ56: 138 | CN56: 138 | CR56: 138 | CV56: 138 | CZ56: 138 | DD56: 138 | DH56: 138 | DL56: 138 | DQ56: =SUMPRODUCT(--(MOD(COLUMN(BT56:CQ56),4)=MOD(COLUMN(BT56),4)),BT56:CQ56)+SUMPRODUCT(--(MOD(COLUMN(CR56:DO56),4)=MOD(COLUMN(CR56),4)),CR56:DO56) -> 1656 | DR56: =SUMPRODUCT(--(MOD(COLUMN(BT56:CQ56),4)=MOD(COLUMN(BT56),4)),BT56:CQ56)*#REF!+SUMPRODUCT(--(MOD(COLUMN(CR56:DO56),4)=MOD(COLUMN(CR56),4)),CR56:DO56)*#REF! -> #REF! | DU56: 276 | DY56: 276 | EC56: 276 | EG56: 276 | EK56: 276 | EO56: 276 | ES56: 276 | EW56: 276 | FA56: 276 | FE56: 276 | FI56: 276 | FM56: 276 | FR56: =SUMPRODUCT(--(MOD(COLUMN(DU56:ER56),4)=MOD(COLUMN(DU56),4)),DU56:ER56)+SUMPRODUCT(--(MOD(COLUMN(ES56:FP56),4)=MOD(COLUMN(ES56),4)),ES56:FP56) -> 3312 | FS56: =SUMPRODUCT(--(MOD(COLUMN(DU56:ER56),4)=MOD(COLUMN(DU56),4)),DU56:ER56)*#REF!+SUMPRODUCT(--(MOD(COLUMN(ES56:FP56),4)=MOD(COLUMN(ES56),4)),ES56:FP56)*#REF! -> #REF!
A57: АВГ АВТОКОМПОНЕНТЫ ООО | B57: Отсрочка 30 дней | C57: ВБК Восток | D57: Прасолов, Соловьёв | E57: =IF(ISBLANK(G57),"",IF($A$6:$A$64=$A57,COUNTIF($A$6:A57,$A57),"")) -> 7 | F57: 1 | G57: 4235041001 | H57: Тормозная камера, тип 20 | I57: 135.5 | L57: =IF(K57="RUB",J57/ЮАНЬ,IF(K57="EUR",J57*ЕВРО/ЮАНЬ,"")) | N57: =IF(BP57>0,1,IF(BN57>0,2,)) -> 1 | O57: 8 | S57: 8 | U57: 0 | W57: 8 | X57: =20 -> 20 | Y57: 20 | AA57: 28 | AE57: 28 | AF57: =2 -> 2 | AG57: 2 | AI57: 28 | AM57: 56 | AQ57: 56 | AU57: 56 | AV57: =SUM(AV53:AV54)/3 -> 28 | AY57: 56 | AZ57: =SUM(AZ53:AZ54)/3 -> 56 | BC57: 56 | BD57: =SUM(BD53:BD54)/3 -> 56 | BG57: 56 | BH57: =SUM(BH53:BH54)/3 -> 56 | BL57: =SUMPRODUCT(--(MOD(COLUMN($O57:$AL57),4)=MOD(COLUMN($O57)+0,4)),$O57:$AL57) +SUMPRODUCT(--(MOD(COLUMN($AM57:$BJ57),4)=MOD(COLUMN($AM57)+0,4)),$AM57:$BJ57) -> 444 | BM57: =SUMPRODUCT(--(MOD(COLUMN($O57:$AL57),4)=MOD(COLUMN($O57)+0,4)),$O57:$AL57)*$I57 +SUMPRODUCT(--(MOD(COLUMN($AM57:$BJ57),4)=MOD(COLUMN($AM57)+0,4)),$AM57:$BJ57)*$I57 -> 60162 | BN57: =SUMPRODUCT(--(MOD(COLUMN($O57:$AL57),4)=MOD(COLUMN($O57)+1,4)),$O57:$AL57) +SUMPRODUCT(--(MOD(COLUMN($AM57:$BJ57),4)=MOD(COLUMN($AM57)+1,4)),$AM57:$BJ57) -> 218 | BO57: =SUMPRODUCT(--(MOD(COLUMN($O57:$AL57),4)=MOD(COLUMN($O57)+1,4)),$O57:$AL57)*$I57 +SUMPRODUCT(--(MOD(COLUMN($AM57:$BJ57),4)=MOD(COLUMN($AM57)+1,4)),$AM57:$BJ57)*$I57 -> 29539 | BP57: =SUMPRODUCT(--(MOD(COLUMN($O57:$AL57),4)=MOD(COLUMN($O57)+2,4)),$O57:$AL57) +SUMPRODUCT(--(MOD(COLUMN($AM57:$BJ57),4)=MOD(COLUMN($AM57)+2,4)),$AM57:$BJ57) -> 22 | BQ57: =SUMPRODUCT(--(MOD(COLUMN($O57:$AL57),4)=MOD(COLUMN($O57)+2,4)),$O57:$AL57)*$I57 +SUMPRODUCT(--(MOD(COLUMN($AM57:$BJ57),4)=MOD(COLUMN($AM57)+2,4)),$AM57:$BJ57)*$I57 -> 2981 | BT57: 138 | BX57: 138 | CB57: 138 | CF57: 138 | CJ57: 138 | CN57: 138 | CR57: 138 | CV57: 138 | CZ57: 138 | DD57: 138 | DH57: 138 | DL57: 138 | DQ57: =SUMPRODUCT(--(MOD(COLUMN(BT57:CQ57),4)=MOD(COLUMN(BT57),4)),BT57:CQ57)+SUMPRODUCT(--(MOD(COLUMN(CR57:DO57),4)=MOD(COLUMN(CR57),4)),CR57:DO57) -> 1656 | DR57: =SUMPRODUCT(--(MOD(COLUMN(BT57:CQ57),4)=MOD(COLUMN(BT57),4)),BT57:CQ57)*#REF!+SUMPRODUCT(--(MOD(COLUMN(CR57:DO57),4)=MOD(COLUMN(CR57),4)),CR57:DO57)*#REF! -> #REF! | DU57: 276 | DY57: 276 | EC57: 276 | EG57: 276 | EK57: 276 | EO57: 276 | ES57: 276 | EW57: 276 | FA57: 276 | FE57: 276 | FI57: 276 | FM57: 276 | FR57: =SUMPRODUCT(--(MOD(COLUMN(DU57:ER57),4)=MOD(COLUMN(DU57),4)),DU57:ER57)+SUMPRODUCT(--(MOD(COLUMN(ES57:FP57),4)=MOD(COLUMN(ES57),4)),ES57:FP57) -> 3312 | FS57: =SUMPRODUCT(--(MOD(COLUMN(DU57:ER57),4)=MOD(COLUMN(DU57),4)),DU57:ER57)*#REF!+SUMPRODUCT(--(MOD(COLUMN(ES57:FP57),4)=MOD(COLUMN(ES57),4)),ES57:FP57)*#REF! -> #REF!
A58: АВГ АВТОКОМПОНЕНТЫ ООО | B58: Отсрочка 30 дней | C58: ВБК Восток | D58: Прасолов, Соловьёв | E58: =IF(ISBLANK(G58),"",IF($A$6:$A$64=$A58,COUNTIF($A$6:A58,$A58),"")) -> 8 | F58: 1 | G58: 9254800504 | H58: Энергоаккумулятор, тип 20/24 | I58: 311.5 | L58: =IF(K58="RUB",J58/ЮАНЬ,IF(K58="EUR",J58*ЕВРО/ЮАНЬ,"")) | N58: =IF(BP58>0,1,IF(BN58>0,2,)) -> 1 | O58: 16 | S58: 16 | U58: 0 | W58: 16 | X58: =20 -> 20 | Y58: 20 | AA58: 56 | AE58: 56 | AF58: =4 -> 4 | AG58: 4 | AI58: 56 | AM58: 112 | AQ58: 112 | AU58: 112 | AV58: =SUM(AV53:AV54)/3*2 -> 56 | AY58: 112 | AZ58: =SUM(AZ53:AZ54)/3*2 -> 112 | BC58: 112 | BD58: =SUM(BD53:BD54)/3*2 -> 112 | BG58: 112 | BH58: =SUM(BH53:BH54)/3*2 -> 112 | BL58: =SUMPRODUCT(--(MOD(COLUMN($O58:$AL58),4)=MOD(COLUMN($O58)+0,4)),$O58:$AL58) +SUMPRODUCT(--(MOD(COLUMN($AM58:$BJ58),4)=MOD(COLUMN($AM58)+0,4)),$AM58:$BJ58) -> 888 | BM58: =SUMPRODUCT(--(MOD(COLUMN($O58:$AL58),4)=MOD(COLUMN($O58)+0,4)),$O58:$AL58)*$I58 +SUMPRODUCT(--(MOD(COLUMN($AM58:$BJ58),4)=MOD(COLUMN($AM58)+0,4)),$AM58:$BJ58)*$I58 -> 276612 | BN58: =SUMPRODUCT(--(MOD(COLUMN($O58:$AL58),4)=MOD(COLUMN($O58)+1,4)),$O58:$AL58) +SUMPRODUCT(--(MOD(COLUMN($AM58:$BJ58),4)=MOD(COLUMN($AM58)+1,4)),$AM58:$BJ58) -> 416 | BO58: =SUMPRODUCT(--(MOD(COLUMN($O58:$AL58),4)=MOD(COLUMN($O58)+1,4)),$O58:$AL58)*$I58 +SUMPRODUCT(--(MOD(COLUMN($AM58:$BJ58),4)=MOD(COLUMN($AM58)+1,4)),$AM58:$BJ58)*$I58 -> 129584 | BP58: =SUMPRODUCT(--(MOD(COLUMN($O58:$AL58),4)=MOD(COLUMN($O58)+2,4)),$O58:$AL58) +SUMPRODUCT(--(MOD(COLUMN($AM58:$BJ58),4)=MOD(COLUMN($AM58)+2,4)),$AM58:$BJ58) -> 24 | BQ58: =SUMPRODUCT(--(MOD(COLUMN($O58:$AL58),4)=MOD(COLUMN($O58)+2,4)),$O58:$AL58)*$I58 +SUMPRODUCT(--(MOD(COLUMN($AM58:$BJ58),4)=MOD(COLUMN($AM58)+2,4)),$AM58:$BJ58)*$I58 -> 7476 | BT58: 276 | BX58: 276 | CB58: 276 | CF58: 276 | CJ58: 276 | CN58: 276 | CR58: 276 | CV58: 276 | CZ58: 276 | DD58: 276 | DH58: 276 | DL58: 276 | DQ58: =SUMPRODUCT(--(MOD(COLUMN(BT58:CQ58),4)=MOD(COLUMN(BT58),4)),BT58:CQ58)+SUMPRODUCT(--(MOD(COLUMN(CR58:DO58),4)=MOD(COLUMN(CR58),4)),CR58:DO58) -> 3312 | DR58: =SUMPRODUCT(--(MOD(COLUMN(BT58:CQ58),4)=MOD(COLUMN(BT58),4)),BT58:CQ58)*#REF!+SUMPRODUCT(--(MOD(COLUMN(CR58:DO58),4)=MOD(COLUMN(CR58),4)),CR58:DO58)*#REF! -> #REF! | DU58: 552 | DY58: 552 | EC58: 552 | EG58: 552 | EK58: 552 | EO58: 552 | ES58: 552 | EW58: 552 | FA58: 552 | FE58: 552 | FI58: 552 | FM58: 552 | FR58: =SUMPRODUCT(--(MOD(COLUMN(DU58:ER58),4)=MOD(COLUMN(DU58),4)),DU58:ER58)+SUMPRODUCT(--(MOD(COLUMN(ES58:FP58),4)=MOD(COLUMN(ES58),4)),ES58:FP58) -> 6624 | FS58: =SUMPRODUCT(--(MOD(COLUMN(DU58:ER58),4)=MOD(COLUMN(DU58),4)),DU58:ER58)*#REF!+SUMPRODUCT(--(MOD(COLUMN(ES58:FP58),4)=MOD(COLUMN(ES58),4)),ES58:FP58)*#REF! -> #REF!
A59: АВГ АВТОКОМПОНЕНТЫ ООО | B59: Отсрочка 30 дней | C59: ВБК Восток | D59: Прасолов, Соловьёв | E59: =IF(ISBLANK(G59),"",IF($A$6:$A$64=$A59,COUNTIF($A$6:A59,$A59),"")) -> 9 | F59: 1 | G59: 4231069000 | H59: Камера тормозная тип 24 | I59: =144/НДС_20 -> 120 | L59: =IF(K59="RUB",J59/ЮАНЬ,IF(K59="EUR",J59*ЕВРО/ЮАНЬ,"")) | N59: =IF(BP59>0,1,IF(BN59>0,2,)) -> 1 | U59: 0 | X59: =20 -> 20 | Y59: 20 | AF59: =6 -> 6 | AG59: 6 | BL59: =SUMPRODUCT(--(MOD(COLUMN($O59:$AL59),4)=MOD(COLUMN($O59)+0,4)),$O59:$AL59) +SUMPRODUCT(--(MOD(COLUMN($AM59:$BJ59),4)=MOD(COLUMN($AM59)+0,4)),$AM59:$BJ59) -> 0 | BM59: =SUMPRODUCT(--(MOD(COLUMN($O59:$AL59),4)=MOD(COLUMN($O59)+0,4)),$O59:$AL59)*$I59 +SUMPRODUCT(--(MOD(COLUMN($AM59:$BJ59),4)=MOD(COLUMN($AM59)+0,4)),$AM59:$BJ59)*$I59 -> 0 | BN59: =SUMPRODUCT(--(MOD(COLUMN($O59:$AL59),4)=MOD(COLUMN($O59)+1,4)),$O59:$AL59) +SUMPRODUCT(--(MOD(COLUMN($AM59:$BJ59),4)=MOD(COLUMN($AM59)+1,4)),$AM59:$BJ59) -> 26 | BO59: =SUMPRODUCT(--(MOD(COLUMN($O59:$AL59),4)=MOD(COLUMN($O59)+1,4)),$O59:$AL59)*$I59 +SUMPRODUCT(--(MOD(COLUMN($AM59:$BJ59),4)=MOD(COLUMN($AM59)+1,4)),$AM59:$BJ59)*$I59 -> 3120 | BP59: =SUMPRODUCT(--(MOD(COLUMN($O59:$AL59),4)=MOD(COLUMN($O59)+2,4)),$O59:$AL59) +SUMPRODUCT(--(MOD(COLUMN($AM59:$BJ59),4)=MOD(COLUMN($AM59)+2,4)),$AM59:$BJ59) -> 26 | BQ59: =SUMPRODUCT(--(MOD(COLUMN($O59:$AL59),4)=MOD(COLUMN($O59)+2,4)),$O59:$AL59)*$I59 +SUMPRODUCT(--(MOD(COLUMN($AM59:$BJ59),4)=MOD(COLUMN($AM59)+2,4)),$AM59:$BJ59)*$I59 -> 3120 | DQ59: =SUMPRODUCT(--(MOD(COLUMN(BT59:CQ59),4)=MOD(COLUMN(BT59),4)),BT59:CQ59)+SUMPRODUCT(--(MOD(COLUMN(CR59:DO59),4)=MOD(COLUMN(CR59),4)),CR59:DO59) -> 0 | DR59: =SUMPRODUCT(--(MOD(COLUMN(BT59:CQ59),4)=MOD(COLUMN(BT59),4)),BT59:CQ59)*#REF!+SUMPRODUCT(--(MOD(COLUMN(CR59:DO59),4)=MOD(COLUMN(CR59),4)),CR59:DO59)*#REF! -> #REF! | FR59: =SUMPRODUCT(--(MOD(COLUMN(DU59:ER59),4)=MOD(COLUMN(DU59),4)),DU59:ER59)+SUMPRODUCT(--(MOD(COLUMN(ES59:FP59),4)=MOD(COLUMN(ES59),4)),ES59:FP59) -> 0 | FS59: =SUMPRODUCT(--(MOD(COLUMN(DU59:ER59),4)=MOD(COLUMN(DU59),4)),DU59:ER59)*#REF!+SUMPRODUCT(--(MOD(COLUMN(ES59:FP59),4)=MOD(COLUMN(ES59),4)),ES59:FP59)*#REF! -> #REF!
A60: АВГ АВТОКОМПОНЕНТЫ ООО | B60: Отсрочка 30 дней | C60: ВБК Восток | D60: Прасолов, Соловьёв | E60: =IF(ISBLANK(G60),"",IF($A$6:$A$64=$A60,COUNTIF($A$6:A60,$A60),"")) -> 10 | F60: 1 | G60: 4231079000 | H60: Камера тормозная тип 30 | I60: =150.9/НДС_20 -> 125.75 | L60: =IF(K60="RUB",J60/ЮАНЬ,IF(K60="EUR",J60*ЕВРО/ЮАНЬ,"")) | N60: =IF(BP60>0,1,IF(BN60>0,2,)) -> 0 | U60: 0 | BL60: =SUMPRODUCT(--(MOD(COLUMN($O60:$AL60),4)=MOD(COLUMN($O60)+0,4)),$O60:$AL60) +SUMPRODUCT(--(MOD(COLUMN($AM60:$BJ60),4)=MOD(COLUMN($AM60)+0,4)),$AM60:$BJ60) -> 0 | BM60: =SUMPRODUCT(--(MOD(COLUMN($O60:$AL60),4)=MOD(COLUMN($O60)+0,4)),$O60:$AL60)*$I60 +SUMPRODUCT(--(MOD(COLUMN($AM60:$BJ60),4)=MOD(COLUMN($AM60)+0,4)),$AM60:$BJ60)*$I60 -> 0 | BN60: =SUMPRODUCT(--(MOD(COLUMN($O60:$AL60),4)=MOD(COLUMN($O60)+1,4)),$O60:$AL60) +SUMPRODUCT(--(MOD(COLUMN($AM60:$BJ60),4)=MOD(COLUMN($AM60)+1,4)),$AM60:$BJ60) -> 0 | BO60: =SUMPRODUCT(--(MOD(COLUMN($O60:$AL60),4)=MOD(COLUMN($O60)+1,4)),$O60:$AL60)*$I60 +SUMPRODUCT(--(MOD(COLUMN($AM60:$BJ60),4)=MOD(COLUMN($AM60)+1,4)),$AM60:$BJ60)*$I60 -> 0 | BP60: =SUMPRODUCT(--(MOD(COLUMN($O60:$AL60),4)=MOD(COLUMN($O60)+2,4)),$O60:$AL60) +SUMPRODUCT(--(MOD(COLUMN($AM60:$BJ60),4)=MOD(COLUMN($AM60)+2,4)),$AM60:$BJ60) -> 0 | BQ60: =SUMPRODUCT(--(MOD(COLUMN($O60:$AL60),4)=MOD(COLUMN($O60)+2,4)),$O60:$AL60)*$I60 +SUMPRODUCT(--(MOD(COLUMN($AM60:$BJ60),4)=MOD(COLUMN($AM60)+2,4)),$AM60:$BJ60)*$I60 -> 0 | DQ60: =SUMPRODUCT(--(MOD(COLUMN(BT60:CQ60),4)=MOD(COLUMN(BT60),4)),BT60:CQ60)+SUMPRODUCT(--(MOD(COLUMN(CR60:DO60),4)=MOD(COLUMN(CR60),4)),CR60:DO60) -> 0 | DR60: =SUMPRODUCT(--(MOD(COLUMN(BT60:CQ60),4)=MOD(COLUMN(BT60),4)),BT60:CQ60)*#REF!+SUMPRODUCT(--(MOD(COLUMN(CR60:DO60),4)=MOD(COLUMN(CR60),4)),CR60:DO60)*#REF! -> #REF! | FR60: =SUMPRODUCT(--(MOD(COLUMN(DU60:ER60),4)=MOD(COLUMN(DU60),4)),DU60:ER60)+SUMPRODUCT(--(MOD(COLUMN(ES60:FP60),4)=MOD(COLUMN(ES60),4)),ES60:FP60) -> 0 | FS60: =SUMPRODUCT(--(MOD(COLUMN(DU60:ER60),4)=MOD(COLUMN(DU60),4)),DU60:ER60)*#REF!+SUMPRODUCT(--(MOD(COLUMN(ES60:FP60),4)=MOD(COLUMN(ES60),4)),ES60:FP60)*#REF! -> #REF!
A61: АВГ АВТОКОМПОНЕНТЫ ООО | B61: Отсрочка 30 дней | C61: ВБК Восток | D61: Прасолов, Соловьёв | E61: =IF(ISBLANK(G61),"",IF($A$6:$A$64=$A61,COUNTIF($A$6:A61,$A61),"")) -> 11 | F61: 1 | G61: 9253761210 | H61: Энергоаккумулятор тип 24/30 | I61: 243 | L61: =IF(K61="RUB",J61/ЮАНЬ,IF(K61="EUR",J61*ЕВРО/ЮАНЬ,"")) | N61: =IF(BP61>0,1,IF(BN61>0,2,)) -> 1 | U61: 0 | X61: =20 -> 20 | Y61: 20 | AF61: =12 -> 12 | AG61: 12 | BL61: =SUMPRODUCT(--(MOD(COLUMN($O61:$AL61),4)=MOD(COLUMN($O61)+0,4)),$O61:$AL61) +SUMPRODUCT(--(MOD(COLUMN($AM61:$BJ61),4)=MOD(COLUMN($AM61)+0,4)),$AM61:$BJ61) -> 0 | BM61: =SUMPRODUCT(--(MOD(COLUMN($O61:$AL61),4)=MOD(COLUMN($O61)+0,4)),$O61:$AL61)*$I61 +SUMPRODUCT(--(MOD(COLUMN($AM61:$BJ61),4)=MOD(COLUMN($AM61)+0,4)),$AM61:$BJ61)*$I61 -> 0 | BN61: =SUMPRODUCT(--(MOD(COLUMN($O61:$AL61),4)=MOD(COLUMN($O61)+1,4)),$O61:$AL61) +SUMPRODUCT(--(MOD(COLUMN($AM61:$BJ61),4)=MOD(COLUMN($AM61)+1,4)),$AM61:$BJ61) -> 32 | BO61: =SUMPRODUCT(--(MOD(COLUMN($O61:$AL61),4)=MOD(COLUMN($O61)+1,4)),$O61:$AL61)*$I61 +SUMPRODUCT(--(MOD(COLUMN($AM61:$BJ61),4)=MOD(COLUMN($AM61)+1,4)),$AM61:$BJ61)*$I61 -> 7776 | BP61: =SUMPRODUCT(--(MOD(COLUMN($O61:$AL61),4)=MOD(COLUMN($O61)+2,4)),$O61:$AL61) +SUMPRODUCT(--(MOD(COLUMN($AM61:$BJ61),4)=MOD(COLUMN($AM61)+2,4)),$AM61:$BJ61) -> 32 | BQ61: =SUMPRODUCT(--(MOD(COLUMN($O61:$AL61),4)=MOD(COLUMN($O61)+2,4)),$O61:$AL61)*$I61 +SUMPRODUCT(--(MOD(COLUMN($AM61:$BJ61),4)=MOD(COLUMN($AM61)+2,4)),$AM61:$BJ61)*$I61 -> 7776 | DQ61: =SUMPRODUCT(--(MOD(COLUMN(BT61:CQ61),4)=MOD(COLUMN(BT61),4)),BT61:CQ61)+SUMPRODUCT(--(MOD(COLUMN(CR61:DO61),4)=MOD(COLUMN(CR61),4)),CR61:DO61) -> 0 | DR61: =SUMPRODUCT(--(MOD(COLUMN(BT61:CQ61),4)=MOD(COLUMN(BT61),4)),BT61:CQ61)*#REF!+SUMPRODUCT(--(MOD(COLUMN(CR61:DO61),4)=MOD(COLUMN(CR61),4)),CR61:DO61)*#REF! -> #REF! | FR61: =SUMPRODUCT(--(MOD(COLUMN(DU61:ER61),4)=MOD(COLUMN(DU61),4)),DU61:ER61)+SUMPRODUCT(--(MOD(COLUMN(ES61:FP61),4)=MOD(COLUMN(ES61),4)),ES61:FP61) -> 0 | FS61: =SUMPRODUCT(--(MOD(COLUMN(DU61:ER61),4)=MOD(COLUMN(DU61),4)),DU61:ER61)*#REF!+SUMPRODUCT(--(MOD(COLUMN(ES61:FP61),4)=MOD(COLUMN(ES61),4)),ES61:FP61)*#REF! -> #REF!
A62: АВГ АВТОКОМПОНЕНТЫ ООО | B62: Отсрочка 30 дней | C62: ВБК Восток | D62: Прасолов, Соловьёв | E62: =IF(ISBLANK(G62),"",IF($A$6:$A$64=$A62,COUNTIF($A$6:A62,$A62),"")) -> 12 | F62: 1 | G62: 9253771100 | H62: Энергоаккумулятор тип 30/30 | I62: =297.9/НДС_20 -> 248.25 | L62: =IF(K62="RUB",J62/ЮАНЬ,IF(K62="EUR",J62*ЕВРО/ЮАНЬ,"")) | N62: =IF(BP62>0,1,IF(BN62>0,2,)) -> 0 | BL62: =SUMPRODUCT(--(MOD(COLUMN($O62:$AL62),4)=MOD(COLUMN($O62)+0,4)),$O62:$AL62) +SUMPRODUCT(--(MOD(COLUMN($AM62:$BJ62),4)=MOD(COLUMN($AM62)+0,4)),$AM62:$BJ62) -> 0 | BM62: =SUMPRODUCT(--(MOD(COLUMN($O62:$AL62),4)=MOD(COLUMN($O62)+0,4)),$O62:$AL62)*$I62 +SUMPRODUCT(--(MOD(COLUMN($AM62:$BJ62),4)=MOD(COLUMN($AM62)+0,4)),$AM62:$BJ62)*$I62 -> 0 | BN62: =SUMPRODUCT(--(MOD(COLUMN($O62:$AL62),4)=MOD(COLUMN($O62)+1,4)),$O62:$AL62) +SUMPRODUCT(--(MOD(COLUMN($AM62:$BJ62),4)=MOD(COLUMN($AM62)+1,4)),$AM62:$BJ62) -> 0 | BO62: =SUMPRODUCT(--(MOD(COLUMN($O62:$AL62),4)=MOD(COLUMN($O62)+1,4)),$O62:$AL62)*$I62 +SUMPRODUCT(--(MOD(COLUMN($AM62:$BJ62),4)=MOD(COLUMN($AM62)+1,4)),$AM62:$BJ62)*$I62 -> 0 | BP62: =SUMPRODUCT(--(MOD(COLUMN($O62:$AL62),4)=MOD(COLUMN($O62)+2,4)),$O62:$AL62) +SUMPRODUCT(--(MOD(COLUMN($AM62:$BJ62),4)=MOD(COLUMN($AM62)+2,4)),$AM62:$BJ62) -> 0 | BQ62: =SUMPRODUCT(--(MOD(COLUMN($O62:$AL62),4)=MOD(COLUMN($O62)+2,4)),$O62:$AL62)*$I62 +SUMPRODUCT(--(MOD(COLUMN($AM62:$BJ62),4)=MOD(COLUMN($AM62)+2,4)),$AM62:$BJ62)*$I62 -> 0 | DQ62: =SUMPRODUCT(--(MOD(COLUMN(BT62:CQ62),4)=MOD(COLUMN(BT62),4)),BT62:CQ62)+SUMPRODUCT(--(MOD(COLUMN(CR62:DO62),4)=MOD(COLUMN(CR62),4)),CR62:DO62) -> 0 | DR62: =SUMPRODUCT(--(MOD(COLUMN(BT62:CQ62),4)=MOD(COLUMN(BT62),4)),BT62:CQ62)*#REF!+SUMPRODUCT(--(MOD(COLUMN(CR62:DO62),4)=MOD(COLUMN(CR62),4)),CR62:DO62)*#REF! -> #REF! | FR62: =SUMPRODUCT(--(MOD(COLUMN(DU62:ER62),4)=MOD(COLUMN(DU62),4)),DU62:ER62)+SUMPRODUCT(--(MOD(COLUMN(ES62:FP62),4)=MOD(COLUMN(ES62),4)),ES62:FP62) -> 0 | FS62: =SUMPRODUCT(--(MOD(COLUMN(DU62:ER62),4)=MOD(COLUMN(DU62),4)),DU62:ER62)*#REF!+SUMPRODUCT(--(MOD(COLUMN(ES62:FP62),4)=MOD(COLUMN(ES62),4)),ES62:FP62)*#REF! -> #REF!
A63: АВГ АВТОКОМПОНЕНТЫ ООО | E63: =IF(ISBLANK(G63),"",IF($A$6:$A$64=$A63,COUNTIF($A$6:A63,$A63),"")) | H63: Итого | L63: =IF(K63="RUB",J63/ЮАНЬ,IF(K63="EUR",J63*ЕВРО/ЮАНЬ,"")) | N63: =IF(BP63>0,1,IF(BN63>0,2,)) -> 0 | BL63: =SUMPRODUCT(--(MOD(COLUMN($O63:$AL63),4)=MOD(COLUMN($O63)+0,4)),$O63:$AL63) +SUMPRODUCT(--(MOD(COLUMN($AM63:$BJ63),4)=MOD(COLUMN($AM63)+0,4)),$AM63:$BJ63) -> 0 | BM63: =SUMPRODUCT(--(MOD(COLUMN($O63:$AL63),4)=MOD(COLUMN($O63)+0,4)),$O63:$AL63)*$I63 +SUMPRODUCT(--(MOD(COLUMN($AM63:$BJ63),4)=MOD(COLUMN($AM63)+0,4)),$AM63:$BJ63)*$I63 -> 0 | BN63: =SUMPRODUCT(--(MOD(COLUMN($O63:$AL63),4)=MOD(COLUMN($O63)+1,4)),$O63:$AL63) +SUMPRODUCT(--(MOD(COLUMN($AM63:$BJ63),4)=MOD(COLUMN($AM63)+1,4)),$AM63:$BJ63) -> 0 | BO63: =SUMPRODUCT(--(MOD(COLUMN($O63:$AL63),4)=MOD(COLUMN($O63)+1,4)),$O63:$AL63)*$I63 +SUMPRODUCT(--(MOD(COLUMN($AM63:$BJ63),4)=MOD(COLUMN($AM63)+1,4)),$AM63:$BJ63)*$I63 -> 0 | BP63: =SUMPRODUCT(--(MOD(COLUMN($O63:$AL63),4)=MOD(COLUMN($O63)+2,4)),$O63:$AL63) +SUMPRODUCT(--(MOD(COLUMN($AM63:$BJ63),4)=MOD(COLUMN($AM63)+2,4)),$AM63:$BJ63) -> 0 | BQ63: =SUMPRODUCT(--(MOD(COLUMN($O63:$AL63),4)=MOD(COLUMN($O63)+2,4)),$O63:$AL63)*$I63 +SUMPRODUCT(--(MOD(COLUMN($AM63:$BJ63),4)=MOD(COLUMN($AM63)+2,4)),$AM63:$BJ63)*$I63 -> 0 | DQ63: =SUMPRODUCT(--(MOD(COLUMN(BT63:CQ63),4)=MOD(COLUMN(BT63),4)),BT63:CQ63)+SUMPRODUCT(--(MOD(COLUMN(CR63:DO63),4)=MOD(COLUMN(CR63),4)),CR63:DO63) -> 0 | DR63: =SUMPRODUCT(--(MOD(COLUMN(BT63:CQ63),4)=MOD(COLUMN(BT63),4)),BT63:CQ63)*#REF!+SUMPRODUCT(--(MOD(COLUMN(CR63:DO63),4)=MOD(COLUMN(CR63),4)),CR63:DO63)*#REF! -> #REF! | FR63: =SUMPRODUCT(--(MOD(COLUMN(DU63:ER63),4)=MOD(COLUMN(DU63),4)),DU63:ER63)+SUMPRODUCT(--(MOD(COLUMN(ES63:FP63),4)=MOD(COLUMN(ES63),4)),ES63:FP63) -> 0 | FS63: =SUMPRODUCT(--(MOD(COLUMN(DU63:ER63),4)=MOD(COLUMN(DU63),4)),DU63:ER63)*#REF!+SUMPRODUCT(--(MOD(COLUMN(ES63:FP63),4)=MOD(COLUMN(ES63),4)),ES63:FP63)*#REF! -> #REF!
A64: АВГ АВТОКОМПОНЕНТЫ ООО | E64: =IF(ISBLANK(G64),"",IF($A$6:$A$64=$A64,COUNTIF($A$6:A64,$A64),"")) | L64: =IF(K64="RUB",J64/ЮАНЬ,IF(K64="EUR",J64*ЕВРО/ЮАНЬ,"")) | N64: =IF(BP64>0,1,IF(BN64>0,2,)) -> 0 | BL64: =SUMPRODUCT(--(MOD(COLUMN($O64:$AL64),4)=MOD(COLUMN($O64)+0,4)),$O64:$AL64) +SUMPRODUCT(--(MOD(COLUMN($AM64:$BJ64),4)=MOD(COLUMN($AM64)+0,4)),$AM64:$BJ64) -> 0 | BM64: =SUMPRODUCT(--(MOD(COLUMN($O64:$AL64),4)=MOD(COLUMN($O64)+0,4)),$O64:$AL64)*$I64 +SUMPRODUCT(--(MOD(COLUMN($AM64:$BJ64),4)=MOD(COLUMN($AM64)+0,4)),$AM64:$BJ64)*$I64 -> 0 | BN64: =SUMPRODUCT(--(MOD(COLUMN($O64:$AL64),4)=MOD(COLUMN($O64)+1,4)),$O64:$AL64) +SUMPRODUCT(--(MOD(COLUMN($AM64:$BJ64),4)=MOD(COLUMN($AM64)+1,4)),$AM64:$BJ64) -> 0 | BO64: =SUMPRODUCT(--(MOD(COLUMN($O64:$AL64),4)=MOD(COLUMN($O64)+1,4)),$O64:$AL64)*$I64 +SUMPRODUCT(--(MOD(COLUMN($AM64:$BJ64),4)=MOD(COLUMN($AM64)+1,4)),$AM64:$BJ64)*$I64 -> 0 | BP64: =SUMPRODUCT(--(MOD(COLUMN($O64:$AL64),4)=MOD(COLUMN($O64)+2,4)),$O64:$AL64) +SUMPRODUCT(--(MOD(COLUMN($AM64:$BJ64),4)=MOD(COLUMN($AM64)+2,4)),$AM64:$BJ64) -> 0 | BQ64: =SUMPRODUCT(--(MOD(COLUMN($O64:$AL64),4)=MOD(COLUMN($O64)+2,4)),$O64:$AL64)*$I64 +SUMPRODUCT(--(MOD(COLUMN($AM64:$BJ64),4)=MOD(COLUMN($AM64)+2,4)),$AM64:$BJ64)*$I64 -> 0 | DQ64: =SUMPRODUCT(--(MOD(COLUMN(BT64:CQ64),4)=MOD(COLUMN(BT64),4)),BT64:CQ64)+SUMPRODUCT(--(MOD(COLUMN(CR64:DO64),4)=MOD(COLUMN(CR64),4)),CR64:DO64) -> 0 | DR64: =SUMPRODUCT(--(MOD(COLUMN(BT64:CQ64),4)=MOD(COLUMN(BT64),4)),BT64:CQ64)*#REF!+SUMPRODUCT(--(MOD(COLUMN(CR64:DO64),4)=MOD(COLUMN(CR64),4)),CR64:DO64)*#REF! -> #REF! | FR64: =SUMPRODUCT(--(MOD(COLUMN(DU64:ER64),4)=MOD(COLUMN(DU64),4)),DU64:ER64)+SUMPRODUCT(--(MOD(COLUMN(ES64:FP64),4)=MOD(COLUMN(ES64),4)),ES64:FP64) -> 0 | FS64: =SUMPRODUCT(--(MOD(COLUMN(DU64:ER64),4)=MOD(COLUMN(DU64),4)),DU64:ER64)*#REF!+SUMPRODUCT(--(MOD(COLUMN(ES64:FP64),4)=MOD(COLUMN(ES64),4)),ES64:FP64)*#REF! -> #REF!
N65: =IF(BP65>0,1,IF(BN65>0,2,)) -> 0 | BL65: =SUMPRODUCT(--(MOD(COLUMN($O65:$AL65),4)=MOD(COLUMN($O65)+0,4)),$O65:$AL65) +SUMPRODUCT(--(MOD(COLUMN($AM65:$BJ65),4)=MOD(COLUMN($AM65)+0,4)),$AM65:$BJ65) -> 0 | BM65: =SUMPRODUCT(--(MOD(COLUMN($O65:$AL65),4)=MOD(COLUMN($O65)+0,4)),$O65:$AL65)*$I65 +SUMPRODUCT(--(MOD(COLUMN($AM65:$BJ65),4)=MOD(COLUMN($AM65)+0,4)),$AM65:$BJ65)*$I65 -> 0 | BN65: =SUMPRODUCT(--(MOD(COLUMN($O65:$AL65),4)=MOD(COLUMN($O65)+1,4)),$O65:$AL65) +SUMPRODUCT(--(MOD(COLUMN($AM65:$BJ65),4)=MOD(COLUMN($AM65)+1,4)),$AM65:$BJ65) -> 0 | BO65: =SUMPRODUCT(--(MOD(COLUMN($O65:$AL65),4)=MOD(COLUMN($O65)+1,4)),$O65:$AL65)*$I65 +SUMPRODUCT(--(MOD(COLUMN($AM65:$BJ65),4)=MOD(COLUMN($AM65)+1,4)),$AM65:$BJ65)*$I65 -> 0 | BP65: =SUMPRODUCT(--(MOD(COLUMN($O65:$AL65),4)=MOD(COLUMN($O65)+2,4)),$O65:$AL65) +SUMPRODUCT(--(MOD(COLUMN($AM65:$BJ65),4)=MOD(COLUMN($AM65)+2,4)),$AM65:$BJ65) -> 0 | BQ65: =SUMPRODUCT(--(MOD(COLUMN($O65:$AL65),4)=MOD(COLUMN($O65)+2,4)),$O65:$AL65)*$I65 +SUMPRODUCT(--(MOD(COLUMN($AM65:$BJ65),4)=MOD(COLUMN($AM65)+2,4)),$AM65:$BJ65)*$I65 -> 0 | DQ65: =SUMPRODUCT(--(MOD(COLUMN(BT65:CQ65),4)=MOD(COLUMN(BT65),4)),BT65:CQ65)+SUMPRODUCT(--(MOD(COLUMN(CR65:DO65),4)=MOD(COLUMN(CR65),4)),CR65:DO65) -> 0 | DR65: =SUMPRODUCT(--(MOD(COLUMN(BT65:CQ65),4)=MOD(COLUMN(BT65),4)),BT65:CQ65)*#REF!+SUMPRODUCT(--(MOD(COLUMN(CR65:DO65),4)=MOD(COLUMN(CR65),4)),CR65:DO65)*#REF! -> #REF! | FR65: =SUMPRODUCT(--(MOD(COLUMN(DU65:ER65),4)=MOD(COLUMN(DU65),4)),DU65:ER65)+SUMPRODUCT(--(MOD(COLUMN(ES65:FP65),4)=MOD(COLUMN(ES65),4)),ES65:FP65) -> 0 | FS65: =SUMPRODUCT(--(MOD(COLUMN(DU65:ER65),4)=MOD(COLUMN(DU65),4)),DU65:ER65)*#REF!+SUMPRODUCT(--(MOD(COLUMN(ES65:FP65),4)=MOD(COLUMN(ES65),4)),ES65:FP65)*#REF! -> #REF!
A66: АВТОКОМПОНЕНТ НАО | H66: CNY, без НДС: | N66: =IF(BP66>0,1,IF(BN66>0,2,)) -> 1 | O66: =IFERROR(SUMPRODUCT(($A66=$A$6:$A$64)*$I$6:$I$64*O$6:O$64),"") -> 0 | P66: =IFERROR(SUMPRODUCT(($A66=$A$6:$A$64)*$I$6:$I$64*P$6:P$64),"") -> 0 | Q66: =IFERROR(SUMPRODUCT(($A66=$A$6:$A$64)*$I$6:$I$64*Q$6:Q$64),"") -> 0 | R66: =IFERROR(SUMPRODUCT(($A66=$A$6:$A$64)*$I$6:$I$64*R$6:R$64),"") -> 0 | S66: =IFERROR(SUMPRODUCT(($A66=$A$6:$A$64)*$I$6:$I$64*S$6:S$64),"") -> 82000 | T66: =IFERROR(SUMPRODUCT(($A66=$A$6:$A$64)*$I$6:$I$64*T$6:T$64),"") -> 0 | U66: =IFERROR(SUMPRODUCT(($A66=$A$6:$A$64)*$I$6:$I$64*U$6:U$64),"") -> 0 | V66: =IFERROR(SUMPRODUCT(($A66=$A$6:$A$64)*$I$6:$I$64*V$6:V$64),"") -> 0 | ... BJ66: =IFERROR(SUMPRODUCT(($A66=$A$6:$A$64)*$I$6:$I$64*BJ$6:BJ$64),"") -> 0 | BL66: =SUMPRODUCT(--(MOD(COLUMN($O66:$AL66),4)=MOD(COLUMN($O66)+0,4)),$O66:$AL66) +SUMPRODUCT(--(MOD(COLUMN($AM66:$BJ66),4)=MOD(COLUMN($AM66)+0,4)),$AM66:$BJ66) -> 4888472 | BM66: =SUMPRODUCT(--(MOD(COLUMN($O66:$AL66),4)=MOD(COLUMN($O66)+0,4)),$O66:$AL66)*$I66 +SUMPRODUCT(--(MOD(COLUMN($AM66:$BJ66),4)=MOD(COLUMN($AM66)+0,4)),$AM66:$BJ66)*$I66 -> 0 | BN66: =SUMPRODUCT(--(MOD(COLUMN($O66:$AL66),4)=MOD(COLUMN($O66)+1,4)),$O66:$AL66) +SUMPRODUCT(--(MOD(COLUMN($AM66:$BJ66),4)=MOD(COLUMN($AM66)+1,4)),$AM66:$BJ66) -> 2467510 | BO66: =SUMPRODUCT(--(MOD(COLUMN($O66:$AL66),4)=MOD(COLUMN($O66)+1,4)),$O66:$AL66)*$I66 +SUMPRODUCT(--(MOD(COLUMN($AM66:$BJ66),4)=MOD(COLUMN($AM66)+1,4)),$AM66:$BJ66)*$I66 -> 0 | BP66: =SUMPRODUCT(--(MOD(COLUMN($O66:$AL66),4)=MOD(COLUMN($O66)+2,4)),$O66:$AL66) +SUMPRODUCT(--(MOD(COLUMN($AM66:$BJ66),4)=MOD(COLUMN($AM66)+2,4)),$AM66:$BJ66) -> 82000 | BQ66: =SUMPRODUCT(--(MOD(COLUMN($O66:$AL66),4)=MOD(COLUMN($O66)+2,4)),$O66:$AL66)*$I66 +SUMPRODUCT(--(MOD(COLUMN($AM66:$BJ66),4)=MOD(COLUMN($AM66)+2,4)),$AM66:$BJ66)*$I66 -> 0
A67: BPW (нет в системе) | H67: CNY, без НДС: | N67: =IF(BP67>0,1,IF(BN67>0,2,)) -> 0 | O67: =IFERROR(SUMPRODUCT(($A67=$A$6:$A$64)*$I$6:$I$64*O$6:O$64),"") -> 0 | P67: =IFERROR(SUMPRODUCT(($A67=$A$6:$A$64)*$I$6:$I$64*P$6:P$64),"") -> 0 | Q67: =IFERROR(SUMPRODUCT(($A67=$A$6:$A$64)*$I$6:$I$64*Q$6:Q$64),"") -> 0 | R67: =IFERROR(SUMPRODUCT(($A67=$A$6:$A$64)*$I$6:$I$64*R$6:R$64),"") -> 0 | S67: =IFERROR(SUMPRODUCT(($A67=$A$6:$A$64)*$I$6:$I$64*S$6:S$64),"") -> 0 | T67: =IFERROR(SUMPRODUCT(($A67=$A$6:$A$64)*$I$6:$I$64*T$6:T$64),"") -> 0 | U67: =IFERROR(SUMPRODUCT(($A67=$A$6:$A$64)*$I$6:$I$64*U$6:U$64),"") -> 0 | V67: =IFERROR(SUMPRODUCT(($A67=$A$6:$A$64)*$I$6:$I$64*V$6:V$64),"") -> 0 | ... BJ67: =IFERROR(SUMPRODUCT(($A67=$A$6:$A$64)*$I$6:$I$64*BJ$6:BJ$64),"") -> 0 | BL67: =SUMPRODUCT(--(MOD(COLUMN($O67:$AL67),4)=MOD(COLUMN($O67)+0,4)),$O67:$AL67) +SUMPRODUCT(--(MOD(COLUMN($AM67:$BJ67),4)=MOD(COLUMN($AM67)+0,4)),$AM67:$BJ67) -> 0 | BM67: =SUMPRODUCT(--(MOD(COLUMN($O67:$AL67),4)=MOD(COLUMN($O67)+0,4)),$O67:$AL67)*$I67 +SUMPRODUCT(--(MOD(COLUMN($AM67:$BJ67),4)=MOD(COLUMN($AM67)+0,4)),$AM67:$BJ67)*$I67 -> 0 | BN67: =SUMPRODUCT(--(MOD(COLUMN($O67:$AL67),4)=MOD(COLUMN($O67)+1,4)),$O67:$AL67) +SUMPRODUCT(--(MOD(COLUMN($AM67:$BJ67),4)=MOD(COLUMN($AM67)+1,4)),$AM67:$BJ67) -> 0 | BO67: =SUMPRODUCT(--(MOD(COLUMN($O67:$AL67),4)=MOD(COLUMN($O67)+1,4)),$O67:$AL67)*$I67 +SUMPRODUCT(--(MOD(COLUMN($AM67:$BJ67),4)=MOD(COLUMN($AM67)+1,4)),$AM67:$BJ67)*$I67 -> 0 | BP67: =SUMPRODUCT(--(MOD(COLUMN($O67:$AL67),4)=MOD(COLUMN($O67)+2,4)),$O67:$AL67) +SUMPRODUCT(--(MOD(COLUMN($AM67:$BJ67),4)=MOD(COLUMN($AM67)+2,4)),$AM67:$BJ67) -> 0 | BQ67: =SUMPRODUCT(--(MOD(COLUMN($O67:$AL67),4)=MOD(COLUMN($O67)+2,4)),$O67:$AL67)*$I67 +SUMPRODUCT(--(MOD(COLUMN($AM67:$BJ67),4)=MOD(COLUMN($AM67)+2,4)),$AM67:$BJ67)*$I67 -> 0
A68: HJBridge (нет в системе) | H68: CNY, без НДС: | N68: =IF(BP68>0,1,IF(BN68>0,2,)) -> 0 | O68: =IFERROR(SUMPRODUCT(($A68=$A$6:$A$64)*$I$6:$I$64*O$6:O$64),"") -> 0 | P68: =IFERROR(SUMPRODUCT(($A68=$A$6:$A$64)*$I$6:$I$64*P$6:P$64),"") -> 0 | Q68: =IFERROR(SUMPRODUCT(($A68=$A$6:$A$64)*$I$6:$I$64*Q$6:Q$64),"") -> 0 | R68: =IFERROR(SUMPRODUCT(($A68=$A$6:$A$64)*$I$6:$I$64*R$6:R$64),"") -> 0 | S68: =IFERROR(SUMPRODUCT(($A68=$A$6:$A$64)*$I$6:$I$64*S$6:S$64),"") -> 0 | T68: =IFERROR(SUMPRODUCT(($A68=$A$6:$A$64)*$I$6:$I$64*T$6:T$64),"") -> 0 | U68: =IFERROR(SUMPRODUCT(($A68=$A$6:$A$64)*$I$6:$I$64*U$6:U$64),"") -> 0 | V68: =IFERROR(SUMPRODUCT(($A68=$A$6:$A$64)*$I$6:$I$64*V$6:V$64),"") -> 0 | ... BJ68: =IFERROR(SUMPRODUCT(($A68=$A$6:$A$64)*$I$6:$I$64*BJ$6:BJ$64),"") -> 0 | BL68: =SUMPRODUCT(--(MOD(COLUMN($O68:$AL68),4)=MOD(COLUMN($O68)+0,4)),$O68:$AL68) +SUMPRODUCT(--(MOD(COLUMN($AM68:$BJ68),4)=MOD(COLUMN($AM68)+0,4)),$AM68:$BJ68) -> 0 | BM68: =SUMPRODUCT(--(MOD(COLUMN($O68:$AL68),4)=MOD(COLUMN($O68)+0,4)),$O68:$AL68)*$I68 +SUMPRODUCT(--(MOD(COLUMN($AM68:$BJ68),4)=MOD(COLUMN($AM68)+0,4)),$AM68:$BJ68)*$I68 -> 0 | BN68: =SUMPRODUCT(--(MOD(COLUMN($O68:$AL68),4)=MOD(COLUMN($O68)+1,4)),$O68:$AL68) +SUMPRODUCT(--(MOD(COLUMN($AM68:$BJ68),4)=MOD(COLUMN($AM68)+1,4)),$AM68:$BJ68) -> 0 | BO68: =SUMPRODUCT(--(MOD(COLUMN($O68:$AL68),4)=MOD(COLUMN($O68)+1,4)),$O68:$AL68)*$I68 +SUMPRODUCT(--(MOD(COLUMN($AM68:$BJ68),4)=MOD(COLUMN($AM68)+1,4)),$AM68:$BJ68)*$I68 -> 0 | BP68: =SUMPRODUCT(--(MOD(COLUMN($O68:$AL68),4)=MOD(COLUMN($O68)+2,4)),$O68:$AL68) +SUMPRODUCT(--(MOD(COLUMN($AM68:$BJ68),4)=MOD(COLUMN($AM68)+2,4)),$AM68:$BJ68) -> 0 | BQ68: =SUMPRODUCT(--(MOD(COLUMN($O68:$AL68),4)=MOD(COLUMN($O68)+2,4)),$O68:$AL68)*$I68 +SUMPRODUCT(--(MOD(COLUMN($AM68:$BJ68),4)=MOD(COLUMN($AM68)+2,4)),$AM68:$BJ68)*$I68 -> 0
A69: НПО РОСТАР ООО | H69: CNY, без НДС: | N69: =IF(BP69>0,1,IF(BN69>0,2,)) -> 0 | O69: =IFERROR(SUMPRODUCT(($A69=$A$6:$A$64)*$I$6:$I$64*O$6:O$64),"") -> 0 | P69: =IFERROR(SUMPRODUCT(($A69=$A$6:$A$64)*$I$6:$I$64*P$6:P$64),"") -> 0 | Q69: =IFERROR(SUMPRODUCT(($A69=$A$6:$A$64)*$I$6:$I$64*Q$6:Q$64),"") -> 0 | R69: =IFERROR(SUMPRODUCT(($A69=$A$6:$A$64)*$I$6:$I$64*R$6:R$64),"") -> 0 | S69: =IFERROR(SUMPRODUCT(($A69=$A$6:$A$64)*$I$6:$I$64*S$6:S$64),"") -> 0 | T69: =IFERROR(SUMPRODUCT(($A69=$A$6:$A$64)*$I$6:$I$64*T$6:T$64),"") -> 0 | U69: =IFERROR(SUMPRODUCT(($A69=$A$6:$A$64)*$I$6:$I$64*U$6:U$64),"") -> 0 | V69: =IFERROR(SUMPRODUCT(($A69=$A$6:$A$64)*$I$6:$I$64*V$6:V$64),"") -> 0 | ... BJ69: =IFERROR(SUMPRODUCT(($A69=$A$6:$A$64)*$I$6:$I$64*BJ$6:BJ$64),"") -> 0 | BL69: =SUMPRODUCT(--(MOD(COLUMN($O69:$AL69),4)=MOD(COLUMN($O69)+0,4)),$O69:$AL69) +SUMPRODUCT(--(MOD(COLUMN($AM69:$BJ69),4)=MOD(COLUMN($AM69)+0,4)),$AM69:$BJ69) -> 0 | BM69: =SUMPRODUCT(--(MOD(COLUMN($O69:$AL69),4)=MOD(COLUMN($O69)+0,4)),$O69:$AL69)*$I69 +SUMPRODUCT(--(MOD(COLUMN($AM69:$BJ69),4)=MOD(COLUMN($AM69)+0,4)),$AM69:$BJ69)*$I69 -> 0 | BN69: =SUMPRODUCT(--(MOD(COLUMN($O69:$AL69),4)=MOD(COLUMN($O69)+1,4)),$O69:$AL69) +SUMPRODUCT(--(MOD(COLUMN($AM69:$BJ69),4)=MOD(COLUMN($AM69)+1,4)),$AM69:$BJ69) -> 0 | BO69: =SUMPRODUCT(--(MOD(COLUMN($O69:$AL69),4)=MOD(COLUMN($O69)+1,4)),$O69:$AL69)*$I69 +SUMPRODUCT(--(MOD(COLUMN($AM69:$BJ69),4)=MOD(COLUMN($AM69)+1,4)),$AM69:$BJ69)*$I69 -> 0 | BP69: =SUMPRODUCT(--(MOD(COLUMN($O69:$AL69),4)=MOD(COLUMN($O69)+2,4)),$O69:$AL69) +SUMPRODUCT(--(MOD(COLUMN($AM69:$BJ69),4)=MOD(COLUMN($AM69)+2,4)),$AM69:$BJ69) -> 0 | BQ69: =SUMPRODUCT(--(MOD(COLUMN($O69:$AL69),4)=MOD(COLUMN($O69)+2,4)),$O69:$AL69)*$I69 +SUMPRODUCT(--(MOD(COLUMN($AM69:$BJ69),4)=MOD(COLUMN($AM69)+2,4)),$AM69:$BJ69)*$I69 -> 0
A70: ПЛАНТ ООО | H70: CNY, без НДС: | N70: =IF(BP70>0,1,IF(BN70>0,2,)) -> 1 | O70: =IFERROR(SUMPRODUCT(($A70=$A$6:$A$64)*$I$6:$I$64*O$6:O$64),"") -> 0 | P70: =IFERROR(SUMPRODUCT(($A70=$A$6:$A$64)*$I$6:$I$64*P$6:P$64),"") -> 0 | Q70: =IFERROR(SUMPRODUCT(($A70=$A$6:$A$64)*$I$6:$I$64*Q$6:Q$64),"") -> 0 | R70: =IFERROR(SUMPRODUCT(($A70=$A$6:$A$64)*$I$6:$I$64*R$6:R$64),"") -> 0 | S70: =IFERROR(SUMPRODUCT(($A70=$A$6:$A$64)*$I$6:$I$64*S$6:S$64),"") -> 0 | T70: =IFERROR(SUMPRODUCT(($A70=$A$6:$A$64)*$I$6:$I$64*T$6:T$64),"") -> 0 | U70: =IFERROR(SUMPRODUCT(($A70=$A$6:$A$64)*$I$6:$I$64*U$6:U$64),"") -> 0 | V70: =IFERROR(SUMPRODUCT(($A70=$A$6:$A$64)*$I$6:$I$64*V$6:V$64),"") -> 0 | ... BJ70: =IFERROR(SUMPRODUCT(($A70=$A$6:$A$64)*$I$6:$I$64*BJ$6:BJ$64),"") -> 0 | BL70: =SUMPRODUCT(--(MOD(COLUMN($O70:$AL70),4)=MOD(COLUMN($O70)+0,4)),$O70:$AL70) +SUMPRODUCT(--(MOD(COLUMN($AM70:$BJ70),4)=MOD(COLUMN($AM70)+0,4)),$AM70:$BJ70) -> 0 | BM70: =SUMPRODUCT(--(MOD(COLUMN($O70:$AL70),4)=MOD(COLUMN($O70)+0,4)),$O70:$AL70)*$I70 +SUMPRODUCT(--(MOD(COLUMN($AM70:$BJ70),4)=MOD(COLUMN($AM70)+0,4)),$AM70:$BJ70)*$I70 -> 0 | BN70: =SUMPRODUCT(--(MOD(COLUMN($O70:$AL70),4)=MOD(COLUMN($O70)+1,4)),$O70:$AL70) +SUMPRODUCT(--(MOD(COLUMN($AM70:$BJ70),4)=MOD(COLUMN($AM70)+1,4)),$AM70:$BJ70) -> 909920 | BO70: =SUMPRODUCT(--(MOD(COLUMN($O70:$AL70),4)=MOD(COLUMN($O70)+1,4)),$O70:$AL70)*$I70 +SUMPRODUCT(--(MOD(COLUMN($AM70:$BJ70),4)=MOD(COLUMN($AM70)+1,4)),$AM70:$BJ70)*$I70 -> 0 | BP70: =SUMPRODUCT(--(MOD(COLUMN($O70:$AL70),4)=MOD(COLUMN($O70)+2,4)),$O70:$AL70) +SUMPRODUCT(--(MOD(COLUMN($AM70:$BJ70),4)=MOD(COLUMN($AM70)+2,4)),$AM70:$BJ70) -> 599720 | BQ70: =SUMPRODUCT(--(MOD(COLUMN($O70:$AL70),4)=MOD(COLUMN($O70)+2,4)),$O70:$AL70)*$I70 +SUMPRODUCT(--(MOD(COLUMN($AM70:$BJ70),4)=MOD(COLUMN($AM70)+2,4)),$AM70:$BJ70)*$I70 -> 0
A71: АВГ АВТОКОМПОНЕНТЫ ООО | H71: CNY, без НДС: | N71: =IF(BP71>0,1,IF(BN71>0,2,)) -> 1 | O71: =IFERROR(SUMPRODUCT(($A71=$A$6:$A$64)*$I$6:$I$64*O$6:O$64),"") -> 55404 | P71: =IFERROR(SUMPRODUCT(($A71=$A$6:$A$64)*$I$6:$I$64*P$6:P$64),"") -> 0 | Q71: =IFERROR(SUMPRODUCT(($A71=$A$6:$A$64)*$I$6:$I$64*Q$6:Q$64),"") -> 0 | R71: =IFERROR(SUMPRODUCT(($A71=$A$6:$A$64)*$I$6:$I$64*R$6:R$64),"") -> 0 | S71: =IFERROR(SUMPRODUCT(($A71=$A$6:$A$64)*$I$6:$I$64*S$6:S$64),"") -> 55404 | T71: =IFERROR(SUMPRODUCT(($A71=$A$6:$A$64)*$I$6:$I$64*T$6:T$64),"") -> 0 | U71: =IFERROR(SUMPRODUCT(($A71=$A$6:$A$64)*$I$6:$I$64*U$6:U$64),"") -> 0 | V71: =IFERROR(SUMPRODUCT(($A71=$A$6:$A$64)*$I$6:$I$64*V$6:V$64),"") -> 0 | ... BJ71: =IFERROR(SUMPRODUCT(($A71=$A$6:$A$64)*$I$6:$I$64*BJ$6:BJ$64),"") -> 0 | BL71: =SUMPRODUCT(--(MOD(COLUMN($O71:$AL71),4)=MOD(COLUMN($O71)+0,4)),$O71:$AL71) +SUMPRODUCT(--(MOD(COLUMN($AM71:$BJ71),4)=MOD(COLUMN($AM71)+0,4)),$AM71:$BJ71) -> 3074922 | BM71: =SUMPRODUCT(--(MOD(COLUMN($O71:$AL71),4)=MOD(COLUMN($O71)+0,4)),$O71:$AL71)*$I71 +SUMPRODUCT(--(MOD(COLUMN($AM71:$BJ71),4)=MOD(COLUMN($AM71)+0,4)),$AM71:$BJ71)*$I71 -> 0 | BN71: =SUMPRODUCT(--(MOD(COLUMN($O71:$AL71),4)=MOD(COLUMN($O71)+1,4)),$O71:$AL71) +SUMPRODUCT(--(MOD(COLUMN($AM71:$BJ71),4)=MOD(COLUMN($AM71)+1,4)),$AM71:$BJ71) -> 1752271 | BO71: =SUMPRODUCT(--(MOD(COLUMN($O71:$AL71),4)=MOD(COLUMN($O71)+1,4)),$O71:$AL71)*$I71 +SUMPRODUCT(--(MOD(COLUMN($AM71:$BJ71),4)=MOD(COLUMN($AM71)+1,4)),$AM71:$BJ71)*$I71 -> 0 | BP71: =SUMPRODUCT(--(MOD(COLUMN($O71:$AL71),4)=MOD(COLUMN($O71)+2,4)),$O71:$AL71) +SUMPRODUCT(--(MOD(COLUMN($AM71:$BJ71),4)=MOD(COLUMN($AM71)+2,4)),$AM71:$BJ71) -> 53833 | BQ71: =SUMPRODUCT(--(MOD(COLUMN($O71:$AL71),4)=MOD(COLUMN($O71)+2,4)),$O71:$AL71)*$I71 +SUMPRODUCT(--(MOD(COLUMN($AM71:$BJ71),4)=MOD(COLUMN($AM71)+2,4)),$AM71:$BJ71)*$I71 -> 0
A72: ВСЕ | H72: CNY, без НДС: | N72: =IF(BP72>0,1,IF(BN72>0,2,)) -> 1 | O72: =IFERROR(SUMPRODUCT($I$6:$I$64,O$6:O$64),"") -> 55404 | P72: =IFERROR(SUMPRODUCT($I$6:$I$64,P$6:P$64),"") -> 0 | Q72: =IFERROR(SUMPRODUCT($I$6:$I$64,Q$6:Q$64),"") -> 0 | R72: =IFERROR(SUMPRODUCT($I$6:$I$64,R$6:R$64),"") -> 0 | S72: =IFERROR(SUMPRODUCT($I$6:$I$64,S$6:S$64),"") -> 137404 | T72: =IFERROR(SUMPRODUCT($I$6:$I$64,T$6:T$64),"") -> 0 | U72: =IFERROR(SUMPRODUCT($I$6:$I$64,U$6:U$64),"") -> 0 | V72: =IFERROR(SUMPRODUCT($I$6:$I$64,V$6:V$64),"") -> 0 | ... BJ72: =IFERROR(SUMPRODUCT($I$6:$I$64,BJ$6:BJ$64),"") -> 0 | BL72: =SUMPRODUCT(--(MOD(COLUMN($O72:$AL72),4)=MOD(COLUMN($O72)+0,4)),$O72:$AL72) +SUMPRODUCT(--(MOD(COLUMN($AM72:$BJ72),4)=MOD(COLUMN($AM72)+0,4)),$AM72:$BJ72) -> 7963394 | BM72: =SUMPRODUCT(--(MOD(COLUMN($O72:$AL72),4)=MOD(COLUMN($O72)+0,4)),$O72:$AL72)*$I72 +SUMPRODUCT(--(MOD(COLUMN($AM72:$BJ72),4)=MOD(COLUMN($AM72)+0,4)),$AM72:$BJ72)*$I72 -> 0 | BN72: =SUMPRODUCT(--(MOD(COLUMN($O72:$AL72),4)=MOD(COLUMN($O72)+1,4)),$O72:$AL72) +SUMPRODUCT(--(MOD(COLUMN($AM72:$BJ72),4)=MOD(COLUMN($AM72)+1,4)),$AM72:$BJ72) -> 5129701 | BO72: =SUMPRODUCT(--(MOD(COLUMN($O72:$AL72),4)=MOD(COLUMN($O72)+1,4)),$O72:$AL72)*$I72 +SUMPRODUCT(--(MOD(COLUMN($AM72:$BJ72),4)=MOD(COLUMN($AM72)+1,4)),$AM72:$BJ72)*$I72 -> 0 | BP72: =SUMPRODUCT(--(MOD(COLUMN($O72:$AL72),4)=MOD(COLUMN($O72)+2,4)),$O72:$AL72) +SUMPRODUCT(--(MOD(COLUMN($AM72:$BJ72),4)=MOD(COLUMN($AM72)+2,4)),$AM72:$BJ72) -> 735553 | BQ72: =SUMPRODUCT(--(MOD(COLUMN($O72:$AL72),4)=MOD(COLUMN($O72)+2,4)),$O72:$AL72)*$I72 +SUMPRODUCT(--(MOD(COLUMN($AM72:$BJ72),4)=MOD(COLUMN($AM72)+2,4)),$AM72:$BJ72)*$I72 -> 0
A73: АВТОКОМПОНЕНТ НАО | H73: шт.: | N73: =IF(BP73>0,1,IF(BN73>0,2,)) -> 1 | O73: =IFERROR(SUMPRODUCT(($A73=$A$6:$A$64)*($G$6:$G$64>0)*O$6:O$64),"") -> 0 | P73: =IFERROR(SUMPRODUCT(($A73=$A$6:$A$64)*($G$6:$G$64>0)*P$6:P$64),"") -> 0 | Q73: =IFERROR(SUMPRODUCT(($A73=$A$6:$A$64)*($G$6:$G$64>0)*Q$6:Q$64),"") -> 0 | R73: =IFERROR(SUMPRODUCT(($A73=$A$6:$A$64)*($G$6:$G$64>0)*R$6:R$64),"") -> 0 | S73: =IFERROR(SUMPRODUCT(($A73=$A$6:$A$64)*($G$6:$G$64>0)*S$6:S$64),"") -> 2000 | T73: =IFERROR(SUMPRODUCT(($A73=$A$6:$A$64)*($G$6:$G$64>0)*T$6:T$64),"") -> 0 | U73: =IFERROR(SUMPRODUCT(($A73=$A$6:$A$64)*($G$6:$G$64>0)*U$6:U$64),"") -> 0 | V73: =IFERROR(SUMPRODUCT(($A73=$A$6:$A$64)*($G$6:$G$64>0)*V$6:V$64),"") -> 0 | ... BJ73: =IFERROR(SUMPRODUCT(($A73=$A$6:$A$64)*($G$6:$G$64>0)*BJ$6:BJ$64),"") -> 0 | BL73: =SUMPRODUCT(--(MOD(COLUMN($O73:$AL73),4)=MOD(COLUMN($O73)+0,4)),$O73:$AL73) +SUMPRODUCT(--(MOD(COLUMN($AM73:$BJ73),4)=MOD(COLUMN($AM73)+0,4)),$AM73:$BJ73) -> 5860 | BM73: =SUMPRODUCT(--(MOD(COLUMN($O73:$AL73),4)=MOD(COLUMN($O73)+0,4)),$O73:$AL73)*$I73 +SUMPRODUCT(--(MOD(COLUMN($AM73:$BJ73),4)=MOD(COLUMN($AM73)+0,4)),$AM73:$BJ73)*$I73 -> 0 | BN73: =SUMPRODUCT(--(MOD(COLUMN($O73:$AL73),4)=MOD(COLUMN($O73)+1,4)),$O73:$AL73) +SUMPRODUCT(--(MOD(COLUMN($AM73:$BJ73),4)=MOD(COLUMN($AM73)+1,4)),$AM73:$BJ73) -> 5200 | BO73: =SUMPRODUCT(--(MOD(COLUMN($O73:$AL73),4)=MOD(COLUMN($O73)+1,4)),$O73:$AL73)*$I73 +SUMPRODUCT(--(MOD(COLUMN($AM73:$BJ73),4)=MOD(COLUMN($AM73)+1,4)),$AM73:$BJ73)*$I73 -> 0 | BP73: =SUMPRODUCT(--(MOD(COLUMN($O73:$AL73),4)=MOD(COLUMN($O73)+2,4)),$O73:$AL73) +SUMPRODUCT(--(MOD(COLUMN($AM73:$BJ73),4)=MOD(COLUMN($AM73)+2,4)),$AM73:$BJ73) -> 2000 | BQ73: =SUMPRODUCT(--(MOD(COLUMN($O73:$AL73),4)=MOD(COLUMN($O73)+2,4)),$O73:$AL73)*$I73 +SUMPRODUCT(--(MOD(COLUMN($AM73:$BJ73),4)=MOD(COLUMN($AM73)+2,4)),$AM73:$BJ73)*$I73 -> 0
A74: BPW (нет в системе) | H74: шт.: | N74: =IF(BP74>0,1,IF(BN74>0,2,)) -> 0 | O74: =IFERROR(SUMPRODUCT(($A74=$A$6:$A$64)*($G$6:$G$64>0)*O$6:O$64),"") -> 0 | P74: =IFERROR(SUMPRODUCT(($A74=$A$6:$A$64)*($G$6:$G$64>0)*P$6:P$64),"") -> 0 | Q74: =IFERROR(SUMPRODUCT(($A74=$A$6:$A$64)*($G$6:$G$64>0)*Q$6:Q$64),"") -> 0 | R74: =IFERROR(SUMPRODUCT(($A74=$A$6:$A$64)*($G$6:$G$64>0)*R$6:R$64),"") -> 0 | S74: =IFERROR(SUMPRODUCT(($A74=$A$6:$A$64)*($G$6:$G$64>0)*S$6:S$64),"") -> 0 | T74: =IFERROR(SUMPRODUCT(($A74=$A$6:$A$64)*($G$6:$G$64>0)*T$6:T$64),"") -> 0 | U74: =IFERROR(SUMPRODUCT(($A74=$A$6:$A$64)*($G$6:$G$64>0)*U$6:U$64),"") -> 0 | V74: =IFERROR(SUMPRODUCT(($A74=$A$6:$A$64)*($G$6:$G$64>0)*V$6:V$64),"") -> 0 | ... BJ74: =IFERROR(SUMPRODUCT(($A74=$A$6:$A$64)*($G$6:$G$64>0)*BJ$6:BJ$64),"") -> 0 | BL74: =SUMPRODUCT(--(MOD(COLUMN($O74:$AL74),4)=MOD(COLUMN($O74)+0,4)),$O74:$AL74) +SUMPRODUCT(--(MOD(COLUMN($AM74:$BJ74),4)=MOD(COLUMN($AM74)+0,4)),$AM74:$BJ74) -> 0 | BM74: =SUMPRODUCT(--(MOD(COLUMN($O74:$AL74),4)=MOD(COLUMN($O74)+0,4)),$O74:$AL74)*$I74 +SUMPRODUCT(--(MOD(COLUMN($AM74:$BJ74),4)=MOD(COLUMN($AM74)+0,4)),$AM74:$BJ74)*$I74 -> 0 | BN74: =SUMPRODUCT(--(MOD(COLUMN($O74:$AL74),4)=MOD(COLUMN($O74)+1,4)),$O74:$AL74) +SUMPRODUCT(--(MOD(COLUMN($AM74:$BJ74),4)=MOD(COLUMN($AM74)+1,4)),$AM74:$BJ74) -> 0 | BO74: =SUMPRODUCT(--(MOD(COLUMN($O74:$AL74),4)=MOD(COLUMN($O74)+1,4)),$O74:$AL74)*$I74 +SUMPRODUCT(--(MOD(COLUMN($AM74:$BJ74),4)=MOD(COLUMN($AM74)+1,4)),$AM74:$BJ74)*$I74 -> 0 | BP74: =SUMPRODUCT(--(MOD(COLUMN($O74:$AL74),4)=MOD(COLUMN($O74)+2,4)),$O74:$AL74) +SUMPRODUCT(--(MOD(COLUMN($AM74:$BJ74),4)=MOD(COLUMN($AM74)+2,4)),$AM74:$BJ74) -> 0 | BQ74: =SUMPRODUCT(--(MOD(COLUMN($O74:$AL74),4)=MOD(COLUMN($O74)+2,4)),$O74:$AL74)*$I74 +SUMPRODUCT(--(MOD(COLUMN($AM74:$BJ74),4)=MOD(COLUMN($AM74)+2,4)),$AM74:$BJ74)*$I74 -> 0
A75: HJBridge (нет в системе) | H75: шт.: | N75: =IF(BP75>0,1,IF(BN75>0,2,)) -> 0 | O75: =IFERROR(SUMPRODUCT(($A75=$A$6:$A$64)*($G$6:$G$64>0)*O$6:O$64),"") -> 0 | P75: =IFERROR(SUMPRODUCT(($A75=$A$6:$A$64)*($G$6:$G$64>0)*P$6:P$64),"") -> 0 | Q75: =IFERROR(SUMPRODUCT(($A75=$A$6:$A$64)*($G$6:$G$64>0)*Q$6:Q$64),"") -> 0 | R75: =IFERROR(SUMPRODUCT(($A75=$A$6:$A$64)*($G$6:$G$64>0)*R$6:R$64),"") -> 0 | S75: =IFERROR(SUMPRODUCT(($A75=$A$6:$A$64)*($G$6:$G$64>0)*S$6:S$64),"") -> 0 | T75: =IFERROR(SUMPRODUCT(($A75=$A$6:$A$64)*($G$6:$G$64>0)*T$6:T$64),"") -> 0 | U75: =IFERROR(SUMPRODUCT(($A75=$A$6:$A$64)*($G$6:$G$64>0)*U$6:U$64),"") -> 0 | V75: =IFERROR(SUMPRODUCT(($A75=$A$6:$A$64)*($G$6:$G$64>0)*V$6:V$64),"") -> 0 | ... BJ75: =IFERROR(SUMPRODUCT(($A75=$A$6:$A$64)*($G$6:$G$64>0)*BJ$6:BJ$64),"") -> 0 | BL75: =SUMPRODUCT(--(MOD(COLUMN($O75:$AL75),4)=MOD(COLUMN($O75)+0,4)),$O75:$AL75) +SUMPRODUCT(--(MOD(COLUMN($AM75:$BJ75),4)=MOD(COLUMN($AM75)+0,4)),$AM75:$BJ75) -> 0 | BM75: =SUMPRODUCT(--(MOD(COLUMN($O75:$AL75),4)=MOD(COLUMN($O75)+0,4)),$O75:$AL75)*$I75 +SUMPRODUCT(--(MOD(COLUMN($AM75:$BJ75),4)=MOD(COLUMN($AM75)+0,4)),$AM75:$BJ75)*$I75 -> 0 | BN75: =SUMPRODUCT(--(MOD(COLUMN($O75:$AL75),4)=MOD(COLUMN($O75)+1,4)),$O75:$AL75) +SUMPRODUCT(--(MOD(COLUMN($AM75:$BJ75),4)=MOD(COLUMN($AM75)+1,4)),$AM75:$BJ75) -> 0 | BO75: =SUMPRODUCT(--(MOD(COLUMN($O75:$AL75),4)=MOD(COLUMN($O75)+1,4)),$O75:$AL75)*$I75 +SUMPRODUCT(--(MOD(COLUMN($AM75:$BJ75),4)=MOD(COLUMN($AM75)+1,4)),$AM75:$BJ75)*$I75 -> 0 | BP75: =SUMPRODUCT(--(MOD(COLUMN($O75:$AL75),4)=MOD(COLUMN($O75)+2,4)),$O75:$AL75) +SUMPRODUCT(--(MOD(COLUMN($AM75:$BJ75),4)=MOD(COLUMN($AM75)+2,4)),$AM75:$BJ75) -> 0 | BQ75: =SUMPRODUCT(--(MOD(COLUMN($O75:$AL75),4)=MOD(COLUMN($O75)+2,4)),$O75:$AL75)*$I75 +SUMPRODUCT(--(MOD(COLUMN($AM75:$BJ75),4)=MOD(COLUMN($AM75)+2,4)),$AM75:$BJ75)*$I75 -> 0
A76: НПО РОСТАР ООО | H76: шт.: | N76: =IF(BP76>0,1,IF(BN76>0,2,)) -> 0 | O76: =IFERROR(SUMPRODUCT(($A76=$A$6:$A$64)*($G$6:$G$64>0)*O$6:O$64),"") -> 0 | P76: =IFERROR(SUMPRODUCT(($A76=$A$6:$A$64)*($G$6:$G$64>0)*P$6:P$64),"") -> 0 | Q76: =IFERROR(SUMPRODUCT(($A76=$A$6:$A$64)*($G$6:$G$64>0)*Q$6:Q$64),"") -> 0 | R76: =IFERROR(SUMPRODUCT(($A76=$A$6:$A$64)*($G$6:$G$64>0)*R$6:R$64),"") -> 0 | S76: =IFERROR(SUMPRODUCT(($A76=$A$6:$A$64)*($G$6:$G$64>0)*S$6:S$64),"") -> 0 | T76: =IFERROR(SUMPRODUCT(($A76=$A$6:$A$64)*($G$6:$G$64>0)*T$6:T$64),"") -> 0 | U76: =IFERROR(SUMPRODUCT(($A76=$A$6:$A$64)*($G$6:$G$64>0)*U$6:U$64),"") -> 0 | V76: =IFERROR(SUMPRODUCT(($A76=$A$6:$A$64)*($G$6:$G$64>0)*V$6:V$64),"") -> 0 | ... BJ76: =IFERROR(SUMPRODUCT(($A76=$A$6:$A$64)*($G$6:$G$64>0)*BJ$6:BJ$64),"") -> 0 | BL76: =SUMPRODUCT(--(MOD(COLUMN($O76:$AL76),4)=MOD(COLUMN($O76)+0,4)),$O76:$AL76) +SUMPRODUCT(--(MOD(COLUMN($AM76:$BJ76),4)=MOD(COLUMN($AM76)+0,4)),$AM76:$BJ76) -> 0 | BM76: =SUMPRODUCT(--(MOD(COLUMN($O76:$AL76),4)=MOD(COLUMN($O76)+0,4)),$O76:$AL76)*$I76 +SUMPRODUCT(--(MOD(COLUMN($AM76:$BJ76),4)=MOD(COLUMN($AM76)+0,4)),$AM76:$BJ76)*$I76 -> 0 | BN76: =SUMPRODUCT(--(MOD(COLUMN($O76:$AL76),4)=MOD(COLUMN($O76)+1,4)),$O76:$AL76) +SUMPRODUCT(--(MOD(COLUMN($AM76:$BJ76),4)=MOD(COLUMN($AM76)+1,4)),$AM76:$BJ76) -> 0 | BO76: =SUMPRODUCT(--(MOD(COLUMN($O76:$AL76),4)=MOD(COLUMN($O76)+1,4)),$O76:$AL76)*$I76 +SUMPRODUCT(--(MOD(COLUMN($AM76:$BJ76),4)=MOD(COLUMN($AM76)+1,4)),$AM76:$BJ76)*$I76 -> 0 | BP76: =SUMPRODUCT(--(MOD(COLUMN($O76:$AL76),4)=MOD(COLUMN($O76)+2,4)),$O76:$AL76) +SUMPRODUCT(--(MOD(COLUMN($AM76:$BJ76),4)=MOD(COLUMN($AM76)+2,4)),$AM76:$BJ76) -> 0 | BQ76: =SUMPRODUCT(--(MOD(COLUMN($O76:$AL76),4)=MOD(COLUMN($O76)+2,4)),$O76:$AL76)*$I76 +SUMPRODUCT(--(MOD(COLUMN($AM76:$BJ76),4)=MOD(COLUMN($AM76)+2,4)),$AM76:$BJ76)*$I76 -> 0
A77: ПЛАНТ ООО | H77: шт.: | N77: =IF(BP77>0,1,IF(BN77>0,2,)) -> 1 | O77: =IFERROR(SUMPRODUCT(($A77=$A$6:$A$64)*($G$6:$G$64>0)*O$6:O$64),"") -> 0 | P77: =IFERROR(SUMPRODUCT(($A77=$A$6:$A$64)*($G$6:$G$64>0)*P$6:P$64),"") -> 0 | Q77: =IFERROR(SUMPRODUCT(($A77=$A$6:$A$64)*($G$6:$G$64>0)*Q$6:Q$64),"") -> 0 | R77: =IFERROR(SUMPRODUCT(($A77=$A$6:$A$64)*($G$6:$G$64>0)*R$6:R$64),"") -> 0 | S77: =IFERROR(SUMPRODUCT(($A77=$A$6:$A$64)*($G$6:$G$64>0)*S$6:S$64),"") -> 0 | T77: =IFERROR(SUMPRODUCT(($A77=$A$6:$A$64)*($G$6:$G$64>0)*T$6:T$64),"") -> 0 | U77: =IFERROR(SUMPRODUCT(($A77=$A$6:$A$64)*($G$6:$G$64>0)*U$6:U$64),"") -> 0 | V77: =IFERROR(SUMPRODUCT(($A77=$A$6:$A$64)*($G$6:$G$64>0)*V$6:V$64),"") -> 0 | ... BJ77: =IFERROR(SUMPRODUCT(($A77=$A$6:$A$64)*($G$6:$G$64>0)*BJ$6:BJ$64),"") -> 0 | BL77: =SUMPRODUCT(--(MOD(COLUMN($O77:$AL77),4)=MOD(COLUMN($O77)+0,4)),$O77:$AL77) +SUMPRODUCT(--(MOD(COLUMN($AM77:$BJ77),4)=MOD(COLUMN($AM77)+0,4)),$AM77:$BJ77) -> 0 | BM77: =SUMPRODUCT(--(MOD(COLUMN($O77:$AL77),4)=MOD(COLUMN($O77)+0,4)),$O77:$AL77)*$I77 +SUMPRODUCT(--(MOD(COLUMN($AM77:$BJ77),4)=MOD(COLUMN($AM77)+0,4)),$AM77:$BJ77)*$I77 -> 0 | BN77: =SUMPRODUCT(--(MOD(COLUMN($O77:$AL77),4)=MOD(COLUMN($O77)+1,4)),$O77:$AL77) +SUMPRODUCT(--(MOD(COLUMN($AM77:$BJ77),4)=MOD(COLUMN($AM77)+1,4)),$AM77:$BJ77) -> 440 | BO77: =SUMPRODUCT(--(MOD(COLUMN($O77:$AL77),4)=MOD(COLUMN($O77)+1,4)),$O77:$AL77)*$I77 +SUMPRODUCT(--(MOD(COLUMN($AM77:$BJ77),4)=MOD(COLUMN($AM77)+1,4)),$AM77:$BJ77)*$I77 -> 0 | BP77: =SUMPRODUCT(--(MOD(COLUMN($O77:$AL77),4)=MOD(COLUMN($O77)+2,4)),$O77:$AL77) +SUMPRODUCT(--(MOD(COLUMN($AM77:$BJ77),4)=MOD(COLUMN($AM77)+2,4)),$AM77:$BJ77) -> 290 | BQ77: =SUMPRODUCT(--(MOD(COLUMN($O77:$AL77),4)=MOD(COLUMN($O77)+2,4)),$O77:$AL77)*$I77 +SUMPRODUCT(--(MOD(COLUMN($AM77:$BJ77),4)=MOD(COLUMN($AM77)+2,4)),$AM77:$BJ77)*$I77 -> 0
A78: АВГ АВТОКОМПОНЕНТЫ ООО | H78: шт.: | N78: =IF(BP78>0,1,IF(BN78>0,2,)) -> 1 | O78: =IFERROR(SUMPRODUCT(($A78=$A$6:$A$64)*($G$6:$G$64>0)*O$6:O$64),"") -> 64 | P78: =IFERROR(SUMPRODUCT(($A78=$A$6:$A$64)*($G$6:$G$64>0)*P$6:P$64),"") -> 0 | Q78: =IFERROR(SUMPRODUCT(($A78=$A$6:$A$64)*($G$6:$G$64>0)*Q$6:Q$64),"") -> 0 | R78: =IFERROR(SUMPRODUCT(($A78=$A$6:$A$64)*($G$6:$G$64>0)*R$6:R$64),"") -> 0 | S78: =IFERROR(SUMPRODUCT(($A78=$A$6:$A$64)*($G$6:$G$64>0)*S$6:S$64),"") -> 64 | T78: =IFERROR(SUMPRODUCT(($A78=$A$6:$A$64)*($G$6:$G$64>0)*T$6:T$64),"") -> 0 | U78: =IFERROR(SUMPRODUCT(($A78=$A$6:$A$64)*($G$6:$G$64>0)*U$6:U$64),"") -> 0 | V78: =IFERROR(SUMPRODUCT(($A78=$A$6:$A$64)*($G$6:$G$64>0)*V$6:V$64),"") -> 0 | ... BJ78: =IFERROR(SUMPRODUCT(($A78=$A$6:$A$64)*($G$6:$G$64>0)*BJ$6:BJ$64),"") -> 0 | BL78: =SUMPRODUCT(--(MOD(COLUMN($O78:$AL78),4)=MOD(COLUMN($O78)+0,4)),$O78:$AL78) +SUMPRODUCT(--(MOD(COLUMN($AM78:$BJ78),4)=MOD(COLUMN($AM78)+0,4)),$AM78:$BJ78) -> 3552 | BM78: =SUMPRODUCT(--(MOD(COLUMN($O78:$AL78),4)=MOD(COLUMN($O78)+0,4)),$O78:$AL78)*$I78 +SUMPRODUCT(--(MOD(COLUMN($AM78:$BJ78),4)=MOD(COLUMN($AM78)+0,4)),$AM78:$BJ78)*$I78 -> 0 | BN78: =SUMPRODUCT(--(MOD(COLUMN($O78:$AL78),4)=MOD(COLUMN($O78)+1,4)),$O78:$AL78) +SUMPRODUCT(--(MOD(COLUMN($AM78:$BJ78),4)=MOD(COLUMN($AM78)+1,4)),$AM78:$BJ78) -> 1856 | BO78: =SUMPRODUCT(--(MOD(COLUMN($O78:$AL78),4)=MOD(COLUMN($O78)+1,4)),$O78:$AL78)*$I78 +SUMPRODUCT(--(MOD(COLUMN($AM78:$BJ78),4)=MOD(COLUMN($AM78)+1,4)),$AM78:$BJ78)*$I78 -> 0 | BP78: =SUMPRODUCT(--(MOD(COLUMN($O78:$AL78),4)=MOD(COLUMN($O78)+2,4)),$O78:$AL78) +SUMPRODUCT(--(MOD(COLUMN($AM78:$BJ78),4)=MOD(COLUMN($AM78)+2,4)),$AM78:$BJ78) -> 120 | BQ78: =SUMPRODUCT(--(MOD(COLUMN($O78:$AL78),4)=MOD(COLUMN($O78)+2,4)),$O78:$AL78)*$I78 +SUMPRODUCT(--(MOD(COLUMN($AM78:$BJ78),4)=MOD(COLUMN($AM78)+2,4)),$AM78:$BJ78)*$I78 -> 0
A79: ВСЕ | H79: шт.: | N79: =IF(BP79>0,1,IF(BN79>0,2,)) -> 1 | O79: =IFERROR(SUMPRODUCT(($G$6:$G$64>0)*O$6:O$64),"") -> 64 | P79: =IFERROR(SUMPRODUCT(($G$6:$G$64>0)*P$6:P$64),"") -> 0 | Q79: =IFERROR(SUMPRODUCT(($G$6:$G$64>0)*Q$6:Q$64),"") -> 0 | R79: =IFERROR(SUMPRODUCT(($G$6:$G$64>0)*R$6:R$64),"") -> 0 | S79: =IFERROR(SUMPRODUCT(($G$6:$G$64>0)*S$6:S$64),"") -> 2064 | T79: =IFERROR(SUMPRODUCT(($G$6:$G$64>0)*T$6:T$64),"") -> 0 | U79: =IFERROR(SUMPRODUCT(($G$6:$G$64>0)*U$6:U$64),"") -> 0 | V79: =IFERROR(SUMPRODUCT(($G$6:$G$64>0)*V$6:V$64),"") -> 0 | ... BJ79: =IFERROR(SUMPRODUCT(($G$6:$G$64>0)*BJ$6:BJ$64),"") -> 0 | BL79: =SUMPRODUCT(--(MOD(COLUMN($O79:$AL79),4)=MOD(COLUMN($O79)+0,4)),$O79:$AL79) +SUMPRODUCT(--(MOD(COLUMN($AM79:$BJ79),4)=MOD(COLUMN($AM79)+0,4)),$AM79:$BJ79) -> 9412 | BM79: =SUMPRODUCT(--(MOD(COLUMN($O79:$AL79),4)=MOD(COLUMN($O79)+0,4)),$O79:$AL79)*$I79 +SUMPRODUCT(--(MOD(COLUMN($AM79:$BJ79),4)=MOD(COLUMN($AM79)+0,4)),$AM79:$BJ79)*$I79 -> 0 | BN79: =SUMPRODUCT(--(MOD(COLUMN($O79:$AL79),4)=MOD(COLUMN($O79)+1,4)),$O79:$AL79) +SUMPRODUCT(--(MOD(COLUMN($AM79:$BJ79),4)=MOD(COLUMN($AM79)+1,4)),$AM79:$BJ79) -> 7496 | BO79: =SUMPRODUCT(--(MOD(COLUMN($O79:$AL79),4)=MOD(COLUMN($O79)+1,4)),$O79:$AL79)*$I79 +SUMPRODUCT(--(MOD(COLUMN($AM79:$BJ79),4)=MOD(COLUMN($AM79)+1,4)),$AM79:$BJ79)*$I79 -> 0 | BP79: =SUMPRODUCT(--(MOD(COLUMN($O79:$AL79),4)=MOD(COLUMN($O79)+2,4)),$O79:$AL79) +SUMPRODUCT(--(MOD(COLUMN($AM79:$BJ79),4)=MOD(COLUMN($AM79)+2,4)),$AM79:$BJ79) -> 2410 | BQ79: =SUMPRODUCT(--(MOD(COLUMN($O79:$AL79),4)=MOD(COLUMN($O79)+2,4)),$O79:$AL79)*$I79 +SUMPRODUCT(--(MOD(COLUMN($AM79:$BJ79),4)=MOD(COLUMN($AM79)+2,4)),$AM79:$BJ79)*$I79 -> 0

Sheet ПНЕВМАТИКА
A1: 93.49 | B1: - курс евро/рубль | E1: Дата | G1: 46178 | K1: НДС_20 Проверка
A2: 11.25 | B2: - курс юань/рубль | K2: НДС Проверка
F3: Подсветить артикул: | G3: х | I3: 2026-I | N3: 2026 | BS3: 2027 _ НЕ АКТУАЛИЗИРУЕТСЯ | DT3: 2028 _ НЕ АКТУАЛИЗИРУЕТСЯ
A4: Клиент | B4: Условия оплаты | C4: Поставщик | D4: Менеджер | E4: п\п | F4: 2 - WABCO | G4: Номер изделия/ артикул | H4: Наименование | I4: Цена для плана, CNY, без НДС | J4: Цена в валюте, без НДС | K4: Валюта | L4: Цена от курса, CNY, без НДС | N4: ПР 26 | O4: 46023 | S4: 46054 | W4: 46082 | AA4: 46113 | AE4: 46143 | AI4: 46174 | AM4: 46204 | AQ4: 46235 | AU4: 46266 | AY4: 46296 | BC4: 46327 | BG4: 46357 | BL4: ИТОГО, 2026 | BS4: ПР 27 | BT4: 46388 | BX4: 46419 | CB4: 46447 | CF4: 46478 | CJ4: 46508 | CN4: 46539 | CR4: 46569 | CV4: 46600 | CZ4: 46631 | DD4: 46661 | DH4: 46692 | DL4: 46722 | DQ4: ИТОГО, 2027 | DT4: ПР 28 | DU4: 46753 | DY4: 46784 | EC4: 46813 | EG4: 46844 | EK4: 46874 | EO4: 46905 | ES4: 46935 | EW4: 46966 | FA4: 46997 | FE4: 47027 | FI4: 47058 | FM4: 47088 | FR4: ИТОГО, 2028
O5: AOP, шт | P5: Прогноз, шт | Q5: Факт, шт | R5: Коментарий | S5: AOP, шт | T5: Прогноз, шт | U5: Факт, шт | V5: Коментарий | W5: AOP, шт | X5: Прогноз, шт | Y5: Факт, шт | Z5: Коментарий | AA5: AOP, шт | AB5: Прогноз, шт | AC5: Факт, шт | AD5: Коментарий | AE5: AOP, шт | AF5: Прогноз, шт | AG5: Факт, шт | AH5: Коментарий | AI5: AOP, шт | AJ5: Прогноз, шт | AK5: Факт, шт | AL5: Коментарий | AM5: AOP, шт | AN5: Прогноз, шт | AO5: Факт, шт | AP5: Коментарий | AQ5: AOP, шт | AR5: Прогноз, шт | AS5: Факт, шт | AT5: Коментарий | AU5: AOP, шт | AV5: Прогноз, шт | AW5: Факт, шт | AX5: Коментарий | AY5: AOP, шт | AZ5: Прогноз, шт | BA5: Факт, шт | BB5: Коментарий | BC5: AOP, шт | BD5: Прогноз, шт | BE5: Факт, шт | BF5: Коментарий | BG5: AOP, шт | BH5: Прогноз, шт | BI5: Факт, шт | BJ5: Коментарий | BL5: AOP, шт | BM5: Продажи AOP, CNY | BN5: Прогноз, шт | BO5: Продажи Прогноз, CNY | BP5: Факт, шт | BQ5: Продажи Факт, CNY | BT5: AOP, шт | BU5: Прогноз, шт | BV5: Факт, шт | BW5: Коментарий | BX5: AOP, шт | BY5: Прогноз, шт | BZ5: Факт, шт | CA5: Коментарий | CB5: AOP, шт | CC5: Прогноз, шт | CD5: Факт, шт | CE5: Коментарий | CF5: AOP, шт | CG5: Прогноз, шт | CH5: Факт, шт | CI5: Коментарий | CJ5: AOP, шт | CK5: Прогноз, шт | CL5: Факт, шт | CM5: Коментарий | CN5: AOP, шт | CO5: Прогноз, шт | CP5: Факт, шт | CQ5: Коментарий | CR5: AOP, шт | CS5: Прогноз, шт | CT5: Факт, шт | CU5: Коментарий | CV5: AOP, шт | CW5: Прогноз, шт | CX5: Факт, шт | CY5: Коментарий | CZ5: AOP, шт | DA5: Прогноз, шт | DB5: Факт, шт | DC5: Коментарий | DD5: AOP, шт | DE5: Прогноз, шт | DF5: Факт, шт | DG5: Коментарий | DH5: AOP, шт | DI5: Прогноз, шт | DJ5: Факт, шт | DK5: Коментарий | DL5: AOP, шт | DM5: Прогноз, шт | DN5: Факт, шт | DO5: Коментарий | DQ5: AOP, шт | DR5: Продажи AOP, CNY | DU5: AOP, шт | DV5: Прогноз, шт | DW5: Факт, шт | DX5: Коментарий | DY5: AOP, шт | DZ5: Прогноз, шт | EA5: Факт, шт | EB5: Коментарий | EC5: AOP, шт | ED5: Прогноз, шт | EE5: Факт, шт | EF5: Коментарий | EG5: AOP, шт | EH5: Прогноз, шт | EI5: Факт, шт | EJ5: Коментарий | EK5: AOP, шт | EL5: Прогноз, шт | EM5: Факт, шт | EN5: Коментарий | EO5: AOP, шт | EP5: Прогноз, шт | EQ5: Факт, шт | ER5: Коментарий | ES5: AOP, шт | ET5: Прогноз, шт | EU5: Факт, шт | EV5: Коментарий | EW5: AOP, шт | EX5: Прогноз, шт | EY5: Факт, шт | EZ5: Коментарий | FA5: AOP, шт | FB5: Прогноз, шт | FC5: Факт, шт | FD5: Коментарий | FE5: AOP, шт | FF5: Прогноз, шт | FG5: Факт, шт | FH5: Коментарий | FI5: AOP, шт | FJ5: Прогноз, шт | FK5: Факт, шт | FL5: Коментарий | FM5: AOP, шт | FN5: Прогноз, шт | FO5: Факт, шт | FP5: Коментарий | FR5: AOP, шт | FS5: Продажи AOP, CNY
A6: УЛЬТРА ГРУПП ООО | B6: Предоплата 100% | C6: ВБК Восток | D6: Прасолов, Соловьёв | E6: =IF(ISBLANK(G6),"",IF($A$6:$A$330=$A6,COUNTIF($A$6:A6,$A6),"")) -> 1 | F6: 1 | G6: 9253761210 | H6: Энергоаккумулятор тип 24/30 | I6: =306/НДС -> 250.81967 | N6: =IF(BP6>0,1,IF(BN6>0,2,)) -> 1 | O6: 8 | S6: 8 | W6: 8 | X6: =4*X$11 -> 8 | Y6: 8 | AA6: 12 | AB6: =4*AB$11 -> 8 | AC6: 8 | AE6: 12 | AG6: 0 | AI6: 12 | AJ6: =4*AJ$11 -> 16 | AM6: 12 | AN6: =4*AN$11 -> 8 | AQ6: 12 | AR6: =4*AR$11 -> 12 | AU6: 12 | AV6: =4*AV$11 -> 12 | AY6: 12 | AZ6: =4*AZ$11 -> 12 | BC6: 12 | BD6: =4*BD$11 -> 12 | BG6: 12 | BH6: =4*BH$11 -> 12 | BL6: =SUMPRODUCT(--(MOD(COLUMN($O6:$AL6),4)=MOD(COLUMN($O6)+0,4)),$O6:$AL6) +SUMPRODUCT(--(MOD(COLUMN($AM6:$BJ6),4)=MOD(COLUMN($AM6)+0,4)),$AM6:$BJ6) -> 132 | BM6: =SUMPRODUCT(--(MOD(COLUMN($O6:$AL6),4)=MOD(COLUMN($O6)+0,4)),$O6:$AL6)*$I6 +SUMPRODUCT(--(MOD(COLUMN($AM6:$BJ6),4)=MOD(COLUMN($AM6)+0,4)),$AM6:$BJ6)*$I6 -> 33108.197 | BN6: =SUMPRODUCT(--(MOD(COLUMN($O6:$AL6),4)=MOD(COLUMN($O6)+1,4)),$O6:$AL6) +SUMPRODUCT(--(MOD(COLUMN($AM6:$BJ6),4)=MOD(COLUMN($AM6)+1,4)),$AM6:$BJ6) -> 100 | BO6: =SUMPRODUCT(--(MOD(COLUMN($O6:$AL6),4)=MOD(COLUMN($O6)+1,4)),$O6:$AL6)*$I6 +SUMPRODUCT(--(MOD(COLUMN($AM6:$BJ6),4)=MOD(COLUMN($AM6)+1,4)),$AM6:$BJ6)*$I6 -> 25081.967 | BP6: =SUMPRODUCT(--(MOD(COLUMN($O6:$AL6),4)=MOD(COLUMN($O6)+2,4)),$O6:$AL6) +SUMPRODUCT(--(MOD(COLUMN($AM6:$BJ6),4)=MOD(COLUMN($AM6)+2,4)),$AM6:$BJ6) -> 16 | BQ6: =SUMPRODUCT(--(MOD(COLUMN($O6:$AL6),4)=MOD(COLUMN($O6)+2,4)),$O6:$AL6)*$I6 +SUMPRODUCT(--(MOD(COLUMN($AM6:$BJ6),4)=MOD(COLUMN($AM6)+2,4)),$AM6:$BJ6)*$I6 -> 4013.1148 | DQ6: =SUMPRODUCT(--(MOD(COLUMN(BT6:CQ6),4)=MOD(COLUMN(BT6),4)),BT6:CQ6)+SUMPRODUCT(--(MOD(COLUMN(CR6:DO6),4)=MOD(COLUMN(CR6),4)),CR6:DO6) -> 0 | DR6: =SUMPRODUCT(--(MOD(COLUMN(BT6:CQ6),4)=MOD(COLUMN(BT6),4)),BT6:CQ6)*$I6+SUMPRODUCT(--(MOD(COLUMN(CR6:DO6),4)=MOD(COLUMN(CR6),4)),CR6:DO6)*$I6 -> 0 | FR6: =SUMPRODUCT(--(MOD(COLUMN(DU6:ER6),4)=MOD(COLUMN(DU6),4)),DU6:ER6)+SUMPRODUCT(--(MOD(COLUMN(ES6:FP6),4)=MOD(COLUMN(ES6),4)),ES6:FP6) -> 0 | FS6: =SUMPRODUCT(--(MOD(COLUMN(DU6:ER6),4)=MOD(COLUMN(DU6),4)),DU6:ER6)*$I6+SUMPRODUCT(--(MOD(COLUMN(ES6:FP6),4)=MOD(COLUMN(ES6),4)),ES6:FP6)*$I6 -> 0
A7: УЛЬТРА ГРУПП ООО | B7: Предоплата 100% | C7: ВБК Восток | D7: Прасолов, Соловьёв | E7: =IF(ISBLANK(G7),"",IF($A$6:$A$330=$A7,COUNTIF($A$6:A7,$A7),"")) -> 2 | F7: 1 | G7: 9253771100 | H7: Энергоаккумулятор тип 30/30 | I7: =310/НДС -> 254.09836 | N7: =IF(BP7>0,1,IF(BN7>0,2,)) -> 0 | AG7: 0 | BL7: =SUMPRODUCT(--(MOD(COLUMN($O7:$AL7),4)=MOD(COLUMN($O7)+0,4)),$O7:$AL7) +SUMPRODUCT(--(MOD(COLUMN($AM7:$BJ7),4)=MOD(COLUMN($AM7)+0,4)),$AM7:$BJ7) -> 0 | BM7: =SUMPRODUCT(--(MOD(COLUMN($O7:$AL7),4)=MOD(COLUMN($O7)+0,4)),$O7:$AL7)*$I7 +SUMPRODUCT(--(MOD(COLUMN($AM7:$BJ7),4)=MOD(COLUMN($AM7)+0,4)),$AM7:$BJ7)*$I7 -> 0 | BN7: =SUMPRODUCT(--(MOD(COLUMN($O7:$AL7),4)=MOD(COLUMN($O7)+1,4)),$O7:$AL7) +SUMPRODUCT(--(MOD(COLUMN($AM7:$BJ7),4)=MOD(COLUMN($AM7)+1,4)),$AM7:$BJ7) -> 0 | BO7: =SUMPRODUCT(--(MOD(COLUMN($O7:$AL7),4)=MOD(COLUMN($O7)+1,4)),$O7:$AL7)*$I7 +SUMPRODUCT(--(MOD(COLUMN($AM7:$BJ7),4)=MOD(COLUMN($AM7)+1,4)),$AM7:$BJ7)*$I7 -> 0 | BP7: =SUMPRODUCT(--(MOD(COLUMN($O7:$AL7),4)=MOD(COLUMN($O7)+2,4)),$O7:$AL7) +SUMPRODUCT(--(MOD(COLUMN($AM7:$BJ7),4)=MOD(COLUMN($AM7)+2,4)),$AM7:$BJ7) -> 0 | BQ7: =SUMPRODUCT(--(MOD(COLUMN($O7:$AL7),4)=MOD(COLUMN($O7)+2,4)),$O7:$AL7)*$I7 +SUMPRODUCT(--(MOD(COLUMN($AM7:$BJ7),4)=MOD(COLUMN($AM7)+2,4)),$AM7:$BJ7)*$I7 -> 0 | DQ7: =SUMPRODUCT(--(MOD(COLUMN(BT7:CQ7),4)=MOD(COLUMN(BT7),4)),BT7:CQ7)+SUMPRODUCT(--(MOD(COLUMN(CR7:DO7),4)=MOD(COLUMN(CR7),4)),CR7:DO7) -> 0 | DR7: =SUMPRODUCT(--(MOD(COLUMN(BT7:CQ7),4)=MOD(COLUMN(BT7),4)),BT7:CQ7)*$I7+SUMPRODUCT(--(MOD(COLUMN(CR7:DO7),4)=MOD(COLUMN(CR7),4)),CR7:DO7)*$I7 -> 0 | FR7: =SUMPRODUCT(--(MOD(COLUMN(DU7:ER7),4)=MOD(COLUMN(DU7),4)),DU7:ER7)+SUMPRODUCT(--(MOD(COLUMN(ES7:FP7),4)=MOD(COLUMN(ES7),4)),ES7:FP7) -> 0 | FS7: =SUMPRODUCT(--(MOD(COLUMN(DU7:ER7),4)=MOD(COLUMN(DU7),4)),DU7:ER7)*$I7+SUMPRODUCT(--(MOD(COLUMN(ES7:FP7),4)=MOD(COLUMN(ES7),4)),ES7:FP7)*$I7 -> 0
A8: УЛЬТРА ГРУПП ООО | B8: Предоплата 100% | C8: ВБК РУС | D8: Прасолов, Соловьёв | E8: =IF(ISBLANK(G8),"",IF($A$6:$A$330=$A8,COUNTIF($A$6:A8,$A8),"")) -> 3 | F8: 1 | G8: 9735000510 | H8: Клапан быстрого растормаживания энергоакк. | I8: =146.4/НДС_20 -> 122 | L8: =IF(K8="RUB",J8/ЮАНЬ,IF(K8="EUR",J8*ЕВРО/ЮАНЬ,"")) | N8: =IF(BP8>0,1,IF(BN8>0,2,)) -> 2 | O8: 2 | S8: 2 | W8: 2 | AA8: 3 | AE8: 3 | AG8: 0 | AI8: 3 | AM8: 3 | AQ8: 3 | AU8: 3 | AV8: =1*AV$11 -> 3 | AY8: 3 | AZ8: =1*AZ$11 -> 3 | BC8: 3 | BD8: =1*BD$11 -> 3 | BG8: 3 | BH8: =1*BH$11 -> 3 | BL8: =SUMPRODUCT(--(MOD(COLUMN($O8:$AL8),4)=MOD(COLUMN($O8)+0,4)),$O8:$AL8) +SUMPRODUCT(--(MOD(COLUMN($AM8:$BJ8),4)=MOD(COLUMN($AM8)+0,4)),$AM8:$BJ8) -> 33 | BM8: =SUMPRODUCT(--(MOD(COLUMN($O8:$AL8),4)=MOD(COLUMN($O8)+0,4)),$O8:$AL8)*$I8 +SUMPRODUCT(--(MOD(COLUMN($AM8:$BJ8),4)=MOD(COLUMN($AM8)+0,4)),$AM8:$BJ8)*$I8 -> 4026 | BN8: =SUMPRODUCT(--(MOD(COLUMN($O8:$AL8),4)=MOD(COLUMN($O8)+1,4)),$O8:$AL8) +SUMPRODUCT(--(MOD(COLUMN($AM8:$BJ8),4)=MOD(COLUMN($AM8)+1,4)),$AM8:$BJ8) -> 12 | BO8: =SUMPRODUCT(--(MOD(COLUMN($O8:$AL8),4)=MOD(COLUMN($O8)+1,4)),$O8:$AL8)*$I8 +SUMPRODUCT(--(MOD(COLUMN($AM8:$BJ8),4)=MOD(COLUMN($AM8)+1,4)),$AM8:$BJ8)*$I8 -> 1464 | BP8: =SUMPRODUCT(--(MOD(COLUMN($O8:$AL8),4)=MOD(COLUMN($O8)+2,4)),$O8:$AL8) +SUMPRODUCT(--(MOD(COLUMN($AM8:$BJ8),4)=MOD(COLUMN($AM8)+2,4)),$AM8:$BJ8) -> 0 | BQ8: =SUMPRODUCT(--(MOD(COLUMN($O8:$AL8),4)=MOD(COLUMN($O8)+2,4)),$O8:$AL8)*$I8 +SUMPRODUCT(--(MOD(COLUMN($AM8:$BJ8),4)=MOD(COLUMN($AM8)+2,4)),$AM8:$BJ8)*$I8 -> 0 | DQ8: =SUMPRODUCT(--(MOD(COLUMN(BT8:CQ8),4)=MOD(COLUMN(BT8),4)),BT8:CQ8)+SUMPRODUCT(--(MOD(COLUMN(CR8:DO8),4)=MOD(COLUMN(CR8),4)),CR8:DO8) -> 0 | DR8: =SUMPRODUCT(--(MOD(COLUMN(BT8:CQ8),4)=MOD(COLUMN(BT8),4)),BT8:CQ8)*$I8+SUMPRODUCT(--(MOD(COLUMN(CR8:DO8),4)=MOD(COLUMN(CR8),4)),CR8:DO8)*$I8 -> 0 | FR8: =SUMPRODUCT(--(MOD(COLUMN(DU8:ER8),4)=MOD(COLUMN(DU8),4)),DU8:ER8)+SUMPRODUCT(--(MOD(COLUMN(ES8:FP8),4)=MOD(COLUMN(ES8),4)),ES8:FP8) -> 0 | FS8: =SUMPRODUCT(--(MOD(COLUMN(DU8:ER8),4)=MOD(COLUMN(DU8),4)),DU8:ER8)*$I8+SUMPRODUCT(--(MOD(COLUMN(ES8:FP8),4)=MOD(COLUMN(ES8),4)),ES8:FP8)*$I8 -> 0
A9: УЛЬТРА ГРУПП ООО | B9: Предоплата 100% | C9: ВБК РУС | D9: Прасолов, Соловьёв | E9: =IF(ISBLANK(G9),"",IF($A$6:$A$330=$A9,COUNTIF($A$6:A9,$A9),"")) -> 4 | F9: 1 | G9: 4750103050 | H9: Клапан ограничения давления | I9: =117.6/НДС_20 -> 98 | L9: =IF(K9="RUB",J9/ЮАНЬ,IF(K9="EUR",J9*ЕВРО/ЮАНЬ,"")) | N9: =IF(BP9>0,1,IF(BN9>0,2,)) -> 2 | O9: 2 | S9: 2 | W9: 2 | AA9: 3 | AE9: 3 | AG9: 0 | AI9: 3 | AM9: 3 | AQ9: 3 | AU9: 3 | AV9: =1*AV$11 -> 3 | AY9: 3 | AZ9: =1*AZ$11 -> 3 | BC9: 3 | BD9: =1*BD$11 -> 3 | BG9: 3 | BH9: =1*BH$11 -> 3 | BL9: =SUMPRODUCT(--(MOD(COLUMN($O9:$AL9),4)=MOD(COLUMN($O9)+0,4)),$O9:$AL9) +SUMPRODUCT(--(MOD(COLUMN($AM9:$BJ9),4)=MOD(COLUMN($AM9)+0,4)),$AM9:$BJ9) -> 33 | BM9: =SUMPRODUCT(--(MOD(COLUMN($O9:$AL9),4)=MOD(COLUMN($O9)+0,4)),$O9:$AL9)*$I9 +SUMPRODUCT(--(MOD(COLUMN($AM9:$BJ9),4)=MOD(COLUMN($AM9)+0,4)),$AM9:$BJ9)*$I9 -> 3234 | BN9: =SUMPRODUCT(--(MOD(COLUMN($O9:$AL9),4)=MOD(COLUMN($O9)+1,4)),$O9:$AL9) +SUMPRODUCT(--(MOD(COLUMN($AM9:$BJ9),4)=MOD(COLUMN($AM9)+1,4)),$AM9:$BJ9) -> 12 | BO9: =SUMPRODUCT(--(MOD(COLUMN($O9:$AL9),4)=MOD(COLUMN($O9)+1,4)),$O9:$AL9)*$I9 +SUMPRODUCT(--(MOD(COLUMN($AM9:$BJ9),4)=MOD(COLUMN($AM9)+1,4)),$AM9:$BJ9)*$I9 -> 1176 | BP9: =SUMPRODUCT(--(MOD(COLUMN($O9:$AL9),4)=MOD(COLUMN($O9)+2,4)),$O9:$AL9) +SUMPRODUCT(--(MOD(COLUMN($AM9:$BJ9),4)=MOD(COLUMN($AM9)+2,4)),$AM9:$BJ9) -> 0 | BQ9: =SUMPRODUCT(--(MOD(COLUMN($O9:$AL9),4)=MOD(COLUMN($O9)+2,4)),$O9:$AL9)*$I9 +SUMPRODUCT(--(MOD(COLUMN($AM9:$BJ9),4)=MOD(COLUMN($AM9)+2,4)),$AM9:$BJ9)*$I9 -> 0 | DQ9: =SUMPRODUCT(--(MOD(COLUMN(BT9:CQ9),4)=MOD(COLUMN(BT9),4)),BT9:CQ9)+SUMPRODUCT(--(MOD(COLUMN(CR9:DO9),4)=MOD(COLUMN(CR9),4)),CR9:DO9) -> 0 | DR9: =SUMPRODUCT(--(MOD(COLUMN(BT9:CQ9),4)=MOD(COLUMN(BT9),4)),BT9:CQ9)*$I9+SUMPRODUCT(--(MOD(COLUMN(CR9:DO9),4)=MOD(COLUMN(CR9),4)),CR9:DO9)*$I9 -> 0 | FR9: =SUMPRODUCT(--(MOD(COLUMN(DU9:ER9),4)=MOD(COLUMN(DU9),4)),DU9:ER9)+SUMPRODUCT(--(MOD(COLUMN(ES9:FP9),4)=MOD(COLUMN(ES9),4)),ES9:FP9) -> 0 | FS9: =SUMPRODUCT(--(MOD(COLUMN(DU9:ER9),4)=MOD(COLUMN(DU9),4)),DU9:ER9)*$I9+SUMPRODUCT(--(MOD(COLUMN(ES9:FP9),4)=MOD(COLUMN(ES9),4)),ES9:FP9)*$I9 -> 0
A10: УЛЬТРА ГРУПП ООО | B10: Предоплата 100% | C10: ВБК РУС | D10: Прасолов, Соловьёв | E10: =IF(ISBLANK(G10),"",IF($A$6:$A$330=$A10,COUNTIF($A$6:A10,$A10),"")) -> 5 | F10: 1 | G10: 4494430400 | H10: Кабель клапана управления подъемом оси, 4 м | I10: =191/НДС_20 -> 159.16667 | N10: =IF(BP10>0,1,IF(BN10>0,2,)) -> 0 | AG10: 0 | BL10: =SUMPRODUCT(--(MOD(COLUMN($O10:$AL10),4)=MOD(COLUMN($O10)+0,4)),$O10:$AL10) +SUMPRODUCT(--(MOD(COLUMN($AM10:$BJ10),4)=MOD(COLUMN($AM10)+0,4)),$AM10:$BJ10) -> 0 | BM10: =SUMPRODUCT(--(MOD(COLUMN($O10:$AL10),4)=MOD(COLUMN($O10)+0,4)),$O10:$AL10)*$I10 +SUMPRODUCT(--(MOD(COLUMN($AM10:$BJ10),4)=MOD(COLUMN($AM10)+0,4)),$AM10:$BJ10)*$I10 -> 0 | BN10: =SUMPRODUCT(--(MOD(COLUMN($O10:$AL10),4)=MOD(COLUMN($O10)+1,4)),$O10:$AL10) +SUMPRODUCT(--(MOD(COLUMN($AM10:$BJ10),4)=MOD(COLUMN($AM10)+1,4)),$AM10:$BJ10) -> 0 | BO10: =SUMPRODUCT(--(MOD(COLUMN($O10:$AL10),4)=MOD(COLUMN($O10)+1,4)),$O10:$AL10)*$I10 +SUMPRODUCT(--(MOD(COLUMN($AM10:$BJ10),4)=MOD(COLUMN($AM10)+1,4)),$AM10:$BJ10)*$I10 -> 0 | BP10: =SUMPRODUCT(--(MOD(COLUMN($O10:$AL10),4)=MOD(COLUMN($O10)+2,4)),$O10:$AL10) +SUMPRODUCT(--(MOD(COLUMN($AM10:$BJ10),4)=MOD(COLUMN($AM10)+2,4)),$AM10:$BJ10) -> 0 | BQ10: =SUMPRODUCT(--(MOD(COLUMN($O10:$AL10),4)=MOD(COLUMN($O10)+2,4)),$O10:$AL10)*$I10 +SUMPRODUCT(--(MOD(COLUMN($AM10:$BJ10),4)=MOD(COLUMN($AM10)+2,4)),$AM10:$BJ10)*$I10 -> 0 | DQ10: =SUMPRODUCT(--(MOD(COLUMN(BT10:CQ10),4)=MOD(COLUMN(BT10),4)),BT10:CQ10)+SUMPRODUCT(--(MOD(COLUMN(CR10:DO10),4)=MOD(COLUMN(CR10),4)),CR10:DO10) -> 0 | DR10: =SUMPRODUCT(--(MOD(COLUMN(BT10:CQ10),4)=MOD(COLUMN(BT10),4)),BT10:CQ10)*$I10+SUMPRODUCT(--(MOD(COLUMN(CR10:DO10),4)=MOD(COLUMN(CR10),4)),CR10:DO10)*$I10 -> 0 | FR10: =SUMPRODUCT(--(MOD(COLUMN(DU10:ER10),4)=MOD(COLUMN(DU10),4)),DU10:ER10)+SUMPRODUCT(--(MOD(COLUMN(ES10:FP10),4)=MOD(COLUMN(ES10),4)),ES10:FP10) -> 0 | FS10: =SUMPRODUCT(--(MOD(COLUMN(DU10:ER10),4)=MOD(COLUMN(DU10),4)),DU10:ER10)*$I10+SUMPRODUCT(--(MOD(COLUMN(ES10:FP10),4)=MOD(COLUMN(ES10),4)),ES10:FP10)*$I10 -> 0
A11: УЛЬТРА ГРУПП ООО | B11: Предоплата 100% | C11: ВБК РУС | D11: Прасолов, Соловьёв | E11: =IF(ISBLANK(G11),"",IF($A$6:$A$330=$A11,COUNTIF($A$6:A11,$A11),"")) -> 6 | F11: S | G11: 4441000440 | H11: Комплект базовый "TEBS 2S/2M (18 м W)" | I11: =9119/НДС -> 7474.5902 | L11: =IF(K11="RUB",J11/ЮАНЬ,IF(K11="EUR",J11*ЕВРО/ЮАНЬ,"")) | N11: =IF(BP11>0,1,IF(BN11>0,2,)) -> 1 | O11: 2 | S11: 2 | W11: 2 | X11: =2 -> 2 | Y11: 2 | AA11: 3 | AB11: =2 -> 2 | AC11: 2 | AE11: 3 | AG11: 0 | AI11: 3 | AJ11: 4 | AM11: 3 | AN11: 2 | AQ11: 3 | AR11: 3 | AU11: 3 | AV11: 3 | AY11: 3 | AZ11: 3 | BC11: 3 | BD11: 3 | BG11: 3 | BH11: 3 | BL11: =SUMPRODUCT(--(MOD(COLUMN($O11:$AL11),4)=MOD(COLUMN($O11)+0,4)),$O11:$AL11) +SUMPRODUCT(--(MOD(COLUMN($AM11:$BJ11),4)=MOD(COLUMN($AM11)+0,4)),$AM11:$BJ11) -> 33 | BM11: =SUMPRODUCT(--(MOD(COLUMN($O11:$AL11),4)=MOD(COLUMN($O11)+0,4)),$O11:$AL11)*$I11 +SUMPRODUCT(--(MOD(COLUMN($AM11:$BJ11),4)=MOD(COLUMN($AM11)+0,4)),$AM11:$BJ11)*$I11 -> 246661.48 | BN11: =SUMPRODUCT(--(MOD(COLUMN($O11:$AL11),4)=MOD(COLUMN($O11)+1,4)),$O11:$AL11) +SUMPRODUCT(--(MOD(COLUMN($AM11:$BJ11),4)=MOD(COLUMN($AM11)+1,4)),$AM11:$BJ11) -> 25 | BO11: =SUMPRODUCT(--(MOD(COLUMN($O11:$AL11),4)=MOD(COLUMN($O11)+1,4)),$O11:$AL11)*$I11 +SUMPRODUCT(--(MOD(COLUMN($AM11:$BJ11),4)=MOD(COLUMN($AM11)+1,4)),$AM11:$BJ11)*$I11 -> 186864.75 | BP11: =SUMPRODUCT(--(MOD(COLUMN($O11:$AL11),4)=MOD(COLUMN($O11)+2,4)),$O11:$AL11) +SUMPRODUCT(--(MOD(COLUMN($AM11:$BJ11),4)=MOD(COLUMN($AM11)+2,4)),$AM11:$BJ11) -> 4 | BQ11: =SUMPRODUCT(--(MOD(COLUMN($O11:$AL11),4)=MOD(COLUMN($O11)+2,4)),$O11:$AL11)*$I11 +SUMPRODUCT(--(MOD(COLUMN($AM11:$BJ11),4)=MOD(COLUMN($AM11)+2,4)),$AM11:$BJ11)*$I11 -> 29898.361 | DQ11: =SUMPRODUCT(--(MOD(COLUMN(BT11:CQ11),4)=MOD(COLUMN(BT11),4)),BT11:CQ11)+SUMPRODUCT(--(MOD(COLUMN(CR11:DO11),4)=MOD(COLUMN(CR11),4)),CR11:DO11) -> 0 | DR11: =SUMPRODUCT(--(MOD(COLUMN(BT11:CQ11),4)=MOD(COLUMN(BT11),4)),BT11:CQ11)*$I11+SUMPRODUCT(--(MOD(COLUMN(CR11:DO11),4)=MOD(COLUMN(CR11),4)),CR11:DO11)*$I11 -> 0 | FR11: =SUMPRODUCT(--(MOD(COLUMN(DU11:ER11),4)=MOD(COLUMN(DU11),4)),DU11:ER11)+SUMPRODUCT(--(MOD(COLUMN(ES11:FP11),4)=MOD(COLUMN(ES11),4)),ES11:FP11) -> 0 | FS11: =SUMPRODUCT(--(MOD(COLUMN(DU11:ER11),4)=MOD(COLUMN(DU11),4)),DU11:ER11)*$I11+SUMPRODUCT(--(MOD(COLUMN(ES11:FP11),4)=MOD(COLUMN(ES11),4)),ES11:FP11)*$I11 -> 0
A12: УЛЬТРА ГРУПП ООО | B12: Предоплата 100% | C12: ВБК РУС | D12: Прасолов, Соловьёв | E12: =IF(ISBLANK(G12),"",IF($A$6:$A$330=$A12,COUNTIF($A$6:A12,$A12),"")) -> 7 | F12: S | G12: 4441000260 | H12: Комплект базовый "TEBS 2S/2M (12 м)" | I12: =8355/НДС -> 6848.3607 | L12: =IF(K12="RUB",J12/ЮАНЬ,IF(K12="EUR",J12*ЕВРО/ЮАНЬ,"")) | N12: =IF(BP12>0,1,IF(BN12>0,2,)) -> 0 | AG12: 0 | BL12: =SUMPRODUCT(--(MOD(COLUMN($O12:$AL12),4)=MOD(COLUMN($O12)+0,4)),$O12:$AL12) +SUMPRODUCT(--(MOD(COLUMN($AM12:$BJ12),4)=MOD(COLUMN($AM12)+0,4)),$AM12:$BJ12) -> 0 | BM12: =SUMPRODUCT(--(MOD(COLUMN($O12:$AL12),4)=MOD(COLUMN($O12)+0,4)),$O12:$AL12)*$I12 +SUMPRODUCT(--(MOD(COLUMN($AM12:$BJ12),4)=MOD(COLUMN($AM12)+0,4)),$AM12:$BJ12)*$I12 -> 0 | BN12: =SUMPRODUCT(--(MOD(COLUMN($O12:$AL12),4)=MOD(COLUMN($O12)+1,4)),$O12:$AL12) +SUMPRODUCT(--(MOD(COLUMN($AM12:$BJ12),4)=MOD(COLUMN($AM12)+1,4)),$AM12:$BJ12) -> 0 | BO12: =SUMPRODUCT(--(MOD(COLUMN($O12:$AL12),4)=MOD(COLUMN($O12)+1,4)),$O12:$AL12)*$I12 +SUMPRODUCT(--(MOD(COLUMN($AM12:$BJ12),4)=MOD(COLUMN($AM12)+1,4)),$AM12:$BJ12)*$I12 -> 0 | BP12: =SUMPRODUCT(--(MOD(COLUMN($O12:$AL12),4)=MOD(COLUMN($O12)+2,4)),$O12:$AL12) +SUMPRODUCT(--(MOD(COLUMN($AM12:$BJ12),4)=MOD(COLUMN($AM12)+2,4)),$AM12:$BJ12) -> 0 | BQ12: =SUMPRODUCT(--(MOD(COLUMN($O12:$AL12),4)=MOD(COLUMN($O12)+2,4)),$O12:$AL12)*$I12 +SUMPRODUCT(--(MOD(COLUMN($AM12:$BJ12),4)=MOD(COLUMN($AM12)+2,4)),$AM12:$BJ12)*$I12 -> 0 | DQ12: =SUMPRODUCT(--(MOD(COLUMN(BT12:CQ12),4)=MOD(COLUMN(BT12),4)),BT12:CQ12)+SUMPRODUCT(--(MOD(COLUMN(CR12:DO12),4)=MOD(COLUMN(CR12),4)),CR12:DO12) -> 0 | DR12: =SUMPRODUCT(--(MOD(COLUMN(BT12:CQ12),4)=MOD(COLUMN(BT12),4)),BT12:CQ12)*$I12+SUMPRODUCT(--(MOD(COLUMN(CR12:DO12),4)=MOD(COLUMN(CR12),4)),CR12:DO12)*$I12 -> 0 | FR12: =SUMPRODUCT(--(MOD(COLUMN(DU12:ER12),4)=MOD(COLUMN(DU12),4)),DU12:ER12)+SUMPRODUCT(--(MOD(COLUMN(ES12:FP12),4)=MOD(COLUMN(ES12),4)),ES12:FP12) -> 0 | FS12: =SUMPRODUCT(--(MOD(COLUMN(DU12:ER12),4)=MOD(COLUMN(DU12),4)),DU12:ER12)*$I12+SUMPRODUCT(--(MOD(COLUMN(ES12:FP12),4)=MOD(COLUMN(ES12),4)),ES12:FP12)*$I12 -> 0
A13: УЛЬТРА ГРУПП ООО | B13: Предоплата 100% | C13: ВБК РУС | D13: Прасолов, Соловьёв | E13: =IF(ISBLANK(G13),"",IF($A$6:$A$330=$A13,COUNTIF($A$6:A13,$A13),"")) -> 8 | F13: S | G13: 4441000210 | H13: Комплект клапана подъёма оси LACV (6 м) | I13: =847.9/НДС -> 695 | L13: =IF(K13="RUB",J13/ЮАНЬ,IF(K13="EUR",J13*ЕВРО/ЮАНЬ,"")) | N13: =IF(BP13>0,1,IF(BN13>0,2,)) -> 0 | AG13: 0 | BL13: =SUMPRODUCT(--(MOD(COLUMN($O13:$AL13),4)=MOD(COLUMN($O13)+0,4)),$O13:$AL13) +SUMPRODUCT(--(MOD(COLUMN($AM13:$BJ13),4)=MOD(COLUMN($AM13)+0,4)),$AM13:$BJ13) -> 0 | BM13: =SUMPRODUCT(--(MOD(COLUMN($O13:$AL13),4)=MOD(COLUMN($O13)+0,4)),$O13:$AL13)*$I13 +SUMPRODUCT(--(MOD(COLUMN($AM13:$BJ13),4)=MOD(COLUMN($AM13)+0,4)),$AM13:$BJ13)*$I13 -> 0 | BN13: =SUMPRODUCT(--(MOD(COLUMN($O13:$AL13),4)=MOD(COLUMN($O13)+1,4)),$O13:$AL13) +SUMPRODUCT(--(MOD(COLUMN($AM13:$BJ13),4)=MOD(COLUMN($AM13)+1,4)),$AM13:$BJ13) -> 0 | BO13: =SUMPRODUCT(--(MOD(COLUMN($O13:$AL13),4)=MOD(COLUMN($O13)+1,4)),$O13:$AL13)*$I13 +SUMPRODUCT(--(MOD(COLUMN($AM13:$BJ13),4)=MOD(COLUMN($AM13)+1,4)),$AM13:$BJ13)*$I13 -> 0 | BP13: =SUMPRODUCT(--(MOD(COLUMN($O13:$AL13),4)=MOD(COLUMN($O13)+2,4)),$O13:$AL13) +SUMPRODUCT(--(MOD(COLUMN($AM13:$BJ13),4)=MOD(COLUMN($AM13)+2,4)),$AM13:$BJ13) -> 0 | BQ13: =SUMPRODUCT(--(MOD(COLUMN($O13:$AL13),4)=MOD(COLUMN($O13)+2,4)),$O13:$AL13)*$I13 +SUMPRODUCT(--(MOD(COLUMN($AM13:$BJ13),4)=MOD(COLUMN($AM13)+2,4)),$AM13:$BJ13)*$I13 -> 0 | DQ13: =SUMPRODUCT(--(MOD(COLUMN(BT13:CQ13),4)=MOD(COLUMN(BT13),4)),BT13:CQ13)+SUMPRODUCT(--(MOD(COLUMN(CR13:DO13),4)=MOD(COLUMN(CR13),4)),CR13:DO13) -> 0 | DR13: =SUMPRODUCT(--(MOD(COLUMN(BT13:CQ13),4)=MOD(COLUMN(BT13),4)),BT13:CQ13)*$I13+SUMPRODUCT(--(MOD(COLUMN(CR13:DO13),4)=MOD(COLUMN(CR13),4)),CR13:DO13)*$I13 -> 0 | FR13: =SUMPRODUCT(--(MOD(COLUMN(DU13:ER13),4)=MOD(COLUMN(DU13),4)),DU13:ER13)+SUMPRODUCT(--(MOD(COLUMN(ES13:FP13),4)=MOD(COLUMN(ES13),4)),ES13:FP13) -> 0 | FS13: =SUMPRODUCT(--(MOD(COLUMN(DU13:ER13),4)=MOD(COLUMN(DU13),4)),DU13:ER13)*$I13+SUMPRODUCT(--(MOD(COLUMN(ES13:FP13),4)=MOD(COLUMN(ES13),4)),ES13:FP13)*$I13 -> 0
A14: УЛЬТРА ГРУПП ООО | B14: Предоплата 100% | C14: ВБК РУС | D14: Прасолов, Соловьёв | E14: =IF(ISBLANK(G14),"",IF($A$6:$A$330=$A14,COUNTIF($A$6:A14,$A14),"")) -> 9 | F14: 1 | G14: 9522010010 | H14: Головка соединительная (управляющая) | I14: 0 | L14: =IF(K14="RUB",J14/ЮАНЬ,IF(K14="EUR",J14*ЕВРО/ЮАНЬ,"")) | N14: =IF(BP14>0,1,IF(BN14>0,2,)) -> 1 | O14: 2 | S14: 2 | W14: 2 | X14: =SUMPRODUCT((Комплекты[Пр]=ПНЕВМАТИКА!$F14)*(Комплекты[Обозначение]=ПНЕВМАТИКА!$G14)*Комплекты[Кол-во]*( ((Комплекты[Комплект]=ПНЕВМАТИКА!$G$13)*ПНЕВМАТИКА!X$13)+ ((Комплекты[Комплект]=ПНЕВМАТИКА!$G$12)*ПНЕВМАТИКА!X$12)+ ((Комплекты[Комплект]=ПНЕВМАТИКА!$G$11)*ПНЕВМАТИКА!X$11))) -> 2 | Y14: =SUMPRODUCT((Комплекты[Пр]=ПНЕВМАТИКА!$F14)*(Комплекты[Обозначение]=ПНЕВМАТИКА!$G14)*Комплекты[Кол-во]*( ((Комплекты[Комплект]=ПНЕВМАТИКА!$G$13)*ПНЕВМАТИКА!Y$13)+ ((Комплекты[Комплект]=ПНЕВМАТИКА!$G$12)*ПНЕВМАТИКА!Y$12)+ ((Комплекты[Комплект]=ПНЕВМАТИКА!$G$11)*ПНЕВМАТИКА!Y$11))) -> 2 | AA14: 3 | AB14: =SUMPRODUCT((Комплекты[Пр]=ПНЕВМАТИКА!$F14)*(Комплекты[Обозначение]=ПНЕВМАТИКА!$G14)*Комплекты[Кол-во]*( ((Комплекты[Комплект]=ПНЕВМАТИКА!$G$13)*ПНЕВМАТИКА!AB$13)+ ((Комплекты[Комплект]=ПНЕВМАТИКА!$G$12)*ПНЕВМАТИКА!AB$12)+ ((Комплекты[Комплект]=ПНЕВМАТИКА!$G$11)*ПНЕВМАТИКА!AB$11))) -> 2 | AE14: 3 | AF14: =SUMPRODUCT((Комплекты[Пр]=ПНЕВМАТИКА!$F14)*(Комплекты[Обозначение]=ПНЕВМАТИКА!$G14)*Комплекты[Кол-во]*( ((Комплекты[Комплект]=ПНЕВМАТИКА!$G$13)*ПНЕВМАТИКА!AF$13)+ ((Комплекты[Комплект]=ПНЕВМАТИКА!$G$12)*ПНЕВМАТИКА!AF$12)+ ((Комплекты[Комплект]=ПНЕВМАТИКА!$G$11)*ПНЕВМАТИКА!AF$11))) -> 0 | AG14: =SUMPRODUCT((Комплекты[Пр]=ПНЕВМАТИКА!$F14)*(Комплекты[Обозначение]=ПНЕВМАТИКА!$G14)*Комплекты[Кол-во]*( ((Комплекты[Комплект]=ПНЕВМАТИКА!$G$13)*ПНЕВМАТИКА!AG$13)+ ((Комплекты[Комплект]=ПНЕВМАТИКА!$G$12)*ПНЕВМАТИКА!AG$12)+ ((Комплекты[Комплект]=ПНЕВМАТИКА!$G$11)*ПНЕВМАТИКА!AG$11))) -> 0 | AI14: 3 | AJ14: =SUMPRODUCT((Комплекты[Пр]=ПНЕВМАТИКА!$F14)*(Комплекты[Обозначение]=ПНЕВМАТИКА!$G14)*Комплекты[Кол-во]*( ((Комплекты[Комплект]=ПНЕВМАТИКА!$G$13)*ПНЕВМАТИКА!AJ$13)+ ((Комплекты[Комплект]=ПНЕВМАТИКА!$G$12)*ПНЕВМАТИКА!AJ$12)+ ((Комплекты[Комплект]=ПНЕВМАТИКА!$G$11)*ПНЕВМАТИКА!AJ$11))) -> 4 | AM14: 3 | AN14: =SUMPRODUCT((Комплекты[Пр]=ПНЕВМАТИКА!$F14)*(Комплекты[Обозначение]=ПНЕВМАТИКА!$G14)*Комплекты[Кол-во]*( ((Комплекты[Комплект]=ПНЕВМАТИКА!$G$13)*ПНЕВМАТИКА!AN$13)+ ((Комплекты[Комплект]=ПНЕВМАТИКА!$G$12)*ПНЕВМАТИКА!AN$12)+ ((Комплекты[Комплект]=ПНЕВМАТИКА!$G$11)*ПНЕВМАТИКА!AN$11))) -> 2 | AQ14: 3 | AR14: =SUMPRODUCT((Комплекты[Пр]=ПНЕВМАТИКА!$F14)*(Комплекты[Обозначение]=ПНЕВМАТИКА!$G14)*Комплекты[Кол-во]*( ((Комплекты[Комплект]=ПНЕВМАТИКА!$G$13)*ПНЕВМАТИКА!AR$13)+ ((Комплекты[Комплект]=ПНЕВМАТИКА!$G$12)*ПНЕВМАТИКА!AR$12)+ ((Комплекты[Комплект]=ПНЕВМАТИКА!$G$11)*ПНЕВМАТИКА!AR$11))) -> 3 | AU14: 3 | AV14: =SUMPRODUCT((Комплекты[Пр]=ПНЕВМАТИКА!$F14)*(Комплекты[Обозначение]=ПНЕВМАТИКА!$G14)*Комплекты[Кол-во]*( ((Комплекты[Комплект]=ПНЕВМАТИКА!$G$13)*ПНЕВМАТИКА!AV$13)+ ((Комплекты[Комплект]=ПНЕВМАТИКА!$G$12)*ПНЕВМАТИКА!AV$12)+ ((Комплекты[Комплект]=ПНЕВМАТИКА!$G$11)*ПНЕВМАТИКА!AV$11))) -> 3 | AY14: 3 | AZ14: =SUMPRODUCT((Комплекты[Пр]=ПНЕВМАТИКА!$F14)*(Комплекты[Обозначение]=ПНЕВМАТИКА!$G14)*Комплекты[Кол-во]*( ((Комплекты[Комплект]=ПНЕВМАТИКА!$G$13)*ПНЕВМАТИКА!AZ$13)+ ((Комплекты[Комплект]=ПНЕВМАТИКА!$G$12)*ПНЕВМАТИКА!AZ$12)+ ((Комплекты[Комплект]=ПНЕВМАТИКА!$G$11)*ПНЕВМАТИКА!AZ$11))) -> 3 | BC14: 3 | BD14: =SUMPRODUCT((Комплекты[Пр]=ПНЕВМАТИКА!$F14)*(Комплекты[Обозначение]=ПНЕВМАТИКА!$G14)*Комплекты[Кол-во]*( ((Комплекты[Комплект]=ПНЕВМАТИКА!$G$13)*ПНЕВМАТИКА!BD$13)+ ((Комплекты[Комплект]=ПНЕВМАТИКА!$G$12)*ПНЕВМАТИКА!BD$12)+ ((Комплекты[Комплект]=ПНЕВМАТИКА!$G$11)*ПНЕВМАТИКА!BD$11))) -> 3 | BG14: 3 | BH14: =SUMPRODUCT((Комплекты[Пр]=ПНЕВМАТИКА!$F14)*(Комплекты[Обозначение]=ПНЕВМАТИКА!$G14)*Комплекты[Кол-во]*( ((Комплекты[Комплект]=ПНЕВМАТИКА!$G$13)*ПНЕВМАТИКА!BH$13)+ ((Комплекты[Комплект]=ПНЕВМАТИКА!$G$12)*ПНЕВМАТИКА!BH$12)+ ((Комплекты[Комплект]=ПНЕВМАТИКА!$G$11)*ПНЕВМАТИКА!BH$11))) -> 3 | BL14: =SUMPRODUCT(--(MOD(COLUMN($O14:$AL14),4)=MOD(COLUMN($O14)+0,4)),$O14:$AL14) +SUMPRODUCT(--(MOD(COLUMN($AM14:$BJ14),4)=MOD(COLUMN($AM14)+0,4)),$AM14:$BJ14) -> 33 | BM14: =SUMPRODUCT(--(MOD(COLUMN($O14:$AL14),4)=MOD(COLUMN($O14)+0,4)),$O14:$AL14)*$I14 +SUMPRODUCT(--(MOD(COLUMN($AM14:$BJ14),4)=MOD(COLUMN($AM14)+0,4)),$AM14:$BJ14)*$I14 -> 0 | BN14: =SUMPRODUCT(--(MOD(COLUMN($O14:$AL14),4)=MOD(COLUMN($O14)+1,4)),$O14:$AL14) +SUMPRODUCT(--(MOD(COLUMN($AM14:$BJ14),4)=MOD(COLUMN($AM14)+1,4)),$AM14:$BJ14) -> 25 | BO14: =SUMPRODUCT(--(MOD(COLUMN($O14:$AL14),4)=MOD(COLUMN($O14)+1,4)),$O14:$AL14)*$I14 +SUMPRODUCT(--(MOD(COLUMN($AM14:$BJ14),4)=MOD(COLUMN($AM14)+1,4)),$AM14:$BJ14)*$I14 -> 0 | BP14: =SUMPRODUCT(--(MOD(COLUMN($O14:$AL14),4)=MOD(COLUMN($O14)+2,4)),$O14:$AL14) +SUMPRODUCT(--(MOD(COLUMN($AM14:$BJ14),4)=MOD(COLUMN($AM14)+2,4)),$AM14:$BJ14) -> 2 | BQ14: =SUMPRODUCT(--(MOD(COLUMN($O14:$AL14),4)=MOD(COLUMN($O14)+2,4)),$O14:$AL14)*$I14 +SUMPRODUCT(--(MOD(COLUMN($AM14:$BJ14),4)=MOD(COLUMN($AM14)+2,4)),$AM14:$BJ14)*$I14 -> 0 | DQ14: =SUMPRODUCT(--(MOD(COLUMN(BT14:CQ14),4)=MOD(COLUMN(BT14),4)),BT14:CQ14)+SUMPRODUCT(--(MOD(COLUMN(CR14:DO14),4)=MOD(COLUMN(CR14),4)),CR14:DO14) -> 0 | DR14: =SUMPRODUCT(--(MOD(COLUMN(BT14:CQ14),4)=MOD(COLUMN(BT14),4)),BT14:CQ14)*$I14+SUMPRODUCT(--(MOD(COLUMN(CR14:DO14),4)=MOD(COLUMN(CR14),4)),CR14:DO14)*$I14 -> 0 | FR14: =SUMPRODUCT(--(MOD(COLUMN(DU14:ER14),4)=MOD(COLUMN(DU14),4)),DU14:ER14)+SUMPRODUCT(--(MOD(COLUMN(ES14:FP14),4)=MOD(COLUMN(ES14),4)),ES14:FP14) -> 0 | FS14: =SUMPRODUCT(--(MOD(COLUMN(DU14:ER14),4)=MOD(COLUMN(DU14),4)),DU14:ER14)*$I14+SUMPRODUCT(--(MOD(COLUMN(ES14:FP14),4)=MOD(COLUMN(ES14),4)),ES14:FP14)*$I14 -> 0
A15: УЛЬТРА ГРУПП ООО | B15: Предоплата 100% | C15: ВБК РУС | D15: Прасолов, Соловьёв | E15: =IF(ISBLANK(G15),"",IF($A$6:$A$330=$A15,COUNTIF($A$6:A15,$A15),"")) -> 10 | F15: 1 | G15: 9522010020 | H15: Головка соединительная (питающая) | I15: 0 | L15: =IF(K15="RUB",J15/ЮАНЬ,IF(K15="EUR",J15*ЕВРО/ЮАНЬ,"")) | N15: =IF(BP15>0,1,IF(BN15>0,2,)) -> 1 | O15: 2 | S15: 2 | W15: 2 | X15: =SUMPRODUCT((Комплекты[Пр]=ПНЕВМАТИКА!$F15)*(Комплекты[Обозначение]=ПНЕВМАТИКА!$G15)*Комплекты[Кол-во]*( ((Комплекты[Комплект]=ПНЕВМАТИКА!$G$13)*ПНЕВМАТИКА!X$13)+ ((Комплекты[Комплект]=ПНЕВМАТИКА!$G$12)*ПНЕВМАТИКА!X$12)+ ((Комплекты[Комплект]=ПНЕВМАТИКА!$G$11)*ПНЕВМАТИКА!X$11))) -> 2 | Y15: =SUMPRODUCT((Комплекты[Пр]=ПНЕВМАТИКА!$F15)*(Комплекты[Обозначение]=ПНЕВМАТИКА!$G15)*Комплекты[Кол-во]*( ((Комплекты[Комплект]=ПНЕВМАТИКА!$G$13)*ПНЕВМАТИКА!Y$13)+ ((Комплекты[Комплект]=ПНЕВМАТИКА!$G$12)*ПНЕВМАТИКА!Y$12)+ ((Комплекты[Комплект]=ПНЕВМАТИКА!$G$11)*ПНЕВМАТИКА!Y$11))) -> 2 | AA15: 3 | AB15: =SUMPRODUCT((Комплекты[Пр]=ПНЕВМАТИКА!$F15)*(Комплекты[Обозначение]=ПНЕВМАТИКА!$G15)*Комплекты[Кол-во]*( ((Комплекты[Комплект]=ПНЕВМАТИКА!$G$13)*ПНЕВМАТИКА!AB$13)+ ((Комплекты[Комплект]=ПНЕВМАТИКА!$G$12)*ПНЕВМАТИКА!AB$12)+ ((Комплекты[Комплект]=ПНЕВМАТИКА!$G$11)*ПНЕВМАТИКА!AB$11))) -> 2 | AE15: 3 | AF15: =SUMPRODUCT((Комплекты[Пр]=ПНЕВМАТИКА!$F15)*(Комплекты[Обозначение]=ПНЕВМАТИКА!$G15)*Комплекты[Кол-во]*( ((Комплекты[Комплект]=ПНЕВМАТИКА!$G$13)*ПНЕВМАТИКА!AF$13)+ ((Комплекты[Комплект]=ПНЕВМАТИКА!$G$12)*ПНЕВМАТИКА!AF$12)+ ((Комплекты[Комплект]=ПНЕВМАТИКА!$G$11)*ПНЕВМАТИКА!AF$11))) -> 0 | AG15: =SUMPRODUCT((Комплекты[Пр]=ПНЕВМАТИКА!$F15)*(Комплекты[Обозначение]=ПНЕВМАТИКА!$G15)*Комплекты[Кол-во]*( ((Комплекты[Комплект]=ПНЕВМАТИКА!$G$13)*ПНЕВМАТИКА!AG$13)+ ((Комплекты[Комплект]=ПНЕВМАТИКА!$G$12)*ПНЕВМАТИКА!AG$12)+ ((Комплекты[Комплект]=ПНЕВМАТИКА!$G$11)*ПНЕВМАТИКА!AG$11))) -> 0 | AI15: 3 | AJ15: =SUMPRODUCT((Комплекты[Пр]=ПНЕВМАТИКА!$F15)*(Комплекты[Обозначение]=ПНЕВМАТИКА!$G15)*Комплекты[Кол-во]*( ((Комплекты[Комплект]=ПНЕВМАТИКА!$G$13)*ПНЕВМАТИКА!AJ$13)+ ((Комплекты[Комплект]=ПНЕВМАТИКА!$G$12)*ПНЕВМАТИКА!AJ$12)+ ((Комплекты[Комплект]=ПНЕВМАТИКА!$G$11)*ПНЕВМАТИКА!AJ$11))) -> 4 | AM15: 3 | AN15: =SUMPRODUCT((Комплекты[Пр]=ПНЕВМАТИКА!$F15)*(Комплекты[Обозначение]=ПНЕВМАТИКА!$G15)*Комплекты[Кол-во]*( ((Комплекты[Комплект]=ПНЕВМАТИКА!$G$13)*ПНЕВМАТИКА!AN$13)+ ((Комплекты[Комплект]=ПНЕВМАТИКА!$G$12)*ПНЕВМАТИКА!AN$12)+ ((Комплекты[Комплект]=ПНЕВМАТИКА!$G$11)*ПНЕВМАТИКА!AN$11))) -> 2 | AQ15: 3 | AR15: =SUMPRODUCT((Комплекты[Пр]=ПНЕВМАТИКА!$F15)*(Комплекты[Обозначение]=ПНЕВМАТИКА!$G15)*Комплекты[Кол-во]*( ((Комплекты[Комплект]=ПНЕВМАТИКА!$G$13)*ПНЕВМАТИКА!AR$13)+ ((Комплекты[Комплект]=ПНЕВМАТИКА!$G$12)*ПНЕВМАТИКА!AR$12)+ ((Комплекты[Комплект]=ПНЕВМАТИКА!$G$11)*ПНЕВМАТИКА!AR$11))) -> 3 | AU15: 3 | AV15: =SUMPRODUCT((Комплекты[Пр]=ПНЕВМАТИКА!$F15)*(Комплекты[Обозначение]=ПНЕВМАТИКА!$G15)*Комплекты[Кол-во]*( ((Комплекты[Комплект]=ПНЕВМАТИКА!$G$13)*ПНЕВМАТИКА!AV$13)+ ((Комплекты[Комплект]=ПНЕВМАТИКА!$G$12)*ПНЕВМАТИКА!AV$12)+ ((Комплекты[Комплект]=ПНЕВМАТИКА!$G$11)*ПНЕВМАТИКА!AV$11))) -> 3 | AY15: 3 | AZ15: =SUMPRODUCT((Комплекты[Пр]=ПНЕВМАТИКА!$F15)*(Комплекты[Обозначение]=ПНЕВМАТИКА!$G15)*Комплекты[Кол-во]*( ((Комплекты[Комплект]=ПНЕВМАТИКА!$G$13)*ПНЕВМАТИКА!AZ$13)+ ((Комплекты[Комплект]=ПНЕВМАТИКА!$G$12)*ПНЕВМАТИКА!AZ$12)+ ((Комплекты[Комплект]=ПНЕВМАТИКА!$G$11)*ПНЕВМАТИКА!AZ$11))) -> 3 | BC15: 3 | BD15: =SUMPRODUCT((Комплекты[Пр]=ПНЕВМАТИКА!$F15)*(Комплекты[Обозначение]=ПНЕВМАТИКА!$G15)*Комплекты[Кол-во]*( ((Комплекты[Комплект]=ПНЕВМАТИКА!$G$13)*ПНЕВМАТИКА!BD$13)+ ((Комплекты[Комплект]=ПНЕВМАТИКА!$G$12)*ПНЕВМАТИКА!BD$12)+ ((Комплекты[Комплект]=ПНЕВМАТИКА!$G$11)*ПНЕВМАТИКА!BD$11))) -> 3 | BG15: 3 | BH15: =SUMPRODUCT((Комплекты[Пр]=ПНЕВМАТИКА!$F15)*(Комплекты[Обозначение]=ПНЕВМАТИКА!$G15)*Комплекты[Кол-во]*( ((Комплекты[Комплект]=ПНЕВМАТИКА!$G$13)*ПНЕВМАТИКА!BH$13)+ ((Комплекты[Комплект]=ПНЕВМАТИКА!$G$12)*ПНЕВМАТИКА!BH$12)+ ((Комплекты[Комплект]=ПНЕВМАТИКА!$G$11)*ПНЕВМАТИКА!BH$11))) -> 3 | BL15: =SUMPRODUCT(--(MOD(COLUMN($O15:$AL15),4)=MOD(COLUMN($O15)+0,4)),$O15:$AL15) +SUMPRODUCT(--(MOD(COLUMN($AM15:$BJ15),4)=MOD(COLUMN($AM15)+0,4)),$AM15:$BJ15) -> 33 | BM15: =SUMPRODUCT(--(MOD(COLUMN($O15:$AL15),4)=MOD(COLUMN($O15)+0,4)),$O15:$AL15)*$I15 +SUMPRODUCT(--(MOD(COLUMN($AM15:$BJ15),4)=MOD(COLUMN($AM15)+0,4)),$AM15:$BJ15)*$I15 -> 0 | BN15: =SUMPRODUCT(--(MOD(COLUMN($O15:$AL15),4)=MOD(COLUMN($O15)+1,4)),$O15:$AL15) +SUMPRODUCT(--(MOD(COLUMN($AM15:$BJ15),4)=MOD(COLUMN($AM15)+1,4)),$AM15:$BJ15) -> 25 | BO15: =SUMPRODUCT(--(MOD(COLUMN($O15:$AL15),4)=MOD(COLUMN($O15)+1,4)),$O15:$AL15)*$I15 +SUMPRODUCT(--(MOD(COLUMN($AM15:$BJ15),4)=MOD(COLUMN($AM15)+1,4)),$AM15:$BJ15)*$I15 -> 0 | BP15: =SUMPRODUCT(--(MOD(COLUMN($O15:$AL15),4)=MOD(COLUMN($O15)+2,4)),$O15:$AL15) +SUMPRODUCT(--(MOD(COLUMN($AM15:$BJ15),4)=MOD(COLUMN($AM15)+2,4)),$AM15:$BJ15) -> 2 | BQ15: =SUMPRODUCT(--(MOD(COLUMN($O15:$AL15),4)=MOD(COLUMN($O15)+2,4)),$O15:$AL15)*$I15 +SUMPRODUCT(--(MOD(COLUMN($AM15:$BJ15),4)=MOD(COLUMN($AM15)+2,4)),$AM15:$BJ15)*$I15 -> 0 | DQ15: =SUMPRODUCT(--(MOD(COLUMN(BT15:CQ15),4)=MOD(COLUMN(BT15),4)),BT15:CQ15)+SUMPRODUCT(--(MOD(COLUMN(CR15:DO15),4)=MOD(COLUMN(CR15),4)),CR15:DO15) -> 0 | DR15: =SUMPRODUCT(--(MOD(COLUMN(BT15:CQ15),4)=MOD(COLUMN(BT15),4)),BT15:CQ15)*$I15+SUMPRODUCT(--(MOD(COLUMN(CR15:DO15),4)=MOD(COLUMN(CR15),4)),CR15:DO15)*$I15 -> 0 | FR15: =SUMPRODUCT(--(MOD(COLUMN(DU15:ER15),4)=MOD(COLUMN(DU15),4)),DU15:ER15)+SUMPRODUCT(--(MOD(COLUMN(ES15:FP15),4)=MOD(COLUMN(ES15),4)),ES15:FP15) -> 0 | FS15: =SUMPRODUCT(--(MOD(COLUMN(DU15:ER15),4)=MOD(COLUMN(DU15),4)),DU15:ER15)*$I15+SUMPRODUCT(--(MOD(COLUMN(ES15:FP15),4)=MOD(COLUMN(ES15),4)),ES15:FP15)*$I15 -> 0
A16: УЛЬТРА ГРУПП ООО | B16: Предоплата 100% | C16: ВБК РУС | D16: Прасолов, Соловьёв | E16: =IF(ISBLANK(G16),"",IF($A$6:$A$330=$A16,COUNTIF($A$6:A16,$A16),"")) -> 11 | F16: 1 | G16: 9710029000 | H16: Воздухораспределитель с клапаном растормаживания | I16: 0 | L16: =IF(K16="RUB",J16/ЮАНЬ,IF(K16="EUR",J16*ЕВРО/ЮАНЬ,"")) | N16: =IF(BP16>0,1,IF(BN16>0,2,)) -> 1 | O16: 2 | S16: 2 | W16: 2 | X16: =SUMPRODUCT((Комплекты[Пр]=ПНЕВМАТИКА!$F16)*(Комплекты[Обозначение]=ПНЕВМАТИКА!$G16)*Комплекты[Кол-во]*( ((Комплекты[Комплект]=ПНЕВМАТИКА!$G$13)*ПНЕВМАТИКА!X$13)+ ((Комплекты[Комплект]=ПНЕВМАТИКА!$G$12)*ПНЕВМАТИКА!X$12)+ ((Комплекты[Комплект]=ПНЕВМАТИКА!$G$11)*ПНЕВМАТИКА!X$11))) -> 2 | Y16: =SUMPRODUCT((Комплекты[Пр]=ПНЕВМАТИКА!$F16)*(Комплекты[Обозначение]=ПНЕВМАТИКА!$G16)*Комплекты[Кол-во]*( ((Комплекты[Комплект]=ПНЕВМАТИКА!$G$13)*ПНЕВМАТИКА!Y$13)+ ((Комплекты[Комплект]=ПНЕВМАТИКА!$G$12)*ПНЕВМАТИКА!Y$12)+ ((Комплекты[Комплект]=ПНЕВМАТИКА!$G$11)*ПНЕВМАТИКА!Y$11))) -> 2 | AA16: 3 | AB16: =SUMPRODUCT((Комплекты[Пр]=ПНЕВМАТИКА!$F16)*(Комплекты[Обозначение]=ПНЕВМАТИКА!$G16)*Комплекты[Кол-во]*( ((Комплекты[Комплект]=ПНЕВМАТИКА!$G$13)*ПНЕВМАТИКА!AB$13)+ ((Комплекты[Комплект]=ПНЕВМАТИКА!$G$12)*ПНЕВМАТИКА!AB$12)+ ((Комплекты[Комплект]=ПНЕВМАТИКА!$G$11)*ПНЕВМАТИКА!AB$11))) -> 2 | AE16: 3 | AF16: =SUMPRODUCT((Комплекты[Пр]=ПНЕВМАТИКА!$F16)*(Комплекты[Обозначение]=ПНЕВМАТИКА!$G16)*Комплекты[Кол-во]*( ((Комплекты[Комплект]=ПНЕВМАТИКА!$G$13)*ПНЕВМАТИКА!AF$13)+ ((Комплекты[Комплект]=ПНЕВМАТИКА!$G$12)*ПНЕВМАТИКА!AF$12)+ ((Комплекты[Комплект]=ПНЕВМАТИКА!$G$11)*ПНЕВМАТИКА!AF$11))) -> 0 | AG16: =SUMPRODUCT((Комплекты[Пр]=ПНЕВМАТИКА!$F16)*(Комплекты[Обозначение]=ПНЕВМАТИКА!$G16)*Комплекты[Кол-во]*( ((Комплекты[Комплект]=ПНЕВМАТИКА!$G$13)*ПНЕВМАТИКА!AG$13)+ ((Комплекты[Комплект]=ПНЕВМАТИКА!$G$12)*ПНЕВМАТИКА!AG$12)+ ((Комплекты[Комплект]=ПНЕВМАТИКА!$G$11)*ПНЕВМАТИКА!AG$11))) -> 0 | AI16: 3 | AJ16: =SUMPRODUCT((Комплекты[Пр]=ПНЕВМАТИКА!$F16)*(Комплекты[Обозначение]=ПНЕВМАТИКА!$G16)*Комплекты[Кол-во]*( ((Комплекты[Комплект]=ПНЕВМАТИКА!$G$13)*ПНЕВМАТИКА!AJ$13)+ ((Комплекты[Комплект]=ПНЕВМАТИКА!$G$12)*ПНЕВМАТИКА!AJ$12)+ ((Комплекты[Комплект]=ПНЕВМАТИКА!$G$11)*ПНЕВМАТИКА!AJ$11))) -> 4 | AM16: 3 | AN16: =SUMPRODUCT((Комплекты[Пр]=ПНЕВМАТИКА!$F16)*(Комплекты[Обозначение]=ПНЕВМАТИКА!$G16)*Комплекты[Кол-во]*( ((Комплекты[Комплект]=ПНЕВМАТИКА!$G$13)*ПНЕВМАТИКА!AN$13)+ ((Комплекты[Комплект]=ПНЕВМАТИКА!$G$12)*ПНЕВМАТИКА!AN$12)+ ((Комплекты[Комплект]=ПНЕВМАТИКА!$G$11)*ПНЕВМАТИКА!AN$11))) -> 2 | AQ16: 3 | AR16: =SUMPRODUCT((Комплекты[Пр]=ПНЕВМАТИКА!$F16)*(Комплекты[Обозначение]=ПНЕВМАТИКА!$G16)*Комплекты[Кол-во]*( ((Комплекты[Комплект]=ПНЕВМАТИКА!$G$13)*ПНЕВМАТИКА!AR$13)+ ((Комплекты[Комплект]=ПНЕВМАТИКА!$G$12)*ПНЕВМАТИКА!AR$12)+ ((Комплекты[Комплект]=ПНЕВМАТИКА!$G$11)*ПНЕВМАТИКА!AR$11))) -> 3 | AU16: 3 | AV16: =SUMPRODUCT((Комплекты[Пр]=ПНЕВМАТИКА!$F16)*(Комплекты[Обозначение]=ПНЕВМАТИКА!$G16)*Комплекты[Кол-во]*( ((Комплекты[Комплект]=ПНЕВМАТИКА!$G$13)*ПНЕВМАТИКА!AV$13)+ ((Комплекты[Комплект]=ПНЕВМАТИКА!$G$12)*ПНЕВМАТИКА!AV$12)+ ((Комплекты[Комплект]=ПНЕВМАТИКА!$G$11)*ПНЕВМАТИКА!AV$11))) -> 3 | AY16: 3 | AZ16: =SUMPRODUCT((Комплекты[Пр]=ПНЕВМАТИКА!$F16)*(Комплекты[Обозначение]=ПНЕВМАТИКА!$G16)*Комплекты[Кол-во]*( ((Комплекты[Комплект]=ПНЕВМАТИКА!$G$13)*ПНЕВМАТИКА!AZ$13)+ ((Комплекты[Комплект]=ПНЕВМАТИКА!$G$12)*ПНЕВМАТИКА!AZ$12)+ ((Комплекты[Комплект]=ПНЕВМАТИКА!$G$11)*ПНЕВМАТИКА!AZ$11))) -> 3 | BC16: 3 | BD16: =SUMPRODUCT((Комплекты[Пр]=ПНЕВМАТИКА!$F16)*(Комплекты[Обозначение]=ПНЕВМАТИКА!$G16)*Комплекты[Кол-во]*( ((Комплекты[Комплект]=ПНЕВМАТИКА!$G$13)*ПНЕВМАТИКА!BD$13)+ ((Комплекты[Комплект]=ПНЕВМАТИКА!$G$12)*ПНЕВМАТИКА!BD$12)+ ((Комплекты[Комплект]=ПНЕВМАТИКА!$G$11)*ПНЕВМАТИКА!BD$11))) -> 3 | BG16: 3 | BH16: =SUMPRODUCT((Комплекты[Пр]=ПНЕВМАТИКА!$F16)*(Комплекты[Обозначение]=ПНЕВМАТИКА!$G16)*Комплекты[Кол-во]*( ((Комплекты[Комплект]=ПНЕВМАТИКА!$G$13)*ПНЕВМАТИКА!BH$13)+ ((Комплекты[Комплект]=ПНЕВМАТИКА!$G$12)*ПНЕВМАТИКА!BH$12)+ ((Комплекты[Комплект]=ПНЕВМАТИКА!$G$11)*ПНЕВМАТИКА!BH$11))) -> 3 | BL16: =SUMPRODUCT(--(MOD(COLUMN($O16:$AL16),4)=MOD(COLUMN($O16)+0,4)),$O16:$AL16) +SUMPRODUCT(--(MOD(COLUMN($AM16:$BJ16),4)=MOD(COLUMN($AM16)+0,4)),$AM16:$BJ16) -> 33 | BM16: =SUMPRODUCT(--(MOD(COLUMN($O16:$AL16),4)=MOD(COLUMN($O16)+0,4)),$O16:$AL16)*$I16 +SUMPRODUCT(--(MOD(COLUMN($AM16:$BJ16),4)=MOD(COLUMN($AM16)+0,4)),$AM16:$BJ16)*$I16 -> 0 | BN16: =SUMPRODUCT(--(MOD(COLUMN($O16:$AL16),4)=MOD(COLUMN($O16)+1,4)),$O16:$AL16) +SUMPRODUCT(--(MOD(COLUMN($AM16:$BJ16),4)=MOD(COLUMN($AM16)+1,4)),$AM16:$BJ16) -> 25 | BO16: =SUMPRODUCT(--(MOD(COLUMN($O16:$AL16),4)=MOD(COLUMN($O16)+1,4)),$O16:$AL16)*$I16 +SUMPRODUCT(--(MOD(COLUMN($AM16:$BJ16),4)=MOD(COLUMN($AM16)+1,4)),$AM16:$BJ16)*$I16 -> 0 | BP16: =SUMPRODUCT(--(MOD(COLUMN($O16:$AL16),4)=MOD(COLUMN($O16)+2,4)),$O16:$AL16) +SUMPRODUCT(--(MOD(COLUMN($AM16:$BJ16),4)=MOD(COLUMN($AM16)+2,4)),$AM16:$BJ16) -> 2 | BQ16: =SUMPRODUCT(--(MOD(COLUMN($O16:$AL16),4)=MOD(COLUMN($O16)+2,4)),$O16:$AL16)*$I16 +SUMPRODUCT(--(MOD(COLUMN($AM16:$BJ16),4)=MOD(COLUMN($AM16)+2,4)),$AM16:$BJ16)*$I16 -> 0 | DQ16: =SUMPRODUCT(--(MOD(COLUMN(BT16:CQ16),4)=MOD(COLUMN(BT16),4)),BT16:CQ16)+SUMPRODUCT(--(MOD(COLUMN(CR16:DO16),4)=MOD(COLUMN(CR16),4)),CR16:DO16) -> 0 | DR16: =SUMPRODUCT(--(MOD(COLUMN(BT16:CQ16),4)=MOD(COLUMN(BT16),4)),BT16:CQ16)*$I16+SUMPRODUCT(--(MOD(COLUMN(CR16:DO16),4)=MOD(COLUMN(CR16),4)),CR16:DO16)*$I16 -> 0 | FR16: =SUMPRODUCT(--(MOD(COLUMN(DU16:ER16),4)=MOD(COLUMN(DU16),4)),DU16:ER16)+SUMPRODUCT(--(MOD(COLUMN(ES16:FP16),4)=MOD(COLUMN(ES16),4)),ES16:FP16) -> 0 | FS16: =SUMPRODUCT(--(MOD(COLUMN(DU16:ER16),4)=MOD(COLUMN(DU16),4)),DU16:ER16)*$I16+SUMPRODUCT(--(MOD(COLUMN(ES16:FP16),4)=MOD(COLUMN(ES16),4)),ES16:FP16)*$I16 -> 0
A17: УЛЬТРА ГРУПП ООО | B17: Предоплата 100% | C17: ВБК РУС | D17: Прасолов, Соловьёв | E17: =IF(ISBLANK(G17),"",IF($A$6:$A$330=$A17,COUNTIF($A$6:A17,$A17),"")) -> 12 | F17: 1 | G17: 4801020640 | H17: Электропневматический блок клапанов TEBS_4801020640 | I17: 0 | L17: =IF(K17="RUB",J17/ЮАНЬ,IF(K17="EUR",J17*ЕВРО/ЮАНЬ,"")) | N17: =IF(BP17>0,1,IF(BN17>0,2,)) -> 1 | O17: 2 | S17: 2 | W17: 2 | X17: =SUMPRODUCT((Комплекты[Пр]=ПНЕВМАТИКА!$F17)*(Комплекты[Обозначение]=ПНЕВМАТИКА!$G17)*Комплекты[Кол-во]*( ((Комплекты[Комплект]=ПНЕВМАТИКА!$G$13)*ПНЕВМАТИКА!X$13)+ ((Комплекты[Комплект]=ПНЕВМАТИКА!$G$12)*ПНЕВМАТИКА!X$12)+ ((Комплекты[Комплект]=ПНЕВМАТИКА!$G$11)*ПНЕВМАТИКА!X$11))) -> 2 | Y17: =SUMPRODUCT((Комплекты[Пр]=ПНЕВМАТИКА!$F17)*(Комплекты[Обозначение]=ПНЕВМАТИКА!$G17)*Комплекты[Кол-во]*( ((Комплекты[Комплект]=ПНЕВМАТИКА!$G$13)*ПНЕВМАТИКА!Y$13)+ ((Комплекты[Комплект]=ПНЕВМАТИКА!$G$12)*ПНЕВМАТИКА!Y$12)+ ((Комплекты[Комплект]=ПНЕВМАТИКА!$G$11)*ПНЕВМАТИКА!Y$11))) -> 2 | AA17: 3 | AB17: =SUMPRODUCT((Комплекты[Пр]=ПНЕВМАТИКА!$F17)*(Комплекты[Обозначение]=ПНЕВМАТИКА!$G17)*Комплекты[Кол-во]*( ((Комплекты[Комплект]=ПНЕВМАТИКА!$G$13)*ПНЕВМАТИКА!AB$13)+ ((Комплекты[Комплект]=ПНЕВМАТИКА!$G$12)*ПНЕВМАТИКА!AB$12)+ ((Комплекты[Комплект]=ПНЕВМАТИКА!$G$11)*ПНЕВМАТИКА!AB$11))) -> 2 | AE17: 3 | AF17: =SUMPRODUCT((Комплекты[Пр]=ПНЕВМАТИКА!$F17)*(Комплекты[Обозначение]=ПНЕВМАТИКА!$G17)*Комплекты[Кол-во]*( ((Комплекты[Комплект]=ПНЕВМАТИКА!$G$13)*ПНЕВМАТИКА!AF$13)+ ((Комплекты[Комплект]=ПНЕВМАТИКА!$G$12)*ПНЕВМАТИКА!AF$12)+ ((Комплекты[Комплект]=ПНЕВМАТИКА!$G$11)*ПНЕВМАТИКА!AF$11))) -> 0 | AG17: =SUMPRODUCT((Комплекты[Пр]=ПНЕВМАТИКА!$F17)*(Комплекты[Обозначение]=ПНЕВМАТИКА!$G17)*Комплекты[Кол-во]*( ((Комплекты[Комплект]=ПНЕВМАТИКА!$G$13)*ПНЕВМАТИКА!AG$13)+ ((Комплекты[Комплект]=ПНЕВМАТИКА!$G$12)*ПНЕВМАТИКА!AG$12)+ ((Комплекты[Комплект]=ПНЕВМАТИКА!$G$11)*ПНЕВМАТИКА!AG$11))) -> 0 | AI17: 3 | AJ17: =SUMPRODUCT((Комплекты[Пр]=ПНЕВМАТИКА!$F17)*(Комплекты[Обозначение]=ПНЕВМАТИКА!$G17)*Комплекты[Кол-во]*( ((Комплекты[Комплект]=ПНЕВМАТИКА!$G$13)*ПНЕВМАТИКА!AJ$13)+ ((Комплекты[Комплект]=ПНЕВМАТИКА!$G$12)*ПНЕВМАТИКА!AJ$12)+ ((Комплекты[Комплект]=ПНЕВМАТИКА!$G$11)*ПНЕВМАТИКА!AJ$11))) -> 4 | AM17: 3 | AN17: =SUMPRODUCT((Комплекты[Пр]=ПНЕВМАТИКА!$F17)*(Комплекты[Обозначение]=ПНЕВМАТИКА!$G17)*Комплекты[Кол-во]*( ((Комплекты[Комплект]=ПНЕВМАТИКА!$G$13)*ПНЕВМАТИКА!AN$13)+ ((Комплекты[Комплект]=ПНЕВМАТИКА!$G$12)*ПНЕВМАТИКА!AN$12)+ ((Комплекты[Комплект]=ПНЕВМАТИКА!$G$11)*ПНЕВМАТИКА!AN$11))) -> 2 | AQ17: 3 | AR17: =SUMPRODUCT((Комплекты[Пр]=ПНЕВМАТИКА!$F17)*(Комплекты[Обозначение]=ПНЕВМАТИКА!$G17)*Комплекты[Кол-во]*( ((Комплекты[Комплект]=ПНЕВМАТИКА!$G$13)*ПНЕВМАТИКА!AR$13)+ ((Комплекты[Комплект]=ПНЕВМАТИКА!$G$12)*ПНЕВМАТИКА!AR$12)+ ((Комплекты[Комплект]=ПНЕВМАТИКА!$G$11)*ПНЕВМАТИКА!AR$11))) -> 3 | AU17: 3 | AV17: =SUMPRODUCT((Комплекты[Пр]=ПНЕВМАТИКА!$F17)*(Комплекты[Обозначение]=ПНЕВМАТИКА!$G17)*Комплекты[Кол-во]*( ((Комплекты[Комплект]=ПНЕВМАТИКА!$G$13)*ПНЕВМАТИКА!AV$13)+ ((Комплекты[Комплект]=ПНЕВМАТИКА!$G$12)*ПНЕВМАТИКА!AV$12)+ ((Комплекты[Комплект]=ПНЕВМАТИКА!$G$11)*ПНЕВМАТИКА!AV$11))) -> 3 | AY17: 3 | AZ17: =SUMPRODUCT((Комплекты[Пр]=ПНЕВМАТИКА!$F17)*(Комплекты[Обозначение]=ПНЕВМАТИКА!$G17)*Комплекты[Кол-во]*( ((Комплекты[Комплект]=ПНЕВМАТИКА!$G$13)*ПНЕВМАТИКА!AZ$13)+ ((Комплекты[Комплект]=ПНЕВМАТИКА!$G$12)*ПНЕВМАТИКА!AZ$12)+ ((Комплекты[Комплект]=ПНЕВМАТИКА!$G$11)*ПНЕВМАТИКА!AZ$11))) -> 3 | BC17: 3 | BD17: =SUMPRODUCT((Комплекты[Пр]=ПНЕВМАТИКА!$F17)*(Комплекты[Обозначение]=ПНЕВМАТИКА!$G17)*Комплекты[Кол-во]*( ((Комплекты[Комплект]=ПНЕВМАТИКА!$G$13)*ПНЕВМАТИКА!BD$13)+ ((Комплекты[Комплект]=ПНЕВМАТИКА!$G$12)*ПНЕВМАТИКА!BD$12)+ ((Комплекты[Комплект]=ПНЕВМАТИКА!$G$11)*ПНЕВМАТИКА!BD$11))) -> 3 | BG17: 3 | BH17: =SUMPRODUCT((Комплекты[Пр]=ПНЕВМАТИКА!$F17)*(Комплекты[Обозначение]=ПНЕВМАТИКА!$G17)*Комплекты[Кол-во]*( ((Комплекты[Комплект]=ПНЕВМАТИКА!$G$13)*ПНЕВМАТИКА!BH$13)+ ((Комплекты[Комплект]=ПНЕВМАТИКА!$G$12)*ПНЕВМАТИКА!BH$12)+ ((Комплекты[Комплект]=ПНЕВМАТИКА!$G$11)*ПНЕВМАТИКА!BH$11))) -> 3 | BL17: =SUMPRODUCT(--(MOD(COLUMN($O17:$AL17),4)=MOD(COLUMN($O17)+0,4)),$O17:$AL17) +SUMPRODUCT(--(MOD(COLUMN($AM17:$BJ17),4)=MOD(COLUMN($AM17)+0,4)),$AM17:$BJ17) -> 33 | BM17: =SUMPRODUCT(--(MOD(COLUMN($O17:$AL17),4)=MOD(COLUMN($O17)+0,4)),$O17:$AL17)*$I17 +SUMPRODUCT(--(MOD(COLUMN($AM17:$BJ17),4)=MOD(COLUMN($AM17)+0,4)),$AM17:$BJ17)*$I17 -> 0 | BN17: =SUMPRODUCT(--(MOD(COLUMN($O17:$AL17),4)=MOD(COLUMN($O17)+1,4)),$O17:$AL17) +SUMPRODUCT(--(MOD(COLUMN($AM17:$BJ17),4)=MOD(COLUMN($AM17)+1,4)),$AM17:$BJ17) -> 25 | BO17: =SUMPRODUCT(--(MOD(COLUMN($O17:$AL17),4)=MOD(COLUMN($O17)+1,4)),$O17:$AL17)*$I17 +SUMPRODUCT(--(MOD(COLUMN($AM17:$BJ17),4)=MOD(COLUMN($AM17)+1,4)),$AM17:$BJ17)*$I17 -> 0 | BP17: =SUMPRODUCT(--(MOD(COLUMN($O17:$AL17),4)=MOD(COLUMN($O17)+2,4)),$O17:$AL17) +SUMPRODUCT(--(MOD(COLUMN($AM17:$BJ17),4)=MOD(COLUMN($AM17)+2,4)),$AM17:$BJ17) -> 2 | BQ17: =SUMPRODUCT(--(MOD(COLUMN($O17:$AL17),4)=MOD(COLUMN($O17)+2,4)),$O17:$AL17)*$I17 +SUMPRODUCT(--(MOD(COLUMN($AM17:$BJ17),4)=MOD(COLUMN($AM17)+2,4)),$AM17:$BJ17)*$I17 -> 0 | DQ17: =SUMPRODUCT(--(MOD(COLUMN(BT17:CQ17),4)=MOD(COLUMN(BT17),4)),BT17:CQ17)+SUMPRODUCT(--(MOD(COLUMN(CR17:DO17),4)=MOD(COLUMN(CR17),4)),CR17:DO17) -> 0 | DR17: =SUMPRODUCT(--(MOD(COLUMN(BT17:CQ17),4)=MOD(COLUMN(BT17),4)),BT17:CQ17)*$I17+SUMPRODUCT(--(MOD(COLUMN(CR17:DO17),4)=MOD(COLUMN(CR17),4)),CR17:DO17)*$I17 -> 0 | FR17: =SUMPRODUCT(--(MOD(COLUMN(DU17:ER17),4)=MOD(COLUMN(DU17),4)),DU17:ER17)+SUMPRODUCT(--(MOD(COLUMN(ES17:FP17),4)=MOD(COLUMN(ES17),4)),ES17:FP17) -> 0 | FS17: =SUMPRODUCT(--(MOD(COLUMN(DU17:ER17),4)=MOD(COLUMN(DU17),4)),DU17:ER17)*$I17+SUMPRODUCT(--(MOD(COLUMN(ES17:FP17),4)=MOD(COLUMN(ES17),4)),ES17:FP17)*$I17 -> 0
